Workbook

Sheet Expense Mapping
A1: التصنيف (Sub-Category) | B1: الاسم بالعربي | C1: الاسم بالإنجليزي | D1: الكاتيجوري (Category) | E1: الكاتيجوري بالعربي | F1: التصنيف بالعربي
A2: Sales Discounts (Contra-Revenue) | B2: خصومات اضافية للعملاء | C2: Customer Discounts | D2: Revenue Deductions | E2: تخفيض الإيراد | F2: خصومات المبيعات
A3: Sales Discounts (Contra-Revenue) | B3: خصم نقاط العملاء | C3: Loyalty Points Redemption | D3: Revenue Deductions | E3: تخفيض الإيراد | F3: خصومات المبيعات
A4: Sales Discounts (Contra-Revenue) | B4: مصروفات عملاء تعاقدات | C4: Contract Customers Fees | D4: Revenue Deductions | E4: تخفيض الإيراد | F4: خصومات المبيعات
A5: Sales Discounts (Contra-Revenue) | B5: عروض مبيعات التجميل | C5: Cosmetics Promotions | D5: Revenue Deductions | E5: تخفيض الإيراد | F5: خصومات المبيعات
A6: Inventory Losses (Shrinkage) | B6: مسروقات | C6: Stolen Goods | D6: Cost of Sales | E6: تكلفة المبيعات | F6: عجز وهوالك المخزون
A7: Inventory Losses (Shrinkage) | B7: هوالك وتوالف | C7: Damaged & Expired Items | D7: Cost of Sales | E7: تكلفة المبيعات | F7: عجز وهوالك المخزون
A8: Inventory Losses (Shrinkage) | B8: عجز جرد | C8: Stocktake Shortage | D8: Cost of Sales | E8: تكلفة المبيعات | F8: عجز وهوالك المخزون
A9: Inventory Losses (Shrinkage) | B9: مفقودات ومسروقات | C9: Lost & Stolen Goods | D9: Cost of Sales | E9: تكلفة المبيعات | F9: عجز وهوالك المخزون
A10: Salaries & Benefits | B10: مرتبات الادارة | C10: HQ Salaries | D10: Operating Expenses | E10: المصروفات التشغيلية | F10: الرواتب والمزايا
A11: Salaries & Benefits | B11: مرتبات الفروع | C11: Branch Salaries | D11: Operating Expenses | E11: المصروفات التشغيلية | F11: الرواتب والمزايا
A12: Salaries & Benefits | B12: تأمينات اجتماعية | C12: Social Insurance | D12: Operating Expenses | E12: المصروفات التشغيلية | F12: الرواتب والمزايا
... A114: Consumables | B114: شنط صيدلية | C114: Pharmacy Bags | D114: Operating Expenses | E114: المصروفات التشغيلية | F114: المستهلكات

Sheet Categories
A1: الترتيب | B1: الكاتيجوري (Category) | C1: التصنيف (Sub-Category) | D1: عدد البنود | E1: التصنيف بالعربي
A2: 1 | B2: Revenue Deductions | C2: Sales Discounts (Contra-Revenue) | D2: =COUNTIF('Expense Mapping'!$A$2:$A$113,C2) | E2: خصومات المبيعات
A3: 2 | B3: Cost of Sales | C3: Inventory Losses (Shrinkage) | D3: =COUNTIF('Expense Mapping'!$A$2:$A$113,C3) | E3: عجز وهوالك المخزون
A4: 3 | B4: Operating Expenses | C4: Salaries & Benefits | D4: =COUNTIF('Expense Mapping'!$A$2:$A$113,C4) | E4: الرواتب والمزايا
A5: 4 | B5: Operating Expenses | C5: Incentives and rewards employees | D5: =COUNTIF('Expense Mapping'!$A$2:$A$113,C5) | E5: الحوافز والمكافآت
A6: 5 | B6: Operating Expenses | C6: Rent | D6: =COUNTIF('Expense Mapping'!$A$2:$A$113,C6) | E6: الإيجارات
A7: 6 | B7: Operating Expenses | C7: Utilities expenses | D7: =COUNTIF('Expense Mapping'!$A$2:$A$113,C7) | E7: المرافق
A8: 7 | B8: Operating Expenses | C8: Consumables | D8: 7 | E8: المستهلكات
A9: 8 | B9: Operating Expenses | C9: Repairs and Maintenance | D9: =COUNTIF('Expense Mapping'!$A$2:$A$113,C9) | E9: الإصلاح والصيانة
A10: 9 | B10: Operating Expenses | C10: Vehicles expenses | D10: =COUNTIF('Expense Mapping'!$A$2:$A$113,C10) | E10: مصروفات السيارات
A11: 10 | B11: Operating Expenses | C11: Advertisement & Marketing | D11: =COUNTIF('Expense Mapping'!$A$2:$A$113,C11) | E11: الدعاية والتسويق
A12: 11 | B12: Operating Expenses | C12: Application commision | D12: =COUNTIF('Expense Mapping'!$A$2:$A$113,C12) | E12: عمولة الأبليكيشن
A13: 12 | B13: Operating Expenses | C13: Delivery & Shipping | D13: =COUNTIF('Expense Mapping'!$A$2:$A$113,C13) | E13: الشحن والتوصيل
A14: 13 | B14: Operating Expenses | C14: Bank & Card Charges | D14: =COUNTIF('Expense Mapping'!$A$2:$A$113,C14) | E14: مصروفات بنكية
A15: 14 | B15: Operating Expenses | C15: Support - IT department expenses | D15: =COUNTIF('Expense Mapping'!$A$2:$A$113,C15) | E15: الدعم الفني
A16: 15 | B16: Operating Expenses | C16: Professional Fees | D16: =COUNTIF('Expense Mapping'!$A$2:$A$113,C16) | E16: أتعاب مهنية
A17: 16 | B17: Operating Expenses | C17: Insurance | D17: =COUNTIF('Expense Mapping'!$A$2:$A$113,C17) | E17: التأمين
A18: 17 | B18: Operating Expenses | C18: Taxes & Government Fees | D18: =COUNTIF('Expense Mapping'!$A$2:$A$113,C18) | E18: ضرائب ورسوم حكومية
A19: 18 | B19: Operating Expenses | C19: Other overhead expenses | D19: =COUNTIF('Expense Mapping'!$A$2:$A$113,C19) | E19: مصروفات عمومية أخرى
A20: 19 | B20: Operating Expenses | C20: Depreciation & Amortization | D20: =COUNTIF('Expense Mapping'!$A$2:$A$113,C20) | E20: الإهلاك والاستهلاك
... A23: 22 | B23: Income Tax | C23: Income Tax (below PBT) | D23: =COUNTIF('Expense Mapping'!$A$2:$A$113,C23) | E23: ضريبة الدخل
C24: الإجمالي | D24: 113
