Workbook
Name linkkksss: INDIRECT(ADDRESS(1,1,,,Dashboard!A1))
Name sheet_link: INDIRECT(ADDRESS(7,3,,,Dashboard!DY1048576))
Name Shheet_Link: INDIRECT(ADDRESS(7,3,,,Dashboard!A1))
Name shshshs: INDIRECT(ADDRESS(1,1,,,Dashboard!A1))

Sheet Dashboard
C2: Income Statement
C3: Dashboard | R3: HQ
H7: YEAR TOTAL EXPENSES & YEAR TOTAL INCOME CHART
C8: Income Statement
C9: (YEAR TOTAL) | EJ9: =ADDRESS(7,3,,,R3) -> HQ!$C$7
C11: Total Sales Revenue | D11: : | E11: =AB42 -> 6.1514269e+08
C12: Total Cost of Sales | D12: : | E12: =AC42 -> 4.9701381e+08
C13: Gross Profit | D13: : | E13: =E11-E12 -> 1.1812888e+08
C14: Total Non-Operational Income | D14: : | E14: =AF42 -> 15963483
C15: TOTAL INCOME | D15: : | E15: =E13+E14 -> 1.3409236e+08
C18: TOTAL EXPENSES | D18: : | E18: =AE42 -> 1.1783265e+08 | EI18: تقرير المصروفات حسب الشهر
EI19: تقرير مصروفات إجمالية
EI20: تقرير إحصائية بحجم المبيعات
EI21: تقرير مجمعة حسب الشهر | EJ21: HQ
C22: NET PROFIT | D22: : | E22: =E15-E18 -> 16259709 | EI22: تقرير مصروفات حسب الفرع | EJ22: Aguza
EI23: مجمعة إجمالية | EJ23: October
EJ24: Batal
H25: December | EJ25: Nasr City
EJ26: Sweedy
C27: MONTH TOTAL | H27: EXPENSES DETAILS (MONTH TOTAL) | EJ27: Raya
C28: Income Statement | H28: Operating Expenses | EJ28: Etisalat
C29: =H25 -> December | H29: مرتبات الادارة | J29: =VLOOKUP($H$25,$AA$90:$EI$101,2,FALSE) -> 1313581.9 | K29: =J29/$E$36 -> 0.10384709 | M29: اعلان ودعاية - ايام دعاية | O29: =VLOOKUP($H$25,$AA$90:$EI$101,58,FALSE) -> 0 | P29: =O29/$E$36 -> 0 | AA29: Monthes | AB29: Total Sales Revenue | AC29: Total Cost of Sales | AD29: Total Income | AE29: Total Operating Expenses | AF29: Total Non-Operational Income | AG29: Net Profit | EJ29: Hazzem Hassan
H30: مرتبات الفروع | J30: =VLOOKUP($H$25,$AA$90:$EI$101,3,FALSE) -> 4020526.8 | K30: =J30/$E$36 -> 0.31784847 | M30: اكراميات - ايام دعاية | O30: =VLOOKUP($H$25,$AA$90:$EI$101,59,FALSE) -> 0 | P30: =O30/$E$36 -> 0 | AA30: January | AB30: ='تقرير مجمعة حسب الشهر'!G37 -> 40806682 | AC30: ='تقرير مجمعة حسب الشهر'!I37 -> 32885217 | AD30: ='تقرير مجمعة حسب الشهر'!J37 -> 7921465 | AE30: ='تقرير مجمعة حسب الشهر'!K37 -> 7206089.6 | AF30: ='تقرير مجمعة حسب الشهر'!M37 -> 499374.95 | AG30: =AD30-AE30+AF30 -> 1214750.4 | EJ30: Sena3ia
C31: Total Sales Revenue | D31: : | E31: =VLOOKUP(H25,AA30:AG41,MATCH(C31,AA29:AG29,0),0) -> 62205513 | H31: الكهرباء | J31: =VLOOKUP($H$25,$AA$90:$EI$101,4,FALSE) -> 70345 | K31: =J31/$E$36 -> 0.0055612241 | M31: وجبات وانتقال - ايام دعاية | O31: =VLOOKUP($H$25,$AA$90:$EI$101,60,FALSE) -> 0 | P31: =O31/$E$36 -> 0 | AA31: February | AB31: ='تقرير مجمعة حسب الشهر'!G72 -> 39943440 | AC31: ='تقرير مجمعة حسب الشهر'!I72 -> 32572061 | AD31: ='تقرير مجمعة حسب الشهر'!J72 -> 7371378.7 | AE31: ='تقرير مجمعة حسب الشهر'!K72 -> 7814841 | AF31: ='تقرير مجمعة حسب الشهر'!M72 -> 830716.73 | AG31: =AD31-AE31+AF31 -> 387254.39 | EJ31: Khargia
C32: Total Cost of Sales | D32: : | E32: =VLOOKUP(H25,AA30:AG41,MATCH(C32,AA29:AG29,0),0) -> 49741295 | H32: المياه | J32: =VLOOKUP($H$25,$AA$90:$EI$101,5,FALSE) -> 8069 | K32: =J32/$E$36 -> 0.00063790628 | M32: مكافات لجنة الجرد | O32: =VLOOKUP($H$25,$AA$90:$EI$101,61,FALSE) -> 57487 | P32: =O32/$E$36 -> 0.0045447166 | AA32: March | AB32: ='تقرير مجمعة حسب الشهر'!G108 -> 44391759 | AC32: ='تقرير مجمعة حسب الشهر'!I108 -> 36062858 | AD32: ='تقرير مجمعة حسب الشهر'!J108 -> 8328901.2 | AE32: ='تقرير مجمعة حسب الشهر'!K108 -> 8264417.5 | AF32: ='تقرير مجمعة حسب الشهر'!M108 -> 757642.93 | AG32: =AD32-AE32+AF32 -> 822126.6 | EJ32: Tagmou3
C33: Gross Profit | D33: : | E33: =E31-E32 -> 12464219 | H33: التليفون الارضي | J33: =VLOOKUP($H$25,$AA$90:$EI$101,6,FALSE) -> 0 | K33: =J33/$E$36 -> 0 | M33: انتقالات لجنة الجرد | O33: =VLOOKUP($H$25,$AA$90:$EI$101,62,FALSE) -> 0 | P33: =O33/$E$36 -> 0 | AA33: April | AB33: ='تقرير مجمعة حسب الشهر'!G144 -> 47015527 | AC33: ='تقرير مجمعة حسب الشهر'!I144 -> 38233327 | AD33: ='تقرير مجمعة حسب الشهر'!J144 -> 8782200.4 | AE33: ='تقرير مجمعة حسب الشهر'!K144 -> 8907714.6 | AF33: ='تقرير مجمعة حسب الشهر'!M144 -> 979531.25 | AG33: =AD33-AE33+AF33 -> 854017.1 | EJ33: Maadi
C34: Total Non-Operational Income | D34: : | E34: =VLOOKUP(H25,AA30:AG41,MATCH(C34,AA29:AG29,0),0) -> 5085004.7 | H34: الايجار - الصيدلية | J34: =VLOOKUP($H$25,$AA$90:$EI$101,7,FALSE) -> 510000 | K34: =J34/$E$36 -> 0.040318776 | M34: وجبات لجنة الجرد | O34: =VLOOKUP($H$25,$AA$90:$EI$101,63,FALSE) -> 8375 | P34: =O34/$E$36 -> 0.00066209754 | AA34: May | AB34: ='تقرير مجمعة حسب الشهر'!G180 -> 50394566 | AC34: ='تقرير مجمعة حسب الشهر'!I180 -> 40884079 | AD34: ='تقرير مجمعة حسب الشهر'!J180 -> 9510486.9 | AE34: ='تقرير مجمعة حسب الشهر'!K180 -> 8875833.8 | AF34: ='تقرير مجمعة حسب الشهر'!M180 -> 1545161.9 | AG34: =AD34-AE34+AF34 -> 2179815.1 | EJ34: Zaid
C35: TOTAL INCOME | D35: : | E35: =E33+E34 -> 17549224 | H35: الايجار - الادارة | J35: =VLOOKUP($H$25,$AA$90:$EI$101,8,FALSE) -> 50000 | K35: =J35/$E$36 -> 0.0039528212 | M35: مسروقات | O35: =VLOOKUP($H$25,$AA$90:$EI$101,64,FALSE) -> 0 | P35: =O35/$E$36 -> 0 | AA35: June | AB35: ='تقرير مجمعة حسب الشهر'!G216 -> 51071696 | AC35: ='تقرير مجمعة حسب الشهر'!I216 -> 41196730 | AD35: ='تقرير مجمعة حسب الشهر'!J216 -> 9874965.6 | AE35: ='تقرير مجمعة حسب الشهر'!K216 -> 10183140 | AF35: ='تقرير مجمعة حسب الشهر'!M216 -> 1123699.4 | AG35: =AD35-AE35+AF35 -> 815525.37 | EJ35: Sand Beach
C36: Total Operating Expenses | D36: : | E36: =VLOOKUP(H25,AA30:AG41,MATCH(C36,AA29:AG29,0),0) -> 12649194 | H36: ايجارات متنوعه | J36: =VLOOKUP($H$25,$AA$90:$EI$101,9,FALSE) -> 406756 | K36: =J36/$E$36 -> 0.032156674 | M36: غرامات | O36: =VLOOKUP($H$25,$AA$90:$EI$101,65,FALSE) -> 3005 | P36: =O36/$E$36 -> 0.00023756455 | AA36: July | AB36: ='تقرير مجمعة حسب الشهر'!G252 -> 53894045 | AC36: ='تقرير مجمعة حسب الشهر'!I252 -> 43477556 | AD36: ='تقرير مجمعة حسب الشهر'!J252 -> 10416489 | AE36: ='تقرير مجمعة حسب الشهر'!K252 -> 10168253 | AF36: ='تقرير مجمعة حسب الشهر'!M252 -> 864132.46 | AG36: =AD36-AE36+AF36 -> 1112367.7 | EJ36: Alamya
H37: ادوات مكتبية | J37: =VLOOKUP($H$25,$AA$90:$EI$101,10,FALSE) -> 23690 | K37: =J37/$E$36 -> 0.0018728467 | M37: مستلزمات كمبيوتر | O37: =VLOOKUP($H$25,$AA$90:$EI$101,66,FALSE) -> 15763.5 | P37: =O37/$E$36 -> 0.0012462059 | AA37: August | AB37: ='تقرير مجمعة حسب الشهر'!G288 -> 56253509 | AC37: ='تقرير مجمعة حسب الشهر'!I288 -> 45438716 | AD37: ='تقرير مجمعة حسب الشهر'!J288 -> 10814792 | AE37: ='تقرير مجمعة حسب الشهر'!K288 -> 10307079 | AF37: ='تقرير مجمعة حسب الشهر'!M288 -> 947444.07 | AG37: =AD37-AE37+AF37 -> 1455157.5 | EJ37: Online
C38: TOTAL EXPENSES | D38: : | E38: =E36+E37 -> 12649194 | H38: فواتير الموبايل | J38: =VLOOKUP($H$25,$AA$90:$EI$101,11,FALSE) -> 25005.69 | K38: =J38/$E$36 -> 0.0019768604 | M38: صيانة اجهزة كمبيوتر | O38: =VLOOKUP($H$25,$AA$90:$EI$101,67,FALSE) -> 168858 | P38: =O38/$E$36 -> 0.013349309 | AA38: September | AB38: ='تقرير مجمعة حسب الشهر'!G324 -> 52570347 | AC38: ='تقرير مجمعة حسب الشهر'!I324 -> 42515878 | AD38: ='تقرير مجمعة حسب الشهر'!J324 -> 10054469 | AE38: ='تقرير مجمعة حسب الشهر'!K324 -> 11127271 | AF38: ='تقرير مجمعة حسب الشهر'!M324 -> 1587116 | AG38: =AD38-AE38+AF38 -> 514313.42 | EJ38: Orange
H39: مكافات مبيعات الادوية | J39: =VLOOKUP($H$25,$AA$90:$EI$101,12,FALSE) -> 0 | K39: =J39/$E$36 -> 0 | M39: مطبوعات ورقية | O39: =VLOOKUP($H$25,$AA$90:$EI$101,68,FALSE) -> 0 | P39: =O39/$E$36 -> 0 | AA39: October | AB39: ='تقرير مجمعة حسب الشهر'!G360 -> 58202856 | AC39: ='تقرير مجمعة حسب الشهر'!I360 -> 46888176 | AD39: ='تقرير مجمعة حسب الشهر'!J360 -> 11314681 | AE39: ='تقرير مجمعة حسب الشهر'!K360 -> 11138990 | AF39: ='تقرير مجمعة حسب الشهر'!M360 -> 700625.77 | AG39: =AD39-AE39+AF39 -> 876316.71 | EJ39: Vod.Smart
C40: NET PROFIT | D40: : | E40: =E35-E38-E39 -> 4900030 | H40: مكافات مبيعات التجميل | J40: =VLOOKUP($H$25,$AA$90:$EI$101,13,FALSE) -> 28828.5 | K40: =J40/$E$36 -> 0.0022790781 | M40: شحن بضاعة | O40: =VLOOKUP($H$25,$AA$90:$EI$101,69,FALSE) -> 0 | P40: =O40/$E$36 -> 0 | AA40: November | AB40: ='تقرير مجمعة حسب الشهر'!G396 -> 58392748 | AC40: ='تقرير مجمعة حسب الشهر'!I396 -> 47117919 | AD40: ='تقرير مجمعة حسب الشهر'!J396 -> 11274829 | AE40: ='تقرير مجمعة حسب الشهر'!K396 -> 11189827 | AF40: ='تقرير مجمعة حسب الشهر'!M396 -> 1043032.8 | AG40: =AD40-AE40+AF40 -> 1128034.3 | EJ40: Vod.Zahraa
H41: بوفية وضيافة | J41: =VLOOKUP($H$25,$AA$90:$EI$101,14,FALSE) -> 18790 | K41: =J41/$E$36 -> 0.0014854702 | M41: عيديات ومناسبات | O41: =VLOOKUP($H$25,$AA$90:$EI$101,70,FALSE) -> 0 | P41: =O41/$E$36 -> 0 | AA41: December | AB41: ='تقرير مجمعة حسب الشهر'!G432 -> 62205513 | AC41: ='تقرير مجمعة حسب الشهر'!I432 -> 49741295 | AD41: ='تقرير مجمعة حسب الشهر'!J432 -> 12464219 | AE41: ='تقرير مجمعة حسب الشهر'!K432 -> 12649194 | AF41: ='تقرير مجمعة حسب الشهر'!M432 -> 5085004.7 | AG41: =AD41-AE41+AF41 -> 4900030 | EJ41: Mo7awelat
H42: رسوم وتراخيص وعمولات | J42: =VLOOKUP($H$25,$AA$90:$EI$101,15,FALSE) -> 24875 | K42: =J42/$E$36 -> 0.0019665285 | M42: بدلات متنوعه | O42: =VLOOKUP($H$25,$AA$90:$EI$101,71,FALSE) -> 265150 | P42: =O42/$E$36 -> 0.020961811 | AA42: Total | AB42: =SUM(AB30:AB41) -> 6.1514269e+08 | AC42: =SUM(AC30:AC41) -> 4.9701381e+08 | AD42: =SUM(AD30:AD41) -> 1.1812888e+08 | AE42: =SUM(AE30:AE41) -> 1.1783265e+08 | AF42: =SUM(AF30:AF41) -> 15963483 | AG42: =SUM(AG30:AG41) -> 16259709 | EJ42: Electric
H43: ورق طباعة | J43: =VLOOKUP($H$25,$AA$90:$EI$101,16,FALSE) -> 38500 | K43: =J43/$E$36 -> 0.0030436723 | M43: اجهزة ومستلزمات متنوعه | O43: =VLOOKUP($H$25,$AA$90:$EI$101,72,FALSE) -> 54285 | P43: =O43/$E$36 -> 0.0042915779 | EJ43: M.C.V
H44: بكر طباعة ريسيت | J44: =VLOOKUP($H$25,$AA$90:$EI$101,17,FALSE) -> 54240 | K44: =J44/$E$36 -> 0.0042880204 | M44: احبار طابعات | O44: =VLOOKUP($H$25,$AA$90:$EI$101,73,FALSE) -> 0 | P44: =O44/$E$36 -> 0 | EJ44: Egyplast
H45: بكر طباعة باركود | J45: =VLOOKUP($H$25,$AA$90:$EI$101,18,FALSE) -> 130 | K45: =J45/$E$36 -> 1.0277335e-05 | M45: الانترنت | O45: =VLOOKUP($H$25,$AA$90:$EI$101,74,FALSE) -> 12044.67 | P45: =O45/$E$36 -> 0.00095220853 | EJ45: Etisalat.Katamya
H46: اعلان ودعاية وتسويق | J46: =VLOOKUP($H$25,$AA$90:$EI$101,19,FALSE) -> 55892 | K46: =J46/$E$36 -> 0.0044186216 | M46: الدعم الفني - سوفتك | O46: =VLOOKUP($H$25,$AA$90:$EI$101,75,FALSE) -> 169125 | P46: =O46/$E$36 -> 0.013370418 | EJ46: CFC
H47: اكراميات | J47: =VLOOKUP($H$25,$AA$90:$EI$101,20,FALSE) -> 23831.75 | K47: =J47/$E$36 -> 0.0018840529 | M47: مصروف اهلاك مباني وانشاءات | O47: =VLOOKUP($H$25,$AA$90:$EI$101,76,FALSE) -> 0 | P47: =O47/$E$36 -> 0 | EJ47: North.Coast
H48: زكاة وتبرعات | J48: =VLOOKUP($H$25,$AA$90:$EI$101,21,FALSE) -> 38911.51 | K48: =J48/$E$36 -> 0.0030762048 | M48: مصروف اهلاك سيارات | O48: =VLOOKUP($H$25,$AA$90:$EI$101,77,FALSE) -> 73.33 | P48: =O48/$E$36 -> 5.7972075e-06 | EJ48: Rehab
H49: مصروفات نثرية | J49: =VLOOKUP($H$25,$AA$90:$EI$101,22,FALSE) -> 430 | K49: =J49/$E$36 -> 3.3994262e-05 | M49: مصروف اهلاك اثاث ومكاتب | O49: =VLOOKUP($H$25,$AA$90:$EI$101,78,FALSE) -> 67.47 | P49: =O49/$E$36 -> 5.3339369e-06 | EJ49: HSBC MAADI
H50: تأمينات اجتماعية | J50: =VLOOKUP($H$25,$AA$90:$EI$101,23,FALSE) -> 0 | K50: =J50/$E$36 -> 0 | M50: مصروف اهلاك اجهزة تكييف | O50: =VLOOKUP($H$25,$AA$90:$EI$101,79,FALSE) -> 5097.34 | P50: =O50/$E$36 -> 0.00040297747 | EJ50: HSBC SMART
H51: مستلزمات نظافة | J51: =VLOOKUP($H$25,$AA$90:$EI$101,24,FALSE) -> 3354 | K51: =J51/$E$36 -> 0.00026515524 | M51: مصروف اهلاك اجهزة كمبيوتر ومستلزماتها | O51: =VLOOKUP($H$25,$AA$90:$EI$101,80,FALSE) -> 28246.19 | P51: =O51/$E$36 -> 0.0022330427
H52: رسوم نظافة | J52: =VLOOKUP($H$25,$AA$90:$EI$101,25,FALSE) -> 295 | K52: =J52/$E$36 -> 2.3321645e-05 | M52: مصروف اهلاك برامج كمبيوتر | O52: =VLOOKUP($H$25,$AA$90:$EI$101,81,FALSE) -> 404.52 | P52: =O52/$E$36 -> 3.1979904e-05
H53: تامين على الصيدلية | J53: =VLOOKUP($H$25,$AA$90:$EI$101,26,FALSE) -> 1343.92 | K53: =J53/$E$36 -> 0.00010624551 | M53: مصروف اهلاك اجهزة كهربائية | O53: =VLOOKUP($H$25,$AA$90:$EI$101,82,FALSE) -> 11318.1 | P53: =O53/$E$36 -> 0.0008947685
H54: اصلاح وصيانة التكييفات | J54: =VLOOKUP($H$25,$AA$90:$EI$101,27,FALSE) -> 0 | K54: =J54/$E$36 -> 0 | M54: مصروف اهلاك تجهيزات وديكور | O54: =VLOOKUP($H$25,$AA$90:$EI$101,83,FALSE) -> 18147.88 | P54: =O54/$E$36 -> 0.0014347065
H55: اصلاح وصيانة الكهرباء | J55: =VLOOKUP($H$25,$AA$90:$EI$101,28,FALSE) -> 8285 | K55: =J55/$E$36 -> 0.00065498247 | M55: الضرائب العامة | O55: =VLOOKUP($H$25,$AA$90:$EI$101,84,FALSE) -> 0 | P55: =O55/$E$36 -> 0
H56: اصلاح وصيانة السباكة | J56: =VLOOKUP($H$25,$AA$90:$EI$101,29,FALSE) -> 570 | K56: =J56/$E$36 -> 4.5062161e-05 | M56: الضرائب العقارية | O56: =VLOOKUP($H$25,$AA$90:$EI$101,85,FALSE) -> 0 | P56: =O56/$E$36 -> 0
H57: اصلاح وصيانة اثاث وديكور | J57: =VLOOKUP($H$25,$AA$90:$EI$101,30,FALSE) -> 20 | K57: =J57/$E$36 -> 1.5811285e-06 | M57: خصم نقاط العملاء | O57: =VLOOKUP($H$25,$AA$90:$EI$101,86,FALSE) -> 138781.05 | P57: =O57/$E$36 -> 0.010971533
H58: اصلاح وصيانة اخرى | J58: =VLOOKUP($H$25,$AA$90:$EI$101,31,FALSE) -> 46835 | K58: =J58/$E$36 -> 0.0037026076 | M58: عقود صيانة وتوصيل مرافق | O58: =VLOOKUP($H$25,$AA$90:$EI$101,87,FALSE) -> 0 | P58: =O58/$E$36 -> 0
H59: مكافات | J59: =VLOOKUP($H$25,$AA$90:$EI$101,32,FALSE) -> 31735 | K59: =J59/$E$36 -> 0.0025088556 | M59: مصروفات تأسيس | O59: =VLOOKUP($H$25,$AA$90:$EI$101,88,FALSE) -> 166.66 | P59: =O59/$E$36 -> 1.3175543e-05
H60: هدايا ومزايا عينية | J60: =VLOOKUP($H$25,$AA$90:$EI$101,33,FALSE) -> 108 | K60: =J60/$E$36 -> 8.5380937e-06 | M60: هوالك وتوالف | O60: =VLOOKUP($H$25,$AA$90:$EI$101,89,FALSE) -> 13241.24 | P60: =O60/$E$36 -> 0.0010468051
H61: تارجت الفروع | J61: =VLOOKUP($H$25,$AA$90:$EI$101,34,FALSE) -> 265200 | K61: =J61/$E$36 -> 0.020965763 | M61: عجز جرد | O61: =VLOOKUP($H$25,$AA$90:$EI$101,90,FALSE) -> 124316.57 | P61: =O61/$E$36 -> 0.0098280234
H62: مزايا عاملين | J62: =VLOOKUP($H$25,$AA$90:$EI$101,35,FALSE) -> 7641 | K62: =J62/$E$36 -> 0.00060407013 | M62: تامين على السيارات | O62: =VLOOKUP($H$25,$AA$90:$EI$101,91,FALSE) -> 53192 | P62: =O62/$E$36 -> 0.0042051693
H63: مستهلكات صيدلية | J63: =VLOOKUP($H$25,$AA$90:$EI$101,36,FALSE) -> 1730.74 | K63: =J63/$E$36 -> 0.00013682611 | M63: مصروفات عملاء تعاقدات | O63: =VLOOKUP($H$25,$AA$90:$EI$101,92,FALSE) -> 5114 | P63: =O63/$E$36 -> 0.00040429455
H64: اتعاب استشارات محاسبية | J64: =VLOOKUP($H$25,$AA$90:$EI$101,37,FALSE) -> 8000 | K64: =J64/$E$36 -> 0.00063245139 | M64: ارباح دائنون متنوعون | O64: =VLOOKUP($H$25,$AA$90:$EI$101,93,FALSE) -> 0 | P64: =O64/$E$36 -> 0
H65: اتعاب محاماة | J65: =VLOOKUP($H$25,$AA$90:$EI$101,38,FALSE) -> 0 | K65: =J65/$E$36 -> 0 | M65: مصروفات متنوعه - ايام دعاية | O65: =VLOOKUP($H$25,$AA$90:$EI$101,94,FALSE) -> 500 | P65: =O65/$E$36 -> 3.9528212e-05
H66: مصروفات بنكية | J66: =VLOOKUP($H$25,$AA$90:$EI$101,39,FALSE) -> 133474.6 | K66: =J66/$E$36 -> 0.010552024 | M66: تغليف وشحن بضاعة | O66: =VLOOKUP($H$25,$AA$90:$EI$101,95,FALSE) -> 2960 | P66: =O66/$E$36 -> 0.00023400701
H67: شنط صيدلية | J67: =VLOOKUP($H$25,$AA$90:$EI$101,40,FALSE) -> 181926 | K67: =J67/$E$36 -> 0.014382419 | M67: ديون معدومة | O67: =VLOOKUP($H$25,$AA$90:$EI$101,96,FALSE) -> 0 | P67: =O67/$E$36 -> 0
H68: خصومات اضافية للعملاء | J68: =VLOOKUP($H$25,$AA$90:$EI$101,41,FALSE) -> 3700 | K68: =J68/$E$36 -> 0.00029250877 | M68: دمغات | O68: =VLOOKUP($H$25,$AA$90:$EI$101,97,FALSE) -> 0 | P68: =O68/$E$36 -> 0
H69: اشتراك الخط الساخن | J69: =VLOOKUP($H$25,$AA$90:$EI$101,42,FALSE) -> 0 | K69: =J69/$E$36 -> 0 | M69: خسائر إستبعاد أصول | O69: =VLOOKUP($H$25,$AA$90:$EI$101,98,FALSE) -> 0 | P69: =O69/$E$36 -> 0
H70: ملابس عاملين | J70: =VLOOKUP($H$25,$AA$90:$EI$101,43,FALSE) -> 0 | K70: =J70/$E$36 -> 0 | M70: عروض مبيعات التجميل | O70: =VLOOKUP($H$25,$AA$90:$EI$101,99,FALSE) -> 58315 | P70: =O70/$E$36 -> 0.0046101753
H71: وجبات عاملين | J71: =VLOOKUP($H$25,$AA$90:$EI$101,44,FALSE) -> 4385 | K71: =J71/$E$36 -> 0.00034666242 | M71: فوائد القروض - ابوظبى الاولFAB | O71: =VLOOKUP($H$25,$AA$90:$EI$101,100,FALSE) -> 13038.16 | P71: =O71/$E$36 -> 0.0010307503
H72: انتقالات عمومية | J72: =VLOOKUP($H$25,$AA$90:$EI$101,45,FALSE) -> 0 | K72: =J72/$E$36 -> 0 | M72: فوائد القروض بنك ADIB | O72: =VLOOKUP($H$25,$AA$90:$EI$101,101,FALSE) -> 9610.09 | P72: =O72/$E$36 -> 0.00075973934
H73: وقود السيارات | J73: =VLOOKUP($H$25,$AA$90:$EI$101,46,FALSE) -> 26400 | K73: =J73/$E$36 -> 0.0020870896 | M73: فوائد القروض بنك كريدي أجريكول | O73: =VLOOKUP($H$25,$AA$90:$EI$101,102,FALSE) -> 10952.1 | P73: =O73/$E$36 -> 0.00086583385
H74: زيت السيارات | J74: =VLOOKUP($H$25,$AA$90:$EI$101,47,FALSE) -> 6000 | K74: =J74/$E$36 -> 0.00047433854 | M74: فوائد القروض - العربى الافريقىAAIB | O74: =VLOOKUP($H$25,$AA$90:$EI$101,103,FALSE) -> 36281.33 | P74: =O74/$E$36 -> 0.0028682722
H75: صيانة السيارات - التوكيل | J75: =VLOOKUP($H$25,$AA$90:$EI$101,48,FALSE) -> 0 | K75: =J75/$E$36 -> 0 | M75: فوائد المصرية للتمويل العقارى | O75: =VLOOKUP($H$25,$AA$90:$EI$101,104,FALSE) -> 216471.7 | P75: =O75/$E$36 -> 0.017113478
H76: اصلاح السيارات | J76: =VLOOKUP($H$25,$AA$90:$EI$101,49,FALSE) -> 0 | K76: =J76/$E$36 -> 0 | M76: فوائد القروض البنك الاهلى المصرى | O76: =VLOOKUP($H$25,$AA$90:$EI$101,105,FALSE) -> 18073.64 | P76: =O76/$E$36 -> 0.0014288373
H77: اصلاح وجراج السيارات | J77: =VLOOKUP($H$25,$AA$90:$EI$101,50,FALSE) -> 2335 | K77: =J77/$E$36 -> 0.00018459675 | M77: فوائد القروض بنك الاهلى الكويتى ABK | O77: =VLOOKUP($H$25,$AA$90:$EI$101,106,FALSE) -> 12115.46 | P77: =O77/$E$36 -> 0.00095780493
H78: تجديد رخص السيارت | J78: =VLOOKUP($H$25,$AA$90:$EI$101,51,FALSE) -> 0 | K78: =J78/$E$36 -> 0 | M78: فوائد القروض بنك الاهلى المتحد AUB | O78: =VLOOKUP($H$25,$AA$90:$EI$101,107,FALSE) -> 17795.78 | P78: =O78/$E$36 -> 0.0014068707
H79: اجور ومرتبات - ايام دعاية | J79: =VLOOKUP($H$25,$AA$90:$EI$101,52,FALSE) -> 0 | K79: =J79/$E$36 -> 0 | M79: فوائد القروض البنك التجارى الدولى CIB | O79: =VLOOKUP($H$25,$AA$90:$EI$101,108,FALSE) -> 12786.24 | P79: =O79/$E$36 -> 0.0010108344
H80: كهرباء - ايام دعاية | J80: =VLOOKUP($H$25,$AA$90:$EI$101,53,FALSE) -> 0 | K80: =J80/$E$36 -> 0 | M80: تأمينات اجتماعية - حصة الشركة | O80: =VLOOKUP($H$25,$AA$90:$EI$101,109,FALSE) -> 33150 | P80: =O80/$E$36 -> 0.0026207204
H81: بنزين وزيت - ايام دعاية | J81: =VLOOKUP($H$25,$AA$90:$EI$101,54,FALSE) -> 0 | K81: =J81/$E$36 -> 0 | M81: فوائد القروض - التجارى وفا بنك AWB | O81: =VLOOKUP($H$25,$AA$90:$EI$101,110,FALSE) -> 19338.2 | P81: =O81/$E$36 -> 0.0015288089
H82: عمولات - ايام دعاية | J82: =VLOOKUP($H$25,$AA$90:$EI$101,55,FALSE) -> 0 | K82: =J82/$E$36 -> 0 | M82: فوائد القروض - بنك القاهرة BDC | O82: =VLOOKUP($H$25,$AA$90:$EI$101,111,FALSE) -> 17558.96 | P82: =O82/$E$36 -> 0.0013881486
H83: ايجارات - ايام دعاية | J83: =VLOOKUP($H$25,$AA$90:$EI$101,56,FALSE) -> 0 | K83: =J83/$E$36 -> 0 | M83: اتعاب محاماه | O83: =VLOOKUP($H$25,$AA$90:$EI$101,112,FALSE) -> 11470 | P83: =O83/$E$36 -> 0.00090677717
H84: نقل البضاعة - ايام دعاية | J84: =VLOOKUP($H$25,$AA$90:$EI$101,57,FALSE) -> 0 | K84: =J84/$E$36 -> 0 | M84: خصم أبليكيشن | O84: =VLOOKUP($H$25,$AA$90:$EJ$101,113,FALSE) -> 2803080.6 | P84: =O84/$E$36 -> 0.22160153
H85: عروض مبيعات ابليكشن | J85: =VLOOKUP($H$25,$AA$90:$EW$101,115,FALSE) -> 665695.34 | K85: =J85/$E$36 -> 0.052627492 | M85: مفقودات ومسروقات | O85: =VLOOKUP($H$25,$AA$90:$EJ$101,114,FALSE) -> 0 | P85: =O85/$E$36 -> 0
H86: عمولات ادارية | J86: =VLOOKUP($H$25,$AA$90:$EL$101,116,FALSE) -> 92000 | K86: =J86/$E$36 -> 0.0072731909
O87: =SUM(O29:O86)+SUM(J29:J86) -> 12649194
AB88: 2 | AC88: 3 | AD88: 4 | AE88: 5 | AF88: 6 | AG88: 7 | AH88: 8 | AI88: 9 | AJ88: 10 | AK88: 11 | AL88: 12 | AM88: 13 | AN88: 14 | AO88: 15 | AP88: 16 | AQ88: 17 | AR88: 18 | AS88: 19 | AT88: 20 | AU88: 21 | AV88: 22 | AW88: 23 | AX88: 24 | AY88: 25 | AZ88: 26 | BA88: 27 | BB88: 28 | BC88: 29 | BD88: 30 | BE88: 31 | BF88: 32 | BG88: 33 | BH88: 34 | BI88: 35 | BJ88: 36 | BK88: 37 | BL88: 38 | BM88: 39 | BN88: 40 | BO88: 41 | BP88: 42 | BQ88: 43 | BR88: 44 | BS88: 45 | BT88: 46 | BU88: 47 | BV88: 48 | BW88: 49 | BX88: 50 | BY88: 51 | BZ88: 52 | CA88: 53 | CB88: 54 | CC88: 55 | CD88: 56 | CE88: 57 | CF88: 58 | CG88: 59 | CH88: 60 | CI88: 61 | CJ88: 62 | CK88: 63 | CL88: 64 | CM88: 65 | CN88: 66 | CO88: 67 | CP88: 68 | CQ88: 69 | CR88: 70 | CS88: 71 | CT88: 72 | CU88: 73 | CV88: 74 | CW88: 75 | CX88: 76 | CY88: 77 | CZ88: 78 | DA88: 79 | DB88: 80 | DC88: 81 | DD88: 82 | DE88: 83 | DF88: 84 | DG88: 85 | DH88: 86 | DI88: 87 | DJ88: 88 | DK88: 89 | DL88: 90 | DM88: 91 | DN88: 92 | DO88: 93 | DP88: 94 | DQ88: 95 | DR88: 96 | DS88: 97 | DT88: 98 | DU88: 99 | DV88: 100 | DW88: 101 | DX88: 102 | DY88: 103 | DZ88: 104 | EA88: 105 | EB88: 106 | EC88: 107 | ED88: 108 | EE88: 109 | EF88: 110 | EG88: 111 | EH88: 112 | EI88: 113 | EJ88: 114 | EK88: 115 | EL88: 115
AB89: مرتبات الادارة | AC89: مرتبات الفروع | AD89: الكهرباء | AE89: المياه | AF89: التليفون الارضي | AG89: الايجار - الصيدلية | AH89: الايجار - الادارة | AI89: ايجارات متنوعه | AJ89: ادوات مكتبية | AK89: فواتير الموبايل | AL89: مكافات مبيعات الادوية | AM89: مكافات مبيعات التجميل | AN89: بوفية وضيافة | AO89: رسوم وتراخيص وعمولات | AP89: ورق طباعة | AQ89: بكر طباعة ريسيت | AR89: بكر طباعة باركود | AS89: اعلان ودعاية وتسويق | AT89: اكراميات | AU89: زكاة وتبرعات | AV89: مصروفات نثرية | AW89: تأمينات اجتماعية | AX89: مستلزمات نظافة | AY89: رسوم نظافة | AZ89: تامين على الصيدلية | BA89: اصلاح وصيانة التكييفات | BB89: اصلاح وصيانة الكهرباء | BC89: اصلاح وصيانة السباكة | BD89: اصلاح وصيانة اثاث وديكور | BE89: اصلاح وصيانة اخرى | BF89: مكافات | BG89: هدايا ومزايا عينية | BH89: تارجت الفروع | BI89: مزايا عاملين | BJ89: مستهلكات صيدلية | BK89: اتعاب استشارات محاسبية | BL89: اتعاب محاماة | BM89: مصروفات بنكية | BN89: شنط صيدلية | BO89: خصومات اضافية للعملاء | BP89: اشتراك الخط الساخن | BQ89: ملابس عاملين | BR89: وجبات عاملين | BS89: انتقالات عمومية | BT89: وقود السيارات | BU89: زيت السيارات | BV89: صيانة السيارات - التوكيل | BW89: اصلاح السيارات | BX89: اصلاح وجراج السيارات | BY89: تجديد رخص السيارت | BZ89: اجور ومرتبات - ايام دعاية | CA89: كهرباء - ايام دعاية | CB89: بنزين وزيت - ايام دعاية | CC89: عمولات - ايام دعاية | CD89: ايجارات - ايام دعاية | CE89: نقل البضاعة - ايام دعاية | CF89: اعلان ودعاية - ايام دعاية | CG89: اكراميات - ايام دعاية | CH89: وجبات وانتقال - ايام دعاية | CI89: مكافات لجنة الجرد | CJ89: انتقالات لجنة الجرد | CK89: وجبات لجنة الجرد | CL89: مسروقات | CM89: غرامات | CN89: مستلزمات كمبيوتر | CO89: صيانة اجهزة كمبيوتر | CP89: مطبوعات ورقية | CQ89: شحن بضاعة | CR89: عيديات ومناسبات | CS89: بدلات متنوعه | CT89: اجهزة ومستلزمات متنوعه | CU89: احبار طابعات | CV89: الانترنت | CW89: الدعم الفني - سوفتك | CX89: مصروف اهلاك مباني وانشاءات | CY89: مصروف اهلاك سيارات | CZ89: مصروف اهلاك اثاث ومكاتب | DA89: مصروف اهلاك اجهزة تكييف | DB89: مصروف اهلاك اجهزة كمبيوتر ومستلزماتها | DC89: مصروف اهلاك برامج كمبيوتر | DD89: مصروف اهلاك اجهزة كهربائية | DE89: مصروف اهلاك تجهيزات وديكور | DF89: الضرائب العامة | DG89: الضرائب العقارية | DH89: خصم نقاط العملاء | DI89: عقود صيانة وتوصيل مرافق | DJ89: مصروفات تأسيس | DK89: هوالك وتوالف | DL89: عجز جرد | DM89: تامين على السيارات | DN89: مصروفات عملاء تعاقدات | DO89: ارباح دائنون متنوعون | DP89: مصروفات متنوعه - ايام دعاية | DQ89: تغليف وشحن بضاعة | DR89: ديون معدومة | DS89: دمغات | DT89: خسائر إستبعاد أصول | DU89: عروض مبيعات التجميل | DV89: فوائد القروض - ابوظبى الاولFAB | DW89: فوائد القروض بنك ADIB | DX89: فوائد القروض بنك كريدي أجريكول | DY89: فوائد القروض - العربى الافريقىAAIB | DZ89: فوائد المصرية للتمويل العقارى | EA89: فوائد القروض البنك الاهلى المصرى | EB89: فوائد القروض بنك الاهلى الكويتى ABK | EC89: فوائد القروض بنك الاهلى المتحد AUB | ED89: فوائد القروض البنك التجارى الدولى CIB | EE89: تأمينات اجتماعية - حصة الشركة | EF89: فوائد القروض - التجارى وفا بنك AWB | EG89: فوائد القروض - بنك القاهرة BDC | EH89: اتعاب محاماه | EI89: خصم أبليكيشن | EJ89: مفقودات ومسروقات | EK89: عروض مبيعات ابليكشن | EL89: عمولات ادارية
AA90: January | AB90: =VLOOKUP(AB89,'تقرير مصروفات إجمالية'!$B$3:$C$115,2,FALSE) -> 853477.34 | AC90: =VLOOKUP(AC89,'تقرير مصروفات إجمالية'!$B$3:$C$115,2,FALSE) -> 2432813.8 | AD90: =VLOOKUP(AD89,'تقرير مصروفات إجمالية'!$B$3:$C$115,2,FALSE) -> 33612 | AE90: =VLOOKUP(AE89,'تقرير مصروفات إجمالية'!$B$3:$C$115,2,FALSE) -> 675 | AF90: =VLOOKUP(AF89,'تقرير مصروفات إجمالية'!$B$3:$C$115,2,FALSE) -> 3531 | AG90: =VLOOKUP(AG89,'تقرير مصروفات إجمالية'!$B$3:$C$115,2,FALSE) -> 300000 | AH90: =VLOOKUP(AH89,'تقرير مصروفات إجمالية'!$B$3:$C$115,2,FALSE) -> 100000 | AI90: =VLOOKUP(AI89,'تقرير مصروفات إجمالية'!$B$3:$C$115,2,FALSE) -> 385831 | ... EI90: =VLOOKUP(EI89,'تقرير مصروفات إجمالية'!$B$3:$C$115,2,FALSE) -> 943867.76 | EL90: =VLOOKUP($EL$89,'تقرير مصروفات إجمالية'!$B$3:$O$119,2,FALSE) -> 0
AA91: February | AB91: =VLOOKUP(AB89,'[1]تقرير مصروفات إجمالية'!$B$3:$D$115,3,FALSE) -> 899945.03 | AC91: =VLOOKUP(AC89,'[1]تقرير مصروفات إجمالية'!$B$3:$D$115,3,FALSE) -> 3113708 | AD91: =VLOOKUP(AD89,'[1]تقرير مصروفات إجمالية'!$B$3:$D$115,3,FALSE) -> 17837 | AE91: =VLOOKUP(AE89,'[1]تقرير مصروفات إجمالية'!$B$3:$D$115,3,FALSE) -> 200 | AF91: =VLOOKUP(AF89,'[1]تقرير مصروفات إجمالية'!$B$3:$D$115,3,FALSE) -> 0 | AG91: =VLOOKUP(AG89,'[1]تقرير مصروفات إجمالية'!$B$3:$D$115,3,FALSE) -> 300000 | AH91: =VLOOKUP(AH89,'[1]تقرير مصروفات إجمالية'!$B$3:$D$115,3,FALSE) -> 100000 | AI91: =VLOOKUP(AI89,'[1]تقرير مصروفات إجمالية'!$B$3:$D$115,3,FALSE) -> 383131 | ... EI91: =VLOOKUP(EI89,'[1]تقرير مصروفات إجمالية'!$B$3:$D$115,3,FALSE) -> 1243610.9 | EL91: =VLOOKUP($EL$89,'تقرير مصروفات إجمالية'!$B$3:$O$119,12,FALSE) -> 145389.75
AA92: March | AB92: =IFERROR(VLOOKUP(AB89,'تقرير مصروفات إجمالية'!$B$3:$N$115,4,0),0) -> 896301.69 | AC92: =IFERROR(VLOOKUP(AC89,'تقرير مصروفات إجمالية'!$B$3:$N$115,4,0),0) -> 2927024.3 | AD92: =IFERROR(VLOOKUP(AD89,'تقرير مصروفات إجمالية'!$B$3:$N$115,4,0),0) -> 52992 | AE92: =IFERROR(VLOOKUP(AE89,'تقرير مصروفات إجمالية'!$B$3:$N$115,4,0),0) -> 880 | AF92: =IFERROR(VLOOKUP(AF89,'تقرير مصروفات إجمالية'!$B$3:$N$115,4,0),0) -> 3750 | AG92: =IFERROR(VLOOKUP(AG89,'تقرير مصروفات إجمالية'!$B$3:$N$115,4,0),0) -> 300000 | AH92: =IFERROR(VLOOKUP(AH89,'تقرير مصروفات إجمالية'!$B$3:$N$115,4,0),0) -> 100000 | AI92: =IFERROR(VLOOKUP(AI89,'تقرير مصروفات إجمالية'!$B$3:$N$115,4,0),0) -> 386901 | ... EI92: =IFERROR(VLOOKUP(EI89,'تقرير مصروفات إجمالية'!$B$3:$N$115,4,0),0) -> 1359247.7 | EL92: =VLOOKUP($EL$89,'تقرير مصروفات إجمالية'!$B$3:$O$119,12,FALSE) -> 145389.75
AA93: April | AB93: =VLOOKUP(AB89,'تقرير مصروفات إجمالية'!$B$3:$F$115,5,0) -> 903218.51 | AC93: =VLOOKUP(AC89,'تقرير مصروفات إجمالية'!$B$3:$F$115,5,0) -> 3075055.6 | AD93: =VLOOKUP(AD89,'تقرير مصروفات إجمالية'!$B$3:$F$115,5,0) -> 36566 | AE93: =VLOOKUP(AE89,'تقرير مصروفات إجمالية'!$B$3:$F$115,5,0) -> 2800 | AF93: =VLOOKUP(AF89,'تقرير مصروفات إجمالية'!$B$3:$F$115,5,0) -> 0 | AG93: =VLOOKUP(AG89,'تقرير مصروفات إجمالية'!$B$3:$F$115,5,0) -> 300000 | AH93: =VLOOKUP(AH89,'تقرير مصروفات إجمالية'!$B$3:$F$115,5,0) -> 100000 | AI93: =VLOOKUP(AI89,'تقرير مصروفات إجمالية'!$B$3:$F$115,5,0) -> 389261 | ... EI93: =VLOOKUP(EI89,'تقرير مصروفات إجمالية'!$B$3:$F$115,5,0) -> 1978698 | EL93: =VLOOKUP($EL$89,'تقرير مصروفات إجمالية'!$B$3:$O$119,12,FALSE) -> 145389.75
AA94: May | AB94: =VLOOKUP(AB89,'تقرير مصروفات إجمالية'!$B$3:$N$115,6,FALSE) -> 994803.77 | AC94: =VLOOKUP(AC89,'تقرير مصروفات إجمالية'!$B$3:$N$115,6,FALSE) -> 3212591.6 | AD94: =VLOOKUP(AD89,'تقرير مصروفات إجمالية'!$B$3:$N$115,6,FALSE) -> 44400 | AE94: =VLOOKUP(AE89,'تقرير مصروفات إجمالية'!$B$3:$N$115,6,FALSE) -> 8222 | AF94: =VLOOKUP(AF89,'تقرير مصروفات إجمالية'!$B$3:$N$115,6,FALSE) -> 110 | AG94: =VLOOKUP(AG89,'تقرير مصروفات إجمالية'!$B$3:$N$115,6,FALSE) -> 300000 | AH94: =VLOOKUP(AH89,'تقرير مصروفات إجمالية'!$B$3:$N$115,6,FALSE) -> 100000 | AI94: =VLOOKUP(AI89,'تقرير مصروفات إجمالية'!$B$3:$N$115,6,FALSE) -> 388591 | ... EI94: =VLOOKUP(EI89,'تقرير مصروفات إجمالية'!$B$3:$N$115,6,FALSE) -> 2075060.9 | EL94: =VLOOKUP($EL$89,'تقرير مصروفات إجمالية'!$B$3:$O$119,12,FALSE) -> 145389.75
AA95: June | AB95: =VLOOKUP(AB89,'تقرير مصروفات إجمالية'!$B$3:$N$115,7,FALSE) -> 1006628.8 | AC95: =VLOOKUP(AC89,'تقرير مصروفات إجمالية'!$B$3:$N$115,7,FALSE) -> 3373440.2 | AD95: =VLOOKUP(AD89,'تقرير مصروفات إجمالية'!$B$3:$N$115,7,FALSE) -> 64465 | AE95: =VLOOKUP(AE89,'تقرير مصروفات إجمالية'!$B$3:$N$115,7,FALSE) -> 215 | AF95: =VLOOKUP(AF89,'تقرير مصروفات إجمالية'!$B$3:$N$115,7,FALSE) -> 9345 | AG95: =VLOOKUP(AG89,'تقرير مصروفات إجمالية'!$B$3:$N$115,7,FALSE) -> 300000 | AH95: =VLOOKUP(AH89,'تقرير مصروفات إجمالية'!$B$3:$N$115,7,FALSE) -> 100000 | AI95: =VLOOKUP(AI89,'تقرير مصروفات إجمالية'!$B$3:$N$115,7,FALSE) -> 402741 | ... EI95: =VLOOKUP(EI89,'تقرير مصروفات إجمالية'!$B$3:$N$115,7,FALSE) -> 2768807.4 | EJ95: =VLOOKUP(EJ89,'تقرير مصروفات إجمالية'!$B$3:$N$116,7,FALSE) -> 2157.5 | EL95: =VLOOKUP($EL$89,'تقرير مصروفات إجمالية'!$B$3:$O$119,12,FALSE) -> 145389.75
AA96: July | AB96: =VLOOKUP(AB89,'تقرير مصروفات إجمالية'!$B$3:$N$115,8,FALSE) -> 1108595.7 | AC96: =VLOOKUP(AC89,'تقرير مصروفات إجمالية'!$B$3:$N$115,8,FALSE) -> 3436509.6 | AD96: =VLOOKUP(AD89,'تقرير مصروفات إجمالية'!$B$3:$N$115,8,FALSE) -> 92375 | AE96: =VLOOKUP(AE89,'تقرير مصروفات إجمالية'!$B$3:$N$115,8,FALSE) -> 626 | AF96: =VLOOKUP(AF89,'تقرير مصروفات إجمالية'!$B$3:$N$115,8,FALSE) -> 0 | AG96: =VLOOKUP(AG89,'تقرير مصروفات إجمالية'!$B$3:$N$115,8,FALSE) -> 300000 | AH96: =VLOOKUP(AH89,'تقرير مصروفات إجمالية'!$B$3:$N$115,8,FALSE) -> 100000 | AI96: =VLOOKUP(AI89,'تقرير مصروفات إجمالية'!$B$3:$N$115,8,FALSE) -> 391881 | ... EI96: =VLOOKUP(EI89,'تقرير مصروفات إجمالية'!$B$3:$N$115,8,FALSE) -> 2162727.5 | EJ96: =VLOOKUP(EJ89,'تقرير مصروفات إجمالية'!$B$3:$N$119,8,FALSE) -> 0 | EK96: =VLOOKUP(EK89,'تقرير مصروفات إجمالية'!$B$3:$N$119,8,FALSE) -> 393818.75 | EL96: =VLOOKUP($EL$89,'تقرير مصروفات إجمالية'!$B$3:$O$119,12,FALSE) -> 145389.75
AA97: August | AB97: =VLOOKUP(AB89,'تقرير مصروفات إجمالية'!$B$3:$N$115,9,FALSE) -> 1266314.5 | AC97: =VLOOKUP(AC89,'تقرير مصروفات إجمالية'!$B$3:$N$112,9,FALSE) -> 3489354.8 | AD97: =VLOOKUP(AD89,'تقرير مصروفات إجمالية'!$B$3:$N$112,9,FALSE) -> 71447 | AE97: =VLOOKUP(AE89,'تقرير مصروفات إجمالية'!$B$3:$N$112,9,FALSE) -> 1227 | AF97: =VLOOKUP(AF89,'تقرير مصروفات إجمالية'!$B$3:$N$112,9,FALSE) -> 0 | AG97: =VLOOKUP(AG89,'تقرير مصروفات إجمالية'!$B$3:$N$112,9,FALSE) -> 300000 | AH97: =VLOOKUP(AH89,'تقرير مصروفات إجمالية'!$B$3:$N$112,9,FALSE) -> 100000 | AI97: =VLOOKUP(AI89,'تقرير مصروفات إجمالية'!$B$3:$N$112,9,FALSE) -> 400876 | AJ97: =VLOOKUP(AJ89,'تقرير مصروفات إجمالية'!$B$3:$N$112,9,FALSE) -> 13051 | ... ED97: =VLOOKUP(ED89,'تقرير مصروفات إجمالية'!$B$3:$N$112,9,FALSE) -> 14549.09 | EE97: =VLOOKUP(EE89,'تقرير مصروفات إجمالية'!$B$3:$N$119,9,FALSE) -> 34012.5 | EF97: =VLOOKUP(EF89,'تقرير مصروفات إجمالية'!$B$3:$N$112,9,FALSE) -> 20335.79 | EG97: =VLOOKUP(EG89,'تقرير مصروفات إجمالية'!$B$3:$N$119,9,FALSE) -> 19385.65 | EH97: =VLOOKUP(EH89,'تقرير مصروفات إجمالية'!$B$3:$N$115,9,FALSE) -> 500 | EI97: =VLOOKUP(EI89,'تقرير مصروفات إجمالية'!$B$3:$N$115,9,FALSE) -> 2010834.1 | EJ97: =VLOOKUP(EJ89,'تقرير مصروفات إجمالية'!$B$3:$N$119,9,FALSE) -> 0 | EK97: =VLOOKUP(EK89,'تقرير مصروفات إجمالية'!$B$3:$N$119,9,FALSE) -> 663410.83 | EL97: =VLOOKUP($EL$89,'تقرير مصروفات إجمالية'!$B$3:$O$119,12,FALSE) -> 145389.75
AA98: September | AB98: =VLOOKUP(AB89,'تقرير مصروفات إجمالية'!$B$3:$N$117,10,FALSE) -> 1184810.4 | AC98: =VLOOKUP(AC89,'تقرير مصروفات إجمالية'!$B$3:$N$117,10,FALSE) -> 3538785.7 | AD98: =VLOOKUP(AD89,'تقرير مصروفات إجمالية'!$B$3:$N$117,10,FALSE) -> 112057 | AE98: =VLOOKUP(AE89,'تقرير مصروفات إجمالية'!$B$3:$N$117,10,FALSE) -> 4387 | AF98: =VLOOKUP(AF89,'تقرير مصروفات إجمالية'!$B$3:$N$117,10,FALSE) -> 0 | AG98: =VLOOKUP(AG89,'تقرير مصروفات إجمالية'!$B$3:$N$117,10,FALSE) -> 300000 | AH98: =VLOOKUP(AH89,'تقرير مصروفات إجمالية'!$B$3:$N$117,10,FALSE) -> 100000 | AI98: =VLOOKUP(AI89,'تقرير مصروفات إجمالية'!$B$3:$N$117,10,FALSE) -> 405496 | ... EK98: =VLOOKUP(EK89,'تقرير مصروفات إجمالية'!$B$3:$N$117,10,FALSE) -> 988588.92 | EL98: =VLOOKUP($EL$89,'تقرير مصروفات إجمالية'!$B$3:$O$119,12,FALSE) -> 145389.75
AA99: October | AB99: =VLOOKUP(AB89,'تقرير مصروفات إجمالية'!$B$3:$N$115,11,FALSE) -> 1313118.6 | AC99: =VLOOKUP(AC89,'تقرير مصروفات إجمالية'!$B$3:$N$115,11,FALSE) -> 3752577.6 | AD99: =VLOOKUP(AD89,'تقرير مصروفات إجمالية'!$B$3:$N$115,11,FALSE) -> 118941.75 | AE99: =VLOOKUP(AE89,'تقرير مصروفات إجمالية'!$B$3:$N$115,11,FALSE) -> 2358 | AF99: =VLOOKUP(AF89,'تقرير مصروفات إجمالية'!$B$3:$N$115,11,FALSE) -> 920 | AG99: =VLOOKUP(AG89,'تقرير مصروفات إجمالية'!$B$3:$N$115,11,FALSE) -> 300000 | AH99: =VLOOKUP(AH89,'تقرير مصروفات إجمالية'!$B$3:$N$115,11,FALSE) -> 100000 | AI99: =VLOOKUP(AI89,'تقرير مصروفات إجمالية'!$B$3:$N$115,11,FALSE) -> 390476 | ... EI99: =VLOOKUP(EI89,'تقرير مصروفات إجمالية'!$B$3:$N$115,11,FALSE) -> 2296919.1 | EJ99: =VLOOKUP(EJ89,'تقرير مصروفات إجمالية'!$B$3:$N$117,11,FALSE) -> 0 | EK99: =VLOOKUP(EK89,'تقرير مصروفات إجمالية'!$B$3:$N$117,11,FALSE) -> 851325.59 | EL99: =VLOOKUP($EL$89,'تقرير مصروفات إجمالية'!$B$3:$O$119,12,FALSE) -> 145389.75
AA100: November | AB100: =VLOOKUP(AB89,'تقرير مصروفات إجمالية'!$B$3:$O$119,12,FALSE) -> 1305040.6 | AC100: =VLOOKUP(AC89,'تقرير مصروفات إجمالية'!$B$3:$O$119,12,FALSE) -> 3826155.7 | AD100: =VLOOKUP(AD89,'تقرير مصروفات إجمالية'!$B$3:$O$119,12,FALSE) -> 87318 | AE100: =VLOOKUP(AE89,'تقرير مصروفات إجمالية'!$B$3:$O$119,12,FALSE) -> 979 | AF100: =VLOOKUP(AF89,'تقرير مصروفات إجمالية'!$B$3:$O$119,12,FALSE) -> 2900 | AG100: =VLOOKUP(AG89,'تقرير مصروفات إجمالية'!$B$3:$O$119,12,FALSE) -> 510000 | AH100: =VLOOKUP(AH89,'تقرير مصروفات إجمالية'!$B$3:$O$119,12,FALSE) -> 50000 | AI100: =VLOOKUP(AI89,'تقرير مصروفات إجمالية'!$B$3:$O$119,12,FALSE) -> 407936 | ... EK100: =VLOOKUP(EK89,'تقرير مصروفات إجمالية'!$B$3:$O$119,12,FALSE) -> 432581.85 | EL100: =VLOOKUP($EL$89,'تقرير مصروفات إجمالية'!$B$3:$O$119,12,FALSE) -> 145389.75
AA101: December | AB101: =VLOOKUP(AB89,'تقرير مصروفات إجمالية'!$B$3:$N$115,13,FALSE) -> 1313581.9 | AC101: =VLOOKUP(AC89,'تقرير مصروفات إجمالية'!$B$3:$N$115,13,FALSE) -> 4020526.8 | AD101: =VLOOKUP(AD89,'تقرير مصروفات إجمالية'!$B$3:$N$115,13,FALSE) -> 70345 | AE101: =VLOOKUP(AE89,'تقرير مصروفات إجمالية'!$B$3:$N$115,13,FALSE) -> 8069 | AF101: =VLOOKUP(AF89,'تقرير مصروفات إجمالية'!$B$3:$N$115,13,FALSE) -> 0 | AG101: =VLOOKUP(AG89,'تقرير مصروفات إجمالية'!$B$3:$N$115,13,FALSE) -> 510000 | AH101: =VLOOKUP(AH89,'تقرير مصروفات إجمالية'!$B$3:$N$115,13,FALSE) -> 50000 | AI101: =VLOOKUP(AI89,'تقرير مصروفات إجمالية'!$B$3:$N$115,13,FALSE) -> 406756 | ... EI101: =VLOOKUP(EI89,'تقرير مصروفات إجمالية'!$B$3:$N$115,13,FALSE) -> 2803080.6 | EJ101: =VLOOKUP(EJ89,'تقرير مصروفات إجمالية'!$B$3:$N$119,13,FALSE) -> 0 | EK101: =VLOOKUP(EK89,'تقرير مصروفات إجمالية'!$B$3:$N$119,13,FALSE) -> 665695.34 | EL101: =VLOOKUP(EL89,'تقرير مصروفات إجمالية'!$B$3:$N$119,13,FALSE) -> 92000
AA102: الإجمالي | AB102: =SUM(AB90:AB101) -> 13045837 | AC102: =SUM(AC90:AC101) -> 40198544 | AD102: =SUM(AD90:AD101) -> 802355.75 | AE102: =SUM(AE90:AE101) -> 30638 | AF102: =SUM(AF90:AF101) -> 20556 | AG102: =SUM(AG90:AG101) -> 4020000 | AH102: =SUM(AH90:AH101) -> 1100000 | AI102: =SUM(AI90:AI101) -> 4739877 | ... EL102: =SUM(EL90:EL101) -> 1545897.5
H173: 0

Sheet HQ
C2: INCOME STATEMTN
G3: Income Statement For HQ
D6: Jan | E6: February | F6: March | G6: April | H6: May | I6: June | J6: July | K6: August | L6: September | M6: October | N6: November | O6: December | P6: Total
C7: INCOME DETAILS
C8: المبيعات | D8: =D9+D10+D11 -> 0 | E8: =E9+E10+E11 -> 0 | F8: =F9+F10+F11 -> 0 | G8: =G9+G10+G11 -> 0 | H8: =H9+H10+H11 -> 0 | I8: =I9+I10+I11 -> 0 | J8: =J9+J10+J11 -> 0 | K8: =K9+K10+K11 -> 0 | ... O8: =O9+O10+O11 -> 0 | P8: =SUM(D8:O8) -> 0
C9: نقدى | P9: =SUM(D9:O9) -> 0
C10: دليفرى | P10: =SUM(D10:O10) -> 0
C11: اجل | P11: =SUM(D11:O11) -> 0
C12: تكلفة البضاعة المباعة | P12: =SUM(D12:O12) -> 0
C13: مجمل الربح | D13: =D8-D12 -> 0 | E13: =E8-E12 -> 0 | F13: =F8-F12 -> 0 | G13: =G8-G12 -> 0 | H13: =H8-H12 -> 0 | I13: =I8-I12 -> 0 | J13: =J8-J12 -> 0 | K13: =K8-K12 -> 0 | ... O13: =O8-O12 -> 0 | P13: =SUM(D13:O13) -> 0
C14: خصم نقدى | D14: 223875.51 | E14: 337632.98 | F14: 289944.05 | G14: 78025.57 | H14: 402717.41 | I14: 369287.54 | J14: 218232.85 | K14: 402056.92 | L14: 224091.1 | M14: 152627.12 | N14: 79525.81 | O14: 223453.29 | P14: =SUM(D14:O14) -> 3001470.1
C15: ارباح صرف اصناف بيع اصول | E15: 365 | H15: 21851.9 | P15: =SUM(D15:O15) -> 22216.9
C16: فائض جرد | D16: 367.55 | E16: 21315.47 | F16: 3831.65 | G16: 536.91 | I16: 10453.73 | J16: 0 | P16: =SUM(D16:O16) -> 36505.31
C17: ايرادات اخرى | D17: 79417.32 | E17: =72208.32+20000 -> 92208.32 | F17: 170139.06 | G17: 469365.13 | H17: =116464.98+24250+475192.23 -> 615907.21 | I17: =98027.03+203257.17+56562+6111 -> 363957.2 | J17: =292309.63+3 -> 292312.63 | K17: 195965.83 | L17: 1022901.4 | M17: 139477.83 | N17: 365063.49 | O17: 4552194.2 | P17: =SUM(D17:O17) -> 8358909.6
C18: إجمالي الايرادات اخرى | D18: =SUM(D14:D17) -> 303660.38 | E18: =SUM(E14:E17) -> 451521.77 | F18: =SUM(F14:F17) -> 463914.76 | G18: =SUM(G14:G17) -> 547927.61 | H18: =SUM(H14:H17) -> 1040476.5 | I18: =SUM(I14:I17) -> 743698.47 | J18: =SUM(J14:J17) -> 510545.48 | K18: =SUM(K14:K17) -> 598022.75 | ... O18: =SUM(O14:O17) -> 4775647.5 | P18: =SUM(D18:O18) -> 11419102
C19: مجمل الربح | D19: =D13+D18 -> 303660.38 | E19: =E13+E18 -> 451521.77 | F19: =F13+F18 -> 463914.76 | G19: =G13+G18 -> 547927.61 | H19: =H13+H18 -> 1040476.5 | I19: =I13+I18 -> 743698.47 | J19: =J13+J18 -> 510545.48 | K19: =K13+K18 -> 598022.75 | ... P19: =P13+P18 -> 11419102 | Q19: =P19-P14 -> 8417631.8
C21: EXPENSE DETAILS
C22: مرتبات الادارة | D22: =IFERROR(VLOOKUP(C22,'تقرير المصروفات حسب الشهر'!$C$10:$AD$119,2,FALSE),0) -> 853477.34 | E22: =IFERROR(VLOOKUP(C22,'تقرير المصروفات حسب الشهر'!$C$135:$AD$252,2,FALSE),0) -> 899945.03 | F22: =_xlfn.XLOOKUP(C22,'تقرير المصروفات حسب الشهر'!C261:C373,'تقرير المصروفات حسب الشهر'!D261:D373,0,0) -> 896301.69 | G22: =IFERROR(VLOOKUP(C22,'تقرير المصروفات حسب الشهر'!$C$387:$AD$495,2,FALSE),0) -> 903218.51 | H22: =IFERROR(VLOOKUP(C22,'تقرير المصروفات حسب الشهر'!$C$512:$AD$620,2,FALSE),0) -> 994803.77 | I22: =IFERROR(VLOOKUP(C22,'تقرير المصروفات حسب الشهر'!$C$637:$AD$746,2,FALSE),0) -> 1006628.8 | J22: =IFERROR(VLOOKUP(C22,'تقرير المصروفات حسب الشهر'!$C$763:$AD$872,2,FALSE),0) -> 1108595.7 | K22: =IFERROR(VLOOKUP(C22,'تقرير المصروفات حسب الشهر'!$C$889:$D$999,2,FALSE),0) -> 1266314.5 | L22: =IFERROR(VLOOKUP(C22,'تقرير المصروفات حسب الشهر'!$C$1016:$AD$1126,2,FALSE),0) -> 1184810.4 | M22: =IFERROR(VLOOKUP(C22,'تقرير المصروفات حسب الشهر'!$C$1143:$AD$1254,2,FALSE),0) -> 1313118.6 | N22: =IFERROR(VLOOKUP(C22,'تقرير المصروفات حسب الشهر'!$C$1270:$AD$1381,2,FALSE),0) -> 1305040.6 | O22: =IFERROR(VLOOKUP(C22,'تقرير المصروفات حسب الشهر'!$C$1397:$AI$1512,2,FALSE),0) -> 1313581.9 | P22: =SUM(D22:O22) -> 13045837
C23: مرتبات الفروع | D23: =IFERROR(VLOOKUP(C23,'تقرير المصروفات حسب الشهر'!$C$10:$AD$119,2,FALSE),0) -> 0 | E23: =IFERROR(VLOOKUP(C23,'تقرير المصروفات حسب الشهر'!$C$135:$AD$252,2,FALSE),0) -> 365 | F23: =_xlfn.XLOOKUP(C23,'تقرير المصروفات حسب الشهر'!C262:C374,'تقرير المصروفات حسب الشهر'!D262:D374,0,0) -> 0 | G23: =IFERROR(VLOOKUP(C23,'تقرير المصروفات حسب الشهر'!$C$387:$AD$495,2,FALSE),0) -> 0 | H23: =IFERROR(VLOOKUP(C23,'تقرير المصروفات حسب الشهر'!$C$512:$AD$620,2,FALSE),0) -> 0 | I23: =IFERROR(VLOOKUP(C23,'تقرير المصروفات حسب الشهر'!$C$637:$AD$746,2,FALSE),0) -> 0 | J23: =IFERROR(VLOOKUP(C23,'تقرير المصروفات حسب الشهر'!$C$763:$AD$872,2,FALSE),0) -> 0 | K23: =IFERROR(VLOOKUP(C23,'تقرير المصروفات حسب الشهر'!$C$889:$D$999,2,FALSE),0) -> 0 | L23: =IFERROR(VLOOKUP(C23,'تقرير المصروفات حسب الشهر'!$C$1016:$AD$1126,2,FALSE),0) -> 0 | M23: =IFERROR(VLOOKUP(C23,'تقرير المصروفات حسب الشهر'!$C$1143:$AD$1254,2,FALSE),0) -> 0 | N23: =IFERROR(VLOOKUP(C23,'تقرير المصروفات حسب الشهر'!$C$1270:$AD$1381,2,FALSE),0) -> 0 | O23: =IFERROR(VLOOKUP(C23,'تقرير المصروفات حسب الشهر'!$C$1397:$AI$1512,2,FALSE),0) -> 0 | P23: =SUM(D23:O23) -> 365
C24: الكهرباء | D24: =IFERROR(VLOOKUP(C24,'تقرير المصروفات حسب الشهر'!$C$10:$AD$119,2,FALSE),0) -> 2925 | E24: =IFERROR(VLOOKUP(C24,'تقرير المصروفات حسب الشهر'!$C$135:$AD$252,2,FALSE),0) -> 1000 | F24: =_xlfn.XLOOKUP(C24,'تقرير المصروفات حسب الشهر'!C263:C375,'تقرير المصروفات حسب الشهر'!D263:D375,0,0) -> 17462 | G24: =IFERROR(VLOOKUP(C24,'تقرير المصروفات حسب الشهر'!$C$387:$AD$495,2,FALSE),0) -> 2000 | H24: =IFERROR(VLOOKUP(C24,'تقرير المصروفات حسب الشهر'!$C$512:$AD$620,2,FALSE),0) -> 6374 | I24: =IFERROR(VLOOKUP(C24,'تقرير المصروفات حسب الشهر'!$C$637:$AD$746,2,FALSE),0) -> 22158 | J24: =IFERROR(VLOOKUP(C24,'تقرير المصروفات حسب الشهر'!$C$763:$AD$872,2,FALSE),0) -> 18677 | K24: =IFERROR(VLOOKUP(C24,'تقرير المصروفات حسب الشهر'!$C$889:$D$999,2,FALSE),0) -> 12995 | L24: =IFERROR(VLOOKUP(C24,'تقرير المصروفات حسب الشهر'!$C$1016:$AD$1126,2,FALSE),0) -> 11244 | M24: =IFERROR(VLOOKUP(C24,'تقرير المصروفات حسب الشهر'!$C$1143:$AD$1254,2,FALSE),0) -> 42424.75 | N24: =IFERROR(VLOOKUP(C24,'تقرير المصروفات حسب الشهر'!$C$1270:$AD$1381,2,FALSE),0) -> 16611 | O24: =IFERROR(VLOOKUP(C24,'تقرير المصروفات حسب الشهر'!$C$1397:$AI$1512,2,FALSE),0) -> 8245 | P24: =SUM(D24:O24) -> 162115.75
C25: المياه | D25: =IFERROR(VLOOKUP(C25,'تقرير المصروفات حسب الشهر'!$C$10:$AD$119,2,FALSE),0) -> 0 | E25: =IFERROR(VLOOKUP(C25,'تقرير المصروفات حسب الشهر'!$C$135:$AD$252,2,FALSE),0) -> 0 | F25: =_xlfn.XLOOKUP(C25,'تقرير المصروفات حسب الشهر'!C264:C376,'تقرير المصروفات حسب الشهر'!D264:D376,0,0) -> 0 | G25: =IFERROR(VLOOKUP(C25,'تقرير المصروفات حسب الشهر'!$C$387:$AD$495,2,FALSE),0) -> 0 | H25: =IFERROR(VLOOKUP(C25,'تقرير المصروفات حسب الشهر'!$C$512:$AD$620,2,FALSE),0) -> 0 | I25: =IFERROR(VLOOKUP(C25,'تقرير المصروفات حسب الشهر'!$C$637:$AD$746,2,FALSE),0) -> 0 | J25: =IFERROR(VLOOKUP(C25,'تقرير المصروفات حسب الشهر'!$C$763:$AD$872,2,FALSE),0) -> 306 | K25: =IFERROR(VLOOKUP(C25,'تقرير المصروفات حسب الشهر'!$C$889:$D$999,2,FALSE),0) -> 0 | L25: =IFERROR(VLOOKUP(C25,'تقرير المصروفات حسب الشهر'!$C$1016:$AD$1126,2,FALSE),0) -> 0 | M25: =IFERROR(VLOOKUP(C25,'تقرير المصروفات حسب الشهر'!$C$1143:$AD$1254,2,FALSE),0) -> 0 | N25: =IFERROR(VLOOKUP(C25,'تقرير المصروفات حسب الشهر'!$C$1270:$AD$1381,2,FALSE),0) -> 0 | O25: =IFERROR(VLOOKUP(C25,'تقرير المصروفات حسب الشهر'!$C$1397:$AI$1512,2,FALSE),0) -> 0 | P25: =SUM(D25:O25) -> 306
C26: التليفون الارضي | D26: =IFERROR(VLOOKUP(C26,'تقرير المصروفات حسب الشهر'!$C$10:$AD$119,2,FALSE),0) -> 700 | E26: =IFERROR(VLOOKUP(C26,'تقرير المصروفات حسب الشهر'!$C$135:$AD$252,2,FALSE),0) -> 0 | F26: =_xlfn.XLOOKUP(C26,'تقرير المصروفات حسب الشهر'!C265:C377,'تقرير المصروفات حسب الشهر'!D265:D377,0,0) -> 800 | G26: =IFERROR(VLOOKUP(C26,'تقرير المصروفات حسب الشهر'!$C$387:$AD$495,2,FALSE),0) -> 0 | H26: =IFERROR(VLOOKUP(C26,'تقرير المصروفات حسب الشهر'!$C$512:$AD$620,2,FALSE),0) -> 0 | I26: =IFERROR(VLOOKUP(C26,'تقرير المصروفات حسب الشهر'!$C$637:$AD$746,2,FALSE),0) -> 1600 | J26: =IFERROR(VLOOKUP(C26,'تقرير المصروفات حسب الشهر'!$C$763:$AD$872,2,FALSE),0) -> 0 | K26: =IFERROR(VLOOKUP(C26,'تقرير المصروفات حسب الشهر'!$C$889:$D$999,2,FALSE),0) -> 0 | L26: =IFERROR(VLOOKUP(C26,'تقرير المصروفات حسب الشهر'!$C$1016:$AD$1126,2,FALSE),0) -> 0 | M26: =IFERROR(VLOOKUP(C26,'تقرير المصروفات حسب الشهر'!$C$1143:$AD$1254,2,FALSE),0) -> 920 | N26: =IFERROR(VLOOKUP(C26,'تقرير المصروفات حسب الشهر'!$C$1270:$AD$1381,2,FALSE),0) -> 600 | O26: =IFERROR(VLOOKUP(C26,'تقرير المصروفات حسب الشهر'!$C$1397:$AI$1512,2,FALSE),0) -> 0 | P26: =SUM(D26:O26) -> 4620
C27: الايجار - الصيدلية | D27: =IFERROR(VLOOKUP(C27,'تقرير المصروفات حسب الشهر'!$C$10:$AD$119,2,FALSE),0) -> 0 | E27: =IFERROR(VLOOKUP(C27,'تقرير المصروفات حسب الشهر'!$C$135:$AD$252,2,FALSE),0) -> 0 | F27: =_xlfn.XLOOKUP(C27,'تقرير المصروفات حسب الشهر'!C266:C378,'تقرير المصروفات حسب الشهر'!D266:D378,0,0) -> 0 | G27: =IFERROR(VLOOKUP(C27,'تقرير المصروفات حسب الشهر'!$C$387:$AD$495,2,FALSE),0) -> 0 | H27: =IFERROR(VLOOKUP(C27,'تقرير المصروفات حسب الشهر'!$C$512:$AD$620,2,FALSE),0) -> 0 | I27: =IFERROR(VLOOKUP(C27,'تقرير المصروفات حسب الشهر'!$C$637:$AD$746,2,FALSE),0) -> 0 | J27: =IFERROR(VLOOKUP(C27,'تقرير المصروفات حسب الشهر'!$C$763:$AD$872,2,FALSE),0) -> 0 | K27: =IFERROR(VLOOKUP(C27,'تقرير المصروفات حسب الشهر'!$C$889:$D$999,2,FALSE),0) -> 0 | L27: =IFERROR(VLOOKUP(C27,'تقرير المصروفات حسب الشهر'!$C$1016:$AD$1126,2,FALSE),0) -> 0 | M27: =IFERROR(VLOOKUP(C27,'تقرير المصروفات حسب الشهر'!$C$1143:$AD$1254,2,FALSE),0) -> 0 | N27: =IFERROR(VLOOKUP(C27,'تقرير المصروفات حسب الشهر'!$C$1270:$AD$1381,2,FALSE),0) -> 0 | O27: =IFERROR(VLOOKUP(C27,'تقرير المصروفات حسب الشهر'!$C$1397:$AI$1512,2,FALSE),0) -> 0 | P27: =SUM(D27:O27) -> 0
C28: الايجار - الادارة | D28: =IFERROR(VLOOKUP(C28,'تقرير المصروفات حسب الشهر'!$C$10:$AD$119,2,FALSE),0) -> 100000 | E28: =IFERROR(VLOOKUP(C28,'تقرير المصروفات حسب الشهر'!$C$135:$AD$252,2,FALSE),0) -> 100000 | F28: =_xlfn.XLOOKUP(C28,'تقرير المصروفات حسب الشهر'!C267:C379,'تقرير المصروفات حسب الشهر'!D267:D379,0,0) -> 100000 | G28: =IFERROR(VLOOKUP(C28,'تقرير المصروفات حسب الشهر'!$C$387:$AD$495,2,FALSE),0) -> 100000 | H28: =IFERROR(VLOOKUP(C28,'تقرير المصروفات حسب الشهر'!$C$512:$AD$620,2,FALSE),0) -> 100000 | I28: =IFERROR(VLOOKUP(C28,'تقرير المصروفات حسب الشهر'!$C$637:$AD$746,2,FALSE),0) -> 100000 | J28: =IFERROR(VLOOKUP(C28,'تقرير المصروفات حسب الشهر'!$C$763:$AD$872,2,FALSE),0) -> 100000 | K28: =IFERROR(VLOOKUP(C28,'تقرير المصروفات حسب الشهر'!$C$889:$D$999,2,FALSE),0) -> 100000 | L28: =IFERROR(VLOOKUP(C28,'تقرير المصروفات حسب الشهر'!$C$1016:$AD$1126,2,FALSE),0) -> 100000 | M28: =IFERROR(VLOOKUP(C28,'تقرير المصروفات حسب الشهر'!$C$1143:$AD$1254,2,FALSE),0) -> 100000 | N28: =IFERROR(VLOOKUP(C28,'تقرير المصروفات حسب الشهر'!$C$1270:$AD$1381,2,FALSE),0) -> 50000 | O28: =IFERROR(VLOOKUP(C28,'تقرير المصروفات حسب الشهر'!$C$1397:$AI$1512,2,FALSE),0) -> 50000 | P28: =SUM(D28:O28) -> 1100000
C29: ايجارات متنوعه | D29: =IFERROR(VLOOKUP(C29,'تقرير المصروفات حسب الشهر'!$C$10:$AD$119,2,FALSE),0) -> 40610 | E29: =IFERROR(VLOOKUP(C29,'تقرير المصروفات حسب الشهر'!$C$135:$AD$252,2,FALSE),0) -> 40610 | F29: =_xlfn.XLOOKUP(C29,'تقرير المصروفات حسب الشهر'!C268:C380,'تقرير المصروفات حسب الشهر'!D268:D380,0,0) -> 40610 | G29: =IFERROR(VLOOKUP(C29,'تقرير المصروفات حسب الشهر'!$C$387:$AD$495,2,FALSE),0) -> 40610 | H29: =IFERROR(VLOOKUP(C29,'تقرير المصروفات حسب الشهر'!$C$512:$AD$620,2,FALSE),0) -> 40610 | I29: =IFERROR(VLOOKUP(C29,'تقرير المصروفات حسب الشهر'!$C$637:$AD$746,2,FALSE),0) -> 40610 | J29: =IFERROR(VLOOKUP(C29,'تقرير المصروفات حسب الشهر'!$C$763:$AD$872,2,FALSE),0) -> 41900 | K29: =IFERROR(VLOOKUP(C29,'تقرير المصروفات حسب الشهر'!$C$889:$D$999,2,FALSE),0) -> 41900 | L29: =IFERROR(VLOOKUP(C29,'تقرير المصروفات حسب الشهر'!$C$1016:$AD$1126,2,FALSE),0) -> 43220 | M29: =IFERROR(VLOOKUP(C29,'تقرير المصروفات حسب الشهر'!$C$1143:$AD$1254,2,FALSE),0) -> 41900 | N29: =IFERROR(VLOOKUP(C29,'تقرير المصروفات حسب الشهر'!$C$1270:$AD$1381,2,FALSE),0) -> 43330 | O29: =IFERROR(VLOOKUP(C29,'تقرير المصروفات حسب الشهر'!$C$1397:$AI$1512,2,FALSE),0) -> 43330 | P29: =SUM(D29:O29) -> 499240
C30: ادوات مكتبية | D30: =IFERROR(VLOOKUP(C30,'تقرير المصروفات حسب الشهر'!$C$10:$AD$119,2,FALSE),0) -> 1255 | E30: =IFERROR(VLOOKUP(C30,'تقرير المصروفات حسب الشهر'!$C$135:$AD$252,2,FALSE),0) -> 7710 | F30: =_xlfn.XLOOKUP(C30,'تقرير المصروفات حسب الشهر'!C269:C381,'تقرير المصروفات حسب الشهر'!D269:D381,0,0) -> 3555.6 | G30: =IFERROR(VLOOKUP(C30,'تقرير المصروفات حسب الشهر'!$C$387:$AD$495,2,FALSE),0) -> 9375 | H30: =IFERROR(VLOOKUP(C30,'تقرير المصروفات حسب الشهر'!$C$512:$AD$620,2,FALSE),0) -> 2000 | I30: =IFERROR(VLOOKUP(C30,'تقرير المصروفات حسب الشهر'!$C$637:$AD$746,2,FALSE),0) -> 8290.25 | J30: =IFERROR(VLOOKUP(C30,'تقرير المصروفات حسب الشهر'!$C$763:$AD$872,2,FALSE),0) -> 1123 | K30: =IFERROR(VLOOKUP(C30,'تقرير المصروفات حسب الشهر'!$C$889:$D$999,2,FALSE),0) -> 12220 | L30: =IFERROR(VLOOKUP(C30,'تقرير المصروفات حسب الشهر'!$C$1016:$AD$1126,2,FALSE),0) -> 1000 | M30: =IFERROR(VLOOKUP(C30,'تقرير المصروفات حسب الشهر'!$C$1143:$AD$1254,2,FALSE),0) -> 1000 | N30: =IFERROR(VLOOKUP(C30,'تقرير المصروفات حسب الشهر'!$C$1270:$AD$1381,2,FALSE),0) -> 1650 | O30: =IFERROR(VLOOKUP(C30,'تقرير المصروفات حسب الشهر'!$C$1397:$AI$1512,2,FALSE),0) -> 10375 | P30: =SUM(D30:O30) -> 59553.85
C31: فواتير الموبايل | D31: =IFERROR(VLOOKUP(C31,'تقرير المصروفات حسب الشهر'!$C$10:$AD$119,2,FALSE),0) -> 11807.53 | E31: =IFERROR(VLOOKUP(C31,'تقرير المصروفات حسب الشهر'!$C$135:$AD$252,2,FALSE),0) -> 15279.64 | F31: =_xlfn.XLOOKUP(C31,'تقرير المصروفات حسب الشهر'!C270:C382,'تقرير المصروفات حسب الشهر'!D270:D382,0,0) -> 12903.64 | G31: =IFERROR(VLOOKUP(C31,'تقرير المصروفات حسب الشهر'!$C$387:$AD$495,2,FALSE),0) -> 12719.11 | H31: =IFERROR(VLOOKUP(C31,'تقرير المصروفات حسب الشهر'!$C$512:$AD$620,2,FALSE),0) -> 13043.11 | I31: =IFERROR(VLOOKUP(C31,'تقرير المصروفات حسب الشهر'!$C$637:$AD$746,2,FALSE),0) -> 11919.11 | J31: =IFERROR(VLOOKUP(C31,'تقرير المصروفات حسب الشهر'!$C$763:$AD$872,2,FALSE),0) -> 12253.64 | K31: =IFERROR(VLOOKUP(C31,'تقرير المصروفات حسب الشهر'!$C$889:$D$999,2,FALSE),0) -> 12260.68 | L31: =IFERROR(VLOOKUP(C31,'تقرير المصروفات حسب الشهر'!$C$1016:$AD$1126,2,FALSE),0) -> 12138.8 | M31: =IFERROR(VLOOKUP(C31,'تقرير المصروفات حسب الشهر'!$C$1143:$AD$1254,2,FALSE),0) -> 12580.61 | N31: =IFERROR(VLOOKUP(C31,'تقرير المصروفات حسب الشهر'!$C$1270:$AD$1381,2,FALSE),0) -> 12579.97 | O31: =IFERROR(VLOOKUP(C31,'تقرير المصروفات حسب الشهر'!$C$1397:$AI$1512,2,FALSE),0) -> 18165.74 | P31: =SUM(D31:O31) -> 157651.58
C32: مكافات مبيعات الادوية | D32: =IFERROR(VLOOKUP(C32,'تقرير المصروفات حسب الشهر'!$C$10:$AD$119,2,FALSE),0) -> 0 | E32: =IFERROR(VLOOKUP(C32,'تقرير المصروفات حسب الشهر'!$C$135:$AD$252,2,FALSE),0) -> 0 | F32: =_xlfn.XLOOKUP(C32,'تقرير المصروفات حسب الشهر'!C271:C383,'تقرير المصروفات حسب الشهر'!D271:D383,0,0) -> 0 | G32: =IFERROR(VLOOKUP(C32,'تقرير المصروفات حسب الشهر'!$C$387:$AD$495,2,FALSE),0) -> 0 | H32: =IFERROR(VLOOKUP(C32,'تقرير المصروفات حسب الشهر'!$C$512:$AD$620,2,FALSE),0) -> 0 | I32: =IFERROR(VLOOKUP(C32,'تقرير المصروفات حسب الشهر'!$C$637:$AD$746,2,FALSE),0) -> 0 | J32: =IFERROR(VLOOKUP(C32,'تقرير المصروفات حسب الشهر'!$C$763:$AD$872,2,FALSE),0) -> 275 | K32: =IFERROR(VLOOKUP(C32,'تقرير المصروفات حسب الشهر'!$C$889:$D$999,2,FALSE),0) -> 0 | L32: =IFERROR(VLOOKUP(C32,'تقرير المصروفات حسب الشهر'!$C$1016:$AD$1126,2,FALSE),0) -> 0 | M32: =IFERROR(VLOOKUP(C32,'تقرير المصروفات حسب الشهر'!$C$1143:$AD$1254,2,FALSE),0) -> 0 | N32: =IFERROR(VLOOKUP(C32,'تقرير المصروفات حسب الشهر'!$C$1270:$AD$1381,2,FALSE),0) -> 0 | O32: =IFERROR(VLOOKUP(C32,'تقرير المصروفات حسب الشهر'!$C$1397:$AI$1512,2,FALSE),0) -> 0 | P32: =SUM(D32:O32) -> 275
C33: مكافات مبيعات التجميل | D33: =IFERROR(VLOOKUP(C33,'تقرير المصروفات حسب الشهر'!$C$10:$AD$119,2,FALSE),0) -> 1000 | E33: =IFERROR(VLOOKUP(C33,'تقرير المصروفات حسب الشهر'!$C$135:$AD$252,2,FALSE),0) -> 3715 | F33: =_xlfn.XLOOKUP(C33,'تقرير المصروفات حسب الشهر'!C272:C384,'تقرير المصروفات حسب الشهر'!D272:D384,0,0) -> 1205 | G33: =IFERROR(VLOOKUP(C33,'تقرير المصروفات حسب الشهر'!$C$387:$AD$495,2,FALSE),0) -> 1500 | H33: =IFERROR(VLOOKUP(C33,'تقرير المصروفات حسب الشهر'!$C$512:$AD$620,2,FALSE),0) -> 13940 | I33: =IFERROR(VLOOKUP(C33,'تقرير المصروفات حسب الشهر'!$C$637:$AD$746,2,FALSE),0) -> 4862.5 | J33: =IFERROR(VLOOKUP(C33,'تقرير المصروفات حسب الشهر'!$C$763:$AD$872,2,FALSE),0) -> 26085 | K33: =IFERROR(VLOOKUP(C33,'تقرير المصروفات حسب الشهر'!$C$889:$D$999,2,FALSE),0) -> 4698 | L33: =IFERROR(VLOOKUP(C33,'تقرير المصروفات حسب الشهر'!$C$1016:$AD$1126,2,FALSE),0) -> 8555 | M33: =IFERROR(VLOOKUP(C33,'تقرير المصروفات حسب الشهر'!$C$1143:$AD$1254,2,FALSE),0) -> 31872 | N33: =IFERROR(VLOOKUP(C33,'تقرير المصروفات حسب الشهر'!$C$1270:$AD$1381,2,FALSE),0) -> 1900 | O33: =IFERROR(VLOOKUP(C33,'تقرير المصروفات حسب الشهر'!$C$1397:$AI$1512,2,FALSE),0) -> 24851 | P33: =SUM(D33:O33) -> 124183.5
... C131: فوائد القروض - بنك القاهرة BDC | D131: =IFERROR(VLOOKUP(C131,'تقرير المصروفات حسب الشهر'!$C$10:$AD$119,2,FALSE),0) -> 24094.78 | E131: =IFERROR(VLOOKUP(C131,'تقرير المصروفات حسب الشهر'!$C$135:$AD$252,2,FALSE),0) -> 24094.78 | F131: =_xlfn.XLOOKUP(C131,'تقرير المصروفات حسب الشهر'!C370:C482,'تقرير المصروفات حسب الشهر'!D370:D482,0,0) -> 24094.78 | G131: =IFERROR(VLOOKUP(C131,'تقرير المصروفات حسب الشهر'!$C$387:$AD$495,2,FALSE),0) -> 24094.78 | H131: =IFERROR(VLOOKUP(C131,'تقرير المصروفات حسب الشهر'!$C$512:$AD$620,2,FALSE),0) -> 24094.78 | I131: =IFERROR(VLOOKUP(C131,'تقرير المصروفات حسب الشهر'!$C$637:$AD$746,2,FALSE),0) -> 24094.78 | J131: =IFERROR(VLOOKUP(C131,'تقرير المصروفات حسب الشهر'!$C$763:$AD$872,2,FALSE),0) -> 24094.78 | K131: =IFERROR(VLOOKUP(C131,'تقرير المصروفات حسب الشهر'!$C$889:$D$999,2,FALSE),0) -> 19385.65 | L131: =IFERROR(VLOOKUP(C131,'تقرير المصروفات حسب الشهر'!$C$1016:$AD$1126,2,FALSE),0) -> 18941.97 | M131: =IFERROR(VLOOKUP(C131,'تقرير المصروفات حسب الشهر'!$C$1143:$AD$1254,2,FALSE),0) -> 18489.74 | N131: =IFERROR(VLOOKUP(C131,'تقرير المصروفات حسب الشهر'!$C$1270:$AD$1381,2,FALSE),0) -> 18028.79 | O131: =IFERROR(VLOOKUP(C131,'تقرير المصروفات حسب الشهر'!$C$1397:$AI$1512,2,FALSE),0) -> 17558.96 | P131: =SUM(D131:O131) -> 261068.57
C132: اتعاب محاماه | D132: =IFERROR(VLOOKUP(C132,'تقرير المصروفات حسب الشهر'!$C$10:$AD$124,2,FALSE),0) -> 18700 | E132: =IFERROR(VLOOKUP(C132,'تقرير المصروفات حسب الشهر'!$C$135:$AD$252,2,FALSE),0) -> 28000 | F132: =_xlfn.XLOOKUP(C132,'تقرير المصروفات حسب الشهر'!C371:C483,'تقرير المصروفات حسب الشهر'!D371:D483,0,0) -> 6000 | G132: =IFERROR(VLOOKUP(C132,'تقرير المصروفات حسب الشهر'!$C$387:$AD$495,2,FALSE),0) -> 0 | H132: =IFERROR(VLOOKUP(C132,'تقرير المصروفات حسب الشهر'!$C$512:$AD$621,2,FALSE),0) -> 530 | I132: =IFERROR(VLOOKUP(C132,'تقرير المصروفات حسب الشهر'!$C$637:$AD$746,2,FALSE),0) -> 20000 | J132: =IFERROR(VLOOKUP(C132,'تقرير المصروفات حسب الشهر'!$C$763:$AD$872,2,FALSE),0) -> 10000 | K132: =IFERROR(VLOOKUP(C132,'تقرير المصروفات حسب الشهر'!$C$889:$D$999,2,FALSE),0) -> 500 | L132: =IFERROR(VLOOKUP(C132,'تقرير المصروفات حسب الشهر'!$C$1016:$AD$1126,2,FALSE),0) -> 0 | M132: =IFERROR(VLOOKUP(C132,'تقرير المصروفات حسب الشهر'!$C$1143:$AD$1254,2,FALSE),0) -> 0 | N132: =IFERROR(VLOOKUP(C132,'تقرير المصروفات حسب الشهر'!$C$1270:$AD$1381,2,FALSE),0) -> 0 | O132: =IFERROR(VLOOKUP(C132,'تقرير المصروفات حسب الشهر'!$C$1397:$AI$1512,2,FALSE),0) -> 11470 | P132: =SUM(D132:O132) -> 95200
C133: خصم أبليكيشن | D133: =IFERROR(VLOOKUP(C133,'تقرير المصروفات حسب الشهر'!$C$10:$AD$119,2,FALSE),0) -> 0 | E133: =IFERROR(VLOOKUP(C133,'تقرير المصروفات حسب الشهر'!$C$135:$AD$252,2,FALSE),0) -> 0 | F133: =_xlfn.XLOOKUP(C133,'تقرير المصروفات حسب الشهر'!C372:C484,'تقرير المصروفات حسب الشهر'!D372:D484,0,0) -> 0 | G133: =IFERROR(VLOOKUP(C133,'تقرير المصروفات حسب الشهر'!$C$387:$AD$495,2,FALSE),0) -> 0 | H133: =IFERROR(VLOOKUP(C133,'تقرير المصروفات حسب الشهر'!$C$512:$AD$620,2,FALSE),0) -> 0 | I133: =IFERROR(VLOOKUP(C133,'تقرير المصروفات حسب الشهر'!$C$637:$AD$746,2,FALSE),0) -> 0 | J133: =IFERROR(VLOOKUP(C133,'تقرير المصروفات حسب الشهر'!$C$763:$AD$872,2,FALSE),0) -> 0 | K133: =IFERROR(VLOOKUP(C133,'تقرير المصروفات حسب الشهر'!$C$889:$D$999,2,FALSE),0) -> 0 | L133: =IFERROR(VLOOKUP(C133,'تقرير المصروفات حسب الشهر'!$C$1016:$AD$1126,2,FALSE),0) -> 0 | M133: =IFERROR(VLOOKUP(C133,'تقرير المصروفات حسب الشهر'!$C$1143:$AD$1254,2,FALSE),0) -> 0 | N133: =IFERROR(VLOOKUP(C133,'تقرير المصروفات حسب الشهر'!$C$1270:$AD$1381,2,FALSE),0) -> 0 | O133: =IFERROR(VLOOKUP(C133,'تقرير المصروفات حسب الشهر'!$C$1397:$AI$1512,2,FALSE),0) -> 0 | P133: =SUM(D133:O133) -> 0
C134: عمولات ادارية | D134: =IFERROR(VLOOKUP(C134,'تقرير المصروفات حسب الشهر'!$C$10:$AD$121,2,FALSE),0) -> 0 | E134: =IFERROR(VLOOKUP(C134,'تقرير المصروفات حسب الشهر'!$C$135:$AD$252,2,FALSE),0) -> 145389.75 | F134: =_xlfn.XLOOKUP(C134,'تقرير المصروفات حسب الشهر'!C373:C485,'تقرير المصروفات حسب الشهر'!D373:D485,0,0) -> 145389.75 | G134: =IFERROR(VLOOKUP(C134,'تقرير المصروفات حسب الشهر'!$C$387:$AD$498,2,FALSE),0) -> 145389.75 | H134: =IFERROR(VLOOKUP(C134,'تقرير المصروفات حسب الشهر'!$C$512:$AD$628,2,FALSE),0) -> 145389.75 | I134: =IFERROR(VLOOKUP(C134,'تقرير المصروفات حسب الشهر'!$C$637:$AD$749,2,FALSE),0) -> 145389.75 | J134: =IFERROR(VLOOKUP(C134,'تقرير المصروفات حسب الشهر'!$C$763:$AD$878,2,FALSE),0) -> 145389.75 | K134: =IFERROR(VLOOKUP(C134,'تقرير المصروفات حسب الشهر'!$C$889:$D$1005,2,FALSE),0) -> 145389.75 | L134: =IFERROR(VLOOKUP(C134,'تقرير المصروفات حسب الشهر'!$C$1016:$AD$1130,2,FALSE),0) -> 145389.75 | M134: =IFERROR(VLOOKUP(C134,'تقرير المصروفات حسب الشهر'!$C$1143:$AD$1259,2,FALSE),0) -> 145389.75 | N134: =IFERROR(VLOOKUP(C134,'تقرير المصروفات حسب الشهر'!$C$1270:$AD$1384,2,FALSE),0) -> 145389.75 | O134: =IFERROR(VLOOKUP(C134,'تقرير المصروفات حسب الشهر'!$C$1397:$AI$1512,2,FALSE),0) -> 92000 | P134: =SUM(D134:O134) -> 1545897.5
D135: =IFERROR(VLOOKUP(C135,'تقرير المصروفات حسب الشهر'!$C$10:$AD$119,2,FALSE),0) -> 0 | E135: =IFERROR(VLOOKUP(C135,'تقرير المصروفات حسب الشهر'!$C$135:$AD$252,2,FALSE),0) -> 0 | F135: =_xlfn.XLOOKUP(C135,'تقرير المصروفات حسب الشهر'!C374:C486,'تقرير المصروفات حسب الشهر'!D374:D486,0,0) -> 0 | G135: =IFERROR(VLOOKUP(C135,'تقرير المصروفات حسب الشهر'!$C$387:$AD$495,2,FALSE),0) -> 0 | H135: =IFERROR(VLOOKUP(C135,'تقرير المصروفات حسب الشهر'!$C$512:$AD$620,2,FALSE),0) -> 0 | I135: =IFERROR(VLOOKUP(C135,'تقرير المصروفات حسب الشهر'!$C$637:$AD$746,2,FALSE),0) -> 0 | J135: =IFERROR(VLOOKUP(C135,'تقرير المصروفات حسب الشهر'!$C$763:$AD$872,2,FALSE),0) -> 0 | K135: =IFERROR(VLOOKUP(C135,'تقرير المصروفات حسب الشهر'!$C$889:$D$999,2,FALSE),0) -> 0 | L135: =IFERROR(VLOOKUP(C135,'تقرير المصروفات حسب الشهر'!$C$1016:$AD$1126,2,FALSE),0) -> 0 | M135: =IFERROR(VLOOKUP(C135,'تقرير المصروفات حسب الشهر'!$C$1143:$AD$1254,2,FALSE),0) -> 0 | N135: =IFERROR(VLOOKUP(C135,'تقرير المصروفات حسب الشهر'!$C$1270:$AD$1381,2,FALSE),0) -> 0 | O135: =IFERROR(VLOOKUP(C135,'تقرير المصروفات حسب الشهر'!$C$1397:$AI$1512,2,FALSE),0) -> 0 | P135: =SUM(D135:O135) -> 0
D136: =IFERROR(VLOOKUP(C136,'تقرير المصروفات حسب الشهر'!$C$10:$AD$119,2,FALSE),0) -> 0 | E136: =IFERROR(VLOOKUP(C136,'تقرير المصروفات حسب الشهر'!$C$135:$AD$252,2,FALSE),0) -> 0 | F136: =_xlfn.XLOOKUP(C136,'تقرير المصروفات حسب الشهر'!C375:C487,'تقرير المصروفات حسب الشهر'!D375:D487,0,0) -> 0 | G136: =IFERROR(VLOOKUP(C136,'تقرير المصروفات حسب الشهر'!$C$387:$AD$495,2,FALSE),0) -> 0 | H136: =IFERROR(VLOOKUP(C136,'تقرير المصروفات حسب الشهر'!$C$512:$AD$620,2,FALSE),0) -> 0 | I136: =IFERROR(VLOOKUP(C136,'تقرير المصروفات حسب الشهر'!$C$637:$AD$746,2,FALSE),0) -> 0 | J136: =IFERROR(VLOOKUP(C136,'تقرير المصروفات حسب الشهر'!$C$763:$AD$872,2,FALSE),0) -> 0 | K136: =IFERROR(VLOOKUP(C136,'تقرير المصروفات حسب الشهر'!$C$889:$D$999,2,FALSE),0) -> 0 | L136: =IFERROR(VLOOKUP(C136,'تقرير المصروفات حسب الشهر'!$C$1016:$AD$1126,2,FALSE),0) -> 0 | M136: =IFERROR(VLOOKUP(C136,'تقرير المصروفات حسب الشهر'!$C$1143:$AD$1254,2,FALSE),0) -> 0 | N136: =IFERROR(VLOOKUP(C136,'تقرير المصروفات حسب الشهر'!$C$1270:$AD$1381,2,FALSE),0) -> 0 | O136: =IFERROR(VLOOKUP(C136,'تقرير المصروفات حسب الشهر'!$C$1397:$AI$1512,2,FALSE),0) -> 0 | P136: =SUM(D136:O136) -> 0
D137: =IFERROR(VLOOKUP(C137,'تقرير المصروفات حسب الشهر'!$C$10:$AD$119,2,FALSE),0) -> 0 | E137: =IFERROR(VLOOKUP(C137,'تقرير المصروفات حسب الشهر'!$C$135:$AD$252,2,FALSE),0) -> 0 | F137: =_xlfn.XLOOKUP(C137,'تقرير المصروفات حسب الشهر'!C376:C488,'تقرير المصروفات حسب الشهر'!D376:D488,0,0) -> 0 | G137: =IFERROR(VLOOKUP(C137,'تقرير المصروفات حسب الشهر'!$C$387:$AD$495,2,FALSE),0) -> 0 | H137: =IFERROR(VLOOKUP(C137,'تقرير المصروفات حسب الشهر'!$C$512:$AD$620,2,FALSE),0) -> 0 | I137: =IFERROR(VLOOKUP(C137,'تقرير المصروفات حسب الشهر'!$C$637:$AD$746,2,FALSE),0) -> 0 | J137: =IFERROR(VLOOKUP(C137,'تقرير المصروفات حسب الشهر'!$C$763:$AD$872,2,FALSE),0) -> 0 | K137: =IFERROR(VLOOKUP(C137,'تقرير المصروفات حسب الشهر'!$C$889:$D$999,2,FALSE),0) -> 0 | L137: =IFERROR(VLOOKUP(C137,'تقرير المصروفات حسب الشهر'!$C$1016:$AD$1126,2,FALSE),0) -> 0 | M137: =IFERROR(VLOOKUP(C137,'تقرير المصروفات حسب الشهر'!$C$1143:$AD$1254,2,FALSE),0) -> 0 | N137: =IFERROR(VLOOKUP(C137,'تقرير المصروفات حسب الشهر'!$C$1270:$AD$1381,2,FALSE),0) -> 0 | O137: =IFERROR(VLOOKUP(C137,'تقرير المصروفات حسب الشهر'!$C$1397:$AI$1512,2,FALSE),0) -> 0 | P137: =SUM(D137:O137) -> 0
D138: =IFERROR(VLOOKUP(C138,'تقرير المصروفات حسب الشهر'!$C$10:$AD$119,2,FALSE),0) -> 0 | E138: =IFERROR(VLOOKUP(C138,'تقرير المصروفات حسب الشهر'!$C$135:$AD$252,2,FALSE),0) -> 0 | F138: =_xlfn.XLOOKUP(C138,'تقرير المصروفات حسب الشهر'!C377:C489,'تقرير المصروفات حسب الشهر'!D377:D489,0,0) -> 0 | G138: =IFERROR(VLOOKUP(C138,'تقرير المصروفات حسب الشهر'!$C$387:$AD$495,2,FALSE),0) -> 0 | H138: =IFERROR(VLOOKUP(C138,'تقرير المصروفات حسب الشهر'!$C$512:$AD$620,2,FALSE),0) -> 0 | I138: =IFERROR(VLOOKUP(C138,'تقرير المصروفات حسب الشهر'!$C$637:$AD$746,2,FALSE),0) -> 0 | J138: =IFERROR(VLOOKUP(C138,'تقرير المصروفات حسب الشهر'!$C$763:$AD$872,2,FALSE),0) -> 0 | K138: =IFERROR(VLOOKUP(C138,'تقرير المصروفات حسب الشهر'!$C$889:$D$999,2,FALSE),0) -> 0 | L138: =IFERROR(VLOOKUP(C138,'تقرير المصروفات حسب الشهر'!$C$1016:$AD$1126,2,FALSE),0) -> 0 | M138: =IFERROR(VLOOKUP(C138,'تقرير المصروفات حسب الشهر'!$C$1143:$AD$1254,2,FALSE),0) -> 0 | N138: =IFERROR(VLOOKUP(C138,'تقرير المصروفات حسب الشهر'!$C$1270:$AD$1381,2,FALSE),0) -> 0 | O138: =IFERROR(VLOOKUP(C138,'تقرير المصروفات حسب الشهر'!$C$1397:$AI$1512,2,FALSE),0) -> 0 | P138: =SUM(D138:O138) -> 0
D139: =IFERROR(VLOOKUP(C139,'تقرير المصروفات حسب الشهر'!$C$10:$AD$119,2,FALSE),0) -> 0 | E139: =IFERROR(VLOOKUP(C139,'تقرير المصروفات حسب الشهر'!$C$135:$AD$252,2,FALSE),0) -> 0 | F139: =_xlfn.XLOOKUP(C139,'تقرير المصروفات حسب الشهر'!C378:C490,'تقرير المصروفات حسب الشهر'!D378:D490,0,0) -> 0 | G139: =IFERROR(VLOOKUP(C139,'تقرير المصروفات حسب الشهر'!$C$387:$AD$495,2,FALSE),0) -> 0 | H139: =IFERROR(VLOOKUP(C139,'تقرير المصروفات حسب الشهر'!$C$512:$AD$620,2,FALSE),0) -> 0 | I139: =IFERROR(VLOOKUP(C139,'تقرير المصروفات حسب الشهر'!$C$637:$AD$746,2,FALSE),0) -> 0 | J139: =IFERROR(VLOOKUP(C139,'تقرير المصروفات حسب الشهر'!$C$763:$AD$872,2,FALSE),0) -> 0 | K139: =IFERROR(VLOOKUP(C139,'تقرير المصروفات حسب الشهر'!$C$889:$D$999,2,FALSE),0) -> 0 | L139: =IFERROR(VLOOKUP(C139,'تقرير المصروفات حسب الشهر'!$C$1016:$AD$1126,2,FALSE),0) -> 0 | M139: =IFERROR(VLOOKUP(C139,'تقرير المصروفات حسب الشهر'!$C$1143:$AD$1254,2,FALSE),0) -> 0 | N139: =IFERROR(VLOOKUP(C139,'تقرير المصروفات حسب الشهر'!$C$1270:$AD$1381,2,FALSE),0) -> 0 | O139: =IFERROR(VLOOKUP(C139,'تقرير المصروفات حسب الشهر'!$C$1397:$AI$1512,2,FALSE),0) -> 0 | P139: =SUM(D139:O139) -> 0
C140: إجمالي المصروفات | D140: =SUM(D22:D139) -> 2115892.6 | E140: =SUM(E22:E139) -> 2113613.3 | F140: =SUM(F22:F139) -> 2233776.5 | G140: =SUM(G22:G139) -> 2115627.4 | H140: =SUM(H22:H139) -> 2137158.9 | I140: =SUM(I22:I139) -> 2344883.1 | J140: =SUM(J22:J139) -> 2516501.7 | K140: =SUM(K22:K139) -> 2613856.8 | ... O140: =SUM(O22:O139) -> 2630894.9 | P140: =SUM(D140:O140) -> 28311683
C142: مجمل الربح | D142: =D19 -> 303660.38 | E142: =E19 -> 451521.77 | F142: =F19 -> 463914.76 | G142: =G19 -> 547927.61 | H142: =H19 -> 1040476.5 | I142: =I19 -> 743698.47 | J142: =J19 -> 510545.48 | K142: =K19 -> 598022.75 | ... P142: =P19 -> 11419102
C145: صافي الربح / الخسارة | D145: =D142-D140 -> -1812232.3 | E145: =E142-E140 -> -1662091.5 | F145: =F142-F140 -> -1769861.8 | G145: =G142-G140 -> -1567699.8 | H145: =H142-H140 -> -1096682.4 | I145: =I142-I140 -> -1601184.6 | J145: =J142-J140 -> -2005956.2 | K145: =K142-K140 -> -2015834 | ... P145: =P142-P140 -> -16892581
D149: 2115892.6 | E149: 2268223.5 | F149: 2088386.8 | G149: 1970237.7 | H149: -951412.4 | J149: -1860569.5 | K149: -1870444.3 | N149: =N145+1686907.67 -> -502600.4 | O149: -1293612.2
D150: =D140-D149 -> 0 | E150: =E140-E149 -> -154610.25 | F150: =F140-F149 -> 145389.75 | G150: =G140-G149 -> 145389.75 | H150: =H149-H145 -> 145269.99 | J150: =J149-J145 -> 145386.75 | K150: =K145-K149 -> -145389.75 | O150: =O145-O149 -> 3438364.7

Sheet Aguza
C2: INCOME STATEMTN
F3: Income Statement For AGOUZA
D6: Jan | E6: February | F6: March | G6: April | H6: May | I6: June | J6: July | K6: August | L6: September | M6: October | N6: November | O6: December | P6: TOTAL
C7: INCOME DETAILS
A8: العجوزة | C8: المبيعات | D8: =D9+D10+D11 -> 4953092.3 | E8: =E9+E10+E11 -> 4819082.3 | F8: =F9+F10+F11 -> 5158662.2 | G8: =G9+G10+G11 -> 5613128.2 | H8: =H9+H10+H11 -> 5842714.7 | I8: =I9+I10+I11 -> 6079990.5 | J8: =J9+J10+J11 -> 6096124.6 | K8: =K9+K10+K11 -> 6860530.2 | ... O8: =O9+O10+O11 -> 7710153 | P8: =SUM(D8:O8) -> 74585539
C9: نقدى | D9: =VLOOKUP($A$8,'تقرير إحصائية بحجم المبيعات'!$B$7:$L$31,2,FALSE) -> 3046708.7 | E9: =VLOOKUP($A$8,'تقرير إحصائية بحجم المبيعات'!$B$42:$G$73,2,FALSE) -> 2960938.7 | F9: =VLOOKUP($A$8,'تقرير إحصائية بحجم المبيعات'!$B$78:$E$103,2,FALSE) -> 3363349.8 | G9: =VLOOKUP($A$8,'تقرير إحصائية بحجم المبيعات'!$B$112:$G$137,2,FALSE) -> 3828803.9 | H9: =VLOOKUP($A$8,'تقرير إحصائية بحجم المبيعات'!$B$147:$G$177,2,FALSE) -> 3884393.1 | I9: =VLOOKUP($A$8,'تقرير إحصائية بحجم المبيعات'!$B$182:$G$212,2,FALSE) -> 4309083.3 | J9: =VLOOKUP($A$8,'تقرير إحصائية بحجم المبيعات'!$B$217:$L$243,2,FALSE) -> 4185966 | K9: =VLOOKUP($A$8,'تقرير إحصائية بحجم المبيعات'!$B$252:$L$278,2,FALSE) -> 4835066.8 | L9: =VLOOKUP($A$8,'تقرير إحصائية بحجم المبيعات'!$B$287:$L$313,2,FALSE) -> 4505534.6 | M9: =VLOOKUP($A$8,'تقرير إحصائية بحجم المبيعات'!$B$322:$L$347,2,FALSE) -> 4705280.6 | N9: =VLOOKUP($A$8,'تقرير إحصائية بحجم المبيعات'!$B$357:$L$383,2,FALSE) -> 4700429.7 | O9: =VLOOKUP($A$8,'تقرير إحصائية بحجم المبيعات'!$B$391:$L$420,2,FALSE) -> 5046522.8 | P9: =SUM(D9:O9) -> 49372078
C10: دليفرى | D10: =VLOOKUP($A$8,'تقرير إحصائية بحجم المبيعات'!$B$7:$L$31,3,FALSE) -> 686579.51 | E10: =VLOOKUP($A$8,'تقرير إحصائية بحجم المبيعات'!$B$42:$G$73,3,FALSE) -> 664076.69 | F10: =VLOOKUP($A$8,'تقرير إحصائية بحجم المبيعات'!$B$78:$E$103,3,FALSE) -> 531594.93 | G10: =VLOOKUP($A$8,'تقرير إحصائية بحجم المبيعات'!$B$112:$G$137,3,FALSE) -> 669148.36 | H10: =VLOOKUP($A$8,'تقرير إحصائية بحجم المبيعات'!$B$147:$G$177,3,FALSE) -> 678401.42 | I10: =VLOOKUP($A$8,'تقرير إحصائية بحجم المبيعات'!$B$182:$G$212,3,FALSE) -> 657047.38 | J10: =VLOOKUP($A$8,'تقرير إحصائية بحجم المبيعات'!$B$217:$L$243,3,FALSE) -> 668506.5 | K10: =VLOOKUP($A$8,'تقرير إحصائية بحجم المبيعات'!$B$252:$L$278,3,FALSE) -> 653473.9 | L10: =VLOOKUP($A$8,'تقرير إحصائية بحجم المبيعات'!$B$287:$L$313,3,FALSE) -> 651093.14 | M10: =VLOOKUP($A$8,'تقرير إحصائية بحجم المبيعات'!$B$322:$L$347,3,FALSE) -> 837640.09 | N10: =VLOOKUP($A$8,'تقرير إحصائية بحجم المبيعات'!$B$357:$L$383,3,FALSE) -> 751344.31 | O10: =VLOOKUP($A$8,'تقرير إحصائية بحجم المبيعات'!$B$391:$L$420,3,FALSE) -> 817456.55 | P10: =SUM(D10:O10) -> 8266362.8
C11: اجل | D11: =VLOOKUP($A$8,'تقرير إحصائية بحجم المبيعات'!$B$7:$L$31,4,FALSE) -> 1219804.1 | E11: =VLOOKUP($A$8,'تقرير إحصائية بحجم المبيعات'!$B$42:$G$73,4,FALSE) -> 1194066.9 | F11: =VLOOKUP($A$8,'تقرير إحصائية بحجم المبيعات'!$B$78:$E$103,4,FALSE) -> 1263717.5 | G11: =VLOOKUP($A$8,'تقرير إحصائية بحجم المبيعات'!$B$112:$G$137,4,FALSE) -> 1115175.9 | H11: =VLOOKUP($A$8,'تقرير إحصائية بحجم المبيعات'!$B$147:$G$177,4,FALSE) -> 1279920.1 | I11: =VLOOKUP($A$8,'تقرير إحصائية بحجم المبيعات'!$B$182:$G$212,4,FALSE) -> 1113859.8 | J11: =VLOOKUP($A$8,'تقرير إحصائية بحجم المبيعات'!$B$217:$L$243,4,FALSE) -> 1241652.1 | K11: =VLOOKUP($A$8,'تقرير إحصائية بحجم المبيعات'!$B$252:$L$278,4,FALSE) -> 1371989.5 | L11: =VLOOKUP($A$8,'تقرير إحصائية بحجم المبيعات'!$B$287:$L$313,4,FALSE) -> 1817721.6 | M11: =VLOOKUP($A$8,'تقرير إحصائية بحجم المبيعات'!$B$322:$L$347,4,FALSE) -> 1949631.8 | N11: =VLOOKUP($A$8,'تقرير إحصائية بحجم المبيعات'!$B$357:$L$383,4,FALSE) -> 1533385.2 | O11: =VLOOKUP($A$8,'تقرير إحصائية بحجم المبيعات'!$B$391:$L$420,4,FALSE) -> 1846173.6 | P11: =SUM(D11:O11) -> 16947098
C12: تكلفة البضاعة المباعة | D12: =VLOOKUP($A$8,'تقرير إحصائية بحجم المبيعات'!$B$7:$L$31,11,FALSE) -> 3962640.4 | E12: =VLOOKUP($A$8,'تقرير إحصائية بحجم المبيعات'!$B$42:$L$73,11,FALSE) -> 3883691 | F12: =VLOOKUP($A$8,'تقرير إحصائية بحجم المبيعات'!$B$78:$L$103,11,FALSE) -> 4146557.4 | G12: =VLOOKUP($A$8,'تقرير إحصائية بحجم المبيعات'!$B$112:$L$137,11,FALSE) -> 4499900.3 | H12: =VLOOKUP($A$8,'تقرير إحصائية بحجم المبيعات'!$B$147:$L$177,11,FALSE) -> 4660011.1 | I12: =VLOOKUP($A$8,'تقرير إحصائية بحجم المبيعات'!$B$182:$L$212,11,FALSE) -> 4834090.2 | J12: =VLOOKUP($A$8,'تقرير إحصائية بحجم المبيعات'!$B$217:$L$243,11,FALSE) -> 4883642.4 | K12: =VLOOKUP($A$8,'تقرير إحصائية بحجم المبيعات'!$B$252:$L$278,11,FALSE) -> 5509486.1 | L12: =VLOOKUP($A$8,'تقرير إحصائية بحجم المبيعات'!$B$287:$L$313,11,FALSE) -> 5611199.8 | M12: =VLOOKUP($A$8,'تقرير إحصائية بحجم المبيعات'!$B$322:$L$347,11,FALSE) -> 5952639.3 | N12: =VLOOKUP($A$8,'تقرير إحصائية بحجم المبيعات'!$B$357:$L$383,11,FALSE) -> 5564222 | O12: =VLOOKUP($A$8,'تقرير إحصائية بحجم المبيعات'!$B$391:$L$420,11,FALSE) -> 6048273.5 | P12: =SUM(D12:O12) -> 59556353
C13: مجمل الربح | D13: =D8-D12 -> 990451.96 | E13: =E8-E12 -> 935391.28 | F13: =F8-F12 -> 1012104.8 | G13: =G8-G12 -> 1113227.9 | H13: =H8-H12 -> 1182703.5 | I13: =I8-I12 -> 1245900.2 | J13: =J8-J12 -> 1212482.2 | K13: =K8-K12 -> 1351044.2 | ... O13: =O8-O12 -> 1661879.5 | P13: =SUM(D13:O13) -> 15029186
C14: خصم نقدى | P14: =SUM(D14:O14) -> 0
C15: ارباح صرف اصناف بيع اصول | P15: =SUM(D15:O15) -> 0
C16: فائض جرد | D16: 16005.5 | E16: =1784.79-7.67 -> 1777.12 | F16: -0.21 | I16: 15.63 | K16: 0.01 | L16: 0.76 | N16: 1216.82 | P16: =SUM(D16:O16) -> 19015.63
C17: ايرادات اخرى | H17: 3850 | J17: 26300 | L17: 14000 | M17: -2000 | N17: 9000 | O17: -3200 | P17: =SUM(D17:O17) -> 47950
C18: إجمالي الايرادات اخرى | D18: =SUM(D14:D17) -> 16005.5 | E18: =SUM(E14:E17) -> 1777.12 | F18: =SUM(F14:F17) -> -0.21 | G18: =SUM(G14:G17) -> 0 | H18: =SUM(H14:H17) -> 3850 | I18: =SUM(I14:I17) -> 15.63 | J18: =SUM(J14:J17) -> 26300 | K18: =SUM(K14:K17) -> 0.01 | ... O18: =SUM(O14:O17) -> -3200 | P18: =SUM(D18:O18) -> 66965.63
C19: مجمل الربح | D19: =D13+D18 -> 1006457.5 | E19: =E13+E18 -> 937168.4 | F19: =F13+F18 -> 1012104.6 | G19: =G13+G18 -> 1113227.9 | H19: =H13+H18 -> 1186553.5 | I19: =I13+I18 -> 1245915.8 | J19: =J13+J18 -> 1238782.2 | K19: =K13+K18 -> 1351044.2 | ... O19: =O13+O18 -> 1658679.5 | P19: =SUM(D19:O19) -> 15096151
C21: EXPENSE DETAILS | D21: =D23/D8 -> 0.050035944
C22: مرتبات الادارة | D22: =IFERROR(VLOOKUP(C22,'تقرير المصروفات حسب الشهر'!$C$10:$AD$119,3,FALSE),0) -> 0 | E22: =IFERROR(VLOOKUP(C22,'تقرير المصروفات حسب الشهر'!$C$135:$AD$244,3,FALSE),0) -> 0 | F22: 0 | G22: =IFERROR(VLOOKUP(C22,'تقرير المصروفات حسب الشهر'!$C$387:$AD$495,3,FALSE),0) -> 0 | H22: =IFERROR(VLOOKUP(C22,'تقرير المصروفات حسب الشهر'!$C$512:$AD$620,3,FALSE),0) -> 0 | I22: =IFERROR(VLOOKUP(C22,'تقرير المصروفات حسب الشهر'!$C$637:$AD$746,3,FALSE),0) -> 0 | J22: =IFERROR(VLOOKUP(C22,'تقرير المصروفات حسب الشهر'!$C$763:$AD$872,3,FALSE),0) -> 0 | K22: =IFERROR(VLOOKUP(C22,'تقرير المصروفات حسب الشهر'!$C$890:$AD$999,3,FALSE),0) -> 0 | L22: =IFERROR(VLOOKUP(C22,'تقرير المصروفات حسب الشهر'!$C$1016:$AD$1126,3,FALSE),0) -> 0 | M22: =IFERROR(VLOOKUP(C22,'تقرير المصروفات حسب الشهر'!$C$1143:$AD$1254,3,FALSE),0) -> 0 | N22: =IFERROR(VLOOKUP(C22,'تقرير المصروفات حسب الشهر'!$C$1270:$AD$1381,3,FALSE),0) -> 0 | O22: =IFERROR(VLOOKUP(C22,'تقرير المصروفات حسب الشهر'!$C$1397:$AI$1512,3,FALSE),0) -> 0 | P22: =SUM(D22:O22) -> 0
C23: مرتبات الفروع | D23: =IFERROR(VLOOKUP(C23,'تقرير المصروفات حسب الشهر'!$C$10:$AD$119,3,FALSE),0) -> 247832.65 | E23: =IFERROR(VLOOKUP(C23,'تقرير المصروفات حسب الشهر'!$C$135:$AD$244,3,FALSE),0) -> 252633.85 | F23: 267258.59 | G23: =IFERROR(VLOOKUP(C23,'تقرير المصروفات حسب الشهر'!$C$387:$AD$495,3,FALSE),0) -> 268532.35 | H23: =IFERROR(VLOOKUP(C23,'تقرير المصروفات حسب الشهر'!$C$512:$AD$620,3,FALSE),0) -> 282215.71 | I23: =IFERROR(VLOOKUP(C23,'تقرير المصروفات حسب الشهر'!$C$637:$AD$746,3,FALSE),0) -> 301672.18 | J23: =IFERROR(VLOOKUP(C23,'تقرير المصروفات حسب الشهر'!$C$763:$AD$872,3,FALSE),0) -> 324699.23 | K23: =IFERROR(VLOOKUP(C23,'تقرير المصروفات حسب الشهر'!$C$890:$AD$999,3,FALSE),0) -> 323117.12 | L23: =IFERROR(VLOOKUP(C23,'تقرير المصروفات حسب الشهر'!$C$1016:$AD$1126,3,FALSE),0) -> 366497.25 | M23: =IFERROR(VLOOKUP(C23,'تقرير المصروفات حسب الشهر'!$C$1143:$AD$1254,3,FALSE),0) -> 370937.51 | N23: =IFERROR(VLOOKUP(C23,'تقرير المصروفات حسب الشهر'!$C$1270:$AD$1381,3,FALSE),0) -> 386501.24 | O23: =IFERROR(VLOOKUP(C23,'تقرير المصروفات حسب الشهر'!$C$1397:$AI$1512,3,FALSE),0) -> 397777.67 | P23: =SUM(D23:O23) -> 3789675.3
C24: الكهرباء | D24: =IFERROR(VLOOKUP(C24,'تقرير المصروفات حسب الشهر'!$C$10:$AD$119,3,FALSE),0) -> 6809 | E24: =IFERROR(VLOOKUP(C24,'تقرير المصروفات حسب الشهر'!$C$135:$AD$244,3,FALSE),0) -> 0 | F24: 5553 | G24: =IFERROR(VLOOKUP(C24,'تقرير المصروفات حسب الشهر'!$C$387:$AD$495,3,FALSE),0) -> 0 | H24: =IFERROR(VLOOKUP(C24,'تقرير المصروفات حسب الشهر'!$C$512:$AD$620,3,FALSE),0) -> 5902 | I24: =IFERROR(VLOOKUP(C24,'تقرير المصروفات حسب الشهر'!$C$637:$AD$746,3,FALSE),0) -> 4084 | J24: =IFERROR(VLOOKUP(C24,'تقرير المصروفات حسب الشهر'!$C$763:$AD$872,3,FALSE),0) -> 5313 | K24: =IFERROR(VLOOKUP(C24,'تقرير المصروفات حسب الشهر'!$C$890:$AD$999,3,FALSE),0) -> 7215 | L24: =IFERROR(VLOOKUP(C24,'تقرير المصروفات حسب الشهر'!$C$1016:$AD$1126,3,FALSE),0) -> 8346 | M24: =IFERROR(VLOOKUP(C24,'تقرير المصروفات حسب الشهر'!$C$1143:$AD$1254,3,FALSE),0) -> 7871 | N24: =IFERROR(VLOOKUP(C24,'تقرير المصروفات حسب الشهر'!$C$1270:$AD$1381,3,FALSE),0) -> 5587 | O24: =IFERROR(VLOOKUP(C24,'تقرير المصروفات حسب الشهر'!$C$1397:$AI$1512,3,FALSE),0) -> 0 | P24: =SUM(D24:O24) -> 56680
C25: المياه | D25: =IFERROR(VLOOKUP(C25,'تقرير المصروفات حسب الشهر'!$C$10:$AD$119,3,FALSE),0) -> 200 | E25: =IFERROR(VLOOKUP(C25,'تقرير المصروفات حسب الشهر'!$C$135:$AD$244,3,FALSE),0) -> 200 | F25: 200 | G25: =IFERROR(VLOOKUP(C25,'تقرير المصروفات حسب الشهر'!$C$387:$AD$495,3,FALSE),0) -> 200 | H25: =IFERROR(VLOOKUP(C25,'تقرير المصروفات حسب الشهر'!$C$512:$AD$620,3,FALSE),0) -> 0 | I25: =IFERROR(VLOOKUP(C25,'تقرير المصروفات حسب الشهر'!$C$637:$AD$746,3,FALSE),0) -> 215 | J25: =IFERROR(VLOOKUP(C25,'تقرير المصروفات حسب الشهر'!$C$763:$AD$872,3,FALSE),0) -> 0 | K25: =IFERROR(VLOOKUP(C25,'تقرير المصروفات حسب الشهر'!$C$890:$AD$999,3,FALSE),0) -> 569 | L25: =IFERROR(VLOOKUP(C25,'تقرير المصروفات حسب الشهر'!$C$1016:$AD$1126,3,FALSE),0) -> 490 | M25: =IFERROR(VLOOKUP(C25,'تقرير المصروفات حسب الشهر'!$C$1143:$AD$1254,3,FALSE),0) -> 500 | N25: =IFERROR(VLOOKUP(C25,'تقرير المصروفات حسب الشهر'!$C$1270:$AD$1381,3,FALSE),0) -> 842 | O25: =IFERROR(VLOOKUP(C25,'تقرير المصروفات حسب الشهر'!$C$1397:$AI$1512,3,FALSE),0) -> 831 | P25: =SUM(D25:O25) -> 4247
C26: التليفون الارضي | D26: =IFERROR(VLOOKUP(C26,'تقرير المصروفات حسب الشهر'!$C$10:$AD$119,3,FALSE),0) -> 500 | E26: =IFERROR(VLOOKUP(C26,'تقرير المصروفات حسب الشهر'!$C$135:$AD$244,3,FALSE),0) -> 0 | F26: 350 | G26: =IFERROR(VLOOKUP(C26,'تقرير المصروفات حسب الشهر'!$C$387:$AD$495,3,FALSE),0) -> 0 | H26: =IFERROR(VLOOKUP(C26,'تقرير المصروفات حسب الشهر'!$C$512:$AD$620,3,FALSE),0) -> 0 | I26: =IFERROR(VLOOKUP(C26,'تقرير المصروفات حسب الشهر'!$C$637:$AD$746,3,FALSE),0) -> 800 | J26: =IFERROR(VLOOKUP(C26,'تقرير المصروفات حسب الشهر'!$C$763:$AD$872,3,FALSE),0) -> 0 | K26: =IFERROR(VLOOKUP(C26,'تقرير المصروفات حسب الشهر'!$C$890:$AD$999,3,FALSE),0) -> 0 | L26: =IFERROR(VLOOKUP(C26,'تقرير المصروفات حسب الشهر'!$C$1016:$AD$1126,3,FALSE),0) -> 0 | M26: =IFERROR(VLOOKUP(C26,'تقرير المصروفات حسب الشهر'!$C$1143:$AD$1254,3,FALSE),0) -> 0 | N26: =IFERROR(VLOOKUP(C26,'تقرير المصروفات حسب الشهر'!$C$1270:$AD$1381,3,FALSE),0) -> 400 | O26: =IFERROR(VLOOKUP(C26,'تقرير المصروفات حسب الشهر'!$C$1397:$AI$1512,3,FALSE),0) -> 0 | P26: =SUM(D26:O26) -> 2050
C27: الايجار - الصيدلية | D27: =IFERROR(VLOOKUP(C27,'تقرير المصروفات حسب الشهر'!$C$10:$AD$119,3,FALSE),0) -> 100000 | E27: =IFERROR(VLOOKUP(C27,'تقرير المصروفات حسب الشهر'!$C$135:$AD$244,3,FALSE),0) -> 100000 | F27: 100000 | G27: =IFERROR(VLOOKUP(C27,'تقرير المصروفات حسب الشهر'!$C$387:$AD$495,3,FALSE),0) -> 100000 | H27: =IFERROR(VLOOKUP(C27,'تقرير المصروفات حسب الشهر'!$C$512:$AD$620,3,FALSE),0) -> 100000 | I27: =IFERROR(VLOOKUP(C27,'تقرير المصروفات حسب الشهر'!$C$637:$AD$746,3,FALSE),0) -> 100000 | J27: =IFERROR(VLOOKUP(C27,'تقرير المصروفات حسب الشهر'!$C$763:$AD$872,3,FALSE),0) -> 100000 | K27: =IFERROR(VLOOKUP(C27,'تقرير المصروفات حسب الشهر'!$C$890:$AD$999,3,FALSE),0) -> 100000 | L27: =IFERROR(VLOOKUP(C27,'تقرير المصروفات حسب الشهر'!$C$1016:$AD$1126,3,FALSE),0) -> 100000 | M27: =IFERROR(VLOOKUP(C27,'تقرير المصروفات حسب الشهر'!$C$1143:$AD$1254,3,FALSE),0) -> 100000 | N27: =IFERROR(VLOOKUP(C27,'تقرير المصروفات حسب الشهر'!$C$1270:$AD$1381,3,FALSE),0) -> 170000 | O27: =IFERROR(VLOOKUP(C27,'تقرير المصروفات حسب الشهر'!$C$1397:$AI$1512,3,FALSE),0) -> 170000 | P27: =SUM(D27:O27) -> 1340000
C28: الايجار - الادارة | D28: =IFERROR(VLOOKUP(C28,'تقرير المصروفات حسب الشهر'!$C$10:$AD$119,3,FALSE),0) -> 0 | E28: =IFERROR(VLOOKUP(C28,'تقرير المصروفات حسب الشهر'!$C$135:$AD$244,3,FALSE),0) -> 0 | F28: 0 | G28: =IFERROR(VLOOKUP(C28,'تقرير المصروفات حسب الشهر'!$C$387:$AD$495,3,FALSE),0) -> 0 | H28: =IFERROR(VLOOKUP(C28,'تقرير المصروفات حسب الشهر'!$C$512:$AD$620,3,FALSE),0) -> 0 | I28: =IFERROR(VLOOKUP(C28,'تقرير المصروفات حسب الشهر'!$C$637:$AD$746,3,FALSE),0) -> 0 | J28: =IFERROR(VLOOKUP(C28,'تقرير المصروفات حسب الشهر'!$C$763:$AD$872,3,FALSE),0) -> 0 | K28: =IFERROR(VLOOKUP(C28,'تقرير المصروفات حسب الشهر'!$C$890:$AD$999,3,FALSE),0) -> 0 | L28: =IFERROR(VLOOKUP(C28,'تقرير المصروفات حسب الشهر'!$C$1016:$AD$1126,3,FALSE),0) -> 0 | M28: =IFERROR(VLOOKUP(C28,'تقرير المصروفات حسب الشهر'!$C$1143:$AD$1254,3,FALSE),0) -> 0 | N28: =IFERROR(VLOOKUP(C28,'تقرير المصروفات حسب الشهر'!$C$1270:$AD$1381,3,FALSE),0) -> 0 | O28: =IFERROR(VLOOKUP(C28,'تقرير المصروفات حسب الشهر'!$C$1397:$AI$1512,3,FALSE),0) -> 0 | P28: =SUM(D28:O28) -> 0
C29: ايجارات متنوعه | D29: =IFERROR(VLOOKUP(C29,'تقرير المصروفات حسب الشهر'!$C$10:$AD$119,3,FALSE),0) -> 0 | E29: =IFERROR(VLOOKUP(C29,'تقرير المصروفات حسب الشهر'!$C$135:$AD$244,3,FALSE),0) -> 0 | F29: 0 | G29: =IFERROR(VLOOKUP(C29,'تقرير المصروفات حسب الشهر'!$C$387:$AD$495,3,FALSE),0) -> 0 | H29: =IFERROR(VLOOKUP(C29,'تقرير المصروفات حسب الشهر'!$C$512:$AD$620,3,FALSE),0) -> 0 | I29: =IFERROR(VLOOKUP(C29,'تقرير المصروفات حسب الشهر'!$C$637:$AD$746,3,FALSE),0) -> 0 | J29: =IFERROR(VLOOKUP(C29,'تقرير المصروفات حسب الشهر'!$C$763:$AD$872,3,FALSE),0) -> 0 | K29: =IFERROR(VLOOKUP(C29,'تقرير المصروفات حسب الشهر'!$C$890:$AD$999,3,FALSE),0) -> 0 | L29: =IFERROR(VLOOKUP(C29,'تقرير المصروفات حسب الشهر'!$C$1016:$AD$1126,3,FALSE),0) -> 0 | M29: =IFERROR(VLOOKUP(C29,'تقرير المصروفات حسب الشهر'!$C$1143:$AD$1254,3,FALSE),0) -> 0 | N29: =IFERROR(VLOOKUP(C29,'تقرير المصروفات حسب الشهر'!$C$1270:$AD$1381,3,FALSE),0) -> 0 | O29: =IFERROR(VLOOKUP(C29,'تقرير المصروفات حسب الشهر'!$C$1397:$AI$1512,3,FALSE),0) -> 0 | P29: =SUM(D29:O29) -> 0
C30: ادوات مكتبية | D30: =IFERROR(VLOOKUP(C30,'تقرير المصروفات حسب الشهر'!$C$10:$AD$119,3,FALSE),0) -> 0 | E30: =IFERROR(VLOOKUP(C30,'تقرير المصروفات حسب الشهر'!$C$135:$AD$244,3,FALSE),0) -> 65 | F30: 925.25 | G30: =IFERROR(VLOOKUP(C30,'تقرير المصروفات حسب الشهر'!$C$387:$AD$495,3,FALSE),0) -> 65 | H30: =IFERROR(VLOOKUP(C30,'تقرير المصروفات حسب الشهر'!$C$512:$AD$620,3,FALSE),0) -> 0 | I30: =IFERROR(VLOOKUP(C30,'تقرير المصروفات حسب الشهر'!$C$637:$AD$746,3,FALSE),0) -> 988.25 | J30: =IFERROR(VLOOKUP(C30,'تقرير المصروفات حسب الشهر'!$C$763:$AD$872,3,FALSE),0) -> 70 | K30: =IFERROR(VLOOKUP(C30,'تقرير المصروفات حسب الشهر'!$C$890:$AD$999,3,FALSE),0) -> 0 | L30: =IFERROR(VLOOKUP(C30,'تقرير المصروفات حسب الشهر'!$C$1016:$AD$1126,3,FALSE),0) -> 80 | M30: =IFERROR(VLOOKUP(C30,'تقرير المصروفات حسب الشهر'!$C$1143:$AD$1254,3,FALSE),0) -> 967.5 | N30: =IFERROR(VLOOKUP(C30,'تقرير المصروفات حسب الشهر'!$C$1270:$AD$1381,3,FALSE),0) -> 0 | O30: =IFERROR(VLOOKUP(C30,'تقرير المصروفات حسب الشهر'!$C$1397:$AI$1512,3,FALSE),0) -> 1200 | P30: =SUM(D30:O30) -> 4361
C31: فواتير الموبايل | D31: =IFERROR(VLOOKUP(C31,'تقرير المصروفات حسب الشهر'!$C$10:$AD$119,3,FALSE),0) -> 783.54 | E31: =IFERROR(VLOOKUP(C31,'تقرير المصروفات حسب الشهر'!$C$135:$AD$244,3,FALSE),0) -> 783.54 | F31: 783.54 | G31: =IFERROR(VLOOKUP(C31,'تقرير المصروفات حسب الشهر'!$C$387:$AD$495,3,FALSE),0) -> 791.98 | H31: =IFERROR(VLOOKUP(C31,'تقرير المصروفات حسب الشهر'!$C$512:$AD$620,3,FALSE),0) -> 721.98 | I31: =IFERROR(VLOOKUP(C31,'تقرير المصروفات حسب الشهر'!$C$637:$AD$746,3,FALSE),0) -> 721.98 | J31: =IFERROR(VLOOKUP(C31,'تقرير المصروفات حسب الشهر'!$C$763:$AD$872,3,FALSE),0) -> 721.98 | K31: =IFERROR(VLOOKUP(C31,'تقرير المصروفات حسب الشهر'!$C$890:$AD$999,3,FALSE),0) -> 721.98 | L31: =IFERROR(VLOOKUP(C31,'تقرير المصروفات حسب الشهر'!$C$1016:$AD$1126,3,FALSE),0) -> 871.98 | M31: =IFERROR(VLOOKUP(C31,'تقرير المصروفات حسب الشهر'!$C$1143:$AD$1254,3,FALSE),0) -> 721.98 | N31: =IFERROR(VLOOKUP(C31,'تقرير المصروفات حسب الشهر'!$C$1270:$AD$1381,3,FALSE),0) -> 1071.98 | O31: =IFERROR(VLOOKUP(C31,'تقرير المصروفات حسب الشهر'!$C$1397:$AI$1512,3,FALSE),0) -> 721.98 | P31: =SUM(D31:O31) -> 9418.44
C32: مكافات مبيعات الادوية | D32: =IFERROR(VLOOKUP(C32,'تقرير المصروفات حسب الشهر'!$C$10:$AD$119,3,FALSE),0) -> 0 | E32: =IFERROR(VLOOKUP(C32,'تقرير المصروفات حسب الشهر'!$C$135:$AD$244,3,FALSE),0) -> 0 | F32: 0 | G32: =IFERROR(VLOOKUP(C32,'تقرير المصروفات حسب الشهر'!$C$387:$AD$495,3,FALSE),0) -> 0 | H32: =IFERROR(VLOOKUP(C32,'تقرير المصروفات حسب الشهر'!$C$512:$AD$620,3,FALSE),0) -> 0 | I32: =IFERROR(VLOOKUP(C32,'تقرير المصروفات حسب الشهر'!$C$637:$AD$746,3,FALSE),0) -> 0 | J32: =IFERROR(VLOOKUP(C32,'تقرير المصروفات حسب الشهر'!$C$763:$AD$872,3,FALSE),0) -> 0 | K32: =IFERROR(VLOOKUP(C32,'تقرير المصروفات حسب الشهر'!$C$890:$AD$999,3,FALSE),0) -> 0 | L32: =IFERROR(VLOOKUP(C32,'تقرير المصروفات حسب الشهر'!$C$1016:$AD$1126,3,FALSE),0) -> 0 | M32: =IFERROR(VLOOKUP(C32,'تقرير المصروفات حسب الشهر'!$C$1143:$AD$1254,3,FALSE),0) -> 0 | N32: =IFERROR(VLOOKUP(C32,'تقرير المصروفات حسب الشهر'!$C$1270:$AD$1381,3,FALSE),0) -> 0 | O32: =IFERROR(VLOOKUP(C32,'تقرير المصروفات حسب الشهر'!$C$1397:$AI$1512,3,FALSE),0) -> 0 | P32: =SUM(D32:O32) -> 0
C33: مكافات مبيعات التجميل | D33: =IFERROR(VLOOKUP(C33,'تقرير المصروفات حسب الشهر'!$C$10:$AD$119,3,FALSE),0) -> 1500 | E33: =IFERROR(VLOOKUP(C33,'تقرير المصروفات حسب الشهر'!$C$135:$AD$244,3,FALSE),0) -> 1400 | F33: 1400 | G33: =IFERROR(VLOOKUP(C33,'تقرير المصروفات حسب الشهر'!$C$387:$AD$495,3,FALSE),0) -> 1400 | H33: =IFERROR(VLOOKUP(C33,'تقرير المصروفات حسب الشهر'!$C$512:$AD$620,3,FALSE),0) -> 2200 | I33: =IFERROR(VLOOKUP(C33,'تقرير المصروفات حسب الشهر'!$C$637:$AD$746,3,FALSE),0) -> 1400 | J33: =IFERROR(VLOOKUP(C33,'تقرير المصروفات حسب الشهر'!$C$763:$AD$872,3,FALSE),0) -> 2200 | K33: =IFERROR(VLOOKUP(C33,'تقرير المصروفات حسب الشهر'!$C$890:$AD$999,3,FALSE),0) -> 0 | L33: =IFERROR(VLOOKUP(C33,'تقرير المصروفات حسب الشهر'!$C$1016:$AD$1126,3,FALSE),0) -> 500 | M33: =IFERROR(VLOOKUP(C33,'تقرير المصروفات حسب الشهر'!$C$1143:$AD$1254,3,FALSE),0) -> 0 | N33: =IFERROR(VLOOKUP(C33,'تقرير المصروفات حسب الشهر'!$C$1270:$AD$1381,3,FALSE),0) -> 1150 | O33: =IFERROR(VLOOKUP(C33,'تقرير المصروفات حسب الشهر'!$C$1397:$AI$1512,3,FALSE),0) -> 0 | P33: =SUM(D33:O33) -> 13150
... C130: فوائد القروض - التجارى وفا بنك AWB | D130: =IFERROR(VLOOKUP(C130,'تقرير المصروفات حسب الشهر'!$C$10:$AD$119,3,FALSE),0) -> 0 | E130: =IFERROR(VLOOKUP(C130,'تقرير المصروفات حسب الشهر'!$C$135:$AD$244,3,FALSE),0) -> 0 | F130: 0 | G130: =IFERROR(VLOOKUP(C130,'تقرير المصروفات حسب الشهر'!$C$387:$AD$495,3,FALSE),0) -> 0 | H130: =IFERROR(VLOOKUP(C130,'تقرير المصروفات حسب الشهر'!$C$512:$AD$620,3,FALSE),0) -> 0 | I130: =IFERROR(VLOOKUP(C130,'تقرير المصروفات حسب الشهر'!$C$637:$AD$746,3,FALSE),0) -> 0 | J130: =IFERROR(VLOOKUP(C130,'تقرير المصروفات حسب الشهر'!$C$763:$AD$872,3,FALSE),0) -> 0 | K130: =IFERROR(VLOOKUP(C130,'تقرير المصروفات حسب الشهر'!$C$890:$AD$999,3,FALSE),0) -> 0 | L130: =IFERROR(VLOOKUP(C130,'تقرير المصروفات حسب الشهر'!$C$1016:$AD$1126,3,FALSE),0) -> 0 | M130: =IFERROR(VLOOKUP(C130,'تقرير المصروفات حسب الشهر'!$C$1143:$AD$1254,3,FALSE),0) -> 0 | N130: =IFERROR(VLOOKUP(C130,'تقرير المصروفات حسب الشهر'!$C$1270:$AD$1381,3,FALSE),0) -> 0 | O130: =IFERROR(VLOOKUP(C130,'تقرير المصروفات حسب الشهر'!$C$1397:$AI$1512,3,FALSE),0) -> 0 | P130: =SUM(D130:O130) -> 0
C131: فوائد القروض - بنك القاهرة BDC | D131: =IFERROR(VLOOKUP(C131,'تقرير المصروفات حسب الشهر'!$C$10:$AD$119,3,FALSE),0) -> 0 | E131: =IFERROR(VLOOKUP(C131,'تقرير المصروفات حسب الشهر'!$C$135:$AD$244,3,FALSE),0) -> 0 | F131: 0 | G131: =IFERROR(VLOOKUP(C131,'تقرير المصروفات حسب الشهر'!$C$387:$AD$495,3,FALSE),0) -> 0 | H131: =IFERROR(VLOOKUP(C131,'تقرير المصروفات حسب الشهر'!$C$512:$AD$620,3,FALSE),0) -> 0 | I131: =IFERROR(VLOOKUP(C131,'تقرير المصروفات حسب الشهر'!$C$637:$AD$746,3,FALSE),0) -> 0 | J131: =IFERROR(VLOOKUP(C131,'تقرير المصروفات حسب الشهر'!$C$763:$AD$872,3,FALSE),0) -> 0 | K131: =IFERROR(VLOOKUP(C131,'تقرير المصروفات حسب الشهر'!$C$890:$AD$999,3,FALSE),0) -> 0 | L131: =IFERROR(VLOOKUP(C131,'تقرير المصروفات حسب الشهر'!$C$1016:$AI$1128,3,FALSE),0) -> 0 | M131: =IFERROR(VLOOKUP(C131,'تقرير المصروفات حسب الشهر'!$C$1143:$AD$1254,3,FALSE),0) -> 0 | N131: =IFERROR(VLOOKUP(C131,'تقرير المصروفات حسب الشهر'!$C$1270:$AD$1381,3,FALSE),0) -> 0 | O131: =IFERROR(VLOOKUP(C131,'تقرير المصروفات حسب الشهر'!$C$1397:$AI$1512,3,FALSE),0) -> 0 | P131: =SUM(D131:O131) -> 0
C132: خصم أبليكيشن | D132: =IFERROR(VLOOKUP(C132,'تقرير المصروفات حسب الشهر'!$C$10:$AD$123,3,FALSE),0) -> 184724.06 | E132: =IFERROR(VLOOKUP(C132,'تقرير المصروفات حسب الشهر'!$C$135:$AD$252,3,FALSE),0) -> 227298.83 | F132: 258410.07 | G132: =IFERROR(VLOOKUP(C132,'تقرير المصروفات حسب الشهر'!$C$387:$AD$503,3,FALSE),0) -> 329423.45 | H132: =IFERROR(VLOOKUP(C132,'تقرير المصروفات حسب الشهر'!$C$512:$AD$622,3,FALSE),0) -> 368487.11 | I132: =IFERROR(VLOOKUP(C132,'تقرير المصروفات حسب الشهر'!$C$637:$AD$750,3,FALSE),0) -> 470060.39 | J132: =IFERROR(VLOOKUP(C132,'تقرير المصروفات حسب الشهر'!$C$763:$AD$877,3,FALSE),0) -> 393717.5 | K132: =IFERROR(VLOOKUP(C132,'تقرير المصروفات حسب الشهر'!$C$890:$AD$1002,3,FALSE),0) -> 318750.67 | L132: =IFERROR(VLOOKUP(C132,'تقرير المصروفات حسب الشهر'!$C$1016:$AI$1128,3,FALSE),0) -> 416728.62 | M132: =IFERROR(VLOOKUP(C132,'تقرير المصروفات حسب الشهر'!$C$1143:$AD$1254,3,FALSE),0) -> 370162.41 | N132: =IFERROR(VLOOKUP(C132,'تقرير المصروفات حسب الشهر'!$C$1270:$AD$1382,3,FALSE),0) -> 409886.17 | O132: =IFERROR(VLOOKUP(C132,'تقرير المصروفات حسب الشهر'!$C$1397:$AI$1512,3,FALSE),0) -> 452349.88 | P132: =SUM(D132:O132) -> 4199999.2
C133: عروض مبيعات ابليكشن | J133: =IFERROR(VLOOKUP(C133,'تقرير المصروفات حسب الشهر'!$C$763:$AD$877,3,FALSE),0) -> 62211.04 | K133: =IFERROR(VLOOKUP(C133,'تقرير المصروفات حسب الشهر'!$C$890:$AD$1002,3,FALSE),0) -> 113523.11 | L133: =IFERROR(VLOOKUP(C133,'تقرير المصروفات حسب الشهر'!$C$1016:$AI$1131,3,FALSE),0) -> 164357.2 | M133: =IFERROR(VLOOKUP(C133,'تقرير المصروفات حسب الشهر'!$C$1143:$AD$1258,3,FALSE),0) -> 138156.89 | N133: =IFERROR(VLOOKUP(C133,'تقرير المصروفات حسب الشهر'!$C$1270:$AD$1383,3,FALSE),0) -> 74428.11 | O133: =IFERROR(VLOOKUP(C133,'تقرير المصروفات حسب الشهر'!$C$1397:$AI$1512,3,FALSE),0) -> 102674.67
C134: إجمالي المصروفات | D134: =SUM(D22:D132) -> 702776.09 | E134: =SUM(E22:E132) -> 682847.52 | F134: =SUM(F22:F132) -> 756739.52 | G134: =SUM(G22:G132) -> 838969.2 | H134: =SUM(H22:H132) -> 864941.69 | I134: =SUM(I22:I132) -> 1006657.4 | J134: =SUM(J22:J133) -> 1023718.6 | K134: =SUM(K22:K133) -> 959275.18 | L134: =SUM(L22:L133) -> 1174300.3 | M134: =SUM(M22:M133) -> 1105408.9 | N134: =SUM(N22:N133) -> 1134451.4 | O134: =SUM(O22:O133) -> 1311621.6 | P134: =SUM(D134:O134) -> 11561707
C136: مجمل الربح | D136: =D19 -> 1006457.5 | E136: =E19 -> 937168.4 | F136: =F19 -> 1012104.6 | G136: =G19 -> 1113227.9 | H136: =H19 -> 1186553.5 | I136: =I19 -> 1245915.8 | J136: =J19 -> 1238782.2 | K136: =K19 -> 1351044.2 | ... O136: =O19 -> 1658679.5 | P136: =SUM(D136:O136) -> 15096151
C139: صافي الربح / الخسارة | D139: =D136-D134 -> 303681.37 | E139: =E136-E134 -> 254320.88 | F139: =F136-F134 -> 255365.06 | G139: =G136-G134 -> 274258.69 | H139: =H136-H134 -> 321611.86 | I139: =I136-I134 -> 239258.47 | J139: =J136-J134 -> 215063.67 | K139: =K136-K134 -> 391768.99 | ... O139: =O136-O134 -> 347057.9 | P139: =SUM(D139:O139) -> 3534444
D143: 292132.08 | G143: =274258.69-G139 -> 5.2386895e-10 | I143: 527137.47 | M143: =+M139-432504.42 -> 0
D144: =D139-D143 -> 11549.29 | I144: =I139-I143 -> -287879 | N144: 289188.62
N145: =N139-N144 -> 7514.05

Sheet October
C2: INCOME STATEMTN
F3: Income Statement For OCTOBER
D6: Jan | E6: February | F6: March | G6: April | H6: May | I6: June | J6: July | K6: August | L6: September | M6: October | N6: November | O6: December | P6: TOTAL
C7: INCOME DETAILS
A8: اكتوبر | C8: المبيعات | D8: =D9+D10+D11 -> 4051065.9 | E8: =E9+E10+E11 -> 3643908.5 | F8: =F9+F10+F11 -> 4234876.3 | G8: =G9+G10+G11 -> 4617458.6 | H8: =H9+H10+H11 -> 4985846.7 | I8: =I9+I10+I11 -> 5075626.1 | J8: =J9+J10+J11 -> 5177065.1 | K8: =K9+K10+K11 -> 5402221.3 | ... O8: =O9+O10+O11 -> 6476487.8 | P8: =SUM(D8:O8) -> 60513045
C9: نقدى | D9: =VLOOKUP($A$8,'تقرير إحصائية بحجم المبيعات'!$B$7:$L$31,2,FALSE) -> 2376097.9 | E9: =VLOOKUP($A$8,'تقرير إحصائية بحجم المبيعات'!$B$42:$G$73,2,FALSE) -> 2119720.5 | F9: =VLOOKUP($A$8,'تقرير إحصائية بحجم المبيعات'!$B$78:$E$103,2,FALSE) -> 2517859.1 | G9: =VLOOKUP($A$8,'تقرير إحصائية بحجم المبيعات'!$B$112:$G$137,2,FALSE) -> 2823613.1 | H9: =VLOOKUP($A$8,'تقرير إحصائية بحجم المبيعات'!$B$147:$G$177,2,FALSE) -> 3074623.8 | I9: =VLOOKUP($A$8,'تقرير إحصائية بحجم المبيعات'!$B$182:$G$212,2,FALSE) -> 3240915 | J9: =VLOOKUP($A$8,'تقرير إحصائية بحجم المبيعات'!$B$217:$L$243,2,FALSE) -> 3082150.6 | K9: =VLOOKUP($A$8,'تقرير إحصائية بحجم المبيعات'!$B$252:$L$278,2,FALSE) -> 3467970.8 | L9: =VLOOKUP($A$8,'تقرير إحصائية بحجم المبيعات'!$B$287:$L$313,2,FALSE) -> 3066311.5 | M9: =VLOOKUP($A$8,'تقرير إحصائية بحجم المبيعات'!$B$322:$L$347,2,FALSE) -> 3659880.5 | N9: =VLOOKUP($A$8,'تقرير إحصائية بحجم المبيعات'!$B$357:$L$383,2,FALSE) -> 3840488.2 | O9: =VLOOKUP($A$8,'تقرير إحصائية بحجم المبيعات'!$B$391:$L$420,2,FALSE) -> 4120623.3 | P9: =SUM(D9:O9) -> 37390254
C10: دليفرى | D10: =VLOOKUP($A$8,'تقرير إحصائية بحجم المبيعات'!$B$7:$L$31,3,FALSE) -> 1229205.7 | E10: =VLOOKUP($A$8,'تقرير إحصائية بحجم المبيعات'!$B$42:$G$73,3,FALSE) -> 1203639.7 | F10: =VLOOKUP($A$8,'تقرير إحصائية بحجم المبيعات'!$B$78:$E$103,3,FALSE) -> 1324102.6 | G10: =VLOOKUP($A$8,'تقرير إحصائية بحجم المبيعات'!$B$112:$G$137,3,FALSE) -> 1377184.4 | H10: =VLOOKUP($A$8,'تقرير إحصائية بحجم المبيعات'!$B$147:$G$177,3,FALSE) -> 1414347.5 | I10: =VLOOKUP($A$8,'تقرير إحصائية بحجم المبيعات'!$B$182:$G$212,3,FALSE) -> 1381272.6 | J10: =VLOOKUP($A$8,'تقرير إحصائية بحجم المبيعات'!$B$217:$L$243,3,FALSE) -> 1527866.4 | K10: =VLOOKUP($A$8,'تقرير إحصائية بحجم المبيعات'!$B$252:$L$278,3,FALSE) -> 1482569.8 | L10: =VLOOKUP($A$8,'تقرير إحصائية بحجم المبيعات'!$B$287:$L$313,3,FALSE) -> 1553561.5 | M10: =VLOOKUP($A$8,'تقرير إحصائية بحجم المبيعات'!$B$322:$L$347,3,FALSE) -> 1633411.4 | N10: =VLOOKUP($A$8,'تقرير إحصائية بحجم المبيعات'!$B$357:$L$383,3,FALSE) -> 1775363.9 | O10: =VLOOKUP($A$8,'تقرير إحصائية بحجم المبيعات'!$B$391:$L$420,3,FALSE) -> 1862675 | P10: =SUM(D10:O10) -> 17765200
C11: اجل | D11: =VLOOKUP($A$8,'تقرير إحصائية بحجم المبيعات'!$B$7:$L$31,4,FALSE) -> 445762.32 | E11: =VLOOKUP($A$8,'تقرير إحصائية بحجم المبيعات'!$B$42:$G$73,4,FALSE) -> 320548.27 | F11: =VLOOKUP($A$8,'تقرير إحصائية بحجم المبيعات'!$B$78:$E$103,4,FALSE) -> 392914.6 | G11: =VLOOKUP($A$8,'تقرير إحصائية بحجم المبيعات'!$B$112:$G$137,4,FALSE) -> 416661.03 | H11: =VLOOKUP($A$8,'تقرير إحصائية بحجم المبيعات'!$B$147:$G$177,4,FALSE) -> 496875.43 | I11: =VLOOKUP($A$8,'تقرير إحصائية بحجم المبيعات'!$B$182:$G$212,4,FALSE) -> 453438.45 | J11: =VLOOKUP($A$8,'تقرير إحصائية بحجم المبيعات'!$B$217:$L$243,4,FALSE) -> 567048.12 | K11: =VLOOKUP($A$8,'تقرير إحصائية بحجم المبيعات'!$B$252:$L$278,4,FALSE) -> 451680.68 | L11: =VLOOKUP($A$8,'تقرير إحصائية بحجم المبيعات'!$B$287:$L$313,4,FALSE) -> 464927.19 | M11: =VLOOKUP($A$8,'تقرير إحصائية بحجم المبيعات'!$B$322:$L$347,4,FALSE) -> 411909.74 | N11: =VLOOKUP($A$8,'تقرير إحصائية بحجم المبيعات'!$B$357:$L$383,4,FALSE) -> 442635 | O11: =VLOOKUP($A$8,'تقرير إحصائية بحجم المبيعات'!$B$391:$L$420,4,FALSE) -> 493189.55 | P11: =SUM(D11:O11) -> 5357590.4
C12: تكلفة البضاعة المباعة | D12: =VLOOKUP($A$8,'تقرير إحصائية بحجم المبيعات'!$B$7:$L$31,11,FALSE) -> 3164590.4 | E12: =VLOOKUP($A$8,'تقرير إحصائية بحجم المبيعات'!$B$42:$L$73,11,FALSE) -> 2887679.8 | F12: =VLOOKUP($A$8,'تقرير إحصائية بحجم المبيعات'!$B$78:$L$103,11,FALSE) -> 3356743.4 | G12: =VLOOKUP($A$8,'تقرير إحصائية بحجم المبيعات'!$B$112:$L$137,11,FALSE) -> 3675493.3 | H12: =VLOOKUP($A$8,'تقرير إحصائية بحجم المبيعات'!$B$147:$L$177,11,FALSE) -> 3994106 | I12: =VLOOKUP($A$8,'تقرير إحصائية بحجم المبيعات'!$B$182:$L$212,11,FALSE) -> 4024289.2 | J12: =VLOOKUP($A$8,'تقرير إحصائية بحجم المبيعات'!$B$217:$L$243,11,FALSE) -> 4122723 | K12: =VLOOKUP($A$8,'تقرير إحصائية بحجم المبيعات'!$B$252:$L$278,11,FALSE) -> 4294453.6 | L12: =VLOOKUP($A$8,'تقرير إحصائية بحجم المبيعات'!$B$287:$L$313,11,FALSE) -> 4034129.2 | M12: =VLOOKUP($A$8,'تقرير إحصائية بحجم المبيعات'!$B$322:$L$347,11,FALSE) -> 4525279.4 | N12: =VLOOKUP($A$8,'تقرير إحصائية بحجم المبيعات'!$B$357:$L$383,11,FALSE) -> 4775535.7 | O12: =VLOOKUP($A$8,'تقرير إحصائية بحجم المبيعات'!$B$391:$L$420,11,FALSE) -> 5105721.2 | P12: =SUM(D12:O12) -> 47960744
C13: مجمل الربح | D13: =D8-D12 -> 886475.54 | E13: =E8-E12 -> 756228.75 | F13: =F8-F12 -> 878132.93 | G13: =G8-G12 -> 941965.25 | H13: =H8-H12 -> 991740.77 | I13: =I8-I12 -> 1051336.8 | J13: =J8-J12 -> 1054342.1 | K13: =K8-K12 -> 1107767.7 | ... O13: =O8-O12 -> 1370766.6 | P13: =SUM(D13:O13) -> 12552301
C14: خصم نقدى | P14: =SUM(D14:O14) -> 0
C15: ارباح صرف اصناف بيع اصول | P15: =SUM(D15:O15) -> 0
C16: فائض جرد | D16: 337.87 | E16: =107.02+2.57 -> 109.59 | F16: 2.19 | H16: 21927.94 | K16: 462.23 | L16: 472.19 | M16: 1548.63 | N16: 9608.61 | P16: =SUM(D16:O16) -> 34469.25
C17: ايرادات اخرى | D17: 0.11 | P17: =SUM(D17:O17) -> 0.11
C18: إجمالي الايرادات اخرى | D18: =SUM(D14:D17) -> 337.98 | E18: =SUM(E14:E17) -> 109.59 | F18: =SUM(F14:F17) -> 2.19 | G18: =SUM(G14:G17) -> 0 | H18: =SUM(H14:H17) -> 21927.94 | I18: =SUM(I14:I17) -> 0 | J18: =SUM(J14:J17) -> 0 | K18: =SUM(K14:K17) -> 462.23 | ... O18: =SUM(O14:O17) -> 0 | P18: =SUM(D18:O18) -> 34469.36
C19: مجمل الربح | D19: =D13+D18 -> 886813.52 | E19: =E13+E18 -> 756338.34 | F19: =F13+F18 -> 878135.12 | G19: =G13+G18 -> 941965.25 | H19: =H13+H18 -> 1013668.7 | I19: =I13+I18 -> 1051336.8 | J19: =J13+J18 -> 1054342.1 | K19: =K13+K18 -> 1108229.9 | ... O19: =O13+O18 -> 1370766.6 | P19: =SUM(D19:O19) -> 12586771
D20: =D19/D12 -> 0.28023012 | E20: =E19/E12 -> 0.26191905 | F20: =F19/F12 -> 0.26160329 | G20: =G19/G12 -> 0.25628267 | H20: =H19/H12 -> 0.25379114 | I20: =I19/I12 -> 0.26124783 | J20: =J19/J12 -> 0.25573926 | K20: =K19/K12 -> 0.25806076 | ... N20: =N19/N12 -> 0.27066284
C21: EXPENSE DETAILS
C22: مرتبات الادارة | D22: =IFERROR(VLOOKUP(C22,'تقرير المصروفات حسب الشهر'!$C$10:$AD$119,4,FALSE),0) -> 0 | E22: =IFERROR(VLOOKUP(C22,'تقرير المصروفات حسب الشهر'!$C$135:$AD$244,4,FALSE),0) -> 0 | F22: 0 | G22: =IFERROR(VLOOKUP(C22,'تقرير المصروفات حسب الشهر'!$C$387:$AD$495,4,FALSE),0) -> 0 | H22: =IFERROR(VLOOKUP(C22,'تقرير المصروفات حسب الشهر'!$C$512:$AD$620,4,FALSE),0) -> 0 | I22: =IFERROR(VLOOKUP(C22,'تقرير المصروفات حسب الشهر'!$C$637:$AD$746,4,FALSE),0) -> 0 | J22: =IFERROR(VLOOKUP(C22,'تقرير المصروفات حسب الشهر'!$C$763:$AD$872,4,FALSE),0) -> 0 | K22: =IFERROR(VLOOKUP(C22,'تقرير المصروفات حسب الشهر'!$C$890:$AD$999,4,FALSE),0) -> 0 | L22: =IFERROR(VLOOKUP(C22,'تقرير المصروفات حسب الشهر'!$C$1016:$AD$1126,4,FALSE),0) -> 0 | M22: =IFERROR(VLOOKUP(C22,'تقرير المصروفات حسب الشهر'!$C$1143:$AD$1254,4,FALSE),0) -> 0 | N22: =IFERROR(VLOOKUP(C22,'تقرير المصروفات حسب الشهر'!$C$1270:$AD$1381,4,FALSE),0) -> 0 | O22: =IFERROR(VLOOKUP(C22,'تقرير المصروفات حسب الشهر'!$C$1397:$AI$1512,4,FALSE),0) -> 0 | P22: =SUM(D22:O22) -> 0
C23: مرتبات الفروع | D23: =IFERROR(VLOOKUP(C23,'تقرير المصروفات حسب الشهر'!$C$10:$AD$119,4,FALSE),0) -> 227919.15 | E23: =IFERROR(VLOOKUP(C23,'تقرير المصروفات حسب الشهر'!$C$135:$AD$244,4,FALSE),0) -> 374699.83 | F23: 306375.26 | G23: =IFERROR(VLOOKUP(C23,'تقرير المصروفات حسب الشهر'!$C$387:$AD$495,4,FALSE),0) -> 336340.38 | H23: =IFERROR(VLOOKUP(C23,'تقرير المصروفات حسب الشهر'!$C$512:$AD$620,4,FALSE),0) -> 337529.11 | I23: =IFERROR(VLOOKUP(C23,'تقرير المصروفات حسب الشهر'!$C$637:$AD$746,4,FALSE),0) -> 373904.85 | J23: =IFERROR(VLOOKUP(C23,'تقرير المصروفات حسب الشهر'!$C$763:$AD$872,4,FALSE),0) -> 349136.14 | K23: =IFERROR(VLOOKUP(C23,'تقرير المصروفات حسب الشهر'!$C$890:$AD$999,4,FALSE),0) -> 353162.64 | L23: =IFERROR(VLOOKUP(C23,'تقرير المصروفات حسب الشهر'!$C$1016:$AD$1126,4,FALSE),0) -> 354970.67 | M23: =IFERROR(VLOOKUP(C23,'تقرير المصروفات حسب الشهر'!$C$1143:$AD$1254,4,FALSE),0) -> 359949.02 | N23: =IFERROR(VLOOKUP(C23,'تقرير المصروفات حسب الشهر'!$C$1270:$AD$1381,4,FALSE),0) -> 389446.5 | O23: =IFERROR(VLOOKUP(C23,'تقرير المصروفات حسب الشهر'!$C$1397:$AI$1512,4,FALSE),0) -> 368775.89 | P23: =SUM(D23:O23) -> 4132209.4
C24: الكهرباء | D24: =IFERROR(VLOOKUP(C24,'تقرير المصروفات حسب الشهر'!$C$10:$AD$119,4,FALSE),0) -> 3150 | E24: =IFERROR(VLOOKUP(C24,'تقرير المصروفات حسب الشهر'!$C$135:$AD$244,4,FALSE),0) -> 1855 | F24: 2001 | G24: =IFERROR(VLOOKUP(C24,'تقرير المصروفات حسب الشهر'!$C$387:$AD$495,4,FALSE),0) -> 3075 | H24: =IFERROR(VLOOKUP(C24,'تقرير المصروفات حسب الشهر'!$C$512:$AD$620,4,FALSE),0) -> 5300 | I24: =IFERROR(VLOOKUP(C24,'تقرير المصروفات حسب الشهر'!$C$637:$AD$746,4,FALSE),0) -> 6110 | J24: =IFERROR(VLOOKUP(C24,'تقرير المصروفات حسب الشهر'!$C$763:$AD$872,4,FALSE),0) -> 8115 | K24: =IFERROR(VLOOKUP(C24,'تقرير المصروفات حسب الشهر'!$C$890:$AD$999,4,FALSE),0) -> 8000 | L24: =IFERROR(VLOOKUP(C24,'تقرير المصروفات حسب الشهر'!$C$1016:$AD$1126,4,FALSE),0) -> 7090 | M24: =IFERROR(VLOOKUP(C24,'تقرير المصروفات حسب الشهر'!$C$1143:$AD$1254,4,FALSE),0) -> 5660 | N24: =IFERROR(VLOOKUP(C24,'تقرير المصروفات حسب الشهر'!$C$1270:$AD$1381,4,FALSE),0) -> 3880 | O24: =IFERROR(VLOOKUP(C24,'تقرير المصروفات حسب الشهر'!$C$1397:$AI$1512,4,FALSE),0) -> 3000 | P24: =SUM(D24:O24) -> 57236
C25: المياه | D25: =IFERROR(VLOOKUP(C25,'تقرير المصروفات حسب الشهر'!$C$10:$AD$119,4,FALSE),0) -> 0 | E25: =IFERROR(VLOOKUP(C25,'تقرير المصروفات حسب الشهر'!$C$135:$AD$244,4,FALSE),0) -> 0 | F25: 0 | G25: =IFERROR(VLOOKUP(C25,'تقرير المصروفات حسب الشهر'!$C$387:$AD$495,4,FALSE),0) -> 0 | H25: =IFERROR(VLOOKUP(C25,'تقرير المصروفات حسب الشهر'!$C$512:$AD$620,4,FALSE),0) -> 0 | I25: =IFERROR(VLOOKUP(C25,'تقرير المصروفات حسب الشهر'!$C$637:$AD$746,4,FALSE),0) -> 0 | J25: =IFERROR(VLOOKUP(C25,'تقرير المصروفات حسب الشهر'!$C$763:$AD$872,4,FALSE),0) -> 0 | K25: =IFERROR(VLOOKUP(C25,'تقرير المصروفات حسب الشهر'!$C$890:$AD$999,4,FALSE),0) -> 0 | L25: =IFERROR(VLOOKUP(C25,'تقرير المصروفات حسب الشهر'!$C$1016:$AD$1126,4,FALSE),0) -> 0 | M25: =IFERROR(VLOOKUP(C25,'تقرير المصروفات حسب الشهر'!$C$1143:$AD$1254,4,FALSE),0) -> 0 | N25: =IFERROR(VLOOKUP(C25,'تقرير المصروفات حسب الشهر'!$C$1270:$AD$1381,4,FALSE),0) -> 0 | O25: =IFERROR(VLOOKUP(C25,'تقرير المصروفات حسب الشهر'!$C$1397:$AI$1512,4,FALSE),0) -> 0 | P25: =SUM(D25:O25) -> 0
C26: التليفون الارضي | D26: =IFERROR(VLOOKUP(C26,'تقرير المصروفات حسب الشهر'!$C$10:$AD$119,4,FALSE),0) -> 150 | E26: =IFERROR(VLOOKUP(C26,'تقرير المصروفات حسب الشهر'!$C$135:$AD$244,4,FALSE),0) -> 0 | F26: 600 | G26: =IFERROR(VLOOKUP(C26,'تقرير المصروفات حسب الشهر'!$C$387:$AD$495,4,FALSE),0) -> 0 | H26: =IFERROR(VLOOKUP(C26,'تقرير المصروفات حسب الشهر'!$C$512:$AD$620,4,FALSE),0) -> 0 | I26: =IFERROR(VLOOKUP(C26,'تقرير المصروفات حسب الشهر'!$C$637:$AD$746,4,FALSE),0) -> 1445 | J26: =IFERROR(VLOOKUP(C26,'تقرير المصروفات حسب الشهر'!$C$763:$AD$872,4,FALSE),0) -> 0 | K26: =IFERROR(VLOOKUP(C26,'تقرير المصروفات حسب الشهر'!$C$890:$AD$999,4,FALSE),0) -> 0 | L26: =IFERROR(VLOOKUP(C26,'تقرير المصروفات حسب الشهر'!$C$1016:$AD$1126,4,FALSE),0) -> 0 | M26: =IFERROR(VLOOKUP(C26,'تقرير المصروفات حسب الشهر'!$C$1143:$AD$1254,4,FALSE),0) -> 0 | N26: =IFERROR(VLOOKUP(C26,'تقرير المصروفات حسب الشهر'!$C$1270:$AD$1381,4,FALSE),0) -> 600 | O26: =IFERROR(VLOOKUP(C26,'تقرير المصروفات حسب الشهر'!$C$1397:$AI$1512,4,FALSE),0) -> 0 | P26: =SUM(D26:O26) -> 2795
C27: الايجار - الصيدلية | D27: =IFERROR(VLOOKUP(C27,'تقرير المصروفات حسب الشهر'!$C$10:$AD$119,4,FALSE),0) -> 100000 | E27: =IFERROR(VLOOKUP(C27,'تقرير المصروفات حسب الشهر'!$C$135:$AD$244,4,FALSE),0) -> 100000 | F27: 100000 | G27: =IFERROR(VLOOKUP(C27,'تقرير المصروفات حسب الشهر'!$C$387:$AD$495,4,FALSE),0) -> 100000 | H27: =IFERROR(VLOOKUP(C27,'تقرير المصروفات حسب الشهر'!$C$512:$AD$620,4,FALSE),0) -> 100000 | I27: =IFERROR(VLOOKUP(C27,'تقرير المصروفات حسب الشهر'!$C$637:$AD$746,4,FALSE),0) -> 100000 | J27: =IFERROR(VLOOKUP(C27,'تقرير المصروفات حسب الشهر'!$C$763:$AD$872,4,FALSE),0) -> 100000 | K27: =IFERROR(VLOOKUP(C27,'تقرير المصروفات حسب الشهر'!$C$890:$AD$999,4,FALSE),0) -> 100000 | L27: =IFERROR(VLOOKUP(C27,'تقرير المصروفات حسب الشهر'!$C$1016:$AD$1126,4,FALSE),0) -> 100000 | M27: =IFERROR(VLOOKUP(C27,'تقرير المصروفات حسب الشهر'!$C$1143:$AD$1254,4,FALSE),0) -> 100000 | N27: =IFERROR(VLOOKUP(C27,'تقرير المصروفات حسب الشهر'!$C$1270:$AD$1381,4,FALSE),0) -> 170000 | O27: =IFERROR(VLOOKUP(C27,'تقرير المصروفات حسب الشهر'!$C$1397:$AI$1512,4,FALSE),0) -> 170000 | P27: =SUM(D27:O27) -> 1340000
C28: الايجار - الادارة | D28: =IFERROR(VLOOKUP(C28,'تقرير المصروفات حسب الشهر'!$C$10:$AD$119,4,FALSE),0) -> 0 | E28: =IFERROR(VLOOKUP(C28,'تقرير المصروفات حسب الشهر'!$C$135:$AD$244,4,FALSE),0) -> 0 | F28: 0 | G28: =IFERROR(VLOOKUP(C28,'تقرير المصروفات حسب الشهر'!$C$387:$AD$495,4,FALSE),0) -> 0 | H28: =IFERROR(VLOOKUP(C28,'تقرير المصروفات حسب الشهر'!$C$512:$AD$620,4,FALSE),0) -> 0 | I28: =IFERROR(VLOOKUP(C28,'تقرير المصروفات حسب الشهر'!$C$637:$AD$746,4,FALSE),0) -> 0 | J28: =IFERROR(VLOOKUP(C28,'تقرير المصروفات حسب الشهر'!$C$763:$AD$872,4,FALSE),0) -> 0 | K28: =IFERROR(VLOOKUP(C28,'تقرير المصروفات حسب الشهر'!$C$890:$AD$999,4,FALSE),0) -> 0 | L28: =IFERROR(VLOOKUP(C28,'تقرير المصروفات حسب الشهر'!$C$1016:$AD$1126,4,FALSE),0) -> 0 | M28: =IFERROR(VLOOKUP(C28,'تقرير المصروفات حسب الشهر'!$C$1143:$AD$1254,4,FALSE),0) -> 0 | N28: =IFERROR(VLOOKUP(C28,'تقرير المصروفات حسب الشهر'!$C$1270:$AD$1381,4,FALSE),0) -> 0 | O28: =IFERROR(VLOOKUP(C28,'تقرير المصروفات حسب الشهر'!$C$1397:$AI$1512,4,FALSE),0) -> 0 | P28: =SUM(D28:O28) -> 0
C29: ايجارات متنوعه | D29: =IFERROR(VLOOKUP(C29,'تقرير المصروفات حسب الشهر'!$C$10:$AD$119,4,FALSE),0) -> 26200 | E29: =IFERROR(VLOOKUP(C29,'تقرير المصروفات حسب الشهر'!$C$135:$AD$244,4,FALSE),0) -> 26200 | F29: 26200 | G29: =IFERROR(VLOOKUP(C29,'تقرير المصروفات حسب الشهر'!$C$387:$AD$495,4,FALSE),0) -> 26200 | H29: =IFERROR(VLOOKUP(C29,'تقرير المصروفات حسب الشهر'!$C$512:$AD$620,4,FALSE),0) -> 26200 | I29: =IFERROR(VLOOKUP(C29,'تقرير المصروفات حسب الشهر'!$C$637:$AD$746,4,FALSE),0) -> 26200 | J29: =IFERROR(VLOOKUP(C29,'تقرير المصروفات حسب الشهر'!$C$763:$AD$872,4,FALSE),0) -> 26200 | K29: =IFERROR(VLOOKUP(C29,'تقرير المصروفات حسب الشهر'!$C$890:$AD$999,4,FALSE),0) -> 26200 | L29: =IFERROR(VLOOKUP(C29,'تقرير المصروفات حسب الشهر'!$C$1016:$AD$1126,4,FALSE),0) -> 26200 | M29: =IFERROR(VLOOKUP(C29,'تقرير المصروفات حسب الشهر'!$C$1143:$AD$1254,4,FALSE),0) -> 26200 | N29: =IFERROR(VLOOKUP(C29,'تقرير المصروفات حسب الشهر'!$C$1270:$AD$1381,4,FALSE),0) -> 27200 | O29: =IFERROR(VLOOKUP(C29,'تقرير المصروفات حسب الشهر'!$C$1397:$AI$1512,4,FALSE),0) -> 23200 | P29: =SUM(D29:O29) -> 312400
C30: ادوات مكتبية | D30: =IFERROR(VLOOKUP(C30,'تقرير المصروفات حسب الشهر'!$C$10:$AD$119,4,FALSE),0) -> 0 | E30: =IFERROR(VLOOKUP(C30,'تقرير المصروفات حسب الشهر'!$C$135:$AD$244,4,FALSE),0) -> 0 | F30: 996.5 | G30: =IFERROR(VLOOKUP(C30,'تقرير المصروفات حسب الشهر'!$C$387:$AD$495,4,FALSE),0) -> 0 | H30: =IFERROR(VLOOKUP(C30,'تقرير المصروفات حسب الشهر'!$C$512:$AD$620,4,FALSE),0) -> 0 | I30: =IFERROR(VLOOKUP(C30,'تقرير المصروفات حسب الشهر'!$C$637:$AD$746,4,FALSE),0) -> 1200.25 | J30: =IFERROR(VLOOKUP(C30,'تقرير المصروفات حسب الشهر'!$C$763:$AD$872,4,FALSE),0) -> 65 | K30: =IFERROR(VLOOKUP(C30,'تقرير المصروفات حسب الشهر'!$C$890:$AD$999,4,FALSE),0) -> 0 | L30: =IFERROR(VLOOKUP(C30,'تقرير المصروفات حسب الشهر'!$C$1016:$AD$1126,4,FALSE),0) -> 40 | M30: =IFERROR(VLOOKUP(C30,'تقرير المصروفات حسب الشهر'!$C$1143:$AD$1254,4,FALSE),0) -> 1610.25 | N30: =IFERROR(VLOOKUP(C30,'تقرير المصروفات حسب الشهر'!$C$1270:$AD$1381,4,FALSE),0) -> 0 | O30: =IFERROR(VLOOKUP(C30,'تقرير المصروفات حسب الشهر'!$C$1397:$AI$1512,4,FALSE),0) -> 1450 | P30: =SUM(D30:O30) -> 5362
C31: فواتير الموبايل | D31: =IFERROR(VLOOKUP(C31,'تقرير المصروفات حسب الشهر'!$C$10:$AD$119,4,FALSE),0) -> 2006.17 | E31: =IFERROR(VLOOKUP(C31,'تقرير المصروفات حسب الشهر'!$C$135:$AD$244,4,FALSE),0) -> 3052.17 | F31: 1715 | G31: =IFERROR(VLOOKUP(C31,'تقرير المصروفات حسب الشهر'!$C$387:$AD$495,4,FALSE),0) -> 2010 | H31: =IFERROR(VLOOKUP(C31,'تقرير المصروفات حسب الشهر'!$C$512:$AD$620,4,FALSE),0) -> 1810 | I31: =IFERROR(VLOOKUP(C31,'تقرير المصروفات حسب الشهر'!$C$637:$AD$746,4,FALSE),0) -> 1200 | J31: =IFERROR(VLOOKUP(C31,'تقرير المصروفات حسب الشهر'!$C$763:$AD$872,4,FALSE),0) -> 1900 | K31: =IFERROR(VLOOKUP(C31,'تقرير المصروفات حسب الشهر'!$C$890:$AD$999,4,FALSE),0) -> 0 | L31: =IFERROR(VLOOKUP(C31,'تقرير المصروفات حسب الشهر'!$C$1016:$AD$1126,4,FALSE),0) -> 160 | M31: =IFERROR(VLOOKUP(C31,'تقرير المصروفات حسب الشهر'!$C$1143:$AD$1254,4,FALSE),0) -> 395 | N31: =IFERROR(VLOOKUP(C31,'تقرير المصروفات حسب الشهر'!$C$1270:$AD$1381,4,FALSE),0) -> 670 | O31: =IFERROR(VLOOKUP(C31,'تقرير المصروفات حسب الشهر'!$C$1397:$AI$1512,4,FALSE),0) -> 480 | P31: =SUM(D31:O31) -> 15398.34
C32: مكافات مبيعات الادوية | D32: =IFERROR(VLOOKUP(C32,'تقرير المصروفات حسب الشهر'!$C$10:$AD$119,4,FALSE),0) -> 0 | E32: =IFERROR(VLOOKUP(C32,'تقرير المصروفات حسب الشهر'!$C$135:$AD$244,4,FALSE),0) -> 0 | F32: 0 | G32: =IFERROR(VLOOKUP(C32,'تقرير المصروفات حسب الشهر'!$C$387:$AD$495,4,FALSE),0) -> 0 | H32: =IFERROR(VLOOKUP(C32,'تقرير المصروفات حسب الشهر'!$C$512:$AD$620,4,FALSE),0) -> 0 | I32: =IFERROR(VLOOKUP(C32,'تقرير المصروفات حسب الشهر'!$C$637:$AD$746,4,FALSE),0) -> 0 | J32: =IFERROR(VLOOKUP(C32,'تقرير المصروفات حسب الشهر'!$C$763:$AD$872,4,FALSE),0) -> 0 | K32: =IFERROR(VLOOKUP(C32,'تقرير المصروفات حسب الشهر'!$C$890:$AD$999,4,FALSE),0) -> 0 | L32: =IFERROR(VLOOKUP(C32,'تقرير المصروفات حسب الشهر'!$C$1016:$AD$1126,4,FALSE),0) -> 0 | M32: =IFERROR(VLOOKUP(C32,'تقرير المصروفات حسب الشهر'!$C$1143:$AD$1254,4,FALSE),0) -> 0 | N32: =IFERROR(VLOOKUP(C32,'تقرير المصروفات حسب الشهر'!$C$1270:$AD$1381,4,FALSE),0) -> 0 | O32: =IFERROR(VLOOKUP(C32,'تقرير المصروفات حسب الشهر'!$C$1397:$AI$1512,4,FALSE),0) -> 0 | P32: =SUM(D32:O32) -> 0
C33: مكافات مبيعات التجميل | D33: =IFERROR(VLOOKUP(C33,'تقرير المصروفات حسب الشهر'!$C$10:$AD$119,4,FALSE),0) -> 500 | E33: =IFERROR(VLOOKUP(C33,'تقرير المصروفات حسب الشهر'!$C$135:$AD$244,4,FALSE),0) -> 600 | F33: 500 | G33: =IFERROR(VLOOKUP(C33,'تقرير المصروفات حسب الشهر'!$C$387:$AD$495,4,FALSE),0) -> 750 | H33: =IFERROR(VLOOKUP(C33,'تقرير المصروفات حسب الشهر'!$C$512:$AD$620,4,FALSE),0) -> 750 | I33: =IFERROR(VLOOKUP(C33,'تقرير المصروفات حسب الشهر'!$C$637:$AD$746,4,FALSE),0) -> 500 | J33: =IFERROR(VLOOKUP(C33,'تقرير المصروفات حسب الشهر'!$C$763:$AD$872,4,FALSE),0) -> 750 | K33: =IFERROR(VLOOKUP(C33,'تقرير المصروفات حسب الشهر'!$C$890:$AD$999,4,FALSE),0) -> 500 | L33: =IFERROR(VLOOKUP(C33,'تقرير المصروفات حسب الشهر'!$C$1016:$AD$1126,4,FALSE),0) -> 500 | M33: =IFERROR(VLOOKUP(C33,'تقرير المصروفات حسب الشهر'!$C$1143:$AD$1254,4,FALSE),0) -> 0 | N33: =IFERROR(VLOOKUP(C33,'تقرير المصروفات حسب الشهر'!$C$1270:$AD$1381,4,FALSE),0) -> 900 | O33: =IFERROR(VLOOKUP(C33,'تقرير المصروفات حسب الشهر'!$C$1397:$AI$1512,4,FALSE),0) -> 1800 | P33: =SUM(D33:O33) -> 8050
... C129: تأمينات اجتماعية - حصة الشركة | D129: =IFERROR(VLOOKUP(C129,'تقرير المصروفات حسب الشهر'!$C$10:$AD$119,4,FALSE),0) -> 3450 | E129: =IFERROR(VLOOKUP(C129,'تقرير المصروفات حسب الشهر'!$C$135:$AD$244,4,FALSE),0) -> 3450 | F129: 3450 | G129: =IFERROR(VLOOKUP(C129,'تقرير المصروفات حسب الشهر'!$C$387:$AD$495,4,FALSE),0) -> 3450 | H129: =IFERROR(VLOOKUP(C129,'تقرير المصروفات حسب الشهر'!$C$512:$AD$620,4,FALSE),0) -> 3450 | I129: =IFERROR(VLOOKUP(C129,'تقرير المصروفات حسب الشهر'!$C$637:$AD$746,4,FALSE),0) -> 3450 | J129: =IFERROR(VLOOKUP(C129,'تقرير المصروفات حسب الشهر'!$C$763:$AD$872,4,FALSE),0) -> 3450 | K129: =IFERROR(VLOOKUP(C129,'تقرير المصروفات حسب الشهر'!$C$890:$AD$999,4,FALSE),0) -> 3450 | L129: =IFERROR(VLOOKUP(C129,'تقرير المصروفات حسب الشهر'!$C$1016:$AD$1126,4,FALSE),0) -> 3450 | M129: =IFERROR(VLOOKUP(C129,'تقرير المصروفات حسب الشهر'!$C$1143:$AD$1254,4,FALSE),0) -> 3450 | N129: =IFERROR(VLOOKUP(C129,'تقرير المصروفات حسب الشهر'!$C$1270:$AD$1381,4,FALSE),0) -> 3450 | O129: =IFERROR(VLOOKUP(C129,'تقرير المصروفات حسب الشهر'!$C$1397:$AI$1512,4,FALSE),0) -> 3450 | P129: =SUM(D129:O129) -> 41400
C130: فوائد القروض - التجارى وفا بنك AWB | D130: =IFERROR(VLOOKUP(C130,'تقرير المصروفات حسب الشهر'!$C$10:$AD$119,4,FALSE),0) -> 0 | E130: =IFERROR(VLOOKUP(C130,'تقرير المصروفات حسب الشهر'!$C$135:$AD$244,4,FALSE),0) -> 0 | F130: 0 | G130: =IFERROR(VLOOKUP(C130,'تقرير المصروفات حسب الشهر'!$C$387:$AD$495,4,FALSE),0) -> 0 | H130: =IFERROR(VLOOKUP(C130,'تقرير المصروفات حسب الشهر'!$C$512:$AD$620,4,FALSE),0) -> 0 | I130: =IFERROR(VLOOKUP(C130,'تقرير المصروفات حسب الشهر'!$C$637:$AD$746,4,FALSE),0) -> 0 | J130: =IFERROR(VLOOKUP(C130,'تقرير المصروفات حسب الشهر'!$C$763:$AD$872,4,FALSE),0) -> 0 | K130: =IFERROR(VLOOKUP(C130,'تقرير المصروفات حسب الشهر'!$C$890:$AD$999,4,FALSE),0) -> 0 | L130: =IFERROR(VLOOKUP(C130,'تقرير المصروفات حسب الشهر'!$C$1016:$AI$1128,4,FALSE),0) -> 0 | M130: =IFERROR(VLOOKUP(C130,'تقرير المصروفات حسب الشهر'!$C$1143:$AD$1254,4,FALSE),0) -> 0 | N130: =IFERROR(VLOOKUP(C130,'تقرير المصروفات حسب الشهر'!$C$1270:$AD$1381,4,FALSE),0) -> 0 | O130: =IFERROR(VLOOKUP(C130,'تقرير المصروفات حسب الشهر'!$C$1397:$AI$1512,4,FALSE),0) -> 0 | P130: =SUM(D130:O130) -> 0
C131: فوائد القروض - بنك القاهرة BDC | D131: =IFERROR(VLOOKUP(C131,'تقرير المصروفات حسب الشهر'!$C$10:$AD$119,4,FALSE),0) -> 0 | E131: =IFERROR(VLOOKUP(C131,'تقرير المصروفات حسب الشهر'!$C$135:$AD$244,4,FALSE),0) -> 0 | F131: 0 | G131: =IFERROR(VLOOKUP(C131,'تقرير المصروفات حسب الشهر'!$C$387:$AD$495,4,FALSE),0) -> 0 | H131: =IFERROR(VLOOKUP(C131,'تقرير المصروفات حسب الشهر'!$C$512:$AD$620,4,FALSE),0) -> 0 | I131: =IFERROR(VLOOKUP(C131,'تقرير المصروفات حسب الشهر'!$C$637:$AD$746,4,FALSE),0) -> 0 | J131: =IFERROR(VLOOKUP(C131,'تقرير المصروفات حسب الشهر'!$C$763:$AD$872,4,FALSE),0) -> 0 | K131: =IFERROR(VLOOKUP(C131,'تقرير المصروفات حسب الشهر'!$C$890:$AD$999,4,FALSE),0) -> 0 | L131: =IFERROR(VLOOKUP(C131,'تقرير المصروفات حسب الشهر'!$C$1016:$AI$1128,4,FALSE),0) -> 0 | M131: =IFERROR(VLOOKUP(C131,'تقرير المصروفات حسب الشهر'!$C$1143:$AD$1254,4,FALSE),0) -> 0 | N131: =IFERROR(VLOOKUP(C131,'تقرير المصروفات حسب الشهر'!$C$1270:$AD$1381,4,FALSE),0) -> 0 | O131: =IFERROR(VLOOKUP(C131,'تقرير المصروفات حسب الشهر'!$C$1397:$AI$1512,4,FALSE),0) -> 0 | P131: =SUM(D131:O131) -> 0
C132: خصم أبليكيشن | D132: =IFERROR(VLOOKUP(C132,'تقرير المصروفات حسب الشهر'!$C$10:$AD$123,4,FALSE),0) -> 110901.2 | E132: =IFERROR(VLOOKUP(C132,'تقرير المصروفات حسب الشهر'!$C$135:$AD$252,4,FALSE),0) -> 129654.15 | F132: 101674.29 | G132: =IFERROR(VLOOKUP(C132,'تقرير المصروفات حسب الشهر'!$C$387:$AD$503,4,FALSE),0) -> 147006.87 | H132: =IFERROR(VLOOKUP(C132,'تقرير المصروفات حسب الشهر'!$C$512:$AD$622,4,FALSE),0) -> 180829.58 | I132: =IFERROR(VLOOKUP(C132,'تقرير المصروفات حسب الشهر'!$C$637:$AD$750,4,FALSE),0) -> 275649.23 | J132: =IFERROR(VLOOKUP(C132,'تقرير المصروفات حسب الشهر'!$C$763:$AD$877,4,FALSE),0) -> 208160.84 | K132: =IFERROR(VLOOKUP(C132,'تقرير المصروفات حسب الشهر'!$C$890:$AD$1002,4,FALSE),0) -> 177236.6 | L132: =IFERROR(VLOOKUP(C132,'تقرير المصروفات حسب الشهر'!$C$1016:$AI$1128,4,FALSE),0) -> 208850.26 | M132: =IFERROR(VLOOKUP(C132,'تقرير المصروفات حسب الشهر'!$C$1143:$AD$1254,4,FALSE),0) -> 211409.81 | N132: =IFERROR(VLOOKUP(C132,'تقرير المصروفات حسب الشهر'!$C$1270:$AD$1382,4,FALSE),0) -> 249888.56 | O132: =IFERROR(VLOOKUP(C132,'تقرير المصروفات حسب الشهر'!$C$1397:$AI$1512,4,FALSE),0) -> 294103.39 | P132: =SUM(D132:O132) -> 2295364.8
C133: عروض مبيعات ابليكشن | J133: =IFERROR(VLOOKUP(C133,'تقرير المصروفات حسب الشهر'!$C$763:$AD$877,4,FALSE),0) -> 44918.8 | K133: =IFERROR(VLOOKUP(C133,'تقرير المصروفات حسب الشهر'!$C$890:$AD$1002,4,FALSE),0) -> 84811.02 | L133: =IFERROR(VLOOKUP(C133,'تقرير المصروفات حسب الشهر'!$C$1016:$AI$1131,4,FALSE),0) -> 108196.81 | M133: =IFERROR(VLOOKUP(C133,'تقرير المصروفات حسب الشهر'!$C$1143:$AD$1258,4,FALSE),0) -> 98112.92 | N133: =IFERROR(VLOOKUP(C133,'تقرير المصروفات حسب الشهر'!$C$1270:$AI$1388,4,FALSE),0) -> 71683.78 | O133: =IFERROR(VLOOKUP(C133,'تقرير المصروفات حسب الشهر'!$C$1397:$AI$1512,4,FALSE),0) -> 104369.14
C134: إجمالي المصروفات | D134: =SUM(D22:D133) -> 591189.69 | E134: =SUM(E22:E133) -> 711587.54 | F134: =SUM(F22:F133) -> 650128.34 | G134: =SUM(G22:G133) -> 720715.12 | H134: =SUM(H22:H133) -> 727615.85 | I134: =SUM(I22:I133) -> 887538.72 | J134: =SUM(J22:J133) -> 842125.76 | K134: =SUM(K22:K133) -> 853706.6 | ... O134: =SUM(O22:O133) -> 1164684.2 | P134: =SUM(D134:O134) -> 9971010.3
C136: مجمل الربح | D136: =D19 -> 886813.52 | E136: =E19 -> 756338.34 | F136: =F19 -> 878135.12 | G136: =G19 -> 941965.25 | H136: =H19 -> 1013668.7 | I136: =I19 -> 1051336.8 | J136: =J19 -> 1054342.1 | K136: =K19 -> 1108229.9 | ... O136: =O19 -> 1370766.6 | P136: =SUM(D136:O136) -> 12586771
C139: صافي الربح / الخسارة | D139: =D136-D134 -> 295623.83 | E139: =E136-E134 -> 44750.8 | F139: =F136-F134 -> 228006.78 | G139: =G136-G134 -> 221250.13 | H139: =H136-H134 -> 286052.86 | I139: =I136-I134 -> 163798.1 | J139: =J136-J134 -> 212216.37 | K139: =K136-K134 -> 254523.33 | ... O139: =O136-O134 -> 206082.43 | P139: =SUM(D139:O139) -> 2615760.2
D143: 293913.83 | G143: =221250.3-G139 -> 0.17 | M143: =254585.97-M139 -> 0
D144: =D139-D143 -> 1710 | N144: 49420.98
N145: =N139-N144 -> 238636.07

Sheet Batal
C2: INCOME STATEMTN
F3: Income Statement For Batal
D6: Jan | E6: February | F6: March | G6: April | H6: May | I6: June | J6: July | K6: August | L6: September | M6: October | N6: November | O6: December | P6: TOTAL
C7: INCOME DETAILS
A8: البطل | C8: المبيعات | D8: =D9+D10+D11 -> 3462717.1 | E8: =E9+E10+E11 -> 3293941.3 | F8: =F9+F10+F11 -> 3688163.2 | G8: =G9+G10+G11 -> 3240278.3 | H8: =H9+H10+H11 -> 4084133.6 | I8: =I9+I10+I11 -> 3502389.2 | J8: =J9+J10+J11 -> 3823251.4 | K8: =K9+K10+K11 -> 3541414.9 | ... O8: =O9+O10+O11 -> 4155042.7 | P8: =SUM(D8:O8) -> 39412027
C9: نقدى | D9: =VLOOKUP($A$8,'تقرير إحصائية بحجم المبيعات'!$B$7:$L$31,2,FALSE) -> 1287434.9 | E9: =VLOOKUP($A$8,'تقرير إحصائية بحجم المبيعات'!$B$42:$G$73,2,FALSE) -> 1349164.7 | F9: =VLOOKUP($A$8,'تقرير إحصائية بحجم المبيعات'!$B$78:$E$103,2,FALSE) -> 979039 | G9: =VLOOKUP($A$8,'تقرير إحصائية بحجم المبيعات'!$B$112:$G$137,2,FALSE) -> 1265738.8 | H9: =VLOOKUP($A$8,'تقرير إحصائية بحجم المبيعات'!$B$147:$G$177,2,FALSE) -> 1387310.4 | I9: =VLOOKUP($A$8,'تقرير إحصائية بحجم المبيعات'!$B$182:$G$212,2,FALSE) -> 1379010.5 | J9: =VLOOKUP($A$8,'تقرير إحصائية بحجم المبيعات'!$B$217:$L$243,2,FALSE) -> 1579307.7 | K9: =VLOOKUP($A$8,'تقرير إحصائية بحجم المبيعات'!$B$252:$L$278,2,FALSE) -> 1398602.4 | L9: =VLOOKUP($A$8,'تقرير إحصائية بحجم المبيعات'!$B$287:$L$313,2,FALSE) -> 4800.59 | M9: =VLOOKUP($A$8,'تقرير إحصائية بحجم المبيعات'!$B$322:$L$347,2,FALSE) -> 1396156.7 | N9: =VLOOKUP($A$8,'تقرير إحصائية بحجم المبيعات'!$B$357:$L$383,2,FALSE) -> 2076269.1 | O9: =VLOOKUP($A$8,'تقرير إحصائية بحجم المبيعات'!$B$391:$L$420,2,FALSE) -> 1904279.8 | P9: =SUM(D9:O9) -> 16007115
C10: دليفرى | D10: =VLOOKUP($A$8,'تقرير إحصائية بحجم المبيعات'!$B$7:$L$31,3,FALSE) -> 413419.76 | E10: =VLOOKUP($A$8,'تقرير إحصائية بحجم المبيعات'!$B$42:$G$73,3,FALSE) -> 346016.26 | F10: =VLOOKUP($A$8,'تقرير إحصائية بحجم المبيعات'!$B$78:$E$103,3,FALSE) -> 402991.56 | G10: =VLOOKUP($A$8,'تقرير إحصائية بحجم المبيعات'!$B$112:$G$137,3,FALSE) -> 440049 | H10: =VLOOKUP($A$8,'تقرير إحصائية بحجم المبيعات'!$B$147:$G$177,3,FALSE) -> 412398.89 | I10: =VLOOKUP($A$8,'تقرير إحصائية بحجم المبيعات'!$B$182:$G$212,3,FALSE) -> 443322.54 | J10: =VLOOKUP($A$8,'تقرير إحصائية بحجم المبيعات'!$B$217:$L$243,3,FALSE) -> 489333.06 | K10: =VLOOKUP($A$8,'تقرير إحصائية بحجم المبيعات'!$B$252:$L$278,3,FALSE) -> 325156.46 | L10: =VLOOKUP($A$8,'تقرير إحصائية بحجم المبيعات'!$B$287:$L$313,3,FALSE) -> 0 | M10: =VLOOKUP($A$8,'تقرير إحصائية بحجم المبيعات'!$B$322:$L$347,3,FALSE) -> 309976.28 | N10: =VLOOKUP($A$8,'تقرير إحصائية بحجم المبيعات'!$B$357:$L$383,3,FALSE) -> 367237.34 | O10: =VLOOKUP($A$8,'تقرير إحصائية بحجم المبيعات'!$B$391:$L$420,3,FALSE) -> 574509.8 | P10: =SUM(D10:O10) -> 4524411
C11: اجل | D11: =VLOOKUP($A$8,'تقرير إحصائية بحجم المبيعات'!$B$7:$L$31,4,FALSE) -> 1761862.5 | E11: =VLOOKUP($A$8,'تقرير إحصائية بحجم المبيعات'!$B$42:$G$73,4,FALSE) -> 1598760.4 | F11: =VLOOKUP($A$8,'تقرير إحصائية بحجم المبيعات'!$B$78:$E$103,4,FALSE) -> 2306132.7 | G11: =VLOOKUP($A$8,'تقرير إحصائية بحجم المبيعات'!$B$112:$G$137,4,FALSE) -> 1534490.6 | H11: =VLOOKUP($A$8,'تقرير إحصائية بحجم المبيعات'!$B$147:$G$177,4,FALSE) -> 2284424.4 | I11: =VLOOKUP($A$8,'تقرير إحصائية بحجم المبيعات'!$B$182:$G$212,4,FALSE) -> 1680056.1 | J11: =VLOOKUP($A$8,'تقرير إحصائية بحجم المبيعات'!$B$217:$L$243,4,FALSE) -> 1754610.6 | K11: =VLOOKUP($A$8,'تقرير إحصائية بحجم المبيعات'!$B$252:$L$278,4,FALSE) -> 1817656 | L11: =VLOOKUP($A$8,'تقرير إحصائية بحجم المبيعات'!$B$287:$L$313,4,FALSE) -> 4394.36 | M11: =VLOOKUP($A$8,'تقرير إحصائية بحجم المبيعات'!$B$322:$L$347,4,FALSE) -> 1091080.6 | N11: =VLOOKUP($A$8,'تقرير إحصائية بحجم المبيعات'!$B$357:$L$383,4,FALSE) -> 1370779.8 | O11: =VLOOKUP($A$8,'تقرير إحصائية بحجم المبيعات'!$B$391:$L$420,4,FALSE) -> 1676253.1 | P11: =SUM(D11:O11) -> 18880501
C12: تكلفة البضاعة المباعة | D12: =VLOOKUP($A$8,'تقرير إحصائية بحجم المبيعات'!$B$7:$L$31,11,FALSE) -> 2792022.8 | E12: =VLOOKUP($A$8,'تقرير إحصائية بحجم المبيعات'!$B$42:$L$73,11,FALSE) -> 2737775.8 | F12: =VLOOKUP($A$8,'تقرير إحصائية بحجم المبيعات'!$B$78:$L$103,11,FALSE) -> 3060625.5 | G12: =VLOOKUP($A$8,'تقرير إحصائية بحجم المبيعات'!$B$112:$L$137,11,FALSE) -> 2657008.2 | H12: =VLOOKUP($A$8,'تقرير إحصائية بحجم المبيعات'!$B$147:$L$177,11,FALSE) -> 3372052.9 | I12: =VLOOKUP($A$8,'تقرير إحصائية بحجم المبيعات'!$B$182:$L$212,11,FALSE) -> 2878932.5 | J12: =VLOOKUP($A$8,'تقرير إحصائية بحجم المبيعات'!$B$217:$L$243,11,FALSE) -> 3136323.5 | K12: =VLOOKUP($A$8,'تقرير إحصائية بحجم المبيعات'!$B$252:$L$278,11,FALSE) -> 2881267.7 | L12: =VLOOKUP($A$8,'تقرير إحصائية بحجم المبيعات'!$B$287:$L$313,11,FALSE) -> 8201.62 | M12: =VLOOKUP($A$8,'تقرير إحصائية بحجم المبيعات'!$B$322:$L$347,11,FALSE) -> 2232095.2 | N12: =VLOOKUP($A$8,'تقرير إحصائية بحجم المبيعات'!$B$357:$L$383,11,FALSE) -> 3064911 | O12: =VLOOKUP($A$8,'تقرير إحصائية بحجم المبيعات'!$B$391:$L$420,11,FALSE) -> 3283960.5 | P12: =SUM(D12:O12) -> 32105177
C13: مجمل الربح | D13: =D8-D12 -> 670694.34 | E13: =E8-E12 -> 556165.49 | F13: =F8-F12 -> 627537.68 | G13: =G8-G12 -> 583270.13 | H13: =H8-H12 -> 712080.79 | I13: =I8-I12 -> 623456.75 | J13: =J8-J12 -> 686927.86 | K13: =K8-K12 -> 660147.18 | ... O13: =O8-O12 -> 871082.18 | P13: =SUM(D13:O13) -> 7306849.3
C14: خصم نقدى | P14: =SUM(D14:O14) -> 0
C15: ارباح صرف اصناف بيع اصول | P15: =SUM(D15:O15) -> 0
C16: فائض جرد | D16: 44797.26 | E16: 57205.1 | F16: 43626.53 | G16: 36243.48 | H16: 49333.27 | I16: 31365.91 | J16: 14604.59 | K16: 64701.06 | L16: 155.92 | N16: 3187.87 | P16: =SUM(D16:O16) -> 345220.99
C17: ايرادات اخرى | I17: 14000 | J17: 14600 | K17: 8700 | L17: 900 | M17: 11370 | N17: 4000 | P17: =SUM(D17:O17) -> 53570
C18: إجمالي الايرادات اخرى | D18: =SUM(D14:D17) -> 44797.26 | E18: =SUM(E14:E17) -> 57205.1 | F18: =SUM(F14:F17) -> 43626.53 | G18: =SUM(G14:G17) -> 36243.48 | H18: =SUM(H14:H17) -> 49333.27 | I18: =SUM(I14:I17) -> 45365.91 | J18: =SUM(J14:J17) -> 29204.59 | K18: =SUM(K14:K17) -> 73401.06 | ... O18: =SUM(O14:O17) -> 0 | P18: =SUM(D18:O18) -> 398790.99
C19: مجمل الربح | D19: =D13+D18 -> 715491.6 | E19: =E13+E18 -> 613370.59 | F19: =F13+F18 -> 671164.21 | G19: =G13+G18 -> 619513.61 | H19: =H13+H18 -> 761414.06 | I19: =I13+I18 -> 668822.66 | J19: =J13+J18 -> 716132.45 | K19: =K13+K18 -> 733548.24 | ... O19: =O13+O18 -> 871082.18 | P19: =SUM(D19:O19) -> 7705640.3
C21: EXPENSE DETAILS
C22: مرتبات الادارة | D22: =IFERROR(VLOOKUP(C22,'تقرير المصروفات حسب الشهر'!$C$10:$AD$119,5,FALSE),0) -> 0 | E22: =IFERROR(VLOOKUP(C22,'تقرير المصروفات حسب الشهر'!$C$135:$AD$244,5,FALSE),0) -> 0 | F22: 0 | G22: =IFERROR(VLOOKUP(C22,'تقرير المصروفات حسب الشهر'!$C$387:$AD$495,5,FALSE),0) -> 0 | H22: =IFERROR(VLOOKUP(C22,'تقرير المصروفات حسب الشهر'!$C$512:$AD$620,5,FALSE),0) -> 0 | I22: =IFERROR(VLOOKUP(C22,'تقرير المصروفات حسب الشهر'!$C$637:$AD$746,5,FALSE),0) -> 0 | J22: =IFERROR(VLOOKUP(C22,'تقرير المصروفات حسب الشهر'!$C$763:$AD$872,5,FALSE),0) -> 0 | K22: =IFERROR(VLOOKUP(C22,'تقرير المصروفات حسب الشهر'!$C$890:$AD$999,5,FALSE),0) -> 0 | L22: =IFERROR(VLOOKUP(C22,'تقرير المصروفات حسب الشهر'!$C$1016:$AD$1126,5,FALSE),0) -> 0 | M22: =IFERROR(VLOOKUP(C22,'تقرير المصروفات حسب الشهر'!$C$1143:$AD$1254,5,FALSE),0) -> 0 | N22: =IFERROR(VLOOKUP(C22,'تقرير المصروفات حسب الشهر'!$C$1270:$AD$1381,5,FALSE),0) -> 0 | O22: =IFERROR(VLOOKUP(C22,'تقرير المصروفات حسب الشهر'!$C$1397:$AD$1512,5,FALSE),0) -> 0 | P22: =SUM(D22:O22) -> 0
C23: مرتبات الفروع | D23: =IFERROR(VLOOKUP(C23,'تقرير المصروفات حسب الشهر'!$C$10:$AD$119,5,FALSE),0) -> 202939.78 | E23: =IFERROR(VLOOKUP(C23,'تقرير المصروفات حسب الشهر'!$C$135:$AD$244,5,FALSE),0) -> 243252.1 | F23: 247282.9 | G23: =IFERROR(VLOOKUP(C23,'تقرير المصروفات حسب الشهر'!$C$387:$AD$495,5,FALSE),0) -> 241871.53 | H23: =IFERROR(VLOOKUP(C23,'تقرير المصروفات حسب الشهر'!$C$512:$AD$620,5,FALSE),0) -> 266067.46 | I23: =IFERROR(VLOOKUP(C23,'تقرير المصروفات حسب الشهر'!$C$637:$AD$746,5,FALSE),0) -> 289893.95 | J23: =IFERROR(VLOOKUP(C23,'تقرير المصروفات حسب الشهر'!$C$763:$AD$872,5,FALSE),0) -> 276046.19 | K23: =IFERROR(VLOOKUP(C23,'تقرير المصروفات حسب الشهر'!$C$890:$AD$999,5,FALSE),0) -> 281311.24 | L23: =IFERROR(VLOOKUP(C23,'تقرير المصروفات حسب الشهر'!$C$1016:$AD$1126,5,FALSE),0) -> 248712.67 | M23: =IFERROR(VLOOKUP(C23,'تقرير المصروفات حسب الشهر'!$C$1143:$AD$1254,5,FALSE),0) -> 250960.3 | N23: =IFERROR(VLOOKUP(C23,'تقرير المصروفات حسب الشهر'!$C$1270:$AD$1381,5,FALSE),0) -> 242757.21 | O23: =IFERROR(VLOOKUP(C23,'تقرير المصروفات حسب الشهر'!$C$1397:$AD$1512,5,FALSE),0) -> 244676.78 | P23: =SUM(D23:O23) -> 3035772.1
C24: الكهرباء | D24: =IFERROR(VLOOKUP(C24,'تقرير المصروفات حسب الشهر'!$C$10:$AD$119,5,FALSE),0) -> 3675 | E24: =IFERROR(VLOOKUP(C24,'تقرير المصروفات حسب الشهر'!$C$135:$AD$244,5,FALSE),0) -> 3225 | F24: 3150 | G24: =IFERROR(VLOOKUP(C24,'تقرير المصروفات حسب الشهر'!$C$387:$AD$495,5,FALSE),0) -> 3430 | H24: =IFERROR(VLOOKUP(C24,'تقرير المصروفات حسب الشهر'!$C$512:$AD$620,5,FALSE),0) -> 4432 | I24: =IFERROR(VLOOKUP(C24,'تقرير المصروفات حسب الشهر'!$C$637:$AD$746,5,FALSE),0) -> 5282 | J24: =IFERROR(VLOOKUP(C24,'تقرير المصروفات حسب الشهر'!$C$763:$AD$872,5,FALSE),0) -> 6907 | K24: =IFERROR(VLOOKUP(C24,'تقرير المصروفات حسب الشهر'!$C$890:$AD$999,5,FALSE),0) -> 8391 | L24: =IFERROR(VLOOKUP(C24,'تقرير المصروفات حسب الشهر'!$C$1016:$AD$1126,5,FALSE),0) -> 10650 | M24: =IFERROR(VLOOKUP(C24,'تقرير المصروفات حسب الشهر'!$C$1143:$AD$1254,5,FALSE),0) -> 6581 | N24: =IFERROR(VLOOKUP(C24,'تقرير المصروفات حسب الشهر'!$C$1270:$AD$1381,5,FALSE),0) -> 5235 | O24: =IFERROR(VLOOKUP(C24,'تقرير المصروفات حسب الشهر'!$C$1397:$AD$1512,5,FALSE),0) -> 7745 | P24: =SUM(D24:O24) -> 68703
C25: المياه | D25: =IFERROR(VLOOKUP(C25,'تقرير المصروفات حسب الشهر'!$C$10:$AD$119,5,FALSE),0) -> 0 | E25: =IFERROR(VLOOKUP(C25,'تقرير المصروفات حسب الشهر'!$C$135:$AD$244,5,FALSE),0) -> 0 | F25: 0 | G25: =IFERROR(VLOOKUP(C25,'تقرير المصروفات حسب الشهر'!$C$387:$AD$495,5,FALSE),0) -> 580 | H25: =IFERROR(VLOOKUP(C25,'تقرير المصروفات حسب الشهر'!$C$512:$AD$620,5,FALSE),0) -> 0 | I25: =IFERROR(VLOOKUP(C25,'تقرير المصروفات حسب الشهر'!$C$637:$AD$746,5,FALSE),0) -> 0 | J25: =IFERROR(VLOOKUP(C25,'تقرير المصروفات حسب الشهر'!$C$763:$AD$872,5,FALSE),0) -> 320 | K25: =IFERROR(VLOOKUP(C25,'تقرير المصروفات حسب الشهر'!$C$890:$AD$999,5,FALSE),0) -> 118 | L25: =IFERROR(VLOOKUP(C25,'تقرير المصروفات حسب الشهر'!$C$1016:$AD$1126,5,FALSE),0) -> 0 | M25: =IFERROR(VLOOKUP(C25,'تقرير المصروفات حسب الشهر'!$C$1143:$AD$1254,5,FALSE),0) -> 236 | N25: =IFERROR(VLOOKUP(C25,'تقرير المصروفات حسب الشهر'!$C$1270:$AD$1381,5,FALSE),0) -> 137 | O25: =IFERROR(VLOOKUP(C25,'تقرير المصروفات حسب الشهر'!$C$1397:$AD$1512,5,FALSE),0) -> 0 | P25: =SUM(D25:O25) -> 1391
C26: التليفون الارضي | D26: =IFERROR(VLOOKUP(C26,'تقرير المصروفات حسب الشهر'!$C$10:$AD$119,5,FALSE),0) -> 600 | E26: =IFERROR(VLOOKUP(C26,'تقرير المصروفات حسب الشهر'!$C$135:$AD$244,5,FALSE),0) -> 0 | F26: 350 | G26: =IFERROR(VLOOKUP(C26,'تقرير المصروفات حسب الشهر'!$C$387:$AD$495,5,FALSE),0) -> 0 | H26: =IFERROR(VLOOKUP(C26,'تقرير المصروفات حسب الشهر'!$C$512:$AD$620,5,FALSE),0) -> 0 | I26: =IFERROR(VLOOKUP(C26,'تقرير المصروفات حسب الشهر'!$C$637:$AD$746,5,FALSE),0) -> 800 | J26: =IFERROR(VLOOKUP(C26,'تقرير المصروفات حسب الشهر'!$C$763:$AD$872,5,FALSE),0) -> 0 | K26: =IFERROR(VLOOKUP(C26,'تقرير المصروفات حسب الشهر'!$C$890:$AD$999,5,FALSE),0) -> 0 | L26: =IFERROR(VLOOKUP(C26,'تقرير المصروفات حسب الشهر'!$C$1016:$AD$1126,5,FALSE),0) -> 0 | M26: =IFERROR(VLOOKUP(C26,'تقرير المصروفات حسب الشهر'!$C$1143:$AD$1254,5,FALSE),0) -> 0 | N26: =IFERROR(VLOOKUP(C26,'تقرير المصروفات حسب الشهر'!$C$1270:$AD$1381,5,FALSE),0) -> 400 | O26: =IFERROR(VLOOKUP(C26,'تقرير المصروفات حسب الشهر'!$C$1397:$AD$1512,5,FALSE),0) -> 0 | P26: =SUM(D26:O26) -> 2150
C27: الايجار - الصيدلية | D27: =IFERROR(VLOOKUP(C27,'تقرير المصروفات حسب الشهر'!$C$10:$AD$119,5,FALSE),0) -> 100000 | E27: =IFERROR(VLOOKUP(C27,'تقرير المصروفات حسب الشهر'!$C$135:$AD$244,5,FALSE),0) -> 100000 | F27: 100000 | G27: =IFERROR(VLOOKUP(C27,'تقرير المصروفات حسب الشهر'!$C$387:$AD$495,5,FALSE),0) -> 100000 | H27: =IFERROR(VLOOKUP(C27,'تقرير المصروفات حسب الشهر'!$C$512:$AD$620,5,FALSE),0) -> 100000 | I27: =IFERROR(VLOOKUP(C27,'تقرير المصروفات حسب الشهر'!$C$637:$AD$746,5,FALSE),0) -> 100000 | J27: =IFERROR(VLOOKUP(C27,'تقرير المصروفات حسب الشهر'!$C$763:$AD$872,5,FALSE),0) -> 100000 | K27: =IFERROR(VLOOKUP(C27,'تقرير المصروفات حسب الشهر'!$C$890:$AD$999,5,FALSE),0) -> 100000 | L27: =IFERROR(VLOOKUP(C27,'تقرير المصروفات حسب الشهر'!$C$1016:$AD$1126,5,FALSE),0) -> 100000 | M27: =IFERROR(VLOOKUP(C27,'تقرير المصروفات حسب الشهر'!$C$1143:$AD$1254,5,FALSE),0) -> 100000 | N27: =IFERROR(VLOOKUP(C27,'تقرير المصروفات حسب الشهر'!$C$1270:$AD$1381,5,FALSE),0) -> 170000 | O27: =IFERROR(VLOOKUP(C27,'تقرير المصروفات حسب الشهر'!$C$1397:$AD$1512,5,FALSE),0) -> 170000 | P27: =SUM(D27:O27) -> 1340000
C28: الايجار - الادارة | D28: =IFERROR(VLOOKUP(C28,'تقرير المصروفات حسب الشهر'!$C$10:$AD$119,5,FALSE),0) -> 0 | E28: =IFERROR(VLOOKUP(C28,'تقرير المصروفات حسب الشهر'!$C$135:$AD$244,5,FALSE),0) -> 0 | F28: 0 | G28: =IFERROR(VLOOKUP(C28,'تقرير المصروفات حسب الشهر'!$C$387:$AD$495,5,FALSE),0) -> 0 | H28: =IFERROR(VLOOKUP(C28,'تقرير المصروفات حسب الشهر'!$C$512:$AD$620,5,FALSE),0) -> 0 | I28: =IFERROR(VLOOKUP(C28,'تقرير المصروفات حسب الشهر'!$C$637:$AD$746,5,FALSE),0) -> 0 | J28: =IFERROR(VLOOKUP(C28,'تقرير المصروفات حسب الشهر'!$C$763:$AD$872,5,FALSE),0) -> 0 | K28: =IFERROR(VLOOKUP(C28,'تقرير المصروفات حسب الشهر'!$C$890:$AD$999,5,FALSE),0) -> 0 | L28: =IFERROR(VLOOKUP(C28,'تقرير المصروفات حسب الشهر'!$C$1016:$AD$1126,5,FALSE),0) -> 0 | M28: =IFERROR(VLOOKUP(C28,'تقرير المصروفات حسب الشهر'!$C$1143:$AD$1254,5,FALSE),0) -> 0 | N28: =IFERROR(VLOOKUP(C28,'تقرير المصروفات حسب الشهر'!$C$1270:$AD$1381,5,FALSE),0) -> 0 | O28: =IFERROR(VLOOKUP(C28,'تقرير المصروفات حسب الشهر'!$C$1397:$AD$1512,5,FALSE),0) -> 0 | P28: =SUM(D28:O28) -> 0
C29: ايجارات متنوعه | D29: =IFERROR(VLOOKUP(C29,'تقرير المصروفات حسب الشهر'!$C$10:$AD$119,5,FALSE),0) -> 0 | E29: =IFERROR(VLOOKUP(C29,'تقرير المصروفات حسب الشهر'!$C$135:$AD$244,5,FALSE),0) -> 0 | F29: 0 | G29: =IFERROR(VLOOKUP(C29,'تقرير المصروفات حسب الشهر'!$C$387:$AD$495,5,FALSE),0) -> 0 | H29: =IFERROR(VLOOKUP(C29,'تقرير المصروفات حسب الشهر'!$C$512:$AD$620,5,FALSE),0) -> 0 | I29: =IFERROR(VLOOKUP(C29,'تقرير المصروفات حسب الشهر'!$C$637:$AD$746,5,FALSE),0) -> 0 | J29: =IFERROR(VLOOKUP(C29,'تقرير المصروفات حسب الشهر'!$C$763:$AD$872,5,FALSE),0) -> 0 | K29: =IFERROR(VLOOKUP(C29,'تقرير المصروفات حسب الشهر'!$C$890:$AD$999,5,FALSE),0) -> 12000 | L29: =IFERROR(VLOOKUP(C29,'تقرير المصروفات حسب الشهر'!$C$1016:$AD$1126,5,FALSE),0) -> 0 | M29: =IFERROR(VLOOKUP(C29,'تقرير المصروفات حسب الشهر'!$C$1143:$AD$1254,5,FALSE),0) -> 3000 | N29: =IFERROR(VLOOKUP(C29,'تقرير المصروفات حسب الشهر'!$C$1270:$AD$1381,5,FALSE),0) -> 0 | O29: =IFERROR(VLOOKUP(C29,'تقرير المصروفات حسب الشهر'!$C$1397:$AD$1512,5,FALSE),0) -> 0 | P29: =SUM(D29:O29) -> 15000
C30: ادوات مكتبية | D30: =IFERROR(VLOOKUP(C30,'تقرير المصروفات حسب الشهر'!$C$10:$AD$119,5,FALSE),0) -> 185 | E30: =IFERROR(VLOOKUP(C30,'تقرير المصروفات حسب الشهر'!$C$135:$AD$244,5,FALSE),0) -> 180 | F30: 999.5 | G30: =IFERROR(VLOOKUP(C30,'تقرير المصروفات حسب الشهر'!$C$387:$AD$495,5,FALSE),0) -> 0 | H30: =IFERROR(VLOOKUP(C30,'تقرير المصروفات حسب الشهر'!$C$512:$AD$620,5,FALSE),0) -> 275 | I30: =IFERROR(VLOOKUP(C30,'تقرير المصروفات حسب الشهر'!$C$637:$AD$746,5,FALSE),0) -> 25 | J30: =IFERROR(VLOOKUP(C30,'تقرير المصروفات حسب الشهر'!$C$763:$AD$872,5,FALSE),0) -> 301 | K30: =IFERROR(VLOOKUP(C30,'تقرير المصروفات حسب الشهر'!$C$890:$AD$999,5,FALSE),0) -> 290 | L30: =IFERROR(VLOOKUP(C30,'تقرير المصروفات حسب الشهر'!$C$1016:$AD$1126,5,FALSE),0) -> 0 | M30: =IFERROR(VLOOKUP(C30,'تقرير المصروفات حسب الشهر'!$C$1143:$AD$1254,5,FALSE),0) -> 785.5 | N30: =IFERROR(VLOOKUP(C30,'تقرير المصروفات حسب الشهر'!$C$1270:$AD$1381,5,FALSE),0) -> 25 | O30: =IFERROR(VLOOKUP(C30,'تقرير المصروفات حسب الشهر'!$C$1397:$AD$1512,5,FALSE),0) -> 1100 | P30: =SUM(D30:O30) -> 4166
C31: فواتير الموبايل | D31: =IFERROR(VLOOKUP(C31,'تقرير المصروفات حسب الشهر'!$C$10:$AD$119,5,FALSE),0) -> 464.47 | E31: =IFERROR(VLOOKUP(C31,'تقرير المصروفات حسب الشهر'!$C$135:$AD$244,5,FALSE),0) -> 464.47 | F31: 489.46 | G31: =IFERROR(VLOOKUP(C31,'تقرير المصروفات حسب الشهر'!$C$387:$AD$495,5,FALSE),0) -> 444.46 | H31: =IFERROR(VLOOKUP(C31,'تقرير المصروفات حسب الشهر'!$C$512:$AD$620,5,FALSE),0) -> 444.46 | I31: =IFERROR(VLOOKUP(C31,'تقرير المصروفات حسب الشهر'!$C$637:$AD$746,5,FALSE),0) -> 844.46 | J31: =IFERROR(VLOOKUP(C31,'تقرير المصروفات حسب الشهر'!$C$763:$AD$872,5,FALSE),0) -> 444.46 | K31: =IFERROR(VLOOKUP(C31,'تقرير المصروفات حسب الشهر'!$C$890:$AD$999,5,FALSE),0) -> 444.46 | L31: =IFERROR(VLOOKUP(C31,'تقرير المصروفات حسب الشهر'!$C$1016:$AD$1126,5,FALSE),0) -> 444.46 | M31: =IFERROR(VLOOKUP(C31,'تقرير المصروفات حسب الشهر'!$C$1143:$AD$1254,5,FALSE),0) -> 644.46 | N31: =IFERROR(VLOOKUP(C31,'تقرير المصروفات حسب الشهر'!$C$1270:$AD$1381,5,FALSE),0) -> 444.46 | O31: =IFERROR(VLOOKUP(C31,'تقرير المصروفات حسب الشهر'!$C$1397:$AD$1512,5,FALSE),0) -> 444.46 | P31: =SUM(D31:O31) -> 6018.54
C32: مكافات مبيعات الادوية | D32: =IFERROR(VLOOKUP(C32,'تقرير المصروفات حسب الشهر'!$C$10:$AD$119,5,FALSE),0) -> 0 | E32: =IFERROR(VLOOKUP(C32,'تقرير المصروفات حسب الشهر'!$C$135:$AD$244,5,FALSE),0) -> 0 | F32: 0 | G32: =IFERROR(VLOOKUP(C32,'تقرير المصروفات حسب الشهر'!$C$387:$AD$495,5,FALSE),0) -> 0 | H32: =IFERROR(VLOOKUP(C32,'تقرير المصروفات حسب الشهر'!$C$512:$AD$620,5,FALSE),0) -> 0 | I32: =IFERROR(VLOOKUP(C32,'تقرير المصروفات حسب الشهر'!$C$637:$AD$746,5,FALSE),0) -> 0 | J32: =IFERROR(VLOOKUP(C32,'تقرير المصروفات حسب الشهر'!$C$763:$AD$872,5,FALSE),0) -> 0 | K32: =IFERROR(VLOOKUP(C32,'تقرير المصروفات حسب الشهر'!$C$890:$AD$999,5,FALSE),0) -> 0 | L32: =IFERROR(VLOOKUP(C32,'تقرير المصروفات حسب الشهر'!$C$1016:$AD$1126,5,FALSE),0) -> 0 | M32: =IFERROR(VLOOKUP(C32,'تقرير المصروفات حسب الشهر'!$C$1143:$AD$1254,5,FALSE),0) -> 0 | N32: =IFERROR(VLOOKUP(C32,'تقرير المصروفات حسب الشهر'!$C$1270:$AD$1381,5,FALSE),0) -> 0 | O32: =IFERROR(VLOOKUP(C32,'تقرير المصروفات حسب الشهر'!$C$1397:$AD$1512,5,FALSE),0) -> 0 | P32: =SUM(D32:O32) -> 0
C33: مكافات مبيعات التجميل | D33: =IFERROR(VLOOKUP(C33,'تقرير المصروفات حسب الشهر'!$C$10:$AD$119,5,FALSE),0) -> 0 | E33: =IFERROR(VLOOKUP(C33,'تقرير المصروفات حسب الشهر'!$C$135:$AD$244,5,FALSE),0) -> 0 | F33: 0 | G33: =IFERROR(VLOOKUP(C33,'تقرير المصروفات حسب الشهر'!$C$387:$AD$495,5,FALSE),0) -> 0 | H33: =IFERROR(VLOOKUP(C33,'تقرير المصروفات حسب الشهر'!$C$512:$AD$620,5,FALSE),0) -> 0 | I33: =IFERROR(VLOOKUP(C33,'تقرير المصروفات حسب الشهر'!$C$637:$AD$746,5,FALSE),0) -> 0 | J33: =IFERROR(VLOOKUP(C33,'تقرير المصروفات حسب الشهر'!$C$763:$AD$872,5,FALSE),0) -> 750 | K33: =IFERROR(VLOOKUP(C33,'تقرير المصروفات حسب الشهر'!$C$890:$AD$999,5,FALSE),0) -> 0 | L33: =IFERROR(VLOOKUP(C33,'تقرير المصروفات حسب الشهر'!$C$1016:$AD$1126,5,FALSE),0) -> 0 | M33: =IFERROR(VLOOKUP(C33,'تقرير المصروفات حسب الشهر'!$C$1143:$AD$1254,5,FALSE),0) -> 0 | N33: =IFERROR(VLOOKUP(C33,'تقرير المصروفات حسب الشهر'!$C$1270:$AD$1381,5,FALSE),0) -> 250 | O33: =IFERROR(VLOOKUP(C33,'تقرير المصروفات حسب الشهر'!$C$1397:$AD$1512,5,FALSE),0) -> 0 | P33: =SUM(D33:O33) -> 1000
... C131: فوائد القروض - بنك القاهرة BDC | D131: =IFERROR(VLOOKUP(C131,'تقرير المصروفات حسب الشهر'!$C$10:$AD$119,5,FALSE),0) -> 0 | E131: =IFERROR(VLOOKUP(C131,'تقرير المصروفات حسب الشهر'!$C$135:$AD$244,5,FALSE),0) -> 0 | F131: 0 | G131: =IFERROR(VLOOKUP(C131,'تقرير المصروفات حسب الشهر'!$C$387:$AD$495,5,FALSE),0) -> 0 | H131: =IFERROR(VLOOKUP(C131,'تقرير المصروفات حسب الشهر'!$C$512:$AD$620,5,FALSE),0) -> 0 | I131: =IFERROR(VLOOKUP(C131,'تقرير المصروفات حسب الشهر'!$C$637:$AD$746,5,FALSE),0) -> 0 | J131: =IFERROR(VLOOKUP(C131,'تقرير المصروفات حسب الشهر'!$C$763:$AD$872,5,FALSE),0) -> 0 | K131: =IFERROR(VLOOKUP(C131,'تقرير المصروفات حسب الشهر'!$C$890:$AD$999,5,FALSE),0) -> 0 | L131: =IFERROR(VLOOKUP(C131,'تقرير المصروفات حسب الشهر'!$C$1016:$AD$1126,5,FALSE),0) -> 0 | M131: =IFERROR(VLOOKUP(C131,'تقرير المصروفات حسب الشهر'!$C$1143:$AD$1254,5,FALSE),0) -> 0 | N131: =IFERROR(VLOOKUP(C131,'تقرير المصروفات حسب الشهر'!$C$1270:$AD$1381,5,FALSE),0) -> 0 | O131: =IFERROR(VLOOKUP(C131,'تقرير المصروفات حسب الشهر'!$C$1397:$AD$1512,5,FALSE),0) -> 0 | P131: =SUM(D131:O131) -> 0
C132: خصم أبليكيشن | D132: =IFERROR(VLOOKUP(C132,'تقرير المصروفات حسب الشهر'!$C$10:$AD$119,5,FALSE),0) -> 0 | E132: =IFERROR(VLOOKUP(C132,'تقرير المصروفات حسب الشهر'!$C$135:$AD$252,5,FALSE),0) -> 0 | F132: 38 | G132: =IFERROR(VLOOKUP(C132,'تقرير المصروفات حسب الشهر'!$C$387:$AD$503,5,FALSE),0) -> 0 | H132: =IFERROR(VLOOKUP(C132,'تقرير المصروفات حسب الشهر'!$C$512:$AD$620,5,FALSE),0) -> 0 | I132: =IFERROR(VLOOKUP(C132,'تقرير المصروفات حسب الشهر'!$C$637:$AD$746,5,FALSE),0) -> 0 | J132: =IFERROR(VLOOKUP(C132,'تقرير المصروفات حسب الشهر'!$C$763:$AD$872,5,FALSE),0) -> 0 | K132: =IFERROR(VLOOKUP(C132,'تقرير المصروفات حسب الشهر'!$C$890:$AD$999,5,FALSE),0) -> 0 | L132: =IFERROR(VLOOKUP(C132,'تقرير المصروفات حسب الشهر'!$C$1016:$AD$1126,5,FALSE),0) -> 0 | M132: =IFERROR(VLOOKUP(C132,'تقرير المصروفات حسب الشهر'!$C$1143:$AD$1254,5,FALSE),0) -> 0 | N132: =IFERROR(VLOOKUP(C132,'تقرير المصروفات حسب الشهر'!$C$1270:$AD$1382,5,FALSE),0) -> 0 | O132: =IFERROR(VLOOKUP(C132,'تقرير المصروفات حسب الشهر'!$C$1397:$AD$1512,5,FALSE),0) -> 0 | P132: =SUM(D132:O132) -> 38
C133: إجمالي المصروفات | D133: =SUM(D22:D132) -> 442745.71 | E133: =SUM(E22:E132) -> 443477.99 | F133: =SUM(F22:F132) -> 488095.28 | G133: =SUM(G22:G132) -> 453940.34 | H133: =SUM(H22:H132) -> 482800.97 | I133: =SUM(I22:I132) -> 505379.2 | J133: =SUM(J22:J132) -> 490212.36 | K133: =SUM(K22:K132) -> 491281.75 | ... O133: =SUM(O22:O132) -> 567806.83 | P133: =SUM(D133:O133) -> 5932915.3
C135: مجمل الربح | D135: =D19 -> 715491.6 | E135: =E19 -> 613370.59 | F135: =F19 -> 671164.21 | G135: =G19 -> 619513.61 | H135: =H19 -> 761414.06 | I135: =I19 -> 668822.66 | J135: =J19 -> 716132.45 | K135: =K19 -> 733548.24 | ... O135: =O19 -> 871082.18 | P135: =SUM(D135:O135) -> 7705640.3
C138: صافي الربح / الخسارة | D138: =D135-D133 -> 272745.89 | E138: =E135-E133 -> 169892.6 | F138: =F135-F133 -> 183068.93 | G138: =G135-G133 -> 165573.27 | H138: =H135-H133 -> 278613.09 | I138: =I135-I133 -> 163443.46 | J138: =J135-J133 -> 225920.09 | K138: =K135-K133 -> 242266.49 | ... O138: =O135-O133 -> 303275.35 | P138: =SUM(D138:O138) -> 1772724.9
D142: 271155.02 | G142: =165573.27-G138 -> -3.2014214e-10 | J142: 225920.09
D143: =D138-D142 -> 1590.87 | J143: =J138-J142 -> 0 | N143: =N138-254796.36 -> -35060.89

Sheet Nasr City
C2: INCOME STATEMTN
F3: Income Statement For Nasr City
D6: Jan | E6: February | F6: March | G6: April | H6: May | I6: June | J6: July | K6: August | L6: September | M6: October | N6: November | O6: December | P6: TOTAL
C7: INCOME DETAILS
A8: م.نصر | C8: المبيعات | D8: =D9+D10+D11 -> 6047113.2 | E8: =E9+E10+E11 -> 5751510.4 | F8: =F9+F10+F11 -> 7004459.6 | G8: =G9+G10+G11 -> 7366525.8 | H8: =H9+H10+H11 -> 7812104.3 | I8: =I9+I10+I11 -> 7805089 | J8: =J9+J10+J11 -> 8137183.7 | K8: =K9+K10+K11 -> 8422039.1 | ... O8: =O9+O10+O11 -> 8105649.7 | P8: =SUM(D8:O8) -> 90978965
C9: نقدى | D9: =VLOOKUP($A$8,'تقرير إحصائية بحجم المبيعات'!$B$7:$L$31,2,FALSE) -> 2968127.6 | E9: =VLOOKUP($A$8,'تقرير إحصائية بحجم المبيعات'!$B$42:$G$73,2,FALSE) -> 2907073.9 | F9: =VLOOKUP($A$8,'تقرير إحصائية بحجم المبيعات'!$B$78:$E$103,2,FALSE) -> 3477752.7 | G9: =VLOOKUP($A$8,'تقرير إحصائية بحجم المبيعات'!$B$112:$G$137,2,FALSE) -> 4202403.9 | H9: =VLOOKUP($A$8,'تقرير إحصائية بحجم المبيعات'!$B$147:$G$177,2,FALSE) -> 4668777.2 | I9: =VLOOKUP($A$8,'تقرير إحصائية بحجم المبيعات'!$B$182:$G$212,2,FALSE) -> 4777375 | J9: =VLOOKUP($A$8,'تقرير إحصائية بحجم المبيعات'!$B$217:$L$243,2,FALSE) -> 5228586.7 | K9: =VLOOKUP($A$8,'تقرير إحصائية بحجم المبيعات'!$B$252:$L$278,2,FALSE) -> 5856948.7 | L9: =VLOOKUP($A$8,'تقرير إحصائية بحجم المبيعات'!$B$287:$L$313,2,FALSE) -> 5083204.6 | M9: =VLOOKUP($A$8,'تقرير إحصائية بحجم المبيعات'!$B$322:$L$347,2,FALSE) -> 5763435.8 | N9: =VLOOKUP($A$8,'تقرير إحصائية بحجم المبيعات'!$B$357:$L$383,2,FALSE) -> 5941090.9 | O9: =VLOOKUP($A$8,'تقرير إحصائية بحجم المبيعات'!$B$391:$L$420,2,FALSE) -> 5251205.8 | P9: =SUM(D9:O9) -> 56125983
C10: دليفرى | D10: =VLOOKUP($A$8,'تقرير إحصائية بحجم المبيعات'!$B$7:$L$31,3,FALSE) -> 26884.18 | E10: =VLOOKUP($A$8,'تقرير إحصائية بحجم المبيعات'!$B$42:$G$73,3,FALSE) -> 22099.3 | F10: =VLOOKUP($A$8,'تقرير إحصائية بحجم المبيعات'!$B$78:$E$103,3,FALSE) -> 25190.37 | G10: =VLOOKUP($A$8,'تقرير إحصائية بحجم المبيعات'!$B$112:$G$137,3,FALSE) -> 25810.24 | H10: =VLOOKUP($A$8,'تقرير إحصائية بحجم المبيعات'!$B$147:$G$177,3,FALSE) -> 18535.16 | I10: =VLOOKUP($A$8,'تقرير إحصائية بحجم المبيعات'!$B$182:$G$212,3,FALSE) -> 46263.74 | J10: =VLOOKUP($A$8,'تقرير إحصائية بحجم المبيعات'!$B$217:$L$243,3,FALSE) -> 39259.01 | K10: =VLOOKUP($A$8,'تقرير إحصائية بحجم المبيعات'!$B$252:$L$278,3,FALSE) -> 32827.84 | L10: =VLOOKUP($A$8,'تقرير إحصائية بحجم المبيعات'!$B$287:$L$313,3,FALSE) -> 33383.63 | M10: =VLOOKUP($A$8,'تقرير إحصائية بحجم المبيعات'!$B$322:$L$347,3,FALSE) -> 34164.99 | N10: =VLOOKUP($A$8,'تقرير إحصائية بحجم المبيعات'!$B$357:$L$383,3,FALSE) -> 21738.74 | O10: =VLOOKUP($A$8,'تقرير إحصائية بحجم المبيعات'!$B$391:$L$420,3,FALSE) -> 28080.61 | P10: =SUM(D10:O10) -> 354237.81
C11: اجل | D11: =VLOOKUP($A$8,'تقرير إحصائية بحجم المبيعات'!$B$7:$L$31,4,FALSE) -> 3052101.4 | E11: =VLOOKUP($A$8,'تقرير إحصائية بحجم المبيعات'!$B$42:$G$73,4,FALSE) -> 2822337.2 | F11: =VLOOKUP($A$8,'تقرير إحصائية بحجم المبيعات'!$B$78:$E$103,4,FALSE) -> 3501516.5 | G11: =VLOOKUP($A$8,'تقرير إحصائية بحجم المبيعات'!$B$112:$G$137,4,FALSE) -> 3138311.7 | H11: =VLOOKUP($A$8,'تقرير إحصائية بحجم المبيعات'!$B$147:$G$177,4,FALSE) -> 3124791.9 | I11: =VLOOKUP($A$8,'تقرير إحصائية بحجم المبيعات'!$B$182:$G$212,4,FALSE) -> 2981450.3 | J11: =VLOOKUP($A$8,'تقرير إحصائية بحجم المبيعات'!$B$217:$L$243,4,FALSE) -> 2869338 | K11: =VLOOKUP($A$8,'تقرير إحصائية بحجم المبيعات'!$B$252:$L$278,4,FALSE) -> 2532262.6 | L11: =VLOOKUP($A$8,'تقرير إحصائية بحجم المبيعات'!$B$287:$L$313,4,FALSE) -> 2542432.5 | M11: =VLOOKUP($A$8,'تقرير إحصائية بحجم المبيعات'!$B$322:$L$347,4,FALSE) -> 2600037.3 | N11: =VLOOKUP($A$8,'تقرير إحصائية بحجم المبيعات'!$B$357:$L$383,4,FALSE) -> 2507801.8 | O11: =VLOOKUP($A$8,'تقرير إحصائية بحجم المبيعات'!$B$391:$L$420,4,FALSE) -> 2826363.2 | P11: =SUM(D11:O11) -> 34498745
C12: تكلفة البضاعة المباعة | D12: =VLOOKUP($A$8,'تقرير إحصائية بحجم المبيعات'!$B$7:$L$31,11,FALSE) -> 4964163 | E12: =VLOOKUP($A$8,'تقرير إحصائية بحجم المبيعات'!$B$42:$L$73,11,FALSE) -> 4732710.2 | F12: =VLOOKUP($A$8,'تقرير إحصائية بحجم المبيعات'!$B$78:$L$103,11,FALSE) -> 5757854.2 | G12: =VLOOKUP($A$8,'تقرير إحصائية بحجم المبيعات'!$B$112:$L$137,11,FALSE) -> 6053035 | H12: =VLOOKUP($A$8,'تقرير إحصائية بحجم المبيعات'!$B$147:$L$177,11,FALSE) -> 6422056.6 | I12: =VLOOKUP($A$8,'تقرير إحصائية بحجم المبيعات'!$B$182:$L$212,11,FALSE) -> 6404342.3 | J12: =VLOOKUP($A$8,'تقرير إحصائية بحجم المبيعات'!$B$217:$L$243,11,FALSE) -> 6600107 | K12: =VLOOKUP($A$8,'تقرير إحصائية بحجم المبيعات'!$B$252:$L$278,11,FALSE) -> 6854824.1 | L12: =VLOOKUP($A$8,'تقرير إحصائية بحجم المبيعات'!$B$287:$L$313,11,FALSE) -> 6242404.2 | M12: =VLOOKUP($A$8,'تقرير إحصائية بحجم المبيعات'!$B$322:$L$347,11,FALSE) -> 6844885.1 | N12: =VLOOKUP($A$8,'تقرير إحصائية بحجم المبيعات'!$B$357:$L$383,11,FALSE) -> 6931653.1 | O12: =VLOOKUP($A$8,'تقرير إحصائية بحجم المبيعات'!$B$391:$L$420,11,FALSE) -> 6592423.2 | P12: =SUM(D12:O12) -> 74400458
C13: مجمل الربح | D13: =D8-D12 -> 1082950.2 | E13: =E8-E12 -> 1018800.3 | F13: =F8-F12 -> 1246605.4 | G13: =G8-G12 -> 1313490.9 | H13: =H8-H12 -> 1390047.7 | I13: =I8-I12 -> 1400746.8 | J13: =J8-J12 -> 1537076.7 | K13: =K8-K12 -> 1567215 | ... O13: =O8-O12 -> 1513226.5 | P13: =SUM(D13:O13) -> 16578507
C14: خصم نقدى | P14: =SUM(D14:O14) -> 0
C15: ارباح صرف اصناف بيع اصول | P15: =SUM(D15:O15) -> 0
C16: فائض جرد | E16: 109100.7 | F16: 0.01 | H16: 1154.28 | I16: 111686.53 | J16: 18912.77 | N16: 125017.45 | P16: =SUM(D16:O16) -> 365871.74
C17: ايرادات اخرى | P17: =SUM(D17:O17) -> 0
C18: إجمالي الايرادات اخرى | D18: =SUM(D14:D17) -> 0 | E18: =SUM(E14:E17) -> 109100.7 | F18: =SUM(F14:F17) -> 0.01 | G18: =SUM(G14:G17) -> 0 | H18: =SUM(H14:H17) -> 1154.28 | I18: =SUM(I14:I17) -> 111686.53 | J18: =SUM(J14:J17) -> 18912.77 | K18: =SUM(K14:K17) -> 0 | ... O18: =SUM(O14:O17) -> 0 | P18: =SUM(D18:O18) -> 365871.74
C19: مجمل الربح | D19: =D13+D18 -> 1082950.2 | E19: =E13+E18 -> 1127901 | F19: =F13+F18 -> 1246605.4 | G19: =G13+G18 -> 1313490.9 | H19: =H13+H18 -> 1391202 | I19: =I13+I18 -> 1512433.3 | J19: =J13+J18 -> 1555989.5 | K19: =K13+K18 -> 1567215 | ... O19: =O13+O18 -> 1513226.5 | P19: =SUM(D19:O19) -> 16944379
C21: EXPENSE DETAILS
C22: مرتبات الادارة | D22: =IFERROR(VLOOKUP(C22,'تقرير المصروفات حسب الشهر'!$C$10:$AD$119,6,FALSE),0) -> 0 | E22: =IFERROR(VLOOKUP(C22,'تقرير المصروفات حسب الشهر'!$C$135:$AD$244,6,FALSE),0) -> 0 | F22: 0 | G22: =IFERROR(VLOOKUP(C22,'تقرير المصروفات حسب الشهر'!$C$387:$AD$495,6,FALSE),0) -> 0 | H22: =IFERROR(VLOOKUP(C22,'تقرير المصروفات حسب الشهر'!$C$512:$AD$620,6,FALSE),0) -> 0 | I22: =IFERROR(VLOOKUP(C22,'تقرير المصروفات حسب الشهر'!$C$637:$AD$746,6,FALSE),0) -> 0 | J22: =IFERROR(VLOOKUP(C22,'تقرير المصروفات حسب الشهر'!$C$763:$AD$872,6,FALSE),0) -> 0 | K22: =IFERROR(VLOOKUP(C22,'تقرير المصروفات حسب الشهر'!$C$890:$AD$999,6,FALSE),0) -> 0 | L22: =IFERROR(VLOOKUP(C22,'تقرير المصروفات حسب الشهر'!$C$1016:$AD$1126,6,FALSE),0) -> 0 | M22: =IFERROR(VLOOKUP(C22,'تقرير المصروفات حسب الشهر'!$C$1143:$AD$1254,6,FALSE),0) -> 0 | N22: =IFERROR(VLOOKUP(C22,'تقرير المصروفات حسب الشهر'!$C$1270:$AD$1381,6,FALSE),0) -> 0 | O22: =IFERROR(VLOOKUP(C22,'تقرير المصروفات حسب الشهر'!$C$1397:$AD$1512,6,FALSE),0) -> 0 | P22: =SUM(D22:O22) -> 0
C23: مرتبات الفروع | D23: =IFERROR(VLOOKUP(C23,'تقرير المصروفات حسب الشهر'!$C$10:$AD$119,6,FALSE),0) -> 225190.19 | E23: =IFERROR(VLOOKUP(C23,'تقرير المصروفات حسب الشهر'!$C$135:$AD$244,6,FALSE),0) -> 394064.43 | F23: 335845.78 | G23: =IFERROR(VLOOKUP(C23,'تقرير المصروفات حسب الشهر'!$C$387:$AD$495,6,FALSE),0) -> 351978.74 | H23: =IFERROR(VLOOKUP(C23,'تقرير المصروفات حسب الشهر'!$C$512:$AD$620,6,FALSE),0) -> 410391.49 | I23: =IFERROR(VLOOKUP(C23,'تقرير المصروفات حسب الشهر'!$C$637:$AD$746,6,FALSE),0) -> 450714.87 | J23: =IFERROR(VLOOKUP(C23,'تقرير المصروفات حسب الشهر'!$C$763:$AD$872,6,FALSE),0) -> 412599.93 | K23: =IFERROR(VLOOKUP(C23,'تقرير المصروفات حسب الشهر'!$C$890:$AD$999,6,FALSE),0) -> 438049.72 | L23: =IFERROR(VLOOKUP(C23,'تقرير المصروفات حسب الشهر'!$C$1016:$AD$1126,6,FALSE),0) -> 441099.77 | M23: =IFERROR(VLOOKUP(C23,'تقرير المصروفات حسب الشهر'!$C$1143:$AD$1254,6,FALSE),0) -> 415936.46 | N23: =IFERROR(VLOOKUP(C23,'تقرير المصروفات حسب الشهر'!$C$1270:$AD$1381,6,FALSE),0) -> 439149.09 | O23: =IFERROR(VLOOKUP(C23,'تقرير المصروفات حسب الشهر'!$C$1397:$AD$1512,6,FALSE),0) -> 451068.75 | P23: =SUM(D23:O23) -> 4766089.2
C24: الكهرباء | D24: =IFERROR(VLOOKUP(C24,'تقرير المصروفات حسب الشهر'!$C$10:$AD$119,6,FALSE),0) -> 2670 | E24: =IFERROR(VLOOKUP(C24,'تقرير المصروفات حسب الشهر'!$C$135:$AD$244,6,FALSE),0) -> 3480 | F24: 3553 | G24: =IFERROR(VLOOKUP(C24,'تقرير المصروفات حسب الشهر'!$C$387:$AD$495,6,FALSE),0) -> 3813 | H24: =IFERROR(VLOOKUP(C24,'تقرير المصروفات حسب الشهر'!$C$512:$AD$620,6,FALSE),0) -> 5030 | I24: =IFERROR(VLOOKUP(C24,'تقرير المصروفات حسب الشهر'!$C$637:$AD$746,6,FALSE),0) -> 7051 | J24: =IFERROR(VLOOKUP(C24,'تقرير المصروفات حسب الشهر'!$C$763:$AD$872,6,FALSE),0) -> 9619 | K24: =IFERROR(VLOOKUP(C24,'تقرير المصروفات حسب الشهر'!$C$890:$AD$999,6,FALSE),0) -> 13041 | L24: =IFERROR(VLOOKUP(C24,'تقرير المصروفات حسب الشهر'!$C$1016:$AD$1126,6,FALSE),0) -> 12116 | M24: =IFERROR(VLOOKUP(C24,'تقرير المصروفات حسب الشهر'!$C$1143:$AD$1254,6,FALSE),0) -> 10860 | N24: =IFERROR(VLOOKUP(C24,'تقرير المصروفات حسب الشهر'!$C$1270:$AD$1381,6,FALSE),0) -> 8362 | O24: =IFERROR(VLOOKUP(C24,'تقرير المصروفات حسب الشهر'!$C$1397:$AD$1512,6,FALSE),0) -> 7523 | P24: =SUM(D24:O24) -> 87118
C25: المياه | D25: =IFERROR(VLOOKUP(C25,'تقرير المصروفات حسب الشهر'!$C$10:$AD$119,6,FALSE),0) -> 475 | E25: =IFERROR(VLOOKUP(C25,'تقرير المصروفات حسب الشهر'!$C$135:$AD$244,6,FALSE),0) -> 0 | F25: 0 | G25: =IFERROR(VLOOKUP(C25,'تقرير المصروفات حسب الشهر'!$C$387:$AD$495,6,FALSE),0) -> 2020 | H25: =IFERROR(VLOOKUP(C25,'تقرير المصروفات حسب الشهر'!$C$512:$AD$620,6,FALSE),0) -> 1051 | I25: =IFERROR(VLOOKUP(C25,'تقرير المصروفات حسب الشهر'!$C$637:$AD$746,6,FALSE),0) -> 0 | J25: =IFERROR(VLOOKUP(C25,'تقرير المصروفات حسب الشهر'!$C$763:$AD$872,6,FALSE),0) -> 0 | K25: =IFERROR(VLOOKUP(C25,'تقرير المصروفات حسب الشهر'!$C$890:$AD$999,6,FALSE),0) -> 0 | L25: =IFERROR(VLOOKUP(C25,'تقرير المصروفات حسب الشهر'!$C$1016:$AD$1126,6,FALSE),0) -> 3245 | M25: =IFERROR(VLOOKUP(C25,'تقرير المصروفات حسب الشهر'!$C$1143:$AD$1254,6,FALSE),0) -> 1062 | N25: =IFERROR(VLOOKUP(C25,'تقرير المصروفات حسب الشهر'!$C$1270:$AD$1381,6,FALSE),0) -> 0 | O25: =IFERROR(VLOOKUP(C25,'تقرير المصروفات حسب الشهر'!$C$1397:$AD$1512,6,FALSE),0) -> 5106 | P25: =SUM(D25:O25) -> 12959
C26: التليفون الارضي | D26: =IFERROR(VLOOKUP(C26,'تقرير المصروفات حسب الشهر'!$C$10:$AD$119,6,FALSE),0) -> 350 | E26: =IFERROR(VLOOKUP(C26,'تقرير المصروفات حسب الشهر'!$C$135:$AD$244,6,FALSE),0) -> 0 | F26: 200 | G26: =IFERROR(VLOOKUP(C26,'تقرير المصروفات حسب الشهر'!$C$387:$AD$495,6,FALSE),0) -> 0 | H26: =IFERROR(VLOOKUP(C26,'تقرير المصروفات حسب الشهر'!$C$512:$AD$620,6,FALSE),0) -> 0 | I26: =IFERROR(VLOOKUP(C26,'تقرير المصروفات حسب الشهر'!$C$637:$AD$746,6,FALSE),0) -> 900 | J26: =IFERROR(VLOOKUP(C26,'تقرير المصروفات حسب الشهر'!$C$763:$AD$872,6,FALSE),0) -> 0 | K26: =IFERROR(VLOOKUP(C26,'تقرير المصروفات حسب الشهر'!$C$890:$AD$999,6,FALSE),0) -> 0 | L26: =IFERROR(VLOOKUP(C26,'تقرير المصروفات حسب الشهر'!$C$1016:$AD$1126,6,FALSE),0) -> 0 | M26: =IFERROR(VLOOKUP(C26,'تقرير المصروفات حسب الشهر'!$C$1143:$AD$1254,6,FALSE),0) -> 0 | N26: =IFERROR(VLOOKUP(C26,'تقرير المصروفات حسب الشهر'!$C$1270:$AD$1381,6,FALSE),0) -> 400 | O26: =IFERROR(VLOOKUP(C26,'تقرير المصروفات حسب الشهر'!$C$1397:$AD$1512,6,FALSE),0) -> 0 | P26: =SUM(D26:O26) -> 1850
C27: الايجار - الصيدلية | D27: =IFERROR(VLOOKUP(C27,'تقرير المصروفات حسب الشهر'!$C$10:$AD$119,6,FALSE),0) -> 0 | E27: =IFERROR(VLOOKUP(C27,'تقرير المصروفات حسب الشهر'!$C$135:$AD$244,6,FALSE),0) -> 0 | F27: 0 | G27: =IFERROR(VLOOKUP(C27,'تقرير المصروفات حسب الشهر'!$C$387:$AD$495,6,FALSE),0) -> 0 | H27: =IFERROR(VLOOKUP(C27,'تقرير المصروفات حسب الشهر'!$C$512:$AD$620,6,FALSE),0) -> 0 | I27: =IFERROR(VLOOKUP(C27,'تقرير المصروفات حسب الشهر'!$C$637:$AD$746,6,FALSE),0) -> 0 | J27: =IFERROR(VLOOKUP(C27,'تقرير المصروفات حسب الشهر'!$C$763:$AD$872,6,FALSE),0) -> 0 | K27: =IFERROR(VLOOKUP(C27,'تقرير المصروفات حسب الشهر'!$C$890:$AD$999,6,FALSE),0) -> 0 | L27: =IFERROR(VLOOKUP(C27,'تقرير المصروفات حسب الشهر'!$C$1016:$AD$1126,6,FALSE),0) -> 0 | M27: =IFERROR(VLOOKUP(C27,'تقرير المصروفات حسب الشهر'!$C$1143:$AD$1254,6,FALSE),0) -> 0 | N27: =IFERROR(VLOOKUP(C27,'تقرير المصروفات حسب الشهر'!$C$1270:$AD$1381,6,FALSE),0) -> 0 | O27: =IFERROR(VLOOKUP(C27,'تقرير المصروفات حسب الشهر'!$C$1397:$AD$1512,6,FALSE),0) -> 0 | P27: =SUM(D27:O27) -> 0
C28: الايجار - الادارة | D28: =IFERROR(VLOOKUP(C28,'تقرير المصروفات حسب الشهر'!$C$10:$AD$119,6,FALSE),0) -> 0 | E28: =IFERROR(VLOOKUP(C28,'تقرير المصروفات حسب الشهر'!$C$135:$AD$244,6,FALSE),0) -> 0 | F28: 0 | G28: =IFERROR(VLOOKUP(C28,'تقرير المصروفات حسب الشهر'!$C$387:$AD$495,6,FALSE),0) -> 0 | H28: =IFERROR(VLOOKUP(C28,'تقرير المصروفات حسب الشهر'!$C$512:$AD$620,6,FALSE),0) -> 0 | I28: =IFERROR(VLOOKUP(C28,'تقرير المصروفات حسب الشهر'!$C$637:$AD$746,6,FALSE),0) -> 0 | J28: =IFERROR(VLOOKUP(C28,'تقرير المصروفات حسب الشهر'!$C$763:$AD$872,6,FALSE),0) -> 0 | K28: =IFERROR(VLOOKUP(C28,'تقرير المصروفات حسب الشهر'!$C$890:$AD$999,6,FALSE),0) -> 0 | L28: =IFERROR(VLOOKUP(C28,'تقرير المصروفات حسب الشهر'!$C$1016:$AD$1126,6,FALSE),0) -> 0 | M28: =IFERROR(VLOOKUP(C28,'تقرير المصروفات حسب الشهر'!$C$1143:$AD$1254,6,FALSE),0) -> 0 | N28: =IFERROR(VLOOKUP(C28,'تقرير المصروفات حسب الشهر'!$C$1270:$AD$1381,6,FALSE),0) -> 0 | O28: =IFERROR(VLOOKUP(C28,'تقرير المصروفات حسب الشهر'!$C$1397:$AD$1512,6,FALSE),0) -> 0 | P28: =SUM(D28:O28) -> 0
C29: ايجارات متنوعه | D29: =IFERROR(VLOOKUP(C29,'تقرير المصروفات حسب الشهر'!$C$10:$AD$119,6,FALSE),0) -> 35500 | E29: =IFERROR(VLOOKUP(C29,'تقرير المصروفات حسب الشهر'!$C$135:$AD$244,6,FALSE),0) -> 35500 | F29: 35500 | G29: =IFERROR(VLOOKUP(C29,'تقرير المصروفات حسب الشهر'!$C$387:$AD$495,6,FALSE),0) -> 35500 | H29: =IFERROR(VLOOKUP(C29,'تقرير المصروفات حسب الشهر'!$C$512:$AD$620,6,FALSE),0) -> 35500 | I29: =IFERROR(VLOOKUP(C29,'تقرير المصروفات حسب الشهر'!$C$637:$AD$746,6,FALSE),0) -> 35500 | J29: =IFERROR(VLOOKUP(C29,'تقرير المصروفات حسب الشهر'!$C$763:$AD$872,6,FALSE),0) -> 35500 | K29: =IFERROR(VLOOKUP(C29,'تقرير المصروفات حسب الشهر'!$C$890:$AD$999,6,FALSE),0) -> 35500 | L29: =IFERROR(VLOOKUP(C29,'تقرير المصروفات حسب الشهر'!$C$1016:$AD$1126,6,FALSE),0) -> 35500 | M29: =IFERROR(VLOOKUP(C29,'تقرير المصروفات حسب الشهر'!$C$1143:$AD$1254,6,FALSE),0) -> 35500 | N29: =IFERROR(VLOOKUP(C29,'تقرير المصروفات حسب الشهر'!$C$1270:$AD$1381,6,FALSE),0) -> 35500 | O29: =IFERROR(VLOOKUP(C29,'تقرير المصروفات حسب الشهر'!$C$1397:$AD$1512,6,FALSE),0) -> 35500 | P29: =SUM(D29:O29) -> 426000
C30: ادوات مكتبية | D30: =IFERROR(VLOOKUP(C30,'تقرير المصروفات حسب الشهر'!$C$10:$AD$119,6,FALSE),0) -> 0 | E30: =IFERROR(VLOOKUP(C30,'تقرير المصروفات حسب الشهر'!$C$135:$AD$244,6,FALSE),0) -> 0 | F30: 995.5 | G30: =IFERROR(VLOOKUP(C30,'تقرير المصروفات حسب الشهر'!$C$387:$AD$495,6,FALSE),0) -> 0 | H30: =IFERROR(VLOOKUP(C30,'تقرير المصروفات حسب الشهر'!$C$512:$AD$620,6,FALSE),0) -> 0 | I30: =IFERROR(VLOOKUP(C30,'تقرير المصروفات حسب الشهر'!$C$637:$AD$746,6,FALSE),0) -> 798.9 | J30: =IFERROR(VLOOKUP(C30,'تقرير المصروفات حسب الشهر'!$C$763:$AD$872,6,FALSE),0) -> 0 | K30: =IFERROR(VLOOKUP(C30,'تقرير المصروفات حسب الشهر'!$C$890:$AD$999,6,FALSE),0) -> 90 | L30: =IFERROR(VLOOKUP(C30,'تقرير المصروفات حسب الشهر'!$C$1016:$AD$1126,6,FALSE),0) -> 0 | M30: =IFERROR(VLOOKUP(C30,'تقرير المصروفات حسب الشهر'!$C$1143:$AD$1254,6,FALSE),0) -> 1300.25 | N30: =IFERROR(VLOOKUP(C30,'تقرير المصروفات حسب الشهر'!$C$1270:$AD$1381,6,FALSE),0) -> 0 | O30: =IFERROR(VLOOKUP(C30,'تقرير المصروفات حسب الشهر'!$C$1397:$AD$1512,6,FALSE),0) -> 1250 | P30: =SUM(D30:O30) -> 4434.65
C31: فواتير الموبايل | D31: =IFERROR(VLOOKUP(C31,'تقرير المصروفات حسب الشهر'!$C$10:$AD$119,6,FALSE),0) -> 147.13 | E31: =IFERROR(VLOOKUP(C31,'تقرير المصروفات حسب الشهر'!$C$135:$AD$244,6,FALSE),0) -> 147.13 | F31: 147.13 | G31: =IFERROR(VLOOKUP(C31,'تقرير المصروفات حسب الشهر'!$C$387:$AD$495,6,FALSE),0) -> 147.13 | H31: =IFERROR(VLOOKUP(C31,'تقرير المصروفات حسب الشهر'!$C$512:$AD$620,6,FALSE),0) -> 147.13 | I31: =IFERROR(VLOOKUP(C31,'تقرير المصروفات حسب الشهر'!$C$637:$AD$746,6,FALSE),0) -> 147.13 | J31: =IFERROR(VLOOKUP(C31,'تقرير المصروفات حسب الشهر'!$C$763:$AD$872,6,FALSE),0) -> 147.13 | K31: =IFERROR(VLOOKUP(C31,'تقرير المصروفات حسب الشهر'!$C$890:$AD$999,6,FALSE),0) -> 147.13 | L31: =IFERROR(VLOOKUP(C31,'تقرير المصروفات حسب الشهر'!$C$1016:$AD$1126,6,FALSE),0) -> 147.13 | M31: =IFERROR(VLOOKUP(C31,'تقرير المصروفات حسب الشهر'!$C$1143:$AD$1254,6,FALSE),0) -> 147.13 | N31: =IFERROR(VLOOKUP(C31,'تقرير المصروفات حسب الشهر'!$C$1270:$AD$1381,6,FALSE),0) -> 198.1 | O31: =IFERROR(VLOOKUP(C31,'تقرير المصروفات حسب الشهر'!$C$1397:$AD$1512,6,FALSE),0) -> 147.13 | P31: =SUM(D31:O31) -> 1816.53
C32: مكافات مبيعات الادوية | D32: =IFERROR(VLOOKUP(C32,'تقرير المصروفات حسب الشهر'!$C$10:$AD$119,6,FALSE),0) -> 0 | E32: =IFERROR(VLOOKUP(C32,'تقرير المصروفات حسب الشهر'!$C$135:$AD$244,6,FALSE),0) -> 0 | F32: 0 | G32: =IFERROR(VLOOKUP(C32,'تقرير المصروفات حسب الشهر'!$C$387:$AD$495,6,FALSE),0) -> 0 | H32: =IFERROR(VLOOKUP(C32,'تقرير المصروفات حسب الشهر'!$C$512:$AD$620,6,FALSE),0) -> 0 | I32: =IFERROR(VLOOKUP(C32,'تقرير المصروفات حسب الشهر'!$C$637:$AD$746,6,FALSE),0) -> 0 | J32: =IFERROR(VLOOKUP(C32,'تقرير المصروفات حسب الشهر'!$C$763:$AD$872,6,FALSE),0) -> 0 | K32: =IFERROR(VLOOKUP(C32,'تقرير المصروفات حسب الشهر'!$C$890:$AD$999,6,FALSE),0) -> 0 | L32: =IFERROR(VLOOKUP(C32,'تقرير المصروفات حسب الشهر'!$C$1016:$AD$1126,6,FALSE),0) -> 0 | M32: =IFERROR(VLOOKUP(C32,'تقرير المصروفات حسب الشهر'!$C$1143:$AD$1254,6,FALSE),0) -> 0 | N32: =IFERROR(VLOOKUP(C32,'تقرير المصروفات حسب الشهر'!$C$1270:$AD$1381,6,FALSE),0) -> 0 | O32: =IFERROR(VLOOKUP(C32,'تقرير المصروفات حسب الشهر'!$C$1397:$AD$1512,6,FALSE),0) -> 0 | P32: =SUM(D32:O32) -> 0
C33: مكافات مبيعات التجميل | D33: =IFERROR(VLOOKUP(C33,'تقرير المصروفات حسب الشهر'!$C$10:$AD$119,6,FALSE),0) -> 0 | E33: =IFERROR(VLOOKUP(C33,'تقرير المصروفات حسب الشهر'!$C$135:$AD$244,6,FALSE),0) -> 900 | F33: 650 | G33: =IFERROR(VLOOKUP(C33,'تقرير المصروفات حسب الشهر'!$C$387:$AD$495,6,FALSE),0) -> 900 | H33: =IFERROR(VLOOKUP(C33,'تقرير المصروفات حسب الشهر'!$C$512:$AD$620,6,FALSE),0) -> 500 | I33: =IFERROR(VLOOKUP(C33,'تقرير المصروفات حسب الشهر'!$C$637:$AD$746,6,FALSE),0) -> 900 | J33: =IFERROR(VLOOKUP(C33,'تقرير المصروفات حسب الشهر'!$C$763:$AD$872,6,FALSE),0) -> 650 | K33: =IFERROR(VLOOKUP(C33,'تقرير المصروفات حسب الشهر'!$C$890:$AD$999,6,FALSE),0) -> 900 | L33: =IFERROR(VLOOKUP(C33,'تقرير المصروفات حسب الشهر'!$C$1016:$AD$1126,6,FALSE),0) -> 0 | M33: =IFERROR(VLOOKUP(C33,'تقرير المصروفات حسب الشهر'!$C$1143:$AD$1254,6,FALSE),0) -> 0 | N33: =IFERROR(VLOOKUP(C33,'تقرير المصروفات حسب الشهر'!$C$1270:$AD$1381,6,FALSE),0) -> 750 | O33: =IFERROR(VLOOKUP(C33,'تقرير المصروفات حسب الشهر'!$C$1397:$AD$1512,6,FALSE),0) -> 0 | P33: =SUM(D33:O33) -> 6150
... C123: فوائد القروض - العربى الافريقىAAIB | D123: =IFERROR(VLOOKUP(C123,'تقرير المصروفات حسب الشهر'!$C$10:$AD$119,6,FALSE),0) -> 0 | E123: =IFERROR(VLOOKUP(C123,'تقرير المصروفات حسب الشهر'!$C$135:$AD$244,6,FALSE),0) -> 0 | F123: 0 | G123: =IFERROR(VLOOKUP(C123,'تقرير المصروفات حسب الشهر'!$C$387:$AD$495,6,FALSE),0) -> 0 | H123: =IFERROR(VLOOKUP(C123,'تقرير المصروفات حسب الشهر'!$C$512:$AD$620,6,FALSE),0) -> 0 | I123: =IFERROR(VLOOKUP(C123,'تقرير المصروفات حسب الشهر'!$C$637:$AD$746,6,FALSE),0) -> 0 | J123: =IFERROR(VLOOKUP(C123,'تقرير المصروفات حسب الشهر'!$C$763:$AD$872,6,FALSE),0) -> 0 | K123: =IFERROR(VLOOKUP(C123,'تقرير المصروفات حسب الشهر'!$C$890:$AD$999,6,FALSE),0) -> 0 | L123: =IFERROR(VLOOKUP(C123,'تقرير المصروفات حسب الشهر'!$C$1016:$AD$1126,6,FALSE),0) -> 0 | M123: =IFERROR(VLOOKUP(C123,'تقرير المصروفات حسب الشهر'!$C$1143:$AD$1254,6,FALSE),0) -> 0 | N123: =IFERROR(VLOOKUP(C123,'تقرير المصروفات حسب الشهر'!$C$1270:$AD$1381,6,FALSE),0) -> 0 | O123: =IFERROR(VLOOKUP(C123,'تقرير المصروفات حسب الشهر'!$C$1397:$AD$1512,6,FALSE),0) -> 0 | P123: =SUM(D123:O123) -> 0
C124: فوائد المصرية للتمويل العقارى | D124: =IFERROR(VLOOKUP(C124,'تقرير المصروفات حسب الشهر'!$C$10:$AD$119,6,FALSE),0) -> 0 | E124: =IFERROR(VLOOKUP(C124,'تقرير المصروفات حسب الشهر'!$C$135:$AD$244,6,FALSE),0) -> 0 | F124: 0 | G124: =IFERROR(VLOOKUP(C124,'تقرير المصروفات حسب الشهر'!$C$387:$AD$495,6,FALSE),0) -> 0 | H124: =IFERROR(VLOOKUP(C124,'تقرير المصروفات حسب الشهر'!$C$512:$AD$620,6,FALSE),0) -> 0 | J124: =IFERROR(VLOOKUP(C124,'تقرير المصروفات حسب الشهر'!$C$763:$AD$872,6,FALSE),0) -> 0 | K124: =IFERROR(VLOOKUP(C124,'تقرير المصروفات حسب الشهر'!$C$890:$AD$999,6,FALSE),0) -> 0 | L124: =IFERROR(VLOOKUP(C124,'تقرير المصروفات حسب الشهر'!$C$1016:$AD$1126,6,FALSE),0) -> 0 | M124: =IFERROR(VLOOKUP(C124,'تقرير المصروفات حسب الشهر'!$C$1143:$AD$1254,6,FALSE),0) -> 0 | N124: =IFERROR(VLOOKUP(C124,'تقرير المصروفات حسب الشهر'!$C$1270:$AD$1381,6,FALSE),0) -> 0 | O124: =IFERROR(VLOOKUP(C124,'تقرير المصروفات حسب الشهر'!$C$1397:$AD$1512,6,FALSE),0) -> 0 | P124: =SUM(D124:O124) -> 0
C125: فوائد القروض البنك الاهلى المصرى | D125: =IFERROR(VLOOKUP(C125,'تقرير المصروفات حسب الشهر'!$C$10:$AD$119,6,FALSE),0) -> 0 | E125: =IFERROR(VLOOKUP(C125,'تقرير المصروفات حسب الشهر'!$C$135:$AD$244,6,FALSE),0) -> 0 | F125: 0 | G125: =IFERROR(VLOOKUP(C125,'تقرير المصروفات حسب الشهر'!$C$387:$AD$495,6,FALSE),0) -> 0 | H125: =IFERROR(VLOOKUP(C125,'تقرير المصروفات حسب الشهر'!$C$512:$AD$620,6,FALSE),0) -> 0 | I125: =IFERROR(VLOOKUP(C125,'تقرير المصروفات حسب الشهر'!$C$637:$AD$746,6,FALSE),0) -> 0 | J125: =IFERROR(VLOOKUP(C125,'تقرير المصروفات حسب الشهر'!$C$763:$AD$872,6,FALSE),0) -> 0 | K125: =IFERROR(VLOOKUP(C125,'تقرير المصروفات حسب الشهر'!$C$890:$AD$999,6,FALSE),0) -> 0 | L125: =IFERROR(VLOOKUP(C125,'تقرير المصروفات حسب الشهر'!$C$1016:$AD$1126,6,FALSE),0) -> 0 | M125: =IFERROR(VLOOKUP(C125,'تقرير المصروفات حسب الشهر'!$C$1143:$AD$1254,6,FALSE),0) -> 0 | N125: =IFERROR(VLOOKUP(C125,'تقرير المصروفات حسب الشهر'!$C$1270:$AD$1381,6,FALSE),0) -> 0 | O125: =IFERROR(VLOOKUP(C125,'تقرير المصروفات حسب الشهر'!$C$1397:$AD$1512,6,FALSE),0) -> 0 | P125: =SUM(D125:O125) -> 0
C126: فوائد القروض بنك الاهلى الكويتى ABK | D126: =IFERROR(VLOOKUP(C126,'تقرير المصروفات حسب الشهر'!$C$10:$AD$119,6,FALSE),0) -> 0 | E126: =IFERROR(VLOOKUP(C126,'تقرير المصروفات حسب الشهر'!$C$135:$AD$244,6,FALSE),0) -> 0 | F126: 0 | G126: =IFERROR(VLOOKUP(C126,'تقرير المصروفات حسب الشهر'!$C$387:$AD$495,6,FALSE),0) -> 0 | H126: =IFERROR(VLOOKUP(C126,'تقرير المصروفات حسب الشهر'!$C$512:$AD$620,6,FALSE),0) -> 0 | I126: =IFERROR(VLOOKUP(C126,'تقرير المصروفات حسب الشهر'!$C$637:$AD$746,6,FALSE),0) -> 0 | J126: =IFERROR(VLOOKUP(C126,'تقرير المصروفات حسب الشهر'!$C$763:$AD$872,6,FALSE),0) -> 0 | K126: =IFERROR(VLOOKUP(C126,'تقرير المصروفات حسب الشهر'!$C$890:$AD$999,6,FALSE),0) -> 0 | L126: =IFERROR(VLOOKUP(C126,'تقرير المصروفات حسب الشهر'!$C$1016:$AD$1126,6,FALSE),0) -> 0 | M126: =IFERROR(VLOOKUP(C126,'تقرير المصروفات حسب الشهر'!$C$1143:$AD$1254,6,FALSE),0) -> 0 | N126: =IFERROR(VLOOKUP(C126,'تقرير المصروفات حسب الشهر'!$C$1270:$AD$1381,6,FALSE),0) -> 0 | O126: =IFERROR(VLOOKUP(C126,'تقرير المصروفات حسب الشهر'!$C$1397:$AD$1512,6,FALSE),0) -> 0 | P126: =SUM(D126:O126) -> 0
C127: فوائد القروض بنك الاهلى المتحد AUB | D127: =IFERROR(VLOOKUP(C127,'تقرير المصروفات حسب الشهر'!$C$10:$AD$119,6,FALSE),0) -> 0 | E127: =IFERROR(VLOOKUP(C127,'تقرير المصروفات حسب الشهر'!$C$135:$AD$244,6,FALSE),0) -> 0 | F127: 0 | G127: =IFERROR(VLOOKUP(C127,'تقرير المصروفات حسب الشهر'!$C$387:$AD$495,6,FALSE),0) -> 0 | H127: =IFERROR(VLOOKUP(C127,'تقرير المصروفات حسب الشهر'!$C$512:$AD$620,6,FALSE),0) -> 0 | I127: =IFERROR(VLOOKUP(C127,'تقرير المصروفات حسب الشهر'!$C$637:$AD$746,6,FALSE),0) -> 0 | J127: =IFERROR(VLOOKUP(C127,'تقرير المصروفات حسب الشهر'!$C$763:$AD$872,6,FALSE),0) -> 0 | K127: =IFERROR(VLOOKUP(C127,'تقرير المصروفات حسب الشهر'!$C$890:$AD$999,6,FALSE),0) -> 0 | L127: =IFERROR(VLOOKUP(C127,'تقرير المصروفات حسب الشهر'!$C$1016:$AD$1126,6,FALSE),0) -> 0 | M127: =IFERROR(VLOOKUP(C127,'تقرير المصروفات حسب الشهر'!$C$1143:$AD$1254,6,FALSE),0) -> 0 | N127: =IFERROR(VLOOKUP(C127,'تقرير المصروفات حسب الشهر'!$C$1270:$AD$1381,6,FALSE),0) -> 0 | O127: =IFERROR(VLOOKUP(C127,'تقرير المصروفات حسب الشهر'!$C$1397:$AD$1512,6,FALSE),0) -> 0 | P127: =SUM(D127:O127) -> 0
C128: فوائد القروض البنك التجارى الدولى CIB | D128: =IFERROR(VLOOKUP(C128,'تقرير المصروفات حسب الشهر'!$C$10:$AD$119,6,FALSE),0) -> 0 | E128: =IFERROR(VLOOKUP(C128,'تقرير المصروفات حسب الشهر'!$C$135:$AD$244,6,FALSE),0) -> 0 | F128: 0 | G128: =IFERROR(VLOOKUP(C128,'تقرير المصروفات حسب الشهر'!$C$387:$AD$495,6,FALSE),0) -> 0 | H128: =IFERROR(VLOOKUP(C128,'تقرير المصروفات حسب الشهر'!$C$512:$AD$620,6,FALSE),0) -> 0 | I128: =IFERROR(VLOOKUP(C128,'تقرير المصروفات حسب الشهر'!$C$637:$AD$746,6,FALSE),0) -> 0 | J128: =IFERROR(VLOOKUP(C128,'تقرير المصروفات حسب الشهر'!$C$763:$AD$872,6,FALSE),0) -> 0 | K128: =IFERROR(VLOOKUP(C128,'تقرير المصروفات حسب الشهر'!$C$890:$AD$999,6,FALSE),0) -> 0 | L128: =IFERROR(VLOOKUP(C128,'تقرير المصروفات حسب الشهر'!$C$1016:$AD$1126,6,FALSE),0) -> 0 | M128: =IFERROR(VLOOKUP(C128,'تقرير المصروفات حسب الشهر'!$C$1143:$AD$1254,6,FALSE),0) -> 0 | N128: =IFERROR(VLOOKUP(C128,'تقرير المصروفات حسب الشهر'!$C$1270:$AD$1381,6,FALSE),0) -> 0 | O128: =IFERROR(VLOOKUP(C128,'تقرير المصروفات حسب الشهر'!$C$1397:$AD$1512,6,FALSE),0) -> 0 | P128: =SUM(D128:O128) -> 0
C129: تأمينات اجتماعية - حصة الشركة | D129: =IFERROR(VLOOKUP(C129,'تقرير المصروفات حسب الشهر'!$C$10:$AD$119,6,FALSE),0) -> 431.25 | E129: =IFERROR(VLOOKUP(C129,'تقرير المصروفات حسب الشهر'!$C$135:$AD$244,6,FALSE),0) -> 431.25 | F129: 431.25 | G129: =IFERROR(VLOOKUP(C129,'تقرير المصروفات حسب الشهر'!$C$387:$AD$495,6,FALSE),0) -> 431.25 | H129: =IFERROR(VLOOKUP(C129,'تقرير المصروفات حسب الشهر'!$C$512:$AD$620,6,FALSE),0) -> 862.5 | I129: =IFERROR(VLOOKUP(C129,'تقرير المصروفات حسب الشهر'!$C$637:$AD$746,6,FALSE),0) -> 863 | J129: =IFERROR(VLOOKUP(C129,'تقرير المصروفات حسب الشهر'!$C$763:$AD$872,6,FALSE),0) -> 862.5 | K129: =IFERROR(VLOOKUP(C129,'تقرير المصروفات حسب الشهر'!$C$890:$AD$999,6,FALSE),0) -> 862.5 | L129: =IFERROR(VLOOKUP(C129,'تقرير المصروفات حسب الشهر'!$C$1016:$AD$1126,6,FALSE),0) -> 862.5 | M129: =IFERROR(VLOOKUP(C129,'تقرير المصروفات حسب الشهر'!$C$1143:$AD$1254,6,FALSE),0) -> 862.5 | N129: =IFERROR(VLOOKUP(C129,'تقرير المصروفات حسب الشهر'!$C$1270:$AD$1381,6,FALSE),0) -> 862.5 | O129: =IFERROR(VLOOKUP(C129,'تقرير المصروفات حسب الشهر'!$C$1397:$AD$1512,6,FALSE),0) -> 862.5 | P129: =SUM(D129:O129) -> 8625.5
C130: فوائد القروض - التجارى وفا بنك AWB | D130: =IFERROR(VLOOKUP(C130,'تقرير المصروفات حسب الشهر'!$C$10:$AD$119,6,FALSE),0) -> 0 | E130: =IFERROR(VLOOKUP(C130,'تقرير المصروفات حسب الشهر'!$C$135:$AD$244,6,FALSE),0) -> 0 | F130: 0 | G130: =IFERROR(VLOOKUP(C130,'تقرير المصروفات حسب الشهر'!$C$387:$AD$495,6,FALSE),0) -> 0 | H130: =IFERROR(VLOOKUP(C130,'تقرير المصروفات حسب الشهر'!$C$512:$AD$620,6,FALSE),0) -> 0 | I130: =IFERROR(VLOOKUP(C130,'تقرير المصروفات حسب الشهر'!$C$637:$AD$746,6,FALSE),0) -> 0 | J130: =IFERROR(VLOOKUP(C130,'تقرير المصروفات حسب الشهر'!$C$763:$AD$872,6,FALSE),0) -> 0 | K130: =IFERROR(VLOOKUP(C130,'تقرير المصروفات حسب الشهر'!$C$890:$AD$999,6,FALSE),0) -> 0 | L130: =IFERROR(VLOOKUP(C130,'تقرير المصروفات حسب الشهر'!$C$1016:$AI$1131,6,FALSE),0) -> 0 | M130: =IFERROR(VLOOKUP(C130,'تقرير المصروفات حسب الشهر'!$C$1143:$AD$1254,6,FALSE),0) -> 0 | N130: =IFERROR(VLOOKUP(C130,'تقرير المصروفات حسب الشهر'!$C$1270:$AD$1381,6,FALSE),0) -> 0 | O130: =IFERROR(VLOOKUP(C130,'تقرير المصروفات حسب الشهر'!$C$1397:$AD$1512,6,FALSE),0) -> 0 | P130: =SUM(D130:O130) -> 0
C131: فوائد القروض - بنك القاهرة BDC | D131: =IFERROR(VLOOKUP(C131,'تقرير المصروفات حسب الشهر'!$C$10:$AD$119,6,FALSE),0) -> 0 | E131: =IFERROR(VLOOKUP(C131,'تقرير المصروفات حسب الشهر'!$C$135:$AD$244,6,FALSE),0) -> 0 | F131: 0 | G131: =IFERROR(VLOOKUP(C131,'تقرير المصروفات حسب الشهر'!$C$387:$AD$495,6,FALSE),0) -> 0 | H131: =IFERROR(VLOOKUP(C131,'تقرير المصروفات حسب الشهر'!$C$512:$AD$620,6,FALSE),0) -> 0 | I131: =IFERROR(VLOOKUP(C131,'تقرير المصروفات حسب الشهر'!$C$637:$AD$746,6,FALSE),0) -> 0 | J131: =IFERROR(VLOOKUP(C131,'تقرير المصروفات حسب الشهر'!$C$763:$AD$872,6,FALSE),0) -> 0 | K131: =IFERROR(VLOOKUP(C131,'تقرير المصروفات حسب الشهر'!$C$890:$AD$999,6,FALSE),0) -> 0 | L131: =IFERROR(VLOOKUP(C131,'تقرير المصروفات حسب الشهر'!$C$1016:$AI$1131,6,FALSE),0) -> 0 | M131: =IFERROR(VLOOKUP(C131,'تقرير المصروفات حسب الشهر'!$C$1143:$AD$1254,6,FALSE),0) -> 0 | N131: =IFERROR(VLOOKUP(C131,'تقرير المصروفات حسب الشهر'!$C$1270:$AD$1381,6,FALSE),0) -> 0 | O131: =IFERROR(VLOOKUP(C131,'تقرير المصروفات حسب الشهر'!$C$1397:$AD$1512,6,FALSE),0) -> 0 | P131: =SUM(D131:O131) -> 0
C132: خصم أبليكيشن | D132: =IFERROR(VLOOKUP(C132,'تقرير المصروفات حسب الشهر'!$C$10:$AD$124,6,FALSE),0) -> 199696.6 | E132: =IFERROR(VLOOKUP(C132,'تقرير المصروفات حسب الشهر'!$C$135:$AD$252,6,FALSE),0) -> 252245.03 | F132: 265493.17 | G132: =IFERROR(VLOOKUP(C132,'تقرير المصروفات حسب الشهر'!$C$387:$AD$503,6,FALSE),0) -> 376968.67 | H132: =IFERROR(VLOOKUP(C132,'تقرير المصروفات حسب الشهر'!$C$512:$AD$622,6,FALSE),0) -> 459280.22 | I132: =IFERROR(VLOOKUP(C132,'تقرير المصروفات حسب الشهر'!$C$637:$AD$750,6,FALSE),0) -> 637853.43 | J132: =IFERROR(VLOOKUP(C132,'تقرير المصروفات حسب الشهر'!$C$763:$AD$877,6,FALSE),0) -> 450649.55 | K132: =IFERROR(VLOOKUP(C132,'تقرير المصروفات حسب الشهر'!$C$890:$AD$1007,6,FALSE),0) -> 420723.38 | L132: =IFERROR(VLOOKUP(C132,'تقرير المصروفات حسب الشهر'!$C$1016:$AI$1131,6,FALSE),0) -> 554109.57 | M132: =IFERROR(VLOOKUP(C132,'تقرير المصروفات حسب الشهر'!$C$1143:$AD$1254,6,FALSE),0) -> 487006.42 | N132: =IFERROR(VLOOKUP(C132,'تقرير المصروفات حسب الشهر'!$C$1270:$AD$1382,6,FALSE),0) -> 530750.67 | O132: =IFERROR(VLOOKUP(C132,'تقرير المصروفات حسب الشهر'!$C$1397:$AD$1512,6,FALSE),0) -> 574517.66 | P132: =SUM(D132:O132) -> 5209294.4
C133: مفقودات ومسروقات | I133: =IFERROR(VLOOKUP(C133,'تقرير المصروفات حسب الشهر'!$C$637:$AD$750,6,FALSE),0) -> 2157.5 | J133: =IFERROR(VLOOKUP(C133,'تقرير المصروفات حسب الشهر'!$C$763:$AD$877,6,FALSE),0) -> 0 | K133: =IFERROR(VLOOKUP(C133,'تقرير المصروفات حسب الشهر'!$C$890:$AD$1007,6,FALSE),0) -> 0 | L133: =IFERROR(VLOOKUP(C133,'تقرير المصروفات حسب الشهر'!$C$1016:$AI$1131,6,FALSE),0) -> 0 | M133: =IFERROR(VLOOKUP(C133,'تقرير المصروفات حسب الشهر'!$C$1143:$AD$1254,6,FALSE),0) -> 0 | N133: =IFERROR(VLOOKUP(C133,'تقرير المصروفات حسب الشهر'!$C$1270:$AI$1384,6,FALSE),0) -> 0 | O133: =IFERROR(VLOOKUP(C133,'تقرير المصروفات حسب الشهر'!$C$1397:$AD$1512,6,FALSE),0) -> 0
C134: عروض مبيعات ابليكشن | J134: =IFERROR(VLOOKUP(C134,'تقرير المصروفات حسب الشهر'!$C$763:$AD$877,6,FALSE),0) -> 79332.69 | K134: =IFERROR(VLOOKUP(C134,'تقرير المصروفات حسب الشهر'!$C$890:$AD$1007,6,FALSE),0) -> 139532.67 | L134: =IFERROR(VLOOKUP(C134,'تقرير المصروفات حسب الشهر'!$C$1016:$AI$1131,6,FALSE),0) -> 213602.81 | M134: =IFERROR(VLOOKUP(C134,'تقرير المصروفات حسب الشهر'!$C$1143:$AD$1258,6,FALSE),0) -> 172949.99 | N134: =IFERROR(VLOOKUP(C134,'تقرير المصروفات حسب الشهر'!$C$1270:$AI$1384,6,FALSE),0) -> 80253.04 | O134: =IFERROR(VLOOKUP(C134,'تقرير المصروفات حسب الشهر'!$C$1397:$AD$1512,6,FALSE),0) -> 132161.91
C135: إجمالي المصروفات | D135: =SUM(D22:D132) -> 511847.77 | E135: =SUM(E22:E132) -> 715488.69 | F135: =SUM(F22:F132) -> 768276.94 | G135: =SUM(G22:G132) -> 851796.29 | H135: =SUM(H22:H132) -> 959623.8 | I135: =SUM(I22:I133) -> 1226552 | J135: =SUM(J22:J134) -> 1096504.8 | K135: =SUM(K22:K134) -> 1136298.1 | L135: =SUM(L22:L134) -> 1331460.4 | M135: =SUM(M22:M134) -> 1179195.3 | N135: =SUM(N22:N134) -> 1130944 | O135: =SUM(O22:O134) -> 1380909 | P135: =SUM(D135:O135) -> 12288897
C137: مجمل الربح | D137: =D19 -> 1082950.2 | E137: =E19 -> 1127901 | F137: =F19 -> 1246605.4 | G137: =G19 -> 1313490.9 | H137: =H19 -> 1391202 | I137: =I19 -> 1512433.3 | J137: =J19 -> 1555989.5 | K137: =K19 -> 1567215 | ... O137: =O19 -> 1513226.5 | P137: =SUM(D137:O137) -> 16944379
C140: صافي الربح / الخسارة | D140: =D137-D135 -> 571102.41 | E140: =E137-E135 -> 412412.27 | F140: =F137-F135 -> 478328.49 | G140: =G137-G135 -> 461694.57 | H140: =H137-H135 -> 431578.19 | I140: =I137-I135 -> 285881.24 | J140: =J137-J135 -> 459484.66 | K140: =K137-K135 -> 430916.85 | ... O140: =O137-O135 -> 132317.5 | P140: =SUM(D140:O140) -> 4655481.7
D144: 565819.11 | G144: =461694.23-G140 -> -0.34 | M144: =373557.67-M140 -> 0
D145: =D140-D144 -> 5283.3 | N145: 424547.06
N146: =N140-N145 -> 108504.73

Sheet Sweedy
C2: INCOME STATEMTN
F3: Income Statement For Sweedy
D6: Jan | E6: February | F6: March | G6: April | H6: May | I6: June | J6: July | K6: August | L6: September | M6: October | N6: November | O6: December | P6: TOTAL
C7: INCOME DETAILS
A8: السويدى | C8: المبيعات | D8: =D9+D10+D11 -> 1947540 | E8: =E9+E10+E11 -> 1775257.4 | F8: =F9+F10+F11 -> 1795573.6 | G8: =G9+G10+G11 -> 1839264 | H8: =H9+H10+H11 -> 1940739 | I8: =I9+I10+I11 -> 2032739.8 | J8: =J9+J10+J11 -> 2077568.7 | K8: =K9+K10+K11 -> 2105653.8 | ... O8: =O9+O10+O11 -> 2309123 | P8: =SUM(D8:O8) -> 23981464
C9: نقدى | D9: =VLOOKUP($A$8,'تقرير إحصائية بحجم المبيعات'!$B$7:$L$31,2,FALSE) -> 38601.8 | E9: =VLOOKUP($A$8,'تقرير إحصائية بحجم المبيعات'!$B$42:$G$73,2,FALSE) -> 10047.09 | F9: =VLOOKUP($A$8,'تقرير إحصائية بحجم المبيعات'!$B$78:$E$103,2,FALSE) -> 29421.01 | G9: =VLOOKUP($A$8,'تقرير إحصائية بحجم المبيعات'!$B$112:$G$137,2,FALSE) -> 36603.7 | H9: =VLOOKUP($A$8,'تقرير إحصائية بحجم المبيعات'!$B$147:$G$177,2,FALSE) -> 28323.28 | I9: =VLOOKUP($A$8,'تقرير إحصائية بحجم المبيعات'!$B$182:$G$212,2,FALSE) -> -5878.66 | J9: =VLOOKUP($A$8,'تقرير إحصائية بحجم المبيعات'!$B$217:$L$243,2,FALSE) -> 14657.34 | K9: =VLOOKUP($A$8,'تقرير إحصائية بحجم المبيعات'!$B$252:$L$278,2,FALSE) -> 21317.1 | L9: =VLOOKUP($A$8,'تقرير إحصائية بحجم المبيعات'!$B$287:$L$313,2,FALSE) -> 11360.97 | M9: =VLOOKUP($A$8,'تقرير إحصائية بحجم المبيعات'!$B$322:$L$347,2,FALSE) -> 22469.01 | N9: =VLOOKUP($A$8,'تقرير إحصائية بحجم المبيعات'!$B$357:$L$383,2,FALSE) -> 40387.69 | O9: =VLOOKUP($A$8,'تقرير إحصائية بحجم المبيعات'!$B$391:$L$420,2,FALSE) -> 7172.88 | P9: =SUM(D9:O9) -> 254483.21
C10: دليفرى | D10: =VLOOKUP($A$8,'تقرير إحصائية بحجم المبيعات'!$B$7:$L$31,3,FALSE) -> 0 | E10: =VLOOKUP($A$8,'تقرير إحصائية بحجم المبيعات'!$B$42:$G$73,3,FALSE) -> 0 | F10: =VLOOKUP($A$8,'تقرير إحصائية بحجم المبيعات'!$B$78:$E$103,3,FALSE) -> 0 | G10: =VLOOKUP($A$8,'تقرير إحصائية بحجم المبيعات'!$B$112:$G$137,3,FALSE) -> 0 | H10: =VLOOKUP($A$8,'تقرير إحصائية بحجم المبيعات'!$B$147:$G$177,3,FALSE) -> 0 | I10: =VLOOKUP($A$8,'تقرير إحصائية بحجم المبيعات'!$B$182:$G$212,3,FALSE) -> 0 | J10: =VLOOKUP($A$8,'تقرير إحصائية بحجم المبيعات'!$B$217:$L$243,3,FALSE) -> 0 | K10: =VLOOKUP($A$8,'تقرير إحصائية بحجم المبيعات'!$B$252:$L$278,3,FALSE) -> 0 | L10: =VLOOKUP($A$8,'تقرير إحصائية بحجم المبيعات'!$B$287:$L$313,3,FALSE) -> 0 | M10: =VLOOKUP($A$8,'تقرير إحصائية بحجم المبيعات'!$B$322:$L$347,3,FALSE) -> 0 | N10: =VLOOKUP($A$8,'تقرير إحصائية بحجم المبيعات'!$B$357:$L$383,3,FALSE) -> 0 | O10: =VLOOKUP($A$8,'تقرير إحصائية بحجم المبيعات'!$B$391:$L$420,3,FALSE) -> 0 | P10: =SUM(D10:O10) -> 0
C11: اجل | D11: =VLOOKUP($A$8,'تقرير إحصائية بحجم المبيعات'!$B$7:$L$31,4,FALSE) -> 1908938.2 | E11: =VLOOKUP($A$8,'تقرير إحصائية بحجم المبيعات'!$B$42:$G$73,4,FALSE) -> 1765210.3 | F11: =VLOOKUP($A$8,'تقرير إحصائية بحجم المبيعات'!$B$78:$E$103,4,FALSE) -> 1766152.6 | G11: =VLOOKUP($A$8,'تقرير إحصائية بحجم المبيعات'!$B$112:$G$137,4,FALSE) -> 1802660.3 | H11: =VLOOKUP($A$8,'تقرير إحصائية بحجم المبيعات'!$B$147:$G$177,4,FALSE) -> 1912415.7 | I11: =VLOOKUP($A$8,'تقرير إحصائية بحجم المبيعات'!$B$182:$G$212,4,FALSE) -> 2038618.5 | J11: =VLOOKUP($A$8,'تقرير إحصائية بحجم المبيعات'!$B$217:$L$243,4,FALSE) -> 2062911.3 | K11: =VLOOKUP($A$8,'تقرير إحصائية بحجم المبيعات'!$B$252:$L$278,4,FALSE) -> 2084336.7 | L11: =VLOOKUP($A$8,'تقرير إحصائية بحجم المبيعات'!$B$287:$L$313,4,FALSE) -> 1879123.5 | M11: =VLOOKUP($A$8,'تقرير إحصائية بحجم المبيعات'!$B$322:$L$347,4,FALSE) -> 2211696 | N11: =VLOOKUP($A$8,'تقرير إحصائية بحجم المبيعات'!$B$357:$L$383,4,FALSE) -> 1992967.4 | O11: =VLOOKUP($A$8,'تقرير إحصائية بحجم المبيعات'!$B$391:$L$420,4,FALSE) -> 2301950.1 | P11: =SUM(D11:O11) -> 23726981
C12: تكلفة البضاعة المباعة | D12: =VLOOKUP($A$8,'تقرير إحصائية بحجم المبيعات'!$B$7:$L$31,11,FALSE) -> 1655785.7 | E12: =VLOOKUP($A$8,'تقرير إحصائية بحجم المبيعات'!$B$42:$L$73,11,FALSE) -> 1524135.9 | F12: =VLOOKUP($A$8,'تقرير إحصائية بحجم المبيعات'!$B$78:$L$103,11,FALSE) -> 1550681.3 | G12: =VLOOKUP($A$8,'تقرير إحصائية بحجم المبيعات'!$B$112:$L$137,11,FALSE) -> 1605312.6 | H12: =VLOOKUP($A$8,'تقرير إحصائية بحجم المبيعات'!$B$147:$L$177,11,FALSE) -> 1669227.8 | I12: =VLOOKUP($A$8,'تقرير إحصائية بحجم المبيعات'!$B$182:$L$212,11,FALSE) -> 1704874.8 | J12: =VLOOKUP($A$8,'تقرير إحصائية بحجم المبيعات'!$B$217:$L$243,11,FALSE) -> 1778614.1 | K12: =VLOOKUP($A$8,'تقرير إحصائية بحجم المبيعات'!$B$252:$L$278,11,FALSE) -> 1787608.6 | L12: =VLOOKUP($A$8,'تقرير إحصائية بحجم المبيعات'!$B$287:$L$313,11,FALSE) -> 1645964.4 | M12: =VLOOKUP($A$8,'تقرير إحصائية بحجم المبيعات'!$B$322:$L$347,11,FALSE) -> 1893913.1 | N12: =VLOOKUP($A$8,'تقرير إحصائية بحجم المبيعات'!$B$357:$L$383,11,FALSE) -> 1772017.3 | O12: =VLOOKUP($A$8,'تقرير إحصائية بحجم المبيعات'!$B$391:$L$420,11,FALSE) -> 1984670.7 | P12: =SUM(D12:O12) -> 20572806
C13: مجمل الربح | D13: =D8-D12 -> 291754.34 | E13: =E8-E12 -> 251121.56 | F13: =F8-F12 -> 244892.33 | G13: =G8-G12 -> 233951.38 | H13: =H8-H12 -> 271511.21 | I13: =I8-I12 -> 327865.02 | J13: =J8-J12 -> 298954.55 | K13: =K8-K12 -> 318045.2 | ... O13: =O8-O12 -> 324452.3 | P13: =SUM(D13:O13) -> 3408657.8
C14: خصم نقدى | P14: =SUM(D14:O14) -> 0
C15: ارباح صرف اصناف بيع اصول | P15: =SUM(D15:O15) -> 0
C16: فائض جرد | D16: 83139.27 | E16: 167078.42 | F16: 170152.52 | G16: 300664.49 | H16: 120408.89 | I16: 121612.49 | J16: 173216.14 | K16: 170186.94 | L16: 224186.1 | M16: 234079.19 | N16: 147385.82 | O16: 140043.56 | P16: =SUM(D16:O16) -> 2052153.8
C17: ايرادات اخرى | P17: =SUM(D17:O17) -> 0
C18: إجمالي الايرادات اخرى | D18: =SUM(D14:D17) -> 83139.27 | E18: =SUM(E14:E17) -> 167078.42 | F18: =SUM(F14:F17) -> 170152.52 | G18: =SUM(G14:G17) -> 300664.49 | H18: =SUM(H14:H17) -> 120408.89 | I18: =SUM(I14:I17) -> 121612.49 | J18: =SUM(J14:J17) -> 173216.14 | K18: =SUM(K14:K17) -> 170186.94 | ... O18: =SUM(O14:O17) -> 140043.56 | P18: =SUM(D18:O18) -> 2052153.8
C19: مجمل الربح | D19: =D13+D18 -> 374893.61 | E19: =E13+E18 -> 418199.98 | F19: =F13+F18 -> 415044.85 | G19: =G13+G18 -> 534615.87 | H19: =H13+H18 -> 391920.1 | I19: =I13+I18 -> 449477.51 | J19: =J13+J18 -> 472170.69 | K19: =K13+K18 -> 488232.14 | ... O19: =O13+O18 -> 464495.86 | P19: =SUM(D19:O19) -> 5460811.6
C21: EXPENSE DETAILS
C22: مرتبات الادارة | D22: =IFERROR(VLOOKUP(C22,'تقرير المصروفات حسب الشهر'!$C$10:$AD$119,7,FALSE),0) -> 0 | E22: =IFERROR(VLOOKUP(C22,'تقرير المصروفات حسب الشهر'!$C$135:$AD$244,7,FALSE),0) -> 0 | F22: 0 | G22: =IFERROR(VLOOKUP(C22,'تقرير المصروفات حسب الشهر'!$C$387:$AD$495,7,FALSE),0) -> 0 | H22: =IFERROR(VLOOKUP(C22,'تقرير المصروفات حسب الشهر'!$C$512:$AD$620,7,FALSE),0) -> 0 | I22: =IFERROR(VLOOKUP(C22,'تقرير المصروفات حسب الشهر'!$C$637:$AD$746,7,FALSE),0) -> 0 | J22: =IFERROR(VLOOKUP(C22,'تقرير المصروفات حسب الشهر'!$C$763:$AD$872,7,FALSE),0) -> 0 | K22: =IFERROR(VLOOKUP(C22,'تقرير المصروفات حسب الشهر'!$C$890:$AD$999,7,FALSE),0) -> 0 | L22: =IFERROR(VLOOKUP(C22,'تقرير المصروفات حسب الشهر'!$C$1016:$AD$1126,7,FALSE),0) -> 0 | M22: =IFERROR(VLOOKUP(C22,'تقرير المصروفات حسب الشهر'!$C$1143:$AD$1254,7,FALSE),0) -> 0 | N22: =IFERROR(VLOOKUP(C22,'تقرير المصروفات حسب الشهر'!$C$1270:$AD$1381,7,FALSE),0) | O22: =IFERROR(VLOOKUP(C22,'تقرير المصروفات حسب الشهر'!$C$1397:$AD$1512,7,FALSE),0) -> 0 | P22: =SUM(D22:O22) -> 0
C23: مرتبات الفروع | D23: =IFERROR(VLOOKUP(C23,'تقرير المصروفات حسب الشهر'!$C$10:$AD$119,7,FALSE),0) -> 37720.32 | E23: =IFERROR(VLOOKUP(C23,'تقرير المصروفات حسب الشهر'!$C$135:$AD$244,7,FALSE),0) -> 37302.72 | F23: 35815.87 | G23: =IFERROR(VLOOKUP(C23,'تقرير المصروفات حسب الشهر'!$C$387:$AD$495,7,FALSE),0) -> 35818.18 | H23: =IFERROR(VLOOKUP(C23,'تقرير المصروفات حسب الشهر'!$C$512:$AD$620,7,FALSE),0) -> 40629.63 | I23: =IFERROR(VLOOKUP(C23,'تقرير المصروفات حسب الشهر'!$C$637:$AD$746,7,FALSE),0) -> 43698.58 | J23: =IFERROR(VLOOKUP(C23,'تقرير المصروفات حسب الشهر'!$C$763:$AD$872,7,FALSE),0) -> 39426.625 | K23: =IFERROR(VLOOKUP(C23,'تقرير المصروفات حسب الشهر'!$C$890:$AD$999,7,FALSE),0) -> 42282.12 | L23: =IFERROR(VLOOKUP(C23,'تقرير المصروفات حسب الشهر'!$C$1016:$AD$1126,7,FALSE),0) -> 36645.91 | M23: =IFERROR(VLOOKUP(C23,'تقرير المصروفات حسب الشهر'!$C$1143:$AD$1254,7,FALSE),0) -> 41130.9 | N23: =IFERROR(VLOOKUP(C23,'تقرير المصروفات حسب الشهر'!$C$1270:$AD$1381,7,FALSE),0) -> 44025.24 | O23: =IFERROR(VLOOKUP(C23,'تقرير المصروفات حسب الشهر'!$C$1397:$AD$1512,7,FALSE),0) -> 39293.99 | P23: =SUM(D23:O23) -> 473790.08
C24: الكهرباء | D24: =IFERROR(VLOOKUP(C24,'تقرير المصروفات حسب الشهر'!$C$10:$AD$119,7,FALSE),0) -> 0 | E24: =IFERROR(VLOOKUP(C24,'تقرير المصروفات حسب الشهر'!$C$135:$AD$244,7,FALSE),0) -> 0 | F24: 0 | G24: =IFERROR(VLOOKUP(C24,'تقرير المصروفات حسب الشهر'!$C$387:$AD$495,7,FALSE),0) -> 0 | H24: =IFERROR(VLOOKUP(C24,'تقرير المصروفات حسب الشهر'!$C$512:$AD$620,7,FALSE),0) -> 0 | I24: =IFERROR(VLOOKUP(C24,'تقرير المصروفات حسب الشهر'!$C$637:$AD$746,7,FALSE),0) -> 0 | J24: =IFERROR(VLOOKUP(C24,'تقرير المصروفات حسب الشهر'!$C$763:$AD$872,7,FALSE),0) -> 0 | K24: =IFERROR(VLOOKUP(C24,'تقرير المصروفات حسب الشهر'!$C$890:$AD$999,7,FALSE),0) -> 0 | L24: =IFERROR(VLOOKUP(C24,'تقرير المصروفات حسب الشهر'!$C$1016:$AD$1126,7,FALSE),0) -> 0 | M24: =IFERROR(VLOOKUP(C24,'تقرير المصروفات حسب الشهر'!$C$1143:$AD$1254,7,FALSE),0) -> 0 | N24: =IFERROR(VLOOKUP(C24,'تقرير المصروفات حسب الشهر'!$C$1270:$AD$1381,7,FALSE),0) -> 0 | O24: =IFERROR(VLOOKUP(C24,'تقرير المصروفات حسب الشهر'!$C$1397:$AD$1512,7,FALSE),0) -> 0 | P24: =SUM(D24:O24) -> 0
C25: المياه | D25: =IFERROR(VLOOKUP(C25,'تقرير المصروفات حسب الشهر'!$C$10:$AD$119,7,FALSE),0) -> 0 | E25: =IFERROR(VLOOKUP(C25,'تقرير المصروفات حسب الشهر'!$C$135:$AD$244,7,FALSE),0) -> 0 | F25: 0 | G25: =IFERROR(VLOOKUP(C25,'تقرير المصروفات حسب الشهر'!$C$387:$AD$495,7,FALSE),0) -> 0 | H25: =IFERROR(VLOOKUP(C25,'تقرير المصروفات حسب الشهر'!$C$512:$AD$620,7,FALSE),0) -> 0 | I25: =IFERROR(VLOOKUP(C25,'تقرير المصروفات حسب الشهر'!$C$637:$AD$746,7,FALSE),0) -> 0 | J25: =IFERROR(VLOOKUP(C25,'تقرير المصروفات حسب الشهر'!$C$763:$AD$872,7,FALSE),0) -> 0 | K25: =IFERROR(VLOOKUP(C25,'تقرير المصروفات حسب الشهر'!$C$890:$AD$999,7,FALSE),0) -> 0 | L25: =IFERROR(VLOOKUP(C25,'تقرير المصروفات حسب الشهر'!$C$1016:$AD$1126,7,FALSE),0) -> 0 | M25: =IFERROR(VLOOKUP(C25,'تقرير المصروفات حسب الشهر'!$C$1143:$AD$1254,7,FALSE),0) -> 0 | N25: =IFERROR(VLOOKUP(C25,'تقرير المصروفات حسب الشهر'!$C$1270:$AD$1381,7,FALSE),0) -> 0 | O25: =IFERROR(VLOOKUP(C25,'تقرير المصروفات حسب الشهر'!$C$1397:$AD$1512,7,FALSE),0) -> 0 | P25: =SUM(D25:O25) -> 0
C26: التليفون الارضي | D26: =IFERROR(VLOOKUP(C26,'تقرير المصروفات حسب الشهر'!$C$10:$AD$119,7,FALSE),0) -> 0 | E26: =IFERROR(VLOOKUP(C26,'تقرير المصروفات حسب الشهر'!$C$135:$AD$244,7,FALSE),0) -> 0 | F26: 0 | G26: =IFERROR(VLOOKUP(C26,'تقرير المصروفات حسب الشهر'!$C$387:$AD$495,7,FALSE),0) -> 0 | H26: =IFERROR(VLOOKUP(C26,'تقرير المصروفات حسب الشهر'!$C$512:$AD$620,7,FALSE),0) -> 0 | I26: =IFERROR(VLOOKUP(C26,'تقرير المصروفات حسب الشهر'!$C$637:$AD$746,7,FALSE),0) -> 0 | J26: =IFERROR(VLOOKUP(C26,'تقرير المصروفات حسب الشهر'!$C$763:$AD$872,7,FALSE),0) -> 0 | K26: =IFERROR(VLOOKUP(C26,'تقرير المصروفات حسب الشهر'!$C$890:$AD$999,7,FALSE),0) -> 0 | L26: =IFERROR(VLOOKUP(C26,'تقرير المصروفات حسب الشهر'!$C$1016:$AD$1126,7,FALSE),0) -> 0 | M26: =IFERROR(VLOOKUP(C26,'تقرير المصروفات حسب الشهر'!$C$1143:$AD$1254,7,FALSE),0) -> 0 | N26: =IFERROR(VLOOKUP(C26,'تقرير المصروفات حسب الشهر'!$C$1270:$AD$1381,7,FALSE),0) -> 0 | O26: =IFERROR(VLOOKUP(C26,'تقرير المصروفات حسب الشهر'!$C$1397:$AD$1512,7,FALSE),0) -> 0 | P26: =SUM(D26:O26) -> 0
C27: الايجار - الصيدلية | D27: =IFERROR(VLOOKUP(C27,'تقرير المصروفات حسب الشهر'!$C$10:$AD$119,7,FALSE),0) -> 0 | E27: =IFERROR(VLOOKUP(C27,'تقرير المصروفات حسب الشهر'!$C$135:$AD$244,7,FALSE),0) -> 0 | F27: 0 | G27: =IFERROR(VLOOKUP(C27,'تقرير المصروفات حسب الشهر'!$C$387:$AD$495,7,FALSE),0) -> 0 | H27: =IFERROR(VLOOKUP(C27,'تقرير المصروفات حسب الشهر'!$C$512:$AD$620,7,FALSE),0) -> 0 | I27: =IFERROR(VLOOKUP(C27,'تقرير المصروفات حسب الشهر'!$C$637:$AD$746,7,FALSE),0) -> 0 | J27: =IFERROR(VLOOKUP(C27,'تقرير المصروفات حسب الشهر'!$C$763:$AD$872,7,FALSE),0) -> 0 | K27: =IFERROR(VLOOKUP(C27,'تقرير المصروفات حسب الشهر'!$C$890:$AD$999,7,FALSE),0) -> 0 | L27: =IFERROR(VLOOKUP(C27,'تقرير المصروفات حسب الشهر'!$C$1016:$AD$1126,7,FALSE),0) -> 0 | M27: =IFERROR(VLOOKUP(C27,'تقرير المصروفات حسب الشهر'!$C$1143:$AD$1254,7,FALSE),0) -> 0 | N27: =IFERROR(VLOOKUP(C27,'تقرير المصروفات حسب الشهر'!$C$1270:$AD$1381,7,FALSE),0) -> 0 | O27: =IFERROR(VLOOKUP(C27,'تقرير المصروفات حسب الشهر'!$C$1397:$AD$1512,7,FALSE),0) -> 0 | P27: =SUM(D27:O27) -> 0
C28: الايجار - الادارة | D28: =IFERROR(VLOOKUP(C28,'تقرير المصروفات حسب الشهر'!$C$10:$AD$119,7,FALSE),0) -> 0 | E28: =IFERROR(VLOOKUP(C28,'تقرير المصروفات حسب الشهر'!$C$135:$AD$244,7,FALSE),0) -> 0 | F28: 0 | G28: =IFERROR(VLOOKUP(C28,'تقرير المصروفات حسب الشهر'!$C$387:$AD$495,7,FALSE),0) -> 0 | H28: =IFERROR(VLOOKUP(C28,'تقرير المصروفات حسب الشهر'!$C$512:$AD$620,7,FALSE),0) -> 0 | I28: =IFERROR(VLOOKUP(C28,'تقرير المصروفات حسب الشهر'!$C$637:$AD$746,7,FALSE),0) -> 0 | J28: =IFERROR(VLOOKUP(C28,'تقرير المصروفات حسب الشهر'!$C$763:$AD$872,7,FALSE),0) -> 0 | K28: =IFERROR(VLOOKUP(C28,'تقرير المصروفات حسب الشهر'!$C$890:$AD$999,7,FALSE),0) -> 0 | L28: =IFERROR(VLOOKUP(C28,'تقرير المصروفات حسب الشهر'!$C$1016:$AD$1126,7,FALSE),0) -> 0 | M28: =IFERROR(VLOOKUP(C28,'تقرير المصروفات حسب الشهر'!$C$1143:$AD$1254,7,FALSE),0) -> 0 | N28: =IFERROR(VLOOKUP(C28,'تقرير المصروفات حسب الشهر'!$C$1270:$AD$1381,7,FALSE),0) -> 0 | O28: =IFERROR(VLOOKUP(C28,'تقرير المصروفات حسب الشهر'!$C$1397:$AD$1512,7,FALSE),0) -> 0 | P28: =SUM(D28:O28) -> 0
C29: ايجارات متنوعه | D29: =IFERROR(VLOOKUP(C29,'تقرير المصروفات حسب الشهر'!$C$10:$AD$119,7,FALSE),0) -> 0 | E29: =IFERROR(VLOOKUP(C29,'تقرير المصروفات حسب الشهر'!$C$135:$AD$244,7,FALSE),0) -> 0 | F29: 0 | G29: =IFERROR(VLOOKUP(C29,'تقرير المصروفات حسب الشهر'!$C$387:$AD$495,7,FALSE),0) -> 0 | H29: =IFERROR(VLOOKUP(C29,'تقرير المصروفات حسب الشهر'!$C$512:$AD$620,7,FALSE),0) -> 0 | I29: =IFERROR(VLOOKUP(C29,'تقرير المصروفات حسب الشهر'!$C$637:$AD$746,7,FALSE),0) -> 0 | J29: =IFERROR(VLOOKUP(C29,'تقرير المصروفات حسب الشهر'!$C$763:$AD$872,7,FALSE),0) -> 0 | K29: =IFERROR(VLOOKUP(C29,'تقرير المصروفات حسب الشهر'!$C$890:$AD$999,7,FALSE),0) -> 0 | L29: =IFERROR(VLOOKUP(C29,'تقرير المصروفات حسب الشهر'!$C$1016:$AD$1126,7,FALSE),0) -> 0 | M29: =IFERROR(VLOOKUP(C29,'تقرير المصروفات حسب الشهر'!$C$1143:$AD$1254,7,FALSE),0) -> 0 | N29: =IFERROR(VLOOKUP(C29,'تقرير المصروفات حسب الشهر'!$C$1270:$AD$1381,7,FALSE),0) -> 0 | O29: =IFERROR(VLOOKUP(C29,'تقرير المصروفات حسب الشهر'!$C$1397:$AD$1512,7,FALSE),0) -> 0 | P29: =SUM(D29:O29) -> 0
C30: ادوات مكتبية | D30: =IFERROR(VLOOKUP(C30,'تقرير المصروفات حسب الشهر'!$C$10:$AD$119,7,FALSE),0) -> 0 | E30: =IFERROR(VLOOKUP(C30,'تقرير المصروفات حسب الشهر'!$C$135:$AD$244,7,FALSE),0) -> 0 | F30: 0 | G30: =IFERROR(VLOOKUP(C30,'تقرير المصروفات حسب الشهر'!$C$387:$AD$495,7,FALSE),0) -> 0 | H30: =IFERROR(VLOOKUP(C30,'تقرير المصروفات حسب الشهر'!$C$512:$AD$620,7,FALSE),0) -> 0 | I30: =IFERROR(VLOOKUP(C30,'تقرير المصروفات حسب الشهر'!$C$637:$AD$746,7,FALSE),0) -> 0 | J30: =IFERROR(VLOOKUP(C30,'تقرير المصروفات حسب الشهر'!$C$763:$AD$872,7,FALSE),0) -> 0 | K30: =IFERROR(VLOOKUP(C30,'تقرير المصروفات حسب الشهر'!$C$890:$AD$999,7,FALSE),0) -> 0 | L30: =IFERROR(VLOOKUP(C30,'تقرير المصروفات حسب الشهر'!$C$1016:$AD$1126,7,FALSE),0) -> 0 | M30: =IFERROR(VLOOKUP(C30,'تقرير المصروفات حسب الشهر'!$C$1143:$AD$1254,7,FALSE),0) -> 0 | N30: =IFERROR(VLOOKUP(C30,'تقرير المصروفات حسب الشهر'!$C$1270:$AD$1381,7,FALSE),0) -> 0 | O30: =IFERROR(VLOOKUP(C30,'تقرير المصروفات حسب الشهر'!$C$1397:$AD$1512,7,FALSE),0) -> 0 | P30: =SUM(D30:O30) -> 0
C31: فواتير الموبايل | D31: =IFERROR(VLOOKUP(C31,'تقرير المصروفات حسب الشهر'!$C$10:$AD$119,7,FALSE),0) -> 84.95 | E31: =IFERROR(VLOOKUP(C31,'تقرير المصروفات حسب الشهر'!$C$135:$AD$244,7,FALSE),0) -> 84.95 | F31: 84.95 | G31: =IFERROR(VLOOKUP(C31,'تقرير المصروفات حسب الشهر'!$C$387:$AD$495,7,FALSE),0) -> 84.95 | H31: =IFERROR(VLOOKUP(C31,'تقرير المصروفات حسب الشهر'!$C$512:$AD$620,7,FALSE),0) -> 84.95 | I31: =IFERROR(VLOOKUP(C31,'تقرير المصروفات حسب الشهر'!$C$637:$AD$746,7,FALSE),0) -> 84.95 | J31: =IFERROR(VLOOKUP(C31,'تقرير المصروفات حسب الشهر'!$C$763:$AD$872,7,FALSE),0) -> 84.95 | K31: =IFERROR(VLOOKUP(C31,'تقرير المصروفات حسب الشهر'!$C$890:$AD$999,7,FALSE),0) -> 84.95 | L31: =IFERROR(VLOOKUP(C31,'تقرير المصروفات حسب الشهر'!$C$1016:$AD$1126,7,FALSE),0) -> 84.95 | M31: =IFERROR(VLOOKUP(C31,'تقرير المصروفات حسب الشهر'!$C$1143:$AD$1254,7,FALSE),0) -> 84.95 | N31: =IFERROR(VLOOKUP(C31,'تقرير المصروفات حسب الشهر'!$C$1270:$AD$1381,7,FALSE),0) -> 84.95 | O31: =IFERROR(VLOOKUP(C31,'تقرير المصروفات حسب الشهر'!$C$1397:$AD$1512,7,FALSE),0) -> 84.95 | P31: =SUM(D31:O31) -> 1019.4
C32: مكافات مبيعات الادوية | D32: =IFERROR(VLOOKUP(C32,'تقرير المصروفات حسب الشهر'!$C$10:$AD$119,7,FALSE),0) -> 0 | E32: =IFERROR(VLOOKUP(C32,'تقرير المصروفات حسب الشهر'!$C$135:$AD$244,7,FALSE),0) -> 0 | F32: 0 | G32: =IFERROR(VLOOKUP(C32,'تقرير المصروفات حسب الشهر'!$C$387:$AD$495,7,FALSE),0) -> 0 | H32: =IFERROR(VLOOKUP(C32,'تقرير المصروفات حسب الشهر'!$C$512:$AD$620,7,FALSE),0) -> 0 | I32: =IFERROR(VLOOKUP(C32,'تقرير المصروفات حسب الشهر'!$C$637:$AD$746,7,FALSE),0) -> 0 | J32: =IFERROR(VLOOKUP(C32,'تقرير المصروفات حسب الشهر'!$C$763:$AD$872,7,FALSE),0) -> 0 | K32: =IFERROR(VLOOKUP(C32,'تقرير المصروفات حسب الشهر'!$C$890:$AD$999,7,FALSE),0) -> 0 | L32: =IFERROR(VLOOKUP(C32,'تقرير المصروفات حسب الشهر'!$C$1016:$AD$1126,7,FALSE),0) -> 0 | M32: =IFERROR(VLOOKUP(C32,'تقرير المصروفات حسب الشهر'!$C$1143:$AD$1254,7,FALSE),0) -> 0 | N32: =IFERROR(VLOOKUP(C32,'تقرير المصروفات حسب الشهر'!$C$1270:$AD$1381,7,FALSE),0) -> 0 | O32: =IFERROR(VLOOKUP(C32,'تقرير المصروفات حسب الشهر'!$C$1397:$AD$1512,7,FALSE),0) -> 0 | P32: =SUM(D32:O32) -> 0
C33: مكافات مبيعات التجميل | D33: =IFERROR(VLOOKUP(C33,'تقرير المصروفات حسب الشهر'!$C$10:$AD$119,7,FALSE),0) -> 0 | E33: =IFERROR(VLOOKUP(C33,'تقرير المصروفات حسب الشهر'!$C$135:$AD$244,7,FALSE),0) -> 0 | F33: 0 | G33: =IFERROR(VLOOKUP(C33,'تقرير المصروفات حسب الشهر'!$C$387:$AD$495,7,FALSE),0) -> 0 | H33: =IFERROR(VLOOKUP(C33,'تقرير المصروفات حسب الشهر'!$C$512:$AD$620,7,FALSE),0) -> 0 | I33: =IFERROR(VLOOKUP(C33,'تقرير المصروفات حسب الشهر'!$C$637:$AD$746,7,FALSE),0) -> 0 | J33: =IFERROR(VLOOKUP(C33,'تقرير المصروفات حسب الشهر'!$C$763:$AD$872,7,FALSE),0) -> 0 | K33: =IFERROR(VLOOKUP(C33,'تقرير المصروفات حسب الشهر'!$C$890:$AD$999,7,FALSE),0) -> 0 | L33: =IFERROR(VLOOKUP(C33,'تقرير المصروفات حسب الشهر'!$C$1016:$AD$1126,7,FALSE),0) -> 0 | M33: =IFERROR(VLOOKUP(C33,'تقرير المصروفات حسب الشهر'!$C$1143:$AD$1254,7,FALSE),0) -> 0 | N33: =IFERROR(VLOOKUP(C33,'تقرير المصروفات حسب الشهر'!$C$1270:$AD$1381,7,FALSE),0) -> 0 | O33: =IFERROR(VLOOKUP(C33,'تقرير المصروفات حسب الشهر'!$C$1397:$AD$1512,7,FALSE),0) -> 0 | P33: =SUM(D33:O33) -> 0
... C128: فوائد القروض البنك التجارى الدولى CIB | D128: =IFERROR(VLOOKUP(C128,'تقرير المصروفات حسب الشهر'!$C$10:$AD$119,7,FALSE),0) -> 0 | E128: =IFERROR(VLOOKUP(C128,'تقرير المصروفات حسب الشهر'!$C$135:$AD$244,7,FALSE),0) -> 0 | F128: 0 | G128: =IFERROR(VLOOKUP(C128,'تقرير المصروفات حسب الشهر'!$C$387:$AD$495,7,FALSE),0) -> 0 | H128: =IFERROR(VLOOKUP(C128,'تقرير المصروفات حسب الشهر'!$C$512:$AD$620,7,FALSE),0) -> 0 | I128: =IFERROR(VLOOKUP(C128,'تقرير المصروفات حسب الشهر'!$C$637:$AD$746,7,FALSE),0) -> 0 | J128: =IFERROR(VLOOKUP(C128,'تقرير المصروفات حسب الشهر'!$C$763:$AD$872,7,FALSE),0) -> 0 | K128: =IFERROR(VLOOKUP(C128,'تقرير المصروفات حسب الشهر'!$C$890:$AD$999,7,FALSE),0) -> 0 | L128: =IFERROR(VLOOKUP(C128,'تقرير المصروفات حسب الشهر'!$C$1016:$AD$1126,7,FALSE),0) -> 0 | M128: =IFERROR(VLOOKUP(C128,'تقرير المصروفات حسب الشهر'!$C$1143:$AD$1254,7,FALSE),0) -> 0 | N128: =IFERROR(VLOOKUP(C128,'تقرير المصروفات حسب الشهر'!$C$1270:$AD$1381,7,FALSE),0) -> 0 | O128: =IFERROR(VLOOKUP(C128,'تقرير المصروفات حسب الشهر'!$C$1397:$AD$1512,7,FALSE),0) -> 0 | P128: =SUM(D128:O128) -> 0
C129: تأمينات اجتماعية - حصة الشركة | D129: =IFERROR(VLOOKUP(C129,'تقرير المصروفات حسب الشهر'!$C$10:$AD$119,7,FALSE),0) -> 1293.75 | E129: =IFERROR(VLOOKUP(C129,'تقرير المصروفات حسب الشهر'!$C$135:$AD$244,7,FALSE),0) -> 1293.75 | F129: 1293.75 | G129: =IFERROR(VLOOKUP(C129,'تقرير المصروفات حسب الشهر'!$C$387:$AD$495,7,FALSE),0) -> 1293.75 | H129: =IFERROR(VLOOKUP(C129,'تقرير المصروفات حسب الشهر'!$C$512:$AD$620,7,FALSE),0) -> 1293.75 | I129: =IFERROR(VLOOKUP(C129,'تقرير المصروفات حسب الشهر'!$C$637:$AD$746,7,FALSE),0) -> 1294 | J129: =IFERROR(VLOOKUP(C129,'تقرير المصروفات حسب الشهر'!$C$763:$AD$872,7,FALSE),0) -> 1293.75 | K129: =IFERROR(VLOOKUP(C129,'تقرير المصروفات حسب الشهر'!$C$890:$AD$999,7,FALSE),0) -> 1293.75 | L129: =IFERROR(VLOOKUP(C129,'تقرير المصروفات حسب الشهر'!$C$1016:$AI$1131,7,FALSE),0) -> 1293.75 | M129: =IFERROR(VLOOKUP(C129,'تقرير المصروفات حسب الشهر'!$C$1143:$AD$1254,7,FALSE),0) -> 1293.75 | N129: =IFERROR(VLOOKUP(C129,'تقرير المصروفات حسب الشهر'!$C$1270:$AD$1381,7,FALSE),0) -> 1293.75 | O129: =IFERROR(VLOOKUP(C129,'تقرير المصروفات حسب الشهر'!$C$1397:$AD$1512,7,FALSE),0) -> 1293.75 | P129: =SUM(D129:O129) -> 15525.25
C130: فوائد القروض - التجارى وفا بنك AWB | D130: =IFERROR(VLOOKUP(C130,'تقرير المصروفات حسب الشهر'!$C$10:$AD$119,7,FALSE),0) -> 0 | E130: =IFERROR(VLOOKUP(C130,'تقرير المصروفات حسب الشهر'!$C$135:$AD$244,7,FALSE),0) -> 0 | F130: 0 | G130: =IFERROR(VLOOKUP(C130,'تقرير المصروفات حسب الشهر'!$C$387:$AD$495,7,FALSE),0) -> 0 | H130: =IFERROR(VLOOKUP(C130,'تقرير المصروفات حسب الشهر'!$C$512:$AD$620,7,FALSE),0) -> 0 | I130: =IFERROR(VLOOKUP(C130,'تقرير المصروفات حسب الشهر'!$C$637:$AD$746,7,FALSE),0) -> 0 | J130: =IFERROR(VLOOKUP(C130,'تقرير المصروفات حسب الشهر'!$C$763:$AD$872,7,FALSE),0) -> 0 | K130: =IFERROR(VLOOKUP(C130,'تقرير المصروفات حسب الشهر'!$C$890:$AD$999,7,FALSE),0) -> 0 | L130: =IFERROR(VLOOKUP(C130,'تقرير المصروفات حسب الشهر'!$C$1016:$AI$1131,7,FALSE),0) -> 0 | M130: =IFERROR(VLOOKUP(C130,'تقرير المصروفات حسب الشهر'!$C$1143:$AD$1254,7,FALSE),0) -> 0 | N130: =IFERROR(VLOOKUP(C130,'تقرير المصروفات حسب الشهر'!$C$1270:$AD$1381,7,FALSE),0) -> 0 | O130: =IFERROR(VLOOKUP(C130,'تقرير المصروفات حسب الشهر'!$C$1397:$AD$1512,7,FALSE),0) -> 0 | P130: =SUM(D130:O130) -> 0
C131: فوائد القروض - بنك القاهرة BDC | D131: =IFERROR(VLOOKUP(C131,'تقرير المصروفات حسب الشهر'!$C$10:$AD$119,7,FALSE),0) -> 0 | E131: =IFERROR(VLOOKUP(C131,'تقرير المصروفات حسب الشهر'!$C$135:$AD$244,7,FALSE),0) -> 0 | F131: 0 | G131: =IFERROR(VLOOKUP(C131,'تقرير المصروفات حسب الشهر'!$C$387:$AD$495,7,FALSE),0) -> 0 | H131: =IFERROR(VLOOKUP(C131,'تقرير المصروفات حسب الشهر'!$C$512:$AD$620,7,FALSE),0) -> 0 | I131: =IFERROR(VLOOKUP(C131,'تقرير المصروفات حسب الشهر'!$C$637:$AD$746,7,FALSE),0) -> 0 | J131: =IFERROR(VLOOKUP(C131,'تقرير المصروفات حسب الشهر'!$C$763:$AD$872,7,FALSE),0) -> 0 | K131: =IFERROR(VLOOKUP(C131,'تقرير المصروفات حسب الشهر'!$C$890:$AD$999,7,FALSE),0) -> 0 | L131: =IFERROR(VLOOKUP(C131,'تقرير المصروفات حسب الشهر'!$C$1016:$AI$1131,7,FALSE),0) -> 0 | M131: =IFERROR(VLOOKUP(C131,'تقرير المصروفات حسب الشهر'!$C$1143:$AD$1254,7,FALSE),0) -> 0 | N131: =IFERROR(VLOOKUP(C131,'تقرير المصروفات حسب الشهر'!$C$1270:$AD$1381,7,FALSE),0) -> 0 | O131: =IFERROR(VLOOKUP(C131,'تقرير المصروفات حسب الشهر'!$C$1397:$AD$1512,7,FALSE),0) -> 0 | P131: =SUM(D131:O131) -> 0
C132: إجمالي المصروفات | D132: =SUM(D22:D131) -> 95193.37 | E132: =SUM(E22:E131) -> 60400.12 | F132: =SUM(F22:F131) -> 60003.26 | G132: =SUM(G22:G131) -> 99664.34 | H132: =SUM(H22:H131) -> 74869.1 | I132: =SUM(I22:I131) -> 64655.63 | J132: =SUM(J22:J131) -> 88867.295 | K132: =SUM(K22:K131) -> 67567.31 | ... O132: =SUM(O22:O131) -> 78069.4 | P132: =SUM(D132:O132) -> 934519.31
C134: مجمل الربح | D134: =D19 -> 374893.61 | E134: =E19 -> 418199.98 | F134: =F19 -> 415044.85 | G134: =G19 -> 534615.87 | H134: =H19 -> 391920.1 | I134: =I19 -> 449477.51 | J134: =J19 -> 472170.69 | K134: =K19 -> 488232.14 | ... O134: =O19 -> 464495.86 | P134: =SUM(D134:O134) -> 5460811.6
C137: صافي الربح / الخسارة | D137: =D134-D132 -> 279700.24 | E137: =E134-E132 -> 357799.86 | F137: =F134-F132 -> 355041.59 | G137: =G134-G132 -> 434951.53 | H137: =H134-H132 -> 317051 | I137: =I134-I132 -> 384821.88 | J137: =J134-J132 -> 383303.4 | K137: =K134-K132 -> 420664.83 | ... O137: =O134-O132 -> 386426.46 | P137: =SUM(D137:O137) -> 4526292.3
G141: =434951.53-G137 -> 0

Sheet NTRA
C2: INCOME STATEMTN
F3: Income Statement For NTRA
D6: Jan | E6: February | F6: March | G6: April | H6: May | I6: June | J6: July | K6: August | L6: September | M6: October | N6: November | O6: December | P6: TOTAL
C7: INCOME DETAILS
A8: رايه | C8: المبيعات | D8: =D9+D10+D11 -> 229235.95 | E8: =E9+E10+E11 -> 172031.96 | F8: =F9+F10+F11 -> 151893.71 | G8: =G9+G10+G11 -> 257446.85 | H8: =H9+H10+H11 -> 309072.3 | I8: =I9+I10+I11 -> 426644.02 | J8: =J9+J10+J11 -> 473256.7 | K8: =K9+K10+K11 -> 533204.55 | ... O8: =O9+O10+O11 -> 732395.52 | P8: =SUM(D8:O8) -> 5034392.8
C9: نقدى | D9: =VLOOKUP($A$8,'تقرير إحصائية بحجم المبيعات'!$B$7:$L$31,2,FALSE) -> 49347.64 | E9: =VLOOKUP($A$8,'تقرير إحصائية بحجم المبيعات'!$B$42:$G$73,2,FALSE) -> 46537.91 | F9: =VLOOKUP($A$8,'تقرير إحصائية بحجم المبيعات'!$B$78:$E$103,2,FALSE) -> 42975.23 | G9: =VLOOKUP($A$8,'تقرير إحصائية بحجم المبيعات'!$B$112:$G$137,2,FALSE) -> 9164.71 | H9: =VLOOKUP($A$8,'تقرير إحصائية بحجم المبيعات'!$B$147:$G$177,2,FALSE) -> 12612.34 | I9: =VLOOKUP($A$8,'تقرير إحصائية بحجم المبيعات'!$B$182:$G$212,2,FALSE) -> 24499.87 | J9: =VLOOKUP($A$8,'تقرير إحصائية بحجم المبيعات'!$B$217:$L$243,2,FALSE) -> 23672.37 | K9: =VLOOKUP($A$8,'تقرير إحصائية بحجم المبيعات'!$B$252:$L$278,2,FALSE) -> 31888.21 | L9: =VLOOKUP($A$8,'تقرير إحصائية بحجم المبيعات'!$B$287:$L$313,2,FALSE) -> 40273.44 | M9: =VLOOKUP($A$8,'تقرير إحصائية بحجم المبيعات'!$B$322:$L$347,2,FALSE) -> 29414.6 | N9: =VLOOKUP($A$8,'تقرير إحصائية بحجم المبيعات'!$B$357:$L$383,2,FALSE) -> 51206.22 | O9: =VLOOKUP($A$8,'تقرير إحصائية بحجم المبيعات'!$B$391:$L$420,2,FALSE) -> 35777.86 | P9: =SUM(D9:O9) -> 397370.4
C10: دليفرى | D10: =VLOOKUP($A$8,'تقرير إحصائية بحجم المبيعات'!$B$7:$L$31,3,FALSE) -> 0 | E10: =VLOOKUP($A$8,'تقرير إحصائية بحجم المبيعات'!$B$42:$G$73,3,FALSE) -> 0 | F10: =VLOOKUP($A$8,'تقرير إحصائية بحجم المبيعات'!$B$78:$E$103,3,FALSE) -> 0 | G10: =VLOOKUP($A$8,'تقرير إحصائية بحجم المبيعات'!$B$112:$G$137,3,FALSE) -> 0 | H10: =VLOOKUP($A$8,'تقرير إحصائية بحجم المبيعات'!$B$147:$G$177,3,FALSE) -> 0 | I10: =VLOOKUP($A$8,'تقرير إحصائية بحجم المبيعات'!$B$182:$G$212,3,FALSE) -> 0 | J10: =VLOOKUP($A$8,'تقرير إحصائية بحجم المبيعات'!$B$217:$L$243,3,FALSE) -> 0 | K10: =VLOOKUP($A$8,'تقرير إحصائية بحجم المبيعات'!$B$252:$L$278,3,FALSE) -> 0 | L10: =VLOOKUP($A$8,'تقرير إحصائية بحجم المبيعات'!$B$287:$L$313,3,FALSE) -> 0 | M10: =VLOOKUP($A$8,'تقرير إحصائية بحجم المبيعات'!$B$322:$L$347,3,FALSE) -> 0 | N10: =VLOOKUP($A$8,'تقرير إحصائية بحجم المبيعات'!$B$357:$L$383,3,FALSE) -> 0 | O10: =VLOOKUP($A$8,'تقرير إحصائية بحجم المبيعات'!$B$391:$L$420,3,FALSE) -> 0 | P10: =SUM(D10:O10) -> 0
C11: اجل | D11: =VLOOKUP($A$8,'تقرير إحصائية بحجم المبيعات'!$B$7:$L$31,4,FALSE) -> 179888.31 | E11: =VLOOKUP($A$8,'تقرير إحصائية بحجم المبيعات'!$B$42:$G$73,4,FALSE) -> 125494.05 | F11: =VLOOKUP($A$8,'تقرير إحصائية بحجم المبيعات'!$B$78:$E$103,4,FALSE) -> 108918.48 | G11: =VLOOKUP($A$8,'تقرير إحصائية بحجم المبيعات'!$B$112:$G$137,4,FALSE) -> 248282.14 | H11: =VLOOKUP($A$8,'تقرير إحصائية بحجم المبيعات'!$B$147:$G$177,4,FALSE) -> 296459.96 | I11: =VLOOKUP($A$8,'تقرير إحصائية بحجم المبيعات'!$B$182:$G$212,4,FALSE) -> 402144.15 | J11: =VLOOKUP($A$8,'تقرير إحصائية بحجم المبيعات'!$B$217:$L$243,4,FALSE) -> 449584.33 | K11: =VLOOKUP($A$8,'تقرير إحصائية بحجم المبيعات'!$B$252:$L$278,4,FALSE) -> 501316.34 | L11: =VLOOKUP($A$8,'تقرير إحصائية بحجم المبيعات'!$B$287:$L$313,4,FALSE) -> 474390.66 | M11: =VLOOKUP($A$8,'تقرير إحصائية بحجم المبيعات'!$B$322:$L$347,4,FALSE) -> 561708.62 | N11: =VLOOKUP($A$8,'تقرير إحصائية بحجم المبيعات'!$B$357:$L$383,4,FALSE) -> 592217.65 | O11: =VLOOKUP($A$8,'تقرير إحصائية بحجم المبيعات'!$B$391:$L$420,4,FALSE) -> 696617.66 | P11: =SUM(D11:O11) -> 4637022.3
C12: تكلفة البضاعة المباعة | D12: =VLOOKUP($A$8,'تقرير إحصائية بحجم المبيعات'!$B$7:$L$31,11,FALSE) -> 197826.25 | E12: =VLOOKUP($A$8,'تقرير إحصائية بحجم المبيعات'!$B$42:$L$73,11,FALSE) -> 148205.42 | F12: =VLOOKUP($A$8,'تقرير إحصائية بحجم المبيعات'!$B$78:$L$103,11,FALSE) -> 132498.17 | G12: =VLOOKUP($A$8,'تقرير إحصائية بحجم المبيعات'!$B$112:$L$137,11,FALSE) -> 229666.33 | H12: =VLOOKUP($A$8,'تقرير إحصائية بحجم المبيعات'!$B$147:$L$177,11,FALSE) -> 270303.07 | I12: =VLOOKUP($A$8,'تقرير إحصائية بحجم المبيعات'!$B$182:$L$212,11,FALSE) -> 378252.64 | J12: =VLOOKUP($A$8,'تقرير إحصائية بحجم المبيعات'!$B$217:$L$243,11,FALSE) -> 408942.63 | K12: =VLOOKUP($A$8,'تقرير إحصائية بحجم المبيعات'!$B$252:$L$278,11,FALSE) -> 463003.36 | L12: =VLOOKUP($A$8,'تقرير إحصائية بحجم المبيعات'!$B$287:$L$313,11,FALSE) -> 446632.38 | M12: =VLOOKUP($A$8,'تقرير إحصائية بحجم المبيعات'!$B$322:$L$347,11,FALSE) -> 509300.8 | N12: =VLOOKUP($A$8,'تقرير إحصائية بحجم المبيعات'!$B$357:$L$383,11,FALSE) -> 555019.45 | O12: =VLOOKUP($A$8,'تقرير إحصائية بحجم المبيعات'!$B$391:$L$420,11,FALSE) -> 630090.95 | P12: =SUM(D12:O12) -> 4369741.4
C13: مجمل الربح | D13: =D8-D12 -> 31409.7 | E13: =E8-E12 -> 23826.54 | F13: =F8-F12 -> 19395.54 | G13: =G8-G12 -> 27780.52 | H13: =H8-H12 -> 38769.23 | I13: =I8-I12 -> 48391.38 | J13: =J8-J12 -> 64314.07 | K13: =K8-K12 -> 70201.19 | ... O13: =O8-O12 -> 102304.57 | P13: =SUM(D13:O13) -> 664651.3
C14: خصم نقدى | P14: =SUM(D14:O14) -> 0
C15: ارباح صرف اصناف بيع اصول | P15: =SUM(D15:O15) -> 0
C16: فائض جرد | D16: 41.23 | E16: 46.33 | F16: 439.6 | G16: 3154.37 | K16: 112.47 | N16: 10369.95 | O16: 16688.3 | P16: =SUM(D16:O16) -> 30852.25
C17: ايرادات اخرى | P17: =SUM(D17:O17) -> 0
C18: إجمالي الايرادات اخرى | D18: =SUM(D14:D17) -> 41.23 | E18: =SUM(E14:E17) -> 46.33 | F18: =SUM(F14:F17) -> 439.6 | G18: =SUM(G14:G17) -> 3154.37 | H18: =SUM(H14:H17) -> 0 | I18: =SUM(I14:I17) -> 0 | J18: =SUM(J14:J17) -> 0 | K18: =SUM(K14:K17) -> 112.47 | ... O18: =SUM(O14:O17) -> 16688.3 | P18: =SUM(D18:O18) -> 30852.25
C19: مجمل الربح | D19: =D13+D18 -> 31450.93 | E19: =E13+E18 -> 23872.87 | F19: =F13+F18 -> 19835.14 | G19: =G13+G18 -> 30934.89 | H19: =H13+H18 -> 38769.23 | I19: =I13+I18 -> 48391.38 | J19: =J13+J18 -> 64314.07 | K19: =K13+K18 -> 70313.66 | ... O19: =O13+O18 -> 118992.87 | P19: =SUM(D19:O19) -> 695503.55
C21: EXPENSE DETAILS
C22: مرتبات الادارة | D22: =IFERROR(VLOOKUP(C22,'تقرير المصروفات حسب الشهر'!$C$10:$AD$119,8,FALSE),0) -> 0 | E22: =IFERROR(VLOOKUP(C22,'تقرير المصروفات حسب الشهر'!$C$135:$AD$244,8,FALSE),0) -> 0 | F22: =IFERROR(VLOOKUP(C22,'تقرير المصروفات حسب الشهر'!$C$261:$AD$368,8,FALSE),0) -> 0 | G22: =IFERROR(VLOOKUP(C22,'تقرير المصروفات حسب الشهر'!$C$387:$AD$495,8,FALSE),0) -> 0 | H22: =IFERROR(VLOOKUP(C22,'تقرير المصروفات حسب الشهر'!$C$512:$AD$620,8,FALSE),0) -> 0 | I22: =IFERROR(VLOOKUP(C22,'تقرير المصروفات حسب الشهر'!$C$637:$AD$746,8,FALSE),0) -> 0 | J22: =IFERROR(VLOOKUP(C22,'تقرير المصروفات حسب الشهر'!$C$763:$AD$872,8,FALSE),0) -> 0 | K22: =IFERROR(VLOOKUP(C22,'تقرير المصروفات حسب الشهر'!$C$890:$AD$999,8,FALSE),0) -> 0 | L22: =IFERROR(VLOOKUP(C22,'تقرير المصروفات حسب الشهر'!$C$1016:$AD$1126,8,FALSE),0) -> 0 | M22: =IFERROR(VLOOKUP(C22,'تقرير المصروفات حسب الشهر'!$C$1143:$AD$1254,8,FALSE),0) -> 0 | N22: =IFERROR(VLOOKUP(C22,'تقرير المصروفات حسب الشهر'!$C$1270:$AD$1381,8,FALSE),0) -> 0 | O22: =IFERROR(VLOOKUP(C22,'تقرير المصروفات حسب الشهر'!$C$1397:$AD$1512,8,FALSE),0) -> 0 | P22: =SUM(D22:O22) -> 0
C23: مرتبات الفروع | D23: =IFERROR(VLOOKUP(C23,'تقرير المصروفات حسب الشهر'!$C$10:$AD$119,8,FALSE),0) -> 14221.32 | E23: =IFERROR(VLOOKUP(C23,'تقرير المصروفات حسب الشهر'!$C$135:$AD$244,8,FALSE),0) -> 13610.24 | F23: =IFERROR(VLOOKUP(C23,'تقرير المصروفات حسب الشهر'!$C$261:$AD$368,8,FALSE),0) -> 14160.81 | G23: =IFERROR(VLOOKUP(C23,'تقرير المصروفات حسب الشهر'!$C$387:$AD$495,8,FALSE),0) -> 10701.58 | H23: =IFERROR(VLOOKUP(C23,'تقرير المصروفات حسب الشهر'!$C$512:$AD$620,8,FALSE),0) -> 16220.23 | I23: =IFERROR(VLOOKUP(C23,'تقرير المصروفات حسب الشهر'!$C$637:$AD$746,8,FALSE),0) -> 23238.97 | J23: =IFERROR(VLOOKUP(C23,'تقرير المصروفات حسب الشهر'!$C$763:$AD$872,8,FALSE),0) -> 21298.64 | K23: =IFERROR(VLOOKUP(C23,'تقرير المصروفات حسب الشهر'!$C$890:$AD$999,8,FALSE),0) -> 21718.85 | L23: =IFERROR(VLOOKUP(C23,'تقرير المصروفات حسب الشهر'!$C$1016:$AD$1126,8,FALSE),0) -> 20122.42 | M23: =IFERROR(VLOOKUP(C23,'تقرير المصروفات حسب الشهر'!$C$1143:$AD$1254,8,FALSE),0) -> 22652.78 | N23: =IFERROR(VLOOKUP(C23,'تقرير المصروفات حسب الشهر'!$C$1270:$AD$1381,8,FALSE),0) -> 23089.91 | O23: =IFERROR(VLOOKUP(C23,'تقرير المصروفات حسب الشهر'!$C$1397:$AD$1512,8,FALSE),0) -> 20245.86 | P23: =SUM(D23:O23) -> 221281.61
