Workbook
Name linkkksss: INDIRECT(ADDRESS(1,1,,,Dashboard!A1))
Name sheet_link: INDIRECT(ADDRESS(7,3,,,Dashboard!DY1048576))
Name Shheet_Link: INDIRECT(ADDRESS(7,3,,,Dashboard!A1))
Name shshshs: INDIRECT(ADDRESS(1,1,,,Dashboard!A1))

Sheet Dashboard
C2: Income Statement
C3: Dashboard | R3: HQ
H7: YEAR TOTAL EXPENSES & YEAR TOTAL INCOME CHART
C8: Income Statement
C9: (YEAR TOTAL) | EJ9: =ADDRESS(7,3,,,R3) -> HQ!$C$7
C11: Total Sales Revenue | D11: : | E11: =AB42 -> 5.2493549e+08
C12: Total Cost of Sales | D12: : | E12: =AC42 -> 2.5952038e+08
C13: Gross Profit | D13: : | E13: =E11-E12 -> 2.6541512e+08
C14: Total Non-Operational Income | D14: : | E14: =AF42 -> 5626802.9
C15: TOTAL INCOME | D15: : | E15: =E13+E14 -> 2.7104192e+08
C18: TOTAL EXPENSES | D18: : | E18: =AE42 -> 1.3979296e+08 | EI18: تقرير المصروفات حسب الشهر
EI19: تقرير مصروفات إجمالية
EI20: تقرير إحصائية بحجم المبيعات
EI21: تقرير مجمعة حسب الشهر | EJ21: HQ
C22: NET PROFIT | D22: : | E22: =E15-E18 -> 1.3124896e+08 | EI22: تقرير مصروفات حسب الفرع | EJ22: Aguza
EI23: مجمعة إجمالية | EJ23: October
E24: =2125593.24-E22 -> -1.2912337e+08 | EJ24: Batal
H25: April | EJ25: Nasr City
EJ26: Sweedy
C27: MONTH TOTAL | H27: EXPENSES DETAILS (MONTH TOTAL) | EJ27: Raya
C28: Income Statement | H28: Operating Expenses | EJ28: Etisalat
C29: =H25 -> April | H29: مرتبات الادارة | J29: =VLOOKUP($H$25,$AA$90:$EI$101,2,FALSE) -> 1600742 | K29: =J29/$E$36 -> 0.1145087 | M29: اعلان ودعاية - ايام دعاية | O29: =VLOOKUP($H$25,$AA$90:$EI$101,58,FALSE) -> 0 | P29: =O29/$E$36 -> 0 | AA29: Monthes | AB29: Total Sales Revenue | AC29: Total Cost of Sales | AD29: Total Income | AE29: Total Operating Expenses | AF29: Total Non-Operational Income | AG29: Net Profit | EJ29: Hazzem Hassan
H30: مرتبات الفروع | J30: =VLOOKUP($H$25,$AA$90:$EI$101,3,FALSE) -> 4557559.9 | K30: =J30/$E$36 -> 0.32602396 | M30: اكراميات - ايام دعاية | O30: =VLOOKUP($H$25,$AA$90:$EI$101,59,FALSE) -> 0 | P30: =O30/$E$36 -> 0 | AA30: January | AB30: ='تقرير مجمعة حسب الشهر'!G37 -> 62570428 | AC30: ='تقرير مجمعة حسب الشهر'!I37 -> 50036279 | AD30: ='تقرير مجمعة حسب الشهر'!J37 -> 12534149 | AE30: ='تقرير مجمعة حسب الشهر'!K37 -> 13391338 | AF30: ='تقرير مجمعة حسب الشهر'!M37 -> 955778.8 | AG30: ='تقرير مجمعة حسب الشهر'!N37 -> 98589.467 | EJ30: Sena3ia
C31: Total Sales Revenue | D31: : | E31: =VLOOKUP(H25,AA30:AG41,MATCH(C31,AA29:AG29,0),0) -> 67586212 | H31: الكهرباء | J31: =VLOOKUP($H$25,$AA$90:$EI$101,4,FALSE) -> 41973 | K31: =J31/$E$36 -> 0.0030025285 | M31: وجبات وانتقال - ايام دعاية | O31: =VLOOKUP($H$25,$AA$90:$EI$101,60,FALSE) -> 0 | P31: =O31/$E$36 -> 0 | AA31: February | AB31: ='تقرير مجمعة حسب الشهر'!G72 -> 53972140 | AC31: ='تقرير مجمعة حسب الشهر'!I72 -> 43447228 | AD31: ='تقرير مجمعة حسب الشهر'!J72 -> 10524912 | AE31: ='تقرير مجمعة حسب الشهر'!K72 -> 12519614 | AF31: ='تقرير مجمعة حسب الشهر'!M72 -> 1458073.2 | AG31: =AD31-AE31+AF31 -> -536628.66 | EJ31: Khargia
C32: Total Cost of Sales | D32: : | E32: =VLOOKUP(H25,AA30:AG41,MATCH(C32,AA29:AG29,0),0) -> 54356704 | H32: المياه | J32: =VLOOKUP($H$25,$AA$90:$EI$101,5,FALSE) -> 1993 | K32: =J32/$E$36 -> 0.00014256878 | M32: مكافات لجنة الجرد | O32: =VLOOKUP($H$25,$AA$90:$EI$101,61,FALSE) -> 35716 | P32: =O32/$E$36 -> 0.0025549355 | AA32: March | AB32: ='تقرير مجمعة حسب الشهر'!G108 -> 67087109 | AC32: ='تقرير مجمعة حسب الشهر'!I108 -> 53880856 | AD32: ='تقرير مجمعة حسب الشهر'!J108 -> 13206253 | AE32: ='تقرير مجمعة حسب الشهر'!K108 -> 13105861 | AF32: ='تقرير مجمعة حسب الشهر'!M108 -> 918992.67 | AG32: =AD32-AE32+AF32 -> 1019383.7 | EJ32: Tagmou3
C33: Gross Profit | D33: : | E33: =E31-E32 -> 13229508 | H33: التليفون الارضي | J33: =VLOOKUP($H$25,$AA$90:$EI$101,6,FALSE) -> 0 | K33: =J33/$E$36 -> 0 | M33: انتقالات لجنة الجرد | O33: =VLOOKUP($H$25,$AA$90:$EI$101,62,FALSE) -> 0 | P33: =O33/$E$36 -> 0 | AA33: April | AB33: ='تقرير مجمعة حسب الشهر'!G144 -> 67586212 | AC33: ='تقرير مجمعة حسب الشهر'!I144 -> 54356704 | AD33: ='تقرير مجمعة حسب الشهر'!J144 -> 13229508 | AE33: ='تقرير مجمعة حسب الشهر'!K144 -> 13979218 | AF33: ='تقرير مجمعة حسب الشهر'!M144 -> 2293958.2 | AG33: =AD33-AE33+AF33 -> 1544248.7 | EJ33: Maadi
C34: Total Non-Operational Income | D34: : | E34: =VLOOKUP(H25,AA30:AG41,MATCH(C34,AA29:AG29,0),0) -> 2293958.2 | H34: الايجار - الصيدلية | J34: =VLOOKUP($H$25,$AA$90:$EI$101,7,FALSE) -> 510000 | K34: =J34/$E$36 -> 0.036482728 | M34: وجبات لجنة الجرد | O34: =VLOOKUP($H$25,$AA$90:$EI$101,63,FALSE) -> 0 | P34: =O34/$E$36 -> 0 | AA34: May | AB34: ='تقرير مجمعة حسب الشهر'!G180 -> 72719603 | AC34: ='تقرير مجمعة حسب الشهر'!I180 -> 57799309 | AD34: ='تقرير مجمعة حسب الشهر'!J180 -> 14920294 | AE34: ='تقرير مجمعة حسب الشهر'!K180 -> 7696926.8 | AF34: ='تقرير مجمعة حسب الشهر'!M180 -> 0 | AG34: =AD34-AE34+AF34 -> 7223367.3 | EJ34: Zaid
C35: TOTAL INCOME | D35: : | E35: =E33+E34 -> 15523467 | H35: الايجار - الادارة | J35: =VLOOKUP($H$25,$AA$90:$EI$101,8,FALSE) -> 50000 | K35: =J35/$E$36 -> 0.003576738 | M35: مسروقات | O35: =VLOOKUP($H$25,$AA$90:$EI$101,64,FALSE) -> 0 | P35: =O35/$E$36 -> 0 | AA35: June | AB35: ='تقرير مجمعة حسب الشهر'!G216 -> 29000000 | AC35: ='تقرير مجمعة حسب الشهر'!I216 -> 0 | AD35: ='تقرير مجمعة حسب الشهر'!J216 -> 29000000 | AE35: ='تقرير مجمعة حسب الشهر'!K216 -> 11300000 | AF35: ='تقرير مجمعة حسب الشهر'!M216 -> 0 | AG35: =AD35-AE35+AF35 -> 17700000 | EJ35: Sand Beach
C36: Total Operating Expenses | D36: : | E36: =VLOOKUP(H25,AA30:AG41,MATCH(C36,AA29:AG29,0),0) -> 13979218 | H36: ايجارات متنوعه | J36: =VLOOKUP($H$25,$AA$90:$EI$101,9,FALSE) -> 438636 | K36: =J36/$E$36 -> 0.031377721 | M36: غرامات | O36: =VLOOKUP($H$25,$AA$90:$EI$101,65,FALSE) -> 0 | P36: =O36/$E$36 -> 0 | AA36: July | AB36: ='تقرير مجمعة حسب الشهر'!G252 -> 29000000 | AC36: ='تقرير مجمعة حسب الشهر'!I252 -> 0 | AD36: ='تقرير مجمعة حسب الشهر'!J252 -> 29000000 | AE36: ='تقرير مجمعة حسب الشهر'!K252 -> 11300000 | AF36: ='تقرير مجمعة حسب الشهر'!M252 -> 0 | AG36: =AD36-AE36+AF36 -> 17700000 | EJ36: Alamya
H37: ادوات مكتبية | J37: =VLOOKUP($H$25,$AA$90:$EI$101,10,FALSE) -> 11417 | K37: =J37/$E$36 -> 0.00081671236 | M37: مستلزمات كمبيوتر | O37: =VLOOKUP($H$25,$AA$90:$EI$101,66,FALSE) -> 35519.5 | P37: =O37/$E$36 -> 0.0025408789 | AA37: August | AB37: ='تقرير مجمعة حسب الشهر'!G288 -> 29000000 | AC37: ='تقرير مجمعة حسب الشهر'!I288 -> 0 | AD37: ='تقرير مجمعة حسب الشهر'!J288 -> 29000000 | AE37: ='تقرير مجمعة حسب الشهر'!K288 -> 11300000 | AF37: ='تقرير مجمعة حسب الشهر'!M288 -> 0 | AG37: =AD37-AE37+AF37 -> 17700000 | EJ37: Online
C38: TOTAL EXPENSES | D38: : | E38: =E36+E37 -> 13979218 | H38: فواتير الموبايل | J38: =VLOOKUP($H$25,$AA$90:$EI$101,11,FALSE) -> 20522 | K38: =J38/$E$36 -> 0.0014680364 | M38: صيانة اجهزة كمبيوتر | O38: =VLOOKUP($H$25,$AA$90:$EI$101,67,FALSE) -> 0 | P38: =O38/$E$36 -> 0 | AA38: September | AB38: ='تقرير مجمعة حسب الشهر'!G324 -> 29000000 | AC38: ='تقرير مجمعة حسب الشهر'!I324 -> 0 | AD38: ='تقرير مجمعة حسب الشهر'!J324 -> 29000000 | AE38: ='تقرير مجمعة حسب الشهر'!K324 -> 11300000 | AF38: ='تقرير مجمعة حسب الشهر'!M324 -> 0 | AG38: =AD38-AE38+AF38 -> 17700000 | EJ38: Orange
H39: مكافات مبيعات الادوية | J39: =VLOOKUP($H$25,$AA$90:$EI$101,12,FALSE) -> 0 | K39: =J39/$E$36 -> 0 | M39: مطبوعات ورقية | O39: =VLOOKUP($H$25,$AA$90:$EI$101,68,FALSE) -> 3500 | P39: =O39/$E$36 -> 0.00025037166 | AA39: October | AB39: ='تقرير مجمعة حسب الشهر'!G360 -> 29000000 | AC39: ='تقرير مجمعة حسب الشهر'!I360 -> 0 | AD39: ='تقرير مجمعة حسب الشهر'!J360 -> 29000000 | AE39: ='تقرير مجمعة حسب الشهر'!K360 -> 11300000 | AF39: ='تقرير مجمعة حسب الشهر'!M360 -> 0 | AG39: =AD39-AE39+AF39 -> 17700000 | EJ39: Vod.Smart
C40: NET PROFIT | D40: : | E40: =E35-E38-E39 -> 1544248.7 | H40: مكافات مبيعات التجميل | J40: =VLOOKUP($H$25,$AA$90:$EI$101,13,FALSE) -> 5040 | K40: =J40/$E$36 -> 0.00036053519 | M40: شحن بضاعة | O40: =VLOOKUP($H$25,$AA$90:$EI$101,69,FALSE) -> 0 | P40: =O40/$E$36 -> 0 | AA40: November | AB40: ='تقرير مجمعة حسب الشهر'!G396 -> 28000000 | AC40: ='تقرير مجمعة حسب الشهر'!I396 -> 0 | AD40: ='تقرير مجمعة حسب الشهر'!J396 -> 28000000 | AE40: ='تقرير مجمعة حسب الشهر'!K396 -> 11300000 | AF40: ='تقرير مجمعة حسب الشهر'!M396 -> 0 | AG40: =AD40-AE40+AF40 -> 16700000 | EJ40: Vod.Zahraa
H41: بوفية وضيافة | J41: =VLOOKUP($H$25,$AA$90:$EI$101,14,FALSE) -> 9856 | K41: =J41/$E$36 -> 0.0007050466 | M41: عيديات ومناسبات | O41: =VLOOKUP($H$25,$AA$90:$EI$101,70,FALSE) -> 0 | P41: =O41/$E$36 -> 0 | AA41: December | AB41: ='تقرير مجمعة حسب الشهر'!G432 -> 28000000 | AC41: ='تقرير مجمعة حسب الشهر'!I432 -> 0 | AD41: ='تقرير مجمعة حسب الشهر'!J432 -> 28000000 | AE41: ='تقرير مجمعة حسب الشهر'!K432 -> 11300000 | AF41: ='تقرير مجمعة حسب الشهر'!M432 -> 0 | AG41: =AD41-AE41+AF41 -> 16700000 | EJ41: Mo7awelat
H42: رسوم وتراخيص وعمولات | J42: =VLOOKUP($H$25,$AA$90:$EI$101,15,FALSE) -> 18457 | K42: =J42/$E$36 -> 0.0013203171 | M42: بدلات متنوعه | O42: =VLOOKUP($H$25,$AA$90:$EI$101,71,FALSE) -> 280665 | P42: =O42/$E$36 -> 0.020077304 | AA42: Total | AB42: =SUM(AB30:AB41) -> 5.2493549e+08 | AC42: =SUM(AC30:AC41) -> 2.5952038e+08 | AD42: =SUM(AD30:AD41) -> 2.6541512e+08 | AE42: =SUM(AE30:AE41) -> 1.3979296e+08 | AF42: =SUM(AF30:AF41) -> 5626802.9 | AG42: =SUM(AG30:AG41) -> 1.3124896e+08 | EJ42: Electric
H43: ورق طباعة | J43: =VLOOKUP($H$25,$AA$90:$EI$101,16,FALSE) -> 0 | K43: =J43/$E$36 -> 0 | M43: اجهزة ومستلزمات متنوعه | O43: =VLOOKUP($H$25,$AA$90:$EI$101,72,FALSE) -> 10173.5 | P43: =O43/$E$36 -> 0.00072775889 | EJ43: M.C.V
H44: بكر طباعة ريسيت | J44: =VLOOKUP($H$25,$AA$90:$EI$101,17,FALSE) -> 0 | K44: =J44/$E$36 -> 0 | M44: احبار طابعات | O44: =VLOOKUP($H$25,$AA$90:$EI$101,73,FALSE) -> 32915.24 | P44: =O44/$E$36 -> 0.0023545838 | EJ44: Egyplast
H45: بكر طباعة باركود | J45: =VLOOKUP($H$25,$AA$90:$EI$101,18,FALSE) -> 0 | K45: =J45/$E$36 -> 0 | M45: الانترنت | O45: =VLOOKUP($H$25,$AA$90:$EI$101,74,FALSE) -> 47623.35 | P45: =O45/$E$36 -> 0.0034067249 | EJ45: Etisalat.Katamya
H46: اعلان ودعاية وتسويق | J46: =VLOOKUP($H$25,$AA$90:$EI$101,19,FALSE) -> 38632 | K46: =J46/$E$36 -> 0.0027635309 | M46: الدعم الفني - سوفتك | O46: =VLOOKUP($H$25,$AA$90:$EI$101,75,FALSE) -> 53370 | P46: =O46/$E$36 -> 0.0038178102 | EJ46: CFC
H47: اكراميات | J47: =VLOOKUP($H$25,$AA$90:$EI$101,20,FALSE) -> 26730.47 | K47: =J47/$E$36 -> 0.0019121578 | M47: مصروف اهلاك مباني وانشاءات | O47: =VLOOKUP($H$25,$AA$90:$EI$101,76,FALSE) -> 73.33 | P47: =O47/$E$36 -> 5.245644e-06 | EJ47: North.Coast
H48: زكاة وتبرعات | J48: =VLOOKUP($H$25,$AA$90:$EI$101,21,FALSE) -> 53801.73 | K48: =J48/$E$36 -> 0.0038486939 | M48: مصروف اهلاك سيارات | O48: =VLOOKUP($H$25,$AA$90:$EI$101,77,FALSE) -> 6433.05 | P48: =O48/$E$36 -> 0.00046018669 | EJ48: Rehab
H49: مصروفات نثرية | J49: =VLOOKUP($H$25,$AA$90:$EI$101,22,FALSE) -> 352 | K49: =J49/$E$36 -> 2.5180236e-05 | M49: مصروف اهلاك اثاث ومكاتب | O49: =VLOOKUP($H$25,$AA$90:$EI$101,78,FALSE) -> 4998.5 | P49: =O49/$E$36 -> 0.0003575665 | EJ49: HSBC MAADI
H50: تأمينات اجتماعية | J50: =VLOOKUP($H$25,$AA$90:$EI$101,23,FALSE) -> 0 | K50: =J50/$E$36 -> 0 | M50: مصروف اهلاك اجهزة تكييف | O50: =VLOOKUP($H$25,$AA$90:$EI$101,79,FALSE) -> 12541.25 | P50: =O50/$E$36 -> 0.00089713532 | EJ50: HSBC SMART
H51: مستلزمات نظافة | J51: =VLOOKUP($H$25,$AA$90:$EI$101,24,FALSE) -> 5209 | K51: =J51/$E$36 -> 0.00037262457 | M51: مصروف اهلاك اجهزة كمبيوتر ومستلزماتها | O51: =VLOOKUP($H$25,$AA$90:$EI$101,80,FALSE) -> 56695.49 | P51: =O51/$E$36 -> 0.0040556983
H52: رسوم نظافة | J52: =VLOOKUP($H$25,$AA$90:$EI$101,25,FALSE) -> 395 | K52: =J52/$E$36 -> 2.825623e-05 | M52: مصروف اهلاك برامج كمبيوتر | O52: =VLOOKUP($H$25,$AA$90:$EI$101,81,FALSE) -> 8584.96 | P52: =O52/$E$36 -> 0.00061412306
H53: تامين على الصيدلية | J53: =VLOOKUP($H$25,$AA$90:$EI$101,26,FALSE) -> 1343.92 | K53: =J53/$E$36 -> 9.6136996e-05 | M53: مصروف اهلاك اجهزة كهربائية | O53: =VLOOKUP($H$25,$AA$90:$EI$101,82,FALSE) -> 29708.93 | P53: =O53/$E$36 -> 0.0021252212
H54: اصلاح وصيانة التكييفات | J54: =VLOOKUP($H$25,$AA$90:$EI$101,27,FALSE) -> 24395 | K54: =J54/$E$36 -> 0.0017450905 | M54: مصروف اهلاك تجهيزات وديكور | O54: =VLOOKUP($H$25,$AA$90:$EI$101,83,FALSE) -> 13850.54 | P54: =O54/$E$36 -> 0.00099079506
H55: اصلاح وصيانة الكهرباء | J55: =VLOOKUP($H$25,$AA$90:$EI$101,28,FALSE) -> 2170 | K55: =J55/$E$36 -> 0.00015523043 | M55: الضرائب العامة | O55: =VLOOKUP($H$25,$AA$90:$EI$101,84,FALSE) -> 0 | P55: =O55/$E$36 -> 0
H56: اصلاح وصيانة السباكة | J56: =VLOOKUP($H$25,$AA$90:$EI$101,29,FALSE) -> 925 | K56: =J56/$E$36 -> 6.6169654e-05 | M56: الضرائب العقارية | O56: =VLOOKUP($H$25,$AA$90:$EI$101,85,FALSE) -> 0 | P56: =O56/$E$36 -> 0
H57: اصلاح وصيانة اثاث وديكور | J57: =VLOOKUP($H$25,$AA$90:$EI$101,30,FALSE) -> 0 | K57: =J57/$E$36 -> 0 | M57: خصم نقاط العملاء | O57: =VLOOKUP($H$25,$AA$90:$EI$101,86,FALSE) -> 120299.98 | P57: =O57/$E$36 -> 0.0086056303
H58: اصلاح وصيانة اخرى | J58: =VLOOKUP($H$25,$AA$90:$EI$101,31,FALSE) -> 23635 | K58: =J58/$E$36 -> 0.0016907241 | M58: عقود صيانة وتوصيل مرافق | O58: =VLOOKUP($H$25,$AA$90:$EI$101,87,FALSE) -> 0 | P58: =O58/$E$36 -> 0
H59: مكافات | J59: =VLOOKUP($H$25,$AA$90:$EI$101,32,FALSE) -> 27835 | K59: =J59/$E$36 -> 0.0019911701 | M59: مصروفات تأسيس | O59: =VLOOKUP($H$25,$AA$90:$EI$101,88,FALSE) -> 166.66 | P59: =O59/$E$36 -> 1.1921983e-05
H60: هدايا ومزايا عينية | J60: =VLOOKUP($H$25,$AA$90:$EI$101,33,FALSE) -> 0 | K60: =J60/$E$36 -> 0 | M60: هوالك وتوالف | O60: =VLOOKUP($H$25,$AA$90:$EI$101,89,FALSE) -> 1898.8 | P60: =O60/$E$36 -> 0.0001358302
H61: تارجت الفروع | J61: =VLOOKUP($H$25,$AA$90:$EI$101,34,FALSE) -> 253099 | K61: =J61/$E$36 -> 0.018105376 | M61: عجز جرد | O61: =VLOOKUP($H$25,$AA$90:$EI$101,90,FALSE) -> 43209.83 | P61: =O61/$E$36 -> 0.0030910048
H62: مزايا عاملين | J62: =VLOOKUP($H$25,$AA$90:$EI$101,35,FALSE) -> 14000 | K62: =J62/$E$36 -> 0.0010014866 | M62: تامين على السيارات | O62: =VLOOKUP($H$25,$AA$90:$EI$101,91,FALSE) -> 0 | P62: =O62/$E$36 -> 0
H63: مستهلكات صيدلية | J63: =VLOOKUP($H$25,$AA$90:$EI$101,36,FALSE) -> 3438.3 | K63: =J63/$E$36 -> 0.00024595797 | M63: مصروفات عملاء تعاقدات | O63: =VLOOKUP($H$25,$AA$90:$EI$101,92,FALSE) -> 12522 | P63: =O63/$E$36 -> 0.00089575827
H64: اتعاب استشارات محاسبية | J64: =VLOOKUP($H$25,$AA$90:$EI$101,37,FALSE) -> 28000 | K64: =J64/$E$36 -> 0.0020029733 | M64: ارباح دائنون متنوعون | O64: =VLOOKUP($H$25,$AA$90:$EI$101,93,FALSE) -> 44600 | P64: =O64/$E$36 -> 0.0031904503
H65: اتعاب محاماة | J65: =VLOOKUP($H$25,$AA$90:$EI$101,38,FALSE) -> 0 | K65: =J65/$E$36 -> 0 | M65: مصروفات متنوعه - ايام دعاية | O65: =VLOOKUP($H$25,$AA$90:$EI$101,94,FALSE) -> 8350 | P65: =O65/$E$36 -> 0.00059731525
H66: مصروفات بنكية | J66: =VLOOKUP($H$25,$AA$90:$EI$101,39,FALSE) -> 231973.56 | K66: =J66/$E$36 -> 0.016594173 | M66: تغليف وشحن بضاعة | O66: =VLOOKUP($H$25,$AA$90:$EI$101,95,FALSE) -> 2000 | P66: =O66/$E$36 -> 0.00014306952
H67: شنط صيدلية | J67: =VLOOKUP($H$25,$AA$90:$EI$101,40,FALSE) -> 26277 | K67: =J67/$E$36 -> 0.0018797189 | M67: ديون معدومة | O67: =VLOOKUP($H$25,$AA$90:$EI$101,96,FALSE) -> 322630 | P67: =O67/$E$36 -> 0.02307926
H68: خصومات اضافية للعملاء | J68: =VLOOKUP($H$25,$AA$90:$EI$101,41,FALSE) -> 2900 | K68: =J68/$E$36 -> 0.00020745081 | M68: دمغات | O68: =VLOOKUP($H$25,$AA$90:$EI$101,97,FALSE) -> 0 | P68: =O68/$E$36 -> 0
H69: اشتراك الخط الساخن | J69: =VLOOKUP($H$25,$AA$90:$EI$101,42,FALSE) -> 0 | K69: =J69/$E$36 -> 0 | M69: خسائر إستبعاد أصول | O69: =VLOOKUP($H$25,$AA$90:$EI$101,98,FALSE) -> 0 | P69: =O69/$E$36 -> 0
H70: ملابس عاملين | J70: =VLOOKUP($H$25,$AA$90:$EI$101,43,FALSE) -> 0 | K70: =J70/$E$36 -> 0 | M70: عروض مبيعات التجميل | O70: =VLOOKUP($H$25,$AA$90:$EI$101,99,FALSE) -> 110460.69 | P70: =O70/$E$36 -> 0.007901779
H71: وجبات عاملين | J71: =VLOOKUP($H$25,$AA$90:$EI$101,44,FALSE) -> 4885 | K71: =J71/$E$36 -> 0.00034944731 | M71: فوائد القروض - ابوظبى الاولFAB | O71: =VLOOKUP($H$25,$AA$90:$EI$101,100,FALSE) -> 11419.4 | P71: =O71/$E$36 -> 0.00081688405
H72: انتقالات عمومية | J72: =VLOOKUP($H$25,$AA$90:$EI$101,45,FALSE) -> 0 | K72: =J72/$E$36 -> 0 | M72: فوائد القروض بنك ADIB | O72: =VLOOKUP($H$25,$AA$90:$EI$101,101,FALSE) -> 5589.2 | P72: =O72/$E$36 -> 0.00039982208
H73: وقود السيارات | J73: =VLOOKUP($H$25,$AA$90:$EI$101,46,FALSE) -> 24574 | K73: =J73/$E$36 -> 0.0017578952 | M73: فوائد القروض بنك كريدي أجريكول | O73: =VLOOKUP($H$25,$AA$90:$EI$101,102,FALSE) -> 7841.76 | P73: =O73/$E$36 -> 0.00056095842
H74: زيت السيارات | J74: =VLOOKUP($H$25,$AA$90:$EI$101,47,FALSE) -> 6000 | K74: =J74/$E$36 -> 0.00042920856 | M74: فوائد القروض - العربى الافريقىAAIB | O74: =VLOOKUP($H$25,$AA$90:$EI$101,103,FALSE) -> 31683.79 | P74: =O74/$E$36 -> 0.0022664923
H75: صيانة السيارات - التوكيل | J75: =VLOOKUP($H$25,$AA$90:$EI$101,48,FALSE) -> 0 | K75: =J75/$E$36 -> 0 | M75: فوائد المصرية للتمويل العقارى | O75: =VLOOKUP($H$25,$AA$90:$EI$101,104,FALSE) -> 86527.95 | P75: =O75/$E$36 -> 0.0061897562
H76: اصلاح السيارات | J76: =VLOOKUP($H$25,$AA$90:$EI$101,49,FALSE) -> 0 | K76: =J76/$E$36 -> 0 | M76: فوائد القروض البنك الاهلى المصرى | O76: =VLOOKUP($H$25,$AA$90:$EI$101,105,FALSE) -> 14669.56 | P76: =O76/$E$36 -> 0.0010493835
H77: اصلاح وجراج السيارات | J77: =VLOOKUP($H$25,$AA$90:$EI$101,50,FALSE) -> 1920 | K77: =J77/$E$36 -> 0.00013734674 | M77: فوائد القروض بنك الاهلى الكويتى ABK | O77: =VLOOKUP($H$25,$AA$90:$EI$101,106,FALSE) -> 10227.21 | P77: =O77/$E$36 -> 0.00073160102
H78: تجديد رخص السيارت | J78: =VLOOKUP($H$25,$AA$90:$EI$101,51,FALSE) -> 1130 | K78: =J78/$E$36 -> 8.083428e-05 | M78: فوائد القروض بنك الاهلى المتحد AUB | O78: =VLOOKUP($H$25,$AA$90:$EI$101,107,FALSE) -> 14971.99 | P78: =O78/$E$36 -> 0.0010710177
H79: اجور ومرتبات - ايام دعاية | J79: =VLOOKUP($H$25,$AA$90:$EI$101,52,FALSE) -> 0 | K79: =J79/$E$36 -> 0 | M79: فوائد القروض البنك التجارى الدولى CIB | O79: =VLOOKUP($H$25,$AA$90:$EI$101,108,FALSE) -> 10901.17 | P79: =O79/$E$36 -> 0.00077981259
H80: كهرباء - ايام دعاية | J80: =VLOOKUP($H$25,$AA$90:$EI$101,53,FALSE) -> 0 | K80: =J80/$E$36 -> 0 | M80: تأمينات اجتماعية - حصة الشركة | O80: =VLOOKUP($H$25,$AA$90:$EI$101,109,FALSE) -> 41681.25 | P80: =O80/$E$36 -> 0.0029816582
H81: بنزين وزيت - ايام دعاية | J81: =VLOOKUP($H$25,$AA$90:$EI$101,54,FALSE) -> 0 | K81: =J81/$E$36 -> 0 | M81: فوائد القروض - التجارى وفا بنك AWB | O81: =VLOOKUP($H$25,$AA$90:$EI$101,110,FALSE) -> 18268.93 | P81: =O81/$E$36 -> 0.0013068635
H82: عمولات - ايام دعاية | J82: =VLOOKUP($H$25,$AA$90:$EI$101,55,FALSE) -> 0 | K82: =J82/$E$36 -> 0 | M82: فوائد القروض - بنك القاهرة BDC | O82: =VLOOKUP($H$25,$AA$90:$EI$101,111,FALSE) -> 15587.28 | P82: =O82/$E$36 -> 0.0011150323
H83: ايجارات - ايام دعاية | J83: =VLOOKUP($H$25,$AA$90:$EI$101,56,FALSE) -> 0 | K83: =J83/$E$36 -> 0 | M83: اتعاب محاماه | O83: =VLOOKUP($H$25,$AA$90:$EI$101,112,FALSE) -> 0 | P83: =O83/$E$36 -> 0
H84: نقل البضاعة - ايام دعاية | J84: =VLOOKUP($H$25,$AA$90:$EI$101,57,FALSE) -> 0 | K84: =J84/$E$36 -> 0 | M84: خصم أبليكيشن | O84: =VLOOKUP($H$25,$AA$90:$EJ$101,113,FALSE) -> 3711019.1 | P84: =O84/$E$36 -> 0.26546686
H85: عروض مبيعات ابليكشن | J85: =VLOOKUP($H$25,$AA$90:$EW$101,115,FALSE) -> 0 | K85: =J85/$E$36 -> 0 | M85: مفقودات ومسروقات | O85: =VLOOKUP($H$25,$AA$90:$EJ$101,114,FALSE) -> 0 | P85: =O85/$E$36 -> 0
H86: عمولات ادارية | J86: =VLOOKUP($H$25,$AA$90:$EL$101,116,FALSE) -> 0 | K86: =J86/$E$36 -> 0
O87: =SUM(O29:O86)+SUM(J29:J86) -> 13348712
AB88: 2 | AC88: 3 | AD88: 4 | AE88: 5 | AF88: 6 | AG88: 7 | AH88: 8 | AI88: 9 | AJ88: 10 | AK88: 11 | AL88: 12 | AM88: 13 | AN88: 14 | AO88: 15 | AP88: 16 | AQ88: 17 | AR88: 18 | AS88: 19 | AT88: 20 | AU88: 21 | AV88: 22 | AW88: 23 | AX88: 24 | AY88: 25 | AZ88: 26 | BA88: 27 | BB88: 28 | BC88: 29 | BD88: 30 | BE88: 31 | BF88: 32 | BG88: 33 | BH88: 34 | BI88: 35 | BJ88: 36 | BK88: 37 | BL88: 38 | BM88: 39 | BN88: 40 | BO88: 41 | BP88: 42 | BQ88: 43 | BR88: 44 | BS88: 45 | BT88: 46 | BU88: 47 | BV88: 48 | BW88: 49 | BX88: 50 | BY88: 51 | BZ88: 52 | CA88: 53 | CB88: 54 | CC88: 55 | CD88: 56 | CE88: 57 | CF88: 58 | CG88: 59 | CH88: 60 | CI88: 61 | CJ88: 62 | CK88: 63 | CL88: 64 | CM88: 65 | CN88: 66 | CO88: 67 | CP88: 68 | CQ88: 69 | CR88: 70 | CS88: 71 | CT88: 72 | CU88: 73 | CV88: 74 | CW88: 75 | CX88: 76 | CY88: 77 | CZ88: 78 | DA88: 79 | DB88: 80 | DC88: 81 | DD88: 82 | DE88: 83 | DF88: 84 | DG88: 85 | DH88: 86 | DI88: 87 | DJ88: 88 | DK88: 89 | DL88: 90 | DM88: 91 | DN88: 92 | DO88: 93 | DP88: 94 | DQ88: 95 | DR88: 96 | DS88: 97 | DT88: 98 | DU88: 99 | DV88: 100 | DW88: 101 | DX88: 102 | DY88: 103 | DZ88: 104 | EA88: 105 | EB88: 106 | EC88: 107 | ED88: 108 | EE88: 109 | EF88: 110 | EG88: 111 | EH88: 112 | EI88: 113 | EJ88: 114 | EK88: 115 | EL88: 115
AB89: مرتبات الادارة | AC89: مرتبات الفروع | AD89: الكهرباء | AE89: المياه | AF89: التليفون الارضي | AG89: الايجار - الصيدلية | AH89: الايجار - الادارة | AI89: ايجارات متنوعه | AJ89: ادوات مكتبية | AK89: فواتير الموبايل | AL89: مكافات مبيعات الادوية | AM89: مكافات مبيعات التجميل | AN89: بوفية وضيافة | AO89: رسوم وتراخيص وعمولات | AP89: ورق طباعة | AQ89: بكر طباعة ريسيت | AR89: بكر طباعة باركود | AS89: اعلان ودعاية وتسويق | AT89: اكراميات | AU89: زكاة وتبرعات | AV89: مصروفات نثرية | AW89: تأمينات اجتماعية | AX89: مستلزمات نظافة | AY89: رسوم نظافة | AZ89: تامين على الصيدلية | BA89: اصلاح وصيانة التكييفات | BB89: اصلاح وصيانة الكهرباء | BC89: اصلاح وصيانة السباكة | BD89: اصلاح وصيانة اثاث وديكور | BE89: اصلاح وصيانة اخرى | BF89: مكافات | BG89: هدايا ومزايا عينية | BH89: تارجت الفروع | BI89: مزايا عاملين | BJ89: مستهلكات صيدلية | BK89: اتعاب استشارات محاسبية | BL89: اتعاب محاماة | BM89: مصروفات بنكية | BN89: شنط صيدلية | BO89: خصومات اضافية للعملاء | BP89: اشتراك الخط الساخن | BQ89: ملابس عاملين | BR89: وجبات عاملين | BS89: انتقالات عمومية | BT89: وقود السيارات | BU89: زيت السيارات | BV89: صيانة السيارات - التوكيل | BW89: اصلاح السيارات | BX89: اصلاح وجراج السيارات | BY89: تجديد رخص السيارت | BZ89: اجور ومرتبات - ايام دعاية | CA89: كهرباء - ايام دعاية | CB89: بنزين وزيت - ايام دعاية | CC89: عمولات - ايام دعاية | CD89: ايجارات - ايام دعاية | CE89: نقل البضاعة - ايام دعاية | CF89: اعلان ودعاية - ايام دعاية | CG89: اكراميات - ايام دعاية | CH89: وجبات وانتقال - ايام دعاية | CI89: مكافات لجنة الجرد | CJ89: انتقالات لجنة الجرد | CK89: وجبات لجنة الجرد | CL89: مسروقات | CM89: غرامات | CN89: مستلزمات كمبيوتر | CO89: صيانة اجهزة كمبيوتر | CP89: مطبوعات ورقية | CQ89: شحن بضاعة | CR89: عيديات ومناسبات | CS89: بدلات متنوعه | CT89: اجهزة ومستلزمات متنوعه | CU89: احبار طابعات | CV89: الانترنت | CW89: الدعم الفني - سوفتك | CX89: مصروف اهلاك مباني وانشاءات | CY89: مصروف اهلاك سيارات | CZ89: مصروف اهلاك اثاث ومكاتب | DA89: مصروف اهلاك اجهزة تكييف | DB89: مصروف اهلاك اجهزة كمبيوتر ومستلزماتها | DC89: مصروف اهلاك برامج كمبيوتر | DD89: مصروف اهلاك اجهزة كهربائية | DE89: مصروف اهلاك تجهيزات وديكور | DF89: الضرائب العامة | DG89: الضرائب العقارية | DH89: خصم نقاط العملاء | DI89: عقود صيانة وتوصيل مرافق | DJ89: مصروفات تأسيس | DK89: هوالك وتوالف | DL89: عجز جرد | DM89: تامين على السيارات | DN89: مصروفات عملاء تعاقدات | DO89: ارباح دائنون متنوعون | DP89: مصروفات متنوعه - ايام دعاية | DQ89: تغليف وشحن بضاعة | DR89: ديون معدومة | DS89: دمغات | DT89: خسائر إستبعاد أصول | DU89: عروض مبيعات التجميل | DV89: فوائد القروض - ابوظبى الاولFAB | DW89: فوائد القروض بنك ADIB | DX89: فوائد القروض بنك كريدي أجريكول | DY89: فوائد القروض - العربى الافريقىAAIB | DZ89: فوائد المصرية للتمويل العقارى | EA89: فوائد القروض البنك الاهلى المصرى | EB89: فوائد القروض بنك الاهلى الكويتى ABK | EC89: فوائد القروض بنك الاهلى المتحد AUB | ED89: فوائد القروض البنك التجارى الدولى CIB | EE89: تأمينات اجتماعية - حصة الشركة | EF89: فوائد القروض - التجارى وفا بنك AWB | EG89: فوائد القروض - بنك القاهرة BDC | EH89: اتعاب محاماه | EI89: خصم أبليكيشن | EJ89: مفقودات ومسروقات | EK89: عروض مبيعات ابليكشن | EL89: عمولات ادارية
AA90: January | AB90: =IFERROR(VLOOKUP(AB89,'تقرير مصروفات إجمالية'!$B$3:$C$118,2,FALSE),0) -> 1554391.1 | AC90: =IFERROR(VLOOKUP(AC89,'تقرير مصروفات إجمالية'!$B$3:$C$118,2,FALSE),0) -> 4375458.4 | AD90: =IFERROR(VLOOKUP(AD89,'تقرير مصروفات إجمالية'!$B$3:$C$118,2,FALSE),0) -> 65680 | AE90: =IFERROR(VLOOKUP(AE89,'تقرير مصروفات إجمالية'!$B$3:$C$118,2,FALSE),0) -> 3656 | AF90: =IFERROR(VLOOKUP(AF89,'تقرير مصروفات إجمالية'!$B$3:$C$118,2,FALSE),0) -> 0 | AG90: =IFERROR(VLOOKUP(AG89,'تقرير مصروفات إجمالية'!$B$3:$C$118,2,FALSE),0) -> 510000 | AH90: =IFERROR(VLOOKUP(AH89,'تقرير مصروفات إجمالية'!$B$3:$C$118,2,FALSE),0) -> 50000 | AI90: =IFERROR(VLOOKUP(AI89,'تقرير مصروفات إجمالية'!$B$3:$C$118,2,FALSE),0) -> 418686 | ... EL90: =IFERROR(VLOOKUP(EL89,'تقرير مصروفات إجمالية'!$B$3:$C$118,2,FALSE),0) -> 92000
AA91: February | AB91: =_xlfn.XLOOKUP(AB89,'تقرير مصروفات إجمالية'!$B$3:$B$119,'تقرير مصروفات إجمالية'!$D$3:$D$119,0,0) -> 1494705.5 | AC91: =_xlfn.XLOOKUP(AC89,'تقرير مصروفات إجمالية'!$B$3:$B$119,'تقرير مصروفات إجمالية'!$D$3:$D$119,0,0) -> 4222783.6 | AD91: =_xlfn.XLOOKUP(AD89,'تقرير مصروفات إجمالية'!$B$3:$B$119,'تقرير مصروفات إجمالية'!$D$3:$D$119,0,0) -> 38352 | AE91: =_xlfn.XLOOKUP(AE89,'تقرير مصروفات إجمالية'!$B$3:$B$119,'تقرير مصروفات إجمالية'!$D$3:$D$119,0,0) -> 735 | AF91: =_xlfn.XLOOKUP(AF89,'تقرير مصروفات إجمالية'!$B$3:$B$119,'تقرير مصروفات إجمالية'!$D$3:$D$119,0,0) -> 12100 | AG91: =_xlfn.XLOOKUP(AG89,'تقرير مصروفات إجمالية'!$B$3:$B$119,'تقرير مصروفات إجمالية'!$D$3:$D$119,0,0) -> 510000 | AH91: =_xlfn.XLOOKUP(AH89,'تقرير مصروفات إجمالية'!$B$3:$B$119,'تقرير مصروفات إجمالية'!$D$3:$D$119,0,0) -> 50000 | AI91: =_xlfn.XLOOKUP(AI89,'تقرير مصروفات إجمالية'!$B$3:$B$119,'تقرير مصروفات إجمالية'!$D$3:$D$119,0,0) -> 486126 | ... EL91: =_xlfn.XLOOKUP(EL89,'تقرير مصروفات إجمالية'!$B$3:$B$119,'تقرير مصروفات إجمالية'!$D$3:$D$119,0,0) -> 0
AA92: March | AB92: =_xlfn.XLOOKUP(AB89,'تقرير مصروفات إجمالية'!$B$3:$B$119,'تقرير مصروفات إجمالية'!$E$3:$E$119,0,0) -> 1468661.1 | AC92: =_xlfn.XLOOKUP(AC89,'تقرير مصروفات إجمالية'!$B$3:$B$119,'تقرير مصروفات إجمالية'!$E$3:$E$119,0,0) -> 4442130.7 | AD92: =_xlfn.XLOOKUP(AD89,'تقرير مصروفات إجمالية'!$B$3:$B$119,'تقرير مصروفات إجمالية'!$E$3:$E$119,0,0) -> 40429 | AE92: =_xlfn.XLOOKUP(AE89,'تقرير مصروفات إجمالية'!$B$3:$B$119,'تقرير مصروفات إجمالية'!$E$3:$E$119,0,0) -> 4396 | AF92: =_xlfn.XLOOKUP(AF89,'تقرير مصروفات إجمالية'!$B$3:$B$119,'تقرير مصروفات إجمالية'!$E$3:$E$119,0,0) -> 698.5 | AG92: =_xlfn.XLOOKUP(AG89,'تقرير مصروفات إجمالية'!$B$3:$B$119,'تقرير مصروفات إجمالية'!$E$3:$E$119,0,0) -> 510000 | AH92: =_xlfn.XLOOKUP(AH89,'تقرير مصروفات إجمالية'!$B$3:$B$119,'تقرير مصروفات إجمالية'!$E$3:$E$119,0,0) -> 50000 | AI92: =_xlfn.XLOOKUP(AI89,'تقرير مصروفات إجمالية'!$B$3:$B$119,'تقرير مصروفات إجمالية'!$E$3:$E$119,0,0) -> 434776 | ... EL92: =_xlfn.XLOOKUP(EL89,'تقرير مصروفات إجمالية'!$B$3:$B$119,'تقرير مصروفات إجمالية'!$E$3:$E$119,0,0) -> 142000
AA93: April | AB93: =IFERROR(VLOOKUP(AB89,'تقرير مصروفات إجمالية'!$B$3:$F$115,5,0),0) -> 1600742 | AC93: =IFERROR(VLOOKUP(AC89,'تقرير مصروفات إجمالية'!$B$3:$F$115,5,0),0) -> 4557559.9 | AD93: =IFERROR(VLOOKUP(AD89,'تقرير مصروفات إجمالية'!$B$3:$F$115,5,0),0) -> 41973 | AE93: =IFERROR(VLOOKUP(AE89,'تقرير مصروفات إجمالية'!$B$3:$F$115,5,0),0) -> 1993 | AF93: =IFERROR(VLOOKUP(AF89,'تقرير مصروفات إجمالية'!$B$3:$F$115,5,0),0) -> 0 | AG93: =IFERROR(VLOOKUP(AG89,'تقرير مصروفات إجمالية'!$B$3:$F$115,5,0),0) -> 510000 | AH93: =IFERROR(VLOOKUP(AH89,'تقرير مصروفات إجمالية'!$B$3:$F$115,5,0),0) -> 50000 | AI93: =IFERROR(VLOOKUP(AI89,'تقرير مصروفات إجمالية'!$B$3:$F$115,5,0),0) -> 438636 | ... EL93: =IFERROR(VLOOKUP(EL89,'تقرير مصروفات إجمالية'!$B$3:$F$115,5,0),0) -> 0
AA94: May | AB94: =IFERROR(VLOOKUP(AB89,'تقرير مصروفات إجمالية'!$B$3:$N$115,6,FALSE),0) -> 1389895.6 | AC94: =IFERROR(VLOOKUP(AC89,'تقرير مصروفات إجمالية'!$B$3:$N$115,6,FALSE),0) -> 3399892.8 | AD94: =IFERROR(VLOOKUP(AD89,'تقرير مصروفات إجمالية'!$B$3:$N$115,6,FALSE),0) -> 55277 | AE94: =IFERROR(VLOOKUP(AE89,'تقرير مصروفات إجمالية'!$B$3:$N$115,6,FALSE),0) -> 1090 | AF94: =IFERROR(VLOOKUP(AF89,'تقرير مصروفات إجمالية'!$B$3:$N$115,6,FALSE),0) -> 0 | AG94: =IFERROR(VLOOKUP(AG89,'تقرير مصروفات إجمالية'!$B$3:$N$115,6,FALSE),0) -> 510000 | AH94: =IFERROR(VLOOKUP(AH89,'تقرير مصروفات إجمالية'!$B$3:$N$115,6,FALSE),0) -> 50000 | AI94: =IFERROR(VLOOKUP(AI89,'تقرير مصروفات إجمالية'!$B$3:$N$115,6,FALSE),0) -> 389936 | ... EL94: =IFERROR(VLOOKUP(EL89,'تقرير مصروفات إجمالية'!$B$3:$N$115,6,FALSE),0) -> 0
AA95: June | AB95: =IFERROR(VLOOKUP(AB89,'تقرير مصروفات إجمالية'!$B$3:$N$115,7,FALSE),0) -> 100000 | AC95: =IFERROR(VLOOKUP(AC89,'تقرير مصروفات إجمالية'!$B$3:$N$115,7,FALSE),0) -> 100000 | AD95: =IFERROR(VLOOKUP(AD89,'تقرير مصروفات إجمالية'!$B$3:$N$115,7,FALSE),0) -> 100000 | AE95: =IFERROR(VLOOKUP(AE89,'تقرير مصروفات إجمالية'!$B$3:$N$115,7,FALSE),0) -> 100000 | AF95: =IFERROR(VLOOKUP(AF89,'تقرير مصروفات إجمالية'!$B$3:$N$115,7,FALSE),0) -> 100000 | AG95: =IFERROR(VLOOKUP(AG89,'تقرير مصروفات إجمالية'!$B$3:$N$115,7,FALSE),0) -> 100000 | AH95: =IFERROR(VLOOKUP(AH89,'تقرير مصروفات إجمالية'!$B$3:$N$115,7,FALSE),0) -> 100000 | AI95: =IFERROR(VLOOKUP(AI89,'تقرير مصروفات إجمالية'!$B$3:$N$115,7,FALSE),0) -> 100000 | ... EL95: =IFERROR(VLOOKUP(EL89,'تقرير مصروفات إجمالية'!$B$3:$N$115,7,FALSE),0) -> 0
AA96: July | AB96: =IFERROR(VLOOKUP(AB89,'تقرير مصروفات إجمالية'!$B$3:$N$115,8,FALSE),0) -> 100000 | AC96: =IFERROR(VLOOKUP(AC89,'تقرير مصروفات إجمالية'!$B$3:$N$115,8,FALSE),0) -> 100000 | AD96: =IFERROR(VLOOKUP(AD89,'تقرير مصروفات إجمالية'!$B$3:$N$115,8,FALSE),0) -> 100000 | AE96: =IFERROR(VLOOKUP(AE89,'تقرير مصروفات إجمالية'!$B$3:$N$115,8,FALSE),0) -> 100000 | AF96: =IFERROR(VLOOKUP(AF89,'تقرير مصروفات إجمالية'!$B$3:$N$115,8,FALSE),0) -> 100000 | AG96: =IFERROR(VLOOKUP(AG89,'تقرير مصروفات إجمالية'!$B$3:$N$115,8,FALSE),0) -> 100000 | AH96: =IFERROR(VLOOKUP(AH89,'تقرير مصروفات إجمالية'!$B$3:$N$115,8,FALSE),0) -> 100000 | AI96: =IFERROR(VLOOKUP(AI89,'تقرير مصروفات إجمالية'!$B$3:$N$115,8,FALSE),0) -> 100000 | ... EL96: =IFERROR(VLOOKUP(EL89,'تقرير مصروفات إجمالية'!$B$3:$N$115,8,FALSE),0) -> 0
AA97: August | AB97: =IFERROR(VLOOKUP(AB89,'تقرير مصروفات إجمالية'!$B$3:$N$115,9,FALSE),0) -> 100000 | AC97: =IFERROR(VLOOKUP(AC89,'تقرير مصروفات إجمالية'!$B$3:$N$115,9,FALSE),0) -> 100000 | AD97: =IFERROR(VLOOKUP(AD89,'تقرير مصروفات إجمالية'!$B$3:$N$115,9,FALSE),0) -> 100000 | AE97: =IFERROR(VLOOKUP(AE89,'تقرير مصروفات إجمالية'!$B$3:$N$115,9,FALSE),0) -> 100000 | AF97: =IFERROR(VLOOKUP(AF89,'تقرير مصروفات إجمالية'!$B$3:$N$115,9,FALSE),0) -> 100000 | AG97: =IFERROR(VLOOKUP(AG89,'تقرير مصروفات إجمالية'!$B$3:$N$115,9,FALSE),0) -> 100000 | AH97: =IFERROR(VLOOKUP(AH89,'تقرير مصروفات إجمالية'!$B$3:$N$115,9,FALSE),0) -> 100000 | AI97: =IFERROR(VLOOKUP(AI89,'تقرير مصروفات إجمالية'!$B$3:$N$115,9,FALSE),0) -> 100000 | ... EL97: =IFERROR(VLOOKUP(EL89,'تقرير مصروفات إجمالية'!$B$3:$N$115,9,FALSE),0) -> 0
AA98: September | AB98: =IFERROR(VLOOKUP(AB89,'تقرير مصروفات إجمالية'!$B$3:$N$117,10,FALSE),0) -> 100000 | AC98: =IFERROR(VLOOKUP(AC89,'تقرير مصروفات إجمالية'!$B$3:$N$117,10,FALSE),0) -> 100000 | AD98: =IFERROR(VLOOKUP(AD89,'تقرير مصروفات إجمالية'!$B$3:$N$117,10,FALSE),0) -> 100000 | AE98: =IFERROR(VLOOKUP(AE89,'تقرير مصروفات إجمالية'!$B$3:$N$117,10,FALSE),0) -> 100000 | AF98: =IFERROR(VLOOKUP(AF89,'تقرير مصروفات إجمالية'!$B$3:$N$117,10,FALSE),0) -> 100000 | AG98: =IFERROR(VLOOKUP(AG89,'تقرير مصروفات إجمالية'!$B$3:$N$117,10,FALSE),0) -> 100000 | AH98: =IFERROR(VLOOKUP(AH89,'تقرير مصروفات إجمالية'!$B$3:$N$117,10,FALSE),0) -> 100000 | AI98: =IFERROR(VLOOKUP(AI89,'تقرير مصروفات إجمالية'!$B$3:$N$117,10,FALSE),0) -> 100000 | ... EL98: =IFERROR(VLOOKUP(EL89,'تقرير مصروفات إجمالية'!$B$3:$N$117,10,FALSE),0) -> 0
AA99: October | AB99: =IFERROR(VLOOKUP(AB89,'تقرير مصروفات إجمالية'!$B$3:$N$115,11,FALSE),0) -> 100000 | AC99: =IFERROR(VLOOKUP(AC89,'تقرير مصروفات إجمالية'!$B$3:$N$115,11,FALSE),0) -> 100000 | AD99: =IFERROR(VLOOKUP(AD89,'تقرير مصروفات إجمالية'!$B$3:$N$115,11,FALSE),0) -> 100000 | AE99: =IFERROR(VLOOKUP(AE89,'تقرير مصروفات إجمالية'!$B$3:$N$115,11,FALSE),0) -> 100000 | AF99: =IFERROR(VLOOKUP(AF89,'تقرير مصروفات إجمالية'!$B$3:$N$115,11,FALSE),0) -> 100000 | AG99: =IFERROR(VLOOKUP(AG89,'تقرير مصروفات إجمالية'!$B$3:$N$115,11,FALSE),0) -> 100000 | AH99: =IFERROR(VLOOKUP(AH89,'تقرير مصروفات إجمالية'!$B$3:$N$115,11,FALSE),0) -> 100000 | AI99: =IFERROR(VLOOKUP(AI89,'تقرير مصروفات إجمالية'!$B$3:$N$115,11,FALSE),0) -> 100000 | ... EL99: =IFERROR(VLOOKUP(EL89,'تقرير مصروفات إجمالية'!$B$3:$N$115,11,FALSE),0) -> 0
AA100: November | AB100: =IFERROR(VLOOKUP(AB89,'تقرير مصروفات إجمالية'!$B$3:$O$119,12,FALSE),0) -> 100000 | AC100: =IFERROR(VLOOKUP(AC89,'تقرير مصروفات إجمالية'!$B$3:$O$119,12,FALSE),0) -> 100000 | AD100: =IFERROR(VLOOKUP(AD89,'تقرير مصروفات إجمالية'!$B$3:$O$119,12,FALSE),0) -> 100000 | AE100: =IFERROR(VLOOKUP(AE89,'تقرير مصروفات إجمالية'!$B$3:$O$119,12,FALSE),0) -> 100000 | AF100: =IFERROR(VLOOKUP(AF89,'تقرير مصروفات إجمالية'!$B$3:$O$119,12,FALSE),0) -> 100000 | AG100: =IFERROR(VLOOKUP(AG89,'تقرير مصروفات إجمالية'!$B$3:$O$119,12,FALSE),0) -> 100000 | AH100: =IFERROR(VLOOKUP(AH89,'تقرير مصروفات إجمالية'!$B$3:$O$119,12,FALSE),0) -> 100000 | AI100: =IFERROR(VLOOKUP(AI89,'تقرير مصروفات إجمالية'!$B$3:$O$119,12,FALSE),0) -> 100000 | ... EL100: =IFERROR(VLOOKUP(EL89,'تقرير مصروفات إجمالية'!$B$3:$O$119,12,FALSE),0) -> 0
AA101: December | AB101: =IFERROR(VLOOKUP(AB89,'تقرير مصروفات إجمالية'!$B$3:$N$115,13,FALSE),0) -> 100000 | AC101: =IFERROR(VLOOKUP(AC89,'تقرير مصروفات إجمالية'!$B$3:$N$115,13,FALSE),0) -> 100000 | AD101: =IFERROR(VLOOKUP(AD89,'تقرير مصروفات إجمالية'!$B$3:$N$115,13,FALSE),0) -> 100000 | AE101: =IFERROR(VLOOKUP(AE89,'تقرير مصروفات إجمالية'!$B$3:$N$115,13,FALSE),0) -> 100000 | AF101: =IFERROR(VLOOKUP(AF89,'تقرير مصروفات إجمالية'!$B$3:$N$115,13,FALSE),0) -> 100000 | AG101: =IFERROR(VLOOKUP(AG89,'تقرير مصروفات إجمالية'!$B$3:$N$115,13,FALSE),0) -> 100000 | AH101: =IFERROR(VLOOKUP(AH89,'تقرير مصروفات إجمالية'!$B$3:$N$115,13,FALSE),0) -> 100000 | AI101: =IFERROR(VLOOKUP(AI89,'تقرير مصروفات إجمالية'!$B$3:$N$115,13,FALSE),0) -> 100000 | ... EL101: =IFERROR(VLOOKUP(EL89,'تقرير مصروفات إجمالية'!$B$3:$N$115,13,FALSE),0) -> 0
AA102: الإجمالي | AB102: =SUM(AB90:AB101) -> 8208395.2 | AC102: =SUM(AC90:AC101) -> 21697825 | AD102: =SUM(AD90:AD101) -> 941711 | AE102: =SUM(AE90:AE101) -> 711870 | AF102: =SUM(AF90:AF101) -> 712798.5 | AG102: =SUM(AG90:AG101) -> 3250000 | AH102: =SUM(AH90:AH101) -> 950000 | AI102: =SUM(AI90:AI101) -> 2868160 | ... EL102: =SUM(EL90:EL101) -> 234000
H173: 0

Sheet HQ
C2: INCOME STATEMTN
G3: Income Statement For HQ
D6: Jan | E6: February | F6: March | G6: April | H6: May | I6: June | J6: July | K6: August | L6: September | M6: October | N6: November | O6: December | P6: Total
C7: INCOME DETAILS
C8: المبيعات | D8: =D9+D10+D11 -> 0 | E8: =E9+E10+E11 -> 0 | F8: =F9+F10+F11 -> 0 | G8: =G9+G10+G11 -> 0 | H8: =H9+H10+H11 -> 0 | I8: =I9+I10+I11 -> 0 | J8: =J9+J10+J11 -> 0 | K8: =K9+K10+K11 -> 0 | ... O8: =O9+O10+O11 -> 0 | P8: =SUM(D8:O8) -> 0
C9: نقدى | P9: =SUM(D9:O9) -> 0
C10: دليفرى | P10: =SUM(D10:O10) -> 0
C11: اجل | P11: =SUM(D11:O11) -> 0
C12: تكلفة البضاعة المباعة | P12: =SUM(D12:O12) -> 0
C13: مجمل الربح | D13: =D8-D12 -> 0 | E13: =E8-E12 -> 0 | F13: =F8-F12 -> 0 | G13: =G8-G12 -> 0 | H13: =H8-H12 -> 0 | I13: =I8-I12 -> 0 | J13: =J8-J12 -> 0 | K13: =K8-K12 -> 0 | ... O13: =O8-O12 -> 0 | P13: =SUM(D13:O13) -> 0
C14: خصم نقدى | D14: 260331.75 | E14: 395534.66 | F14: 456251.66 | G14: 303920.72 | P14: =SUM(D14:O14) -> 1416038.8
C15: ارباح صرف اصناف بيع اصول | P15: =SUM(D15:O15) -> 0
C16: فائض جرد | P16: =SUM(D16:O16) -> 0
C17: ايرادات اخرى | D17: 447413.49 | E17: 684132.79 | F17: 360780.84 | G17: 1502257.9 | P17: =SUM(D17:O17) -> 2994585
C18: إجمالي الايرادات اخرى | D18: =SUM(D14:D17) -> 707745.24 | E18: =SUM(E14:E17) -> 1079667.5 | F18: =SUM(F14:F17) -> 817032.5 | G18: =SUM(G14:G17) -> 1806178.7 | H18: =SUM(H14:H17) -> 0 | I18: =SUM(I14:I17) -> 0 | J18: =SUM(J14:J17) -> 0 | K18: =SUM(K14:K17) -> 0 | ... O18: =SUM(O14:O17) -> 0 | P18: =SUM(D18:O18) -> 4410623.8
C19: مجمل الربح | D19: =D13+D18 -> 707745.24 | E19: =E13+E18 -> 1079667.5 | F19: =F13+F18 -> 817032.5 | G19: =G13+G18 -> 1806178.7 | H19: =H13+H18 -> 0 | I19: =I13+I18 -> 0 | J19: =J13+J18 -> 0 | K19: =K13+K18 -> 0 | ... P19: =P13+P18 -> 4410623.8 | Q19: =P19-P14 -> 2994585
C21: EXPENSE DETAILS
C22: مرتبات الادارة | D22: =IFERROR(VLOOKUP(C22,'تقرير المصروفات حسب الشهر'!$C$10:$AD$119,2,FALSE),0) -> 1554391.1 | E22: =IFERROR(VLOOKUP(C22,'تقرير المصروفات حسب الشهر'!$C$136:$AD$254,2,FALSE),0) -> 1494705.5 | F22: =_xlfn.XLOOKUP(C22,'تقرير المصروفات حسب الشهر'!C262:C378,'تقرير المصروفات حسب الشهر'!D262:D378,0,0) -> 1468661.1 | G22: =IFERROR(VLOOKUP(C22,'تقرير المصروفات حسب الشهر'!$C$391:$AD$510,2,FALSE),0) -> 1600742 | H22: =IFERROR(VLOOKUP(C22,'تقرير المصروفات حسب الشهر'!$C$519:$AD$627,2,FALSE),0) -> 1389895.6 | I22: =IFERROR(VLOOKUP(C22,'تقرير المصروفات حسب الشهر'!$C$644:$AD$753,2,FALSE),0) -> 100000 | J22: =IFERROR(VLOOKUP(C22,'تقرير المصروفات حسب الشهر'!$C$770:$AD$879,2,FALSE),0) -> 100000 | K22: =IFERROR(VLOOKUP(C22,'تقرير المصروفات حسب الشهر'!$C$896:$D$1006,2,FALSE),0) -> 100000 | L22: =IFERROR(VLOOKUP(C22,'تقرير المصروفات حسب الشهر'!$C$1023:$AD$1133,2,FALSE),0) -> 100000 | M22: =IFERROR(VLOOKUP(C22,'تقرير المصروفات حسب الشهر'!$C$1150:$AD$1261,2,FALSE),0) -> 100000 | N22: =IFERROR(VLOOKUP(C22,'تقرير المصروفات حسب الشهر'!$C$1277:$AD$1388,2,FALSE),0) -> 100000 | O22: =IFERROR(VLOOKUP(C22,'تقرير المصروفات حسب الشهر'!$C$1404:$AI$1519,2,FALSE),0) -> 100000 | P22: =SUM(D22:O22) -> 8208395.2
C23: مرتبات الفروع | D23: =IFERROR(VLOOKUP(C23,'تقرير المصروفات حسب الشهر'!$C$10:$AD$119,2,FALSE),0) -> 0 | E23: =IFERROR(VLOOKUP(C23,'تقرير المصروفات حسب الشهر'!$C$136:$AD$254,2,FALSE),0) -> 0 | F23: =_xlfn.XLOOKUP(C23,'تقرير المصروفات حسب الشهر'!C263:C379,'تقرير المصروفات حسب الشهر'!D263:D379,0,0) -> 0 | G23: =IFERROR(VLOOKUP(C23,'تقرير المصروفات حسب الشهر'!$C$391:$AD$510,2,FALSE),0) -> 0 | H23: =IFERROR(VLOOKUP(C23,'تقرير المصروفات حسب الشهر'!$C$519:$AD$627,2,FALSE),0) -> 30907.7 | I23: =IFERROR(VLOOKUP(C23,'تقرير المصروفات حسب الشهر'!$C$644:$AD$753,2,FALSE),0) -> 100000 | J23: =IFERROR(VLOOKUP(C23,'تقرير المصروفات حسب الشهر'!$C$770:$AD$879,2,FALSE),0) -> 100000 | K23: =IFERROR(VLOOKUP(C23,'تقرير المصروفات حسب الشهر'!$C$896:$D$1006,2,FALSE),0) -> 100000 | L23: =IFERROR(VLOOKUP(C23,'تقرير المصروفات حسب الشهر'!$C$1023:$AD$1133,2,FALSE),0) -> 100000 | M23: =IFERROR(VLOOKUP(C23,'تقرير المصروفات حسب الشهر'!$C$1150:$AD$1261,2,FALSE),0) -> 100000 | N23: =IFERROR(VLOOKUP(C23,'تقرير المصروفات حسب الشهر'!$C$1277:$AD$1388,2,FALSE),0) -> 100000 | O23: =IFERROR(VLOOKUP(C23,'تقرير المصروفات حسب الشهر'!$C$1404:$AI$1519,2,FALSE),0) -> 100000 | P23: =SUM(D23:O23) -> 730907.7
C24: الكهرباء | D24: =IFERROR(VLOOKUP(C24,'تقرير المصروفات حسب الشهر'!$C$10:$AD$119,2,FALSE),0) -> 10837 | E24: =IFERROR(VLOOKUP(C24,'تقرير المصروفات حسب الشهر'!$C$136:$AD$254,2,FALSE),0) -> 5299 | F24: =_xlfn.XLOOKUP(C24,'تقرير المصروفات حسب الشهر'!C264:C380,'تقرير المصروفات حسب الشهر'!D264:D380,0,0) -> 5446 | G24: =IFERROR(VLOOKUP(C24,'تقرير المصروفات حسب الشهر'!$C$391:$AD$510,2,FALSE),0) -> 8611 | H24: =IFERROR(VLOOKUP(C24,'تقرير المصروفات حسب الشهر'!$C$519:$AD$627,2,FALSE),0) -> 11826 | I24: =IFERROR(VLOOKUP(C24,'تقرير المصروفات حسب الشهر'!$C$644:$AD$753,2,FALSE),0) -> 100000 | J24: =IFERROR(VLOOKUP(C24,'تقرير المصروفات حسب الشهر'!$C$770:$AD$879,2,FALSE),0) -> 100000 | K24: =IFERROR(VLOOKUP(C24,'تقرير المصروفات حسب الشهر'!$C$896:$D$1006,2,FALSE),0) -> 100000 | L24: =IFERROR(VLOOKUP(C24,'تقرير المصروفات حسب الشهر'!$C$1023:$AD$1133,2,FALSE),0) -> 100000 | M24: =IFERROR(VLOOKUP(C24,'تقرير المصروفات حسب الشهر'!$C$1150:$AD$1261,2,FALSE),0) -> 100000 | N24: =IFERROR(VLOOKUP(C24,'تقرير المصروفات حسب الشهر'!$C$1277:$AD$1388,2,FALSE),0) -> 100000 | O24: =IFERROR(VLOOKUP(C24,'تقرير المصروفات حسب الشهر'!$C$1404:$AI$1519,2,FALSE),0) -> 100000 | P24: =SUM(D24:O24) -> 742019
C25: المياه | D25: =IFERROR(VLOOKUP(C25,'تقرير المصروفات حسب الشهر'!$C$10:$AD$119,2,FALSE),0) -> 0 | E25: =IFERROR(VLOOKUP(C25,'تقرير المصروفات حسب الشهر'!$C$136:$AD$254,2,FALSE),0) -> 0 | F25: =_xlfn.XLOOKUP(C25,'تقرير المصروفات حسب الشهر'!C265:C381,'تقرير المصروفات حسب الشهر'!D265:D381,0,0) -> 0 | G25: =IFERROR(VLOOKUP(C25,'تقرير المصروفات حسب الشهر'!$C$391:$AD$510,2,FALSE),0) -> 585 | H25: =IFERROR(VLOOKUP(C25,'تقرير المصروفات حسب الشهر'!$C$519:$AD$627,2,FALSE),0) -> 0 | I25: =IFERROR(VLOOKUP(C25,'تقرير المصروفات حسب الشهر'!$C$644:$AD$753,2,FALSE),0) -> 100000 | J25: =IFERROR(VLOOKUP(C25,'تقرير المصروفات حسب الشهر'!$C$770:$AD$879,2,FALSE),0) -> 100000 | K25: =IFERROR(VLOOKUP(C25,'تقرير المصروفات حسب الشهر'!$C$896:$D$1006,2,FALSE),0) -> 100000 | L25: =IFERROR(VLOOKUP(C25,'تقرير المصروفات حسب الشهر'!$C$1023:$AD$1133,2,FALSE),0) -> 100000 | M25: =IFERROR(VLOOKUP(C25,'تقرير المصروفات حسب الشهر'!$C$1150:$AD$1261,2,FALSE),0) -> 100000 | N25: =IFERROR(VLOOKUP(C25,'تقرير المصروفات حسب الشهر'!$C$1277:$AD$1388,2,FALSE),0) -> 100000 | O25: =IFERROR(VLOOKUP(C25,'تقرير المصروفات حسب الشهر'!$C$1404:$AI$1519,2,FALSE),0) -> 100000 | P25: =SUM(D25:O25) -> 700585
C26: التليفون الارضي | D26: =IFERROR(VLOOKUP(C26,'تقرير المصروفات حسب الشهر'!$C$10:$AD$119,2,FALSE),0) -> 0 | E26: =IFERROR(VLOOKUP(C26,'تقرير المصروفات حسب الشهر'!$C$136:$AD$254,2,FALSE),0) -> 2400 | F26: =_xlfn.XLOOKUP(C26,'تقرير المصروفات حسب الشهر'!C266:C382,'تقرير المصروفات حسب الشهر'!D266:D382,0,0) -> 274.63 | G26: =IFERROR(VLOOKUP(C26,'تقرير المصروفات حسب الشهر'!$C$391:$AD$510,2,FALSE),0) -> 0 | H26: =IFERROR(VLOOKUP(C26,'تقرير المصروفات حسب الشهر'!$C$519:$AD$627,2,FALSE),0) -> 0 | I26: =IFERROR(VLOOKUP(C26,'تقرير المصروفات حسب الشهر'!$C$644:$AD$753,2,FALSE),0) -> 100000 | J26: =IFERROR(VLOOKUP(C26,'تقرير المصروفات حسب الشهر'!$C$770:$AD$879,2,FALSE),0) -> 100000 | K26: =IFERROR(VLOOKUP(C26,'تقرير المصروفات حسب الشهر'!$C$896:$D$1006,2,FALSE),0) -> 100000 | L26: =IFERROR(VLOOKUP(C26,'تقرير المصروفات حسب الشهر'!$C$1023:$AD$1133,2,FALSE),0) -> 100000 | M26: =IFERROR(VLOOKUP(C26,'تقرير المصروفات حسب الشهر'!$C$1150:$AD$1261,2,FALSE),0) -> 100000 | N26: =IFERROR(VLOOKUP(C26,'تقرير المصروفات حسب الشهر'!$C$1277:$AD$1388,2,FALSE),0) -> 100000 | O26: =IFERROR(VLOOKUP(C26,'تقرير المصروفات حسب الشهر'!$C$1404:$AI$1519,2,FALSE),0) -> 100000 | P26: =SUM(D26:O26) -> 702674.63
C27: الايجار - الصيدلية | D27: =IFERROR(VLOOKUP(C27,'تقرير المصروفات حسب الشهر'!$C$10:$AD$119,2,FALSE),0) -> 0 | E27: =IFERROR(VLOOKUP(C27,'تقرير المصروفات حسب الشهر'!$C$136:$AD$254,2,FALSE),0) -> 0 | F27: =_xlfn.XLOOKUP(C27,'تقرير المصروفات حسب الشهر'!C267:C383,'تقرير المصروفات حسب الشهر'!D267:D383,0,0) -> 0 | G27: =IFERROR(VLOOKUP(C27,'تقرير المصروفات حسب الشهر'!$C$391:$AD$510,2,FALSE),0) -> 0 | H27: =IFERROR(VLOOKUP(C27,'تقرير المصروفات حسب الشهر'!$C$519:$AD$627,2,FALSE),0) -> 0 | I27: =IFERROR(VLOOKUP(C27,'تقرير المصروفات حسب الشهر'!$C$644:$AD$753,2,FALSE),0) -> 100000 | J27: =IFERROR(VLOOKUP(C27,'تقرير المصروفات حسب الشهر'!$C$770:$AD$879,2,FALSE),0) -> 100000 | K27: =IFERROR(VLOOKUP(C27,'تقرير المصروفات حسب الشهر'!$C$896:$D$1006,2,FALSE),0) -> 100000 | L27: =IFERROR(VLOOKUP(C27,'تقرير المصروفات حسب الشهر'!$C$1023:$AD$1133,2,FALSE),0) -> 100000 | M27: =IFERROR(VLOOKUP(C27,'تقرير المصروفات حسب الشهر'!$C$1150:$AD$1261,2,FALSE),0) -> 100000 | N27: =IFERROR(VLOOKUP(C27,'تقرير المصروفات حسب الشهر'!$C$1277:$AD$1388,2,FALSE),0) -> 100000 | O27: =IFERROR(VLOOKUP(C27,'تقرير المصروفات حسب الشهر'!$C$1404:$AI$1519,2,FALSE),0) -> 100000 | P27: =SUM(D27:O27) -> 700000
C28: الايجار - الادارة | D28: =IFERROR(VLOOKUP(C28,'تقرير المصروفات حسب الشهر'!$C$10:$AD$119,2,FALSE),0) -> 50000 | E28: =IFERROR(VLOOKUP(C28,'تقرير المصروفات حسب الشهر'!$C$136:$AD$254,2,FALSE),0) -> 50000 | F28: =_xlfn.XLOOKUP(C28,'تقرير المصروفات حسب الشهر'!C268:C384,'تقرير المصروفات حسب الشهر'!D268:D384,0,0) -> 50000 | G28: =IFERROR(VLOOKUP(C28,'تقرير المصروفات حسب الشهر'!$C$391:$AD$510,2,FALSE),0) -> 50000 | H28: =IFERROR(VLOOKUP(C28,'تقرير المصروفات حسب الشهر'!$C$519:$AD$627,2,FALSE),0) -> 50000 | I28: =IFERROR(VLOOKUP(C28,'تقرير المصروفات حسب الشهر'!$C$644:$AD$753,2,FALSE),0) -> 100000 | J28: =IFERROR(VLOOKUP(C28,'تقرير المصروفات حسب الشهر'!$C$770:$AD$879,2,FALSE),0) -> 100000 | K28: =IFERROR(VLOOKUP(C28,'تقرير المصروفات حسب الشهر'!$C$896:$D$1006,2,FALSE),0) -> 100000 | L28: =IFERROR(VLOOKUP(C28,'تقرير المصروفات حسب الشهر'!$C$1023:$AD$1133,2,FALSE),0) -> 100000 | M28: =IFERROR(VLOOKUP(C28,'تقرير المصروفات حسب الشهر'!$C$1150:$AD$1261,2,FALSE),0) -> 100000 | N28: =IFERROR(VLOOKUP(C28,'تقرير المصروفات حسب الشهر'!$C$1277:$AD$1388,2,FALSE),0) -> 100000 | O28: =IFERROR(VLOOKUP(C28,'تقرير المصروفات حسب الشهر'!$C$1404:$AI$1519,2,FALSE),0) -> 100000 | P28: =SUM(D28:O28) -> 950000
C29: ايجارات متنوعه | D29: =IFERROR(VLOOKUP(C29,'تقرير المصروفات حسب الشهر'!$C$10:$AD$119,2,FALSE),0) -> 43330 | E29: =IFERROR(VLOOKUP(C29,'تقرير المصروفات حسب الشهر'!$C$136:$AD$254,2,FALSE),0) -> 64330 | F29: =_xlfn.XLOOKUP(C29,'تقرير المصروفات حسب الشهر'!C269:C385,'تقرير المصروفات حسب الشهر'!D269:D385,0,0) -> 50730 | G29: =IFERROR(VLOOKUP(C29,'تقرير المصروفات حسب الشهر'!$C$391:$AD$510,2,FALSE),0) -> 48130 | H29: =IFERROR(VLOOKUP(C29,'تقرير المصروفات حسب الشهر'!$C$519:$AD$627,2,FALSE),0) -> 48130 | I29: =IFERROR(VLOOKUP(C29,'تقرير المصروفات حسب الشهر'!$C$644:$AD$753,2,FALSE),0) -> 100000 | J29: =IFERROR(VLOOKUP(C29,'تقرير المصروفات حسب الشهر'!$C$770:$AD$879,2,FALSE),0) -> 100000 | K29: =IFERROR(VLOOKUP(C29,'تقرير المصروفات حسب الشهر'!$C$896:$D$1006,2,FALSE),0) -> 100000 | L29: =IFERROR(VLOOKUP(C29,'تقرير المصروفات حسب الشهر'!$C$1023:$AD$1133,2,FALSE),0) -> 100000 | M29: =IFERROR(VLOOKUP(C29,'تقرير المصروفات حسب الشهر'!$C$1150:$AD$1261,2,FALSE),0) -> 100000 | N29: =IFERROR(VLOOKUP(C29,'تقرير المصروفات حسب الشهر'!$C$1277:$AD$1388,2,FALSE),0) -> 100000 | O29: =IFERROR(VLOOKUP(C29,'تقرير المصروفات حسب الشهر'!$C$1404:$AI$1519,2,FALSE),0) -> 100000 | P29: =SUM(D29:O29) -> 954650
C30: ادوات مكتبية | D30: =IFERROR(VLOOKUP(C30,'تقرير المصروفات حسب الشهر'!$C$10:$AD$119,2,FALSE),0) -> 8820 | E30: =IFERROR(VLOOKUP(C30,'تقرير المصروفات حسب الشهر'!$C$136:$AD$254,2,FALSE),0) -> 6850 | F30: =_xlfn.XLOOKUP(C30,'تقرير المصروفات حسب الشهر'!C270:C386,'تقرير المصروفات حسب الشهر'!D270:D386,0,0) -> 4585 | G30: =IFERROR(VLOOKUP(C30,'تقرير المصروفات حسب الشهر'!$C$391:$AD$510,2,FALSE),0) -> 11185 | H30: =IFERROR(VLOOKUP(C30,'تقرير المصروفات حسب الشهر'!$C$519:$AD$627,2,FALSE),0) -> 3009 | I30: =IFERROR(VLOOKUP(C30,'تقرير المصروفات حسب الشهر'!$C$644:$AD$753,2,FALSE),0) -> 100000 | J30: =IFERROR(VLOOKUP(C30,'تقرير المصروفات حسب الشهر'!$C$770:$AD$879,2,FALSE),0) -> 100000 | K30: =IFERROR(VLOOKUP(C30,'تقرير المصروفات حسب الشهر'!$C$896:$D$1006,2,FALSE),0) -> 100000 | L30: =IFERROR(VLOOKUP(C30,'تقرير المصروفات حسب الشهر'!$C$1023:$AD$1133,2,FALSE),0) -> 100000 | M30: =IFERROR(VLOOKUP(C30,'تقرير المصروفات حسب الشهر'!$C$1150:$AD$1261,2,FALSE),0) -> 100000 | N30: =IFERROR(VLOOKUP(C30,'تقرير المصروفات حسب الشهر'!$C$1277:$AD$1388,2,FALSE),0) -> 100000 | O30: =IFERROR(VLOOKUP(C30,'تقرير المصروفات حسب الشهر'!$C$1404:$AI$1519,2,FALSE),0) -> 100000 | P30: =SUM(D30:O30) -> 734449
C31: فواتير الموبايل | D31: =IFERROR(VLOOKUP(C31,'تقرير المصروفات حسب الشهر'!$C$10:$AD$119,2,FALSE),0) -> 13985.85 | E31: =IFERROR(VLOOKUP(C31,'تقرير المصروفات حسب الشهر'!$C$136:$AD$254,2,FALSE),0) -> 15312 | F31: =_xlfn.XLOOKUP(C31,'تقرير المصروفات حسب الشهر'!C271:C387,'تقرير المصروفات حسب الشهر'!D271:D387,0,0) -> 13024.09 | G31: =IFERROR(VLOOKUP(C31,'تقرير المصروفات حسب الشهر'!$C$391:$AD$510,2,FALSE),0) -> 13279.72 | H31: =IFERROR(VLOOKUP(C31,'تقرير المصروفات حسب الشهر'!$C$519:$AD$627,2,FALSE),0) -> 13946.98 | I31: =IFERROR(VLOOKUP(C31,'تقرير المصروفات حسب الشهر'!$C$644:$AD$753,2,FALSE),0) -> 100000 | J31: =IFERROR(VLOOKUP(C31,'تقرير المصروفات حسب الشهر'!$C$770:$AD$879,2,FALSE),0) -> 100000 | K31: =IFERROR(VLOOKUP(C31,'تقرير المصروفات حسب الشهر'!$C$896:$D$1006,2,FALSE),0) -> 100000 | L31: =IFERROR(VLOOKUP(C31,'تقرير المصروفات حسب الشهر'!$C$1023:$AD$1133,2,FALSE),0) -> 100000 | M31: =IFERROR(VLOOKUP(C31,'تقرير المصروفات حسب الشهر'!$C$1150:$AD$1261,2,FALSE),0) -> 100000 | N31: =IFERROR(VLOOKUP(C31,'تقرير المصروفات حسب الشهر'!$C$1277:$AD$1388,2,FALSE),0) -> 100000 | O31: =IFERROR(VLOOKUP(C31,'تقرير المصروفات حسب الشهر'!$C$1404:$AI$1519,2,FALSE),0) -> 100000 | P31: =SUM(D31:O31) -> 769548.64
C32: مكافات مبيعات الادوية | D32: =IFERROR(VLOOKUP(C32,'تقرير المصروفات حسب الشهر'!$C$10:$AD$119,2,FALSE),0) -> 0 | E32: =IFERROR(VLOOKUP(C32,'تقرير المصروفات حسب الشهر'!$C$136:$AD$254,2,FALSE),0) -> 0 | F32: =_xlfn.XLOOKUP(C32,'تقرير المصروفات حسب الشهر'!C272:C388,'تقرير المصروفات حسب الشهر'!D272:D388,0,0) -> 0 | G32: =IFERROR(VLOOKUP(C32,'تقرير المصروفات حسب الشهر'!$C$391:$AD$510,2,FALSE),0) -> 0 | H32: =IFERROR(VLOOKUP(C32,'تقرير المصروفات حسب الشهر'!$C$519:$AD$627,2,FALSE),0) -> 0 | I32: =IFERROR(VLOOKUP(C32,'تقرير المصروفات حسب الشهر'!$C$644:$AD$753,2,FALSE),0) -> 100000 | J32: =IFERROR(VLOOKUP(C32,'تقرير المصروفات حسب الشهر'!$C$770:$AD$879,2,FALSE),0) -> 100000 | K32: =IFERROR(VLOOKUP(C32,'تقرير المصروفات حسب الشهر'!$C$896:$D$1006,2,FALSE),0) -> 100000 | L32: =IFERROR(VLOOKUP(C32,'تقرير المصروفات حسب الشهر'!$C$1023:$AD$1133,2,FALSE),0) -> 100000 | M32: =IFERROR(VLOOKUP(C32,'تقرير المصروفات حسب الشهر'!$C$1150:$AD$1261,2,FALSE),0) -> 100000 | N32: =IFERROR(VLOOKUP(C32,'تقرير المصروفات حسب الشهر'!$C$1277:$AD$1388,2,FALSE),0) -> 100000 | O32: =IFERROR(VLOOKUP(C32,'تقرير المصروفات حسب الشهر'!$C$1404:$AI$1519,2,FALSE),0) -> 100000 | P32: =SUM(D32:O32) -> 700000
C33: مكافات مبيعات التجميل | D33: =IFERROR(VLOOKUP(C33,'تقرير المصروفات حسب الشهر'!$C$10:$AD$119,2,FALSE),0) -> 22129 | E33: =IFERROR(VLOOKUP(C33,'تقرير المصروفات حسب الشهر'!$C$136:$AD$254,2,FALSE),0) -> 4615 | F33: =_xlfn.XLOOKUP(C33,'تقرير المصروفات حسب الشهر'!C273:C389,'تقرير المصروفات حسب الشهر'!D273:D389,0,0) -> 17210 | G33: =IFERROR(VLOOKUP(C33,'تقرير المصروفات حسب الشهر'!$C$391:$AD$510,2,FALSE),0) -> 2692 | H33: =IFERROR(VLOOKUP(C33,'تقرير المصروفات حسب الشهر'!$C$519:$AD$627,2,FALSE),0) -> 21980 | I33: =IFERROR(VLOOKUP(C33,'تقرير المصروفات حسب الشهر'!$C$644:$AD$753,2,FALSE),0) -> 100000 | J33: =IFERROR(VLOOKUP(C33,'تقرير المصروفات حسب الشهر'!$C$770:$AD$879,2,FALSE),0) -> 100000 | K33: =IFERROR(VLOOKUP(C33,'تقرير المصروفات حسب الشهر'!$C$896:$D$1006,2,FALSE),0) -> 100000 | L33: =IFERROR(VLOOKUP(C33,'تقرير المصروفات حسب الشهر'!$C$1023:$AD$1133,2,FALSE),0) -> 100000 | M33: =IFERROR(VLOOKUP(C33,'تقرير المصروفات حسب الشهر'!$C$1150:$AD$1261,2,FALSE),0) -> 100000 | N33: =IFERROR(VLOOKUP(C33,'تقرير المصروفات حسب الشهر'!$C$1277:$AD$1388,2,FALSE),0) -> 100000 | O33: =IFERROR(VLOOKUP(C33,'تقرير المصروفات حسب الشهر'!$C$1404:$AI$1519,2,FALSE),0) -> 100000 | P33: =SUM(D33:O33) -> 768626
... C134: عروض مبيعات ابليكشن | D134: =IFERROR(VLOOKUP(C134,'تقرير المصروفات حسب الشهر'!$C$10:$AD$119,2,FALSE),0) -> 0 | E134: =IFERROR(VLOOKUP(C134,'تقرير المصروفات حسب الشهر'!$C$136:$AD$254,2,FALSE),0) -> 0 | F134: =_xlfn.XLOOKUP(C134,'تقرير المصروفات حسب الشهر'!C374:C490,'تقرير المصروفات حسب الشهر'!D374:D490,0,0) -> 0 | G134: =IFERROR(VLOOKUP(C134,'تقرير المصروفات حسب الشهر'!$C$391:$AD$510,2,FALSE),0) -> 0 | H134: =IFERROR(VLOOKUP(C134,'تقرير المصروفات حسب الشهر'!$C$519:$AD$627,2,FALSE),0) -> 0 | I134: =IFERROR(VLOOKUP(C134,'تقرير المصروفات حسب الشهر'!$C$644:$AD$753,2,FALSE),0) -> 0 | J134: =IFERROR(VLOOKUP(C134,'تقرير المصروفات حسب الشهر'!$C$770:$AD$879,2,FALSE),0) -> 0 | K134: =IFERROR(VLOOKUP(C134,'تقرير المصروفات حسب الشهر'!$C$896:$D$1006,2,FALSE),0) -> 0 | L134: =IFERROR(VLOOKUP(C134,'تقرير المصروفات حسب الشهر'!$C$1023:$AD$1133,2,FALSE),0) -> 0 | M134: =IFERROR(VLOOKUP(C134,'تقرير المصروفات حسب الشهر'!$C$1150:$AD$1261,2,FALSE),0) -> 0 | N134: =IFERROR(VLOOKUP(C134,'تقرير المصروفات حسب الشهر'!$C$1277:$AD$1388,2,FALSE),0) -> 0 | O134: =IFERROR(VLOOKUP(C134,'تقرير المصروفات حسب الشهر'!$C$1404:$AI$1519,2,FALSE),0) -> 100000 | P134: =SUM(D134:O134) -> 100000
C135: عمولات ادارية | D135: =IFERROR(VLOOKUP(C135,'تقرير المصروفات حسب الشهر'!$C$10:$AD$125,2,FALSE),0) -> 92000 | E135: =IFERROR(VLOOKUP(C135,'تقرير المصروفات حسب الشهر'!$C$136:$AD$254,2,FALSE),0) -> 0 | F135: =_xlfn.XLOOKUP(C135,'تقرير المصروفات حسب الشهر'!C375:C491,'تقرير المصروفات حسب الشهر'!D375:D491,0,0) -> 142000 | G135: =IFERROR(VLOOKUP(C135,'تقرير المصروفات حسب الشهر'!$C$391:$AD$510,2,FALSE),0) -> 92000 | H135: =IFERROR(VLOOKUP(C135,'تقرير المصروفات حسب الشهر'!$C$519:$AD$627,2,FALSE),0) -> 0 | I135: =IFERROR(VLOOKUP(C135,'تقرير المصروفات حسب الشهر'!$C$644:$AD$753,2,FALSE),0) -> 0 | J135: =IFERROR(VLOOKUP(C135,'تقرير المصروفات حسب الشهر'!$C$770:$AD$879,2,FALSE),0) -> 0 | K135: =IFERROR(VLOOKUP(C135,'تقرير المصروفات حسب الشهر'!$C$896:$D$1006,2,FALSE),0) -> 0 | L135: =IFERROR(VLOOKUP(C135,'تقرير المصروفات حسب الشهر'!$C$1023:$AD$1133,2,FALSE),0) -> 0 | M135: =IFERROR(VLOOKUP(C135,'تقرير المصروفات حسب الشهر'!$C$1150:$AD$1261,2,FALSE),0) -> 0 | N135: =IFERROR(VLOOKUP(C135,'تقرير المصروفات حسب الشهر'!$C$1277:$AD$1388,2,FALSE),0) -> 0 | O135: =IFERROR(VLOOKUP(C135,'تقرير المصروفات حسب الشهر'!$C$1404:$AI$1519,2,FALSE),0) -> 0 | P135: =SUM(D135:O135) -> 326000
D136: =IFERROR(VLOOKUP(C136,'تقرير المصروفات حسب الشهر'!$C$10:$AD$119,2,FALSE),0) -> 0 | E136: =IFERROR(VLOOKUP(C136,'تقرير المصروفات حسب الشهر'!$C$136:$AD$254,2,FALSE),0) -> 0 | F136: =_xlfn.XLOOKUP(C136,'تقرير المصروفات حسب الشهر'!C376:C492,'تقرير المصروفات حسب الشهر'!D376:D492,0,0) -> 0 | G136: =IFERROR(VLOOKUP(C136,'تقرير المصروفات حسب الشهر'!$C$391:$AD$510,2,FALSE),0) -> 0 | H136: =IFERROR(VLOOKUP(C136,'تقرير المصروفات حسب الشهر'!$C$519:$AD$627,2,FALSE),0) -> 0 | I136: =IFERROR(VLOOKUP(C136,'تقرير المصروفات حسب الشهر'!$C$644:$AD$753,2,FALSE),0) -> 0 | J136: =IFERROR(VLOOKUP(C136,'تقرير المصروفات حسب الشهر'!$C$770:$AD$879,2,FALSE),0) -> 0 | K136: =IFERROR(VLOOKUP(C136,'تقرير المصروفات حسب الشهر'!$C$896:$D$1006,2,FALSE),0) -> 0 | L136: =IFERROR(VLOOKUP(C136,'تقرير المصروفات حسب الشهر'!$C$1023:$AD$1133,2,FALSE),0) -> 0 | M136: =IFERROR(VLOOKUP(C136,'تقرير المصروفات حسب الشهر'!$C$1150:$AD$1261,2,FALSE),0) -> 0 | N136: =IFERROR(VLOOKUP(C136,'تقرير المصروفات حسب الشهر'!$C$1277:$AD$1388,2,FALSE),0) -> 0 | O136: =IFERROR(VLOOKUP(C136,'تقرير المصروفات حسب الشهر'!$C$1404:$AI$1519,2,FALSE),0) -> 0 | P136: =SUM(D136:O136) -> 0
D137: =IFERROR(VLOOKUP(C137,'تقرير المصروفات حسب الشهر'!$C$10:$AD$119,2,FALSE),0) -> 0 | E137: =IFERROR(VLOOKUP(C137,'تقرير المصروفات حسب الشهر'!$C$136:$AD$254,2,FALSE),0) -> 0 | F137: =_xlfn.XLOOKUP(C137,'تقرير المصروفات حسب الشهر'!C377:C493,'تقرير المصروفات حسب الشهر'!D377:D493,0,0) -> 0 | G137: =IFERROR(VLOOKUP(C137,'تقرير المصروفات حسب الشهر'!$C$391:$AD$510,2,FALSE),0) -> 0 | H137: =IFERROR(VLOOKUP(C137,'تقرير المصروفات حسب الشهر'!$C$519:$AD$627,2,FALSE),0) -> 0 | I137: =IFERROR(VLOOKUP(C137,'تقرير المصروفات حسب الشهر'!$C$644:$AD$753,2,FALSE),0) -> 0 | J137: =IFERROR(VLOOKUP(C137,'تقرير المصروفات حسب الشهر'!$C$770:$AD$879,2,FALSE),0) -> 0 | K137: =IFERROR(VLOOKUP(C137,'تقرير المصروفات حسب الشهر'!$C$896:$D$1006,2,FALSE),0) -> 0 | L137: =IFERROR(VLOOKUP(C137,'تقرير المصروفات حسب الشهر'!$C$1023:$AD$1133,2,FALSE),0) -> 0 | M137: =IFERROR(VLOOKUP(C137,'تقرير المصروفات حسب الشهر'!$C$1150:$AD$1261,2,FALSE),0) -> 0 | N137: =IFERROR(VLOOKUP(C137,'تقرير المصروفات حسب الشهر'!$C$1277:$AD$1388,2,FALSE),0) -> 0 | O137: =IFERROR(VLOOKUP(C137,'تقرير المصروفات حسب الشهر'!$C$1404:$AI$1519,2,FALSE),0) -> 0 | P137: =SUM(D137:O137) -> 0
D138: =IFERROR(VLOOKUP(C138,'تقرير المصروفات حسب الشهر'!$C$10:$AD$119,2,FALSE),0) -> 0 | E138: =IFERROR(VLOOKUP(C138,'تقرير المصروفات حسب الشهر'!$C$136:$AD$254,2,FALSE),0) -> 0 | F138: =_xlfn.XLOOKUP(C138,'تقرير المصروفات حسب الشهر'!C378:C494,'تقرير المصروفات حسب الشهر'!D378:D494,0,0) -> 0 | G138: =IFERROR(VLOOKUP(C138,'تقرير المصروفات حسب الشهر'!$C$391:$AD$510,2,FALSE),0) -> 0 | H138: =IFERROR(VLOOKUP(C138,'تقرير المصروفات حسب الشهر'!$C$519:$AD$627,2,FALSE),0) -> 0 | I138: =IFERROR(VLOOKUP(C138,'تقرير المصروفات حسب الشهر'!$C$644:$AD$753,2,FALSE),0) -> 0 | J138: =IFERROR(VLOOKUP(C138,'تقرير المصروفات حسب الشهر'!$C$770:$AD$879,2,FALSE),0) -> 0 | K138: =IFERROR(VLOOKUP(C138,'تقرير المصروفات حسب الشهر'!$C$896:$D$1006,2,FALSE),0) -> 0 | L138: =IFERROR(VLOOKUP(C138,'تقرير المصروفات حسب الشهر'!$C$1023:$AD$1133,2,FALSE),0) -> 0 | M138: =IFERROR(VLOOKUP(C138,'تقرير المصروفات حسب الشهر'!$C$1150:$AD$1261,2,FALSE),0) -> 0 | N138: =IFERROR(VLOOKUP(C138,'تقرير المصروفات حسب الشهر'!$C$1277:$AD$1388,2,FALSE),0) -> 0 | O138: =IFERROR(VLOOKUP(C138,'تقرير المصروفات حسب الشهر'!$C$1404:$AI$1519,2,FALSE),0) -> 0 | P138: =SUM(D138:O138) -> 0
D139: =IFERROR(VLOOKUP(C139,'تقرير المصروفات حسب الشهر'!$C$10:$AD$119,2,FALSE),0) -> 0 | E139: =IFERROR(VLOOKUP(C139,'تقرير المصروفات حسب الشهر'!$C$136:$AD$254,2,FALSE),0) -> 0 | F139: =_xlfn.XLOOKUP(C139,'تقرير المصروفات حسب الشهر'!C379:C495,'تقرير المصروفات حسب الشهر'!D379:D495,0,0) -> 0 | G139: =IFERROR(VLOOKUP(C139,'تقرير المصروفات حسب الشهر'!$C$391:$AD$510,2,FALSE),0) -> 0 | H139: =IFERROR(VLOOKUP(C139,'تقرير المصروفات حسب الشهر'!$C$519:$AD$627,2,FALSE),0) -> 0 | I139: =IFERROR(VLOOKUP(C139,'تقرير المصروفات حسب الشهر'!$C$644:$AD$753,2,FALSE),0) -> 0 | J139: =IFERROR(VLOOKUP(C139,'تقرير المصروفات حسب الشهر'!$C$770:$AD$879,2,FALSE),0) -> 0 | K139: =IFERROR(VLOOKUP(C139,'تقرير المصروفات حسب الشهر'!$C$896:$D$1006,2,FALSE),0) -> 0 | L139: =IFERROR(VLOOKUP(C139,'تقرير المصروفات حسب الشهر'!$C$1023:$AD$1133,2,FALSE),0) -> 0 | M139: =IFERROR(VLOOKUP(C139,'تقرير المصروفات حسب الشهر'!$C$1150:$AD$1261,2,FALSE),0) -> 0 | N139: =IFERROR(VLOOKUP(C139,'تقرير المصروفات حسب الشهر'!$C$1277:$AD$1388,2,FALSE),0) -> 0 | O139: =IFERROR(VLOOKUP(C139,'تقرير المصروفات حسب الشهر'!$C$1404:$AI$1519,2,FALSE),0) -> 0 | P139: =SUM(D139:O139) -> 0
C140: إجمالي المصروفات | D140: =SUM(D22:D139) -> 2880668.4 | E140: =SUM(E22:E139) -> 2812755.2 | F140: =SUM(F22:F139) -> 3008191 | G140: =SUM(G22:G139) -> 3011282.7 | H140: =SUM(H22:H139) -> 2506583.5 | I140: =SUM(I22:I139) -> 11000000 | J140: =SUM(J22:J139) -> 11000000 | K140: =SUM(K22:K139) -> 11000000 | ... O140: =SUM(O22:O139) -> 11300000 | P140: =SUM(D140:O140) -> 91719481
C142: مجمل الربح | D142: =D19 -> 707745.24 | E142: =E19 -> 1079667.5 | F142: =F19 -> 817032.5 | G142: =G19 -> 1806178.7 | H142: =H19 -> 0 | I142: =I19 -> 0 | J142: =J19 -> 0 | K142: =K19 -> 0 | ... P142: =P19 -> 4410623.8
C145: صافي الربح / الخسارة | D145: =D142-D140 -> -2172923.2 | E145: =E142-E140 -> -1733087.8 | F145: =F142-F140 -> -2191158.5 | G145: =G142-G140 -> -1205104.1 | H145: =H142-H140 -> -2506583.5 | I145: =I142-I140 -> -11000000 | J145: =J142-J140 -> -11000000 | K145: =K142-K140 -> -11000000 | ... P145: =P142-P140 -> -87308857
G149: =-1205104.06-G145 -> 0

Sheet Aguza
C2: INCOME STATEMTN
F3: Income Statement For AGOUZA
D6: Jan | E6: February | F6: March | G6: April | H6: May | I6: June | J6: July | K6: August | L6: September | M6: October | N6: November | O6: December | P6: TOTAL
C7: INCOME DETAILS
A8: العجوزة | C8: المبيعات | D8: =D9+D10+D11 -> 7433176.6 | E8: =E9+E10+E11 -> 6302491.1 | F8: =F9+F10+F11 -> 8102573.4 | G8: =G9+G10+G11 -> 8394480.6 | H8: =H9+H10+H11 -> 9610286.1 | I8: =I9+I10+I11 -> 1000000 | J8: =J9+J10+J11 -> 1000000 | K8: =K9+K10+K11 -> 1000000 | ... O8: =O9+O10+O11 -> 1000000 | P8: =SUM(D8:O8) -> 46843008
C9: نقدى | D9: =VLOOKUP($A$8,'تقرير إحصائية بحجم المبيعات'!$B$7:$L$31,2,FALSE) -> 4910885.3 | E9: =VLOOKUP($A$8,'تقرير إحصائية بحجم المبيعات'!$B$42:$G$73,2,FALSE) -> 4136232.3 | F9: =VLOOKUP($A$8,'تقرير إحصائية بحجم المبيعات'!$B$78:$E$103,2,FALSE) -> 4997934.7 | G9: =VLOOKUP($A$8,'تقرير إحصائية بحجم المبيعات'!$B$112:$G$137,2,FALSE) -> 5094880.8 | H9: =VLOOKUP($A$8,'تقرير إحصائية بحجم المبيعات'!$B$147:$G$177,2,FALSE) -> 5883566.6 | I9: =VLOOKUP($A$8,'تقرير إحصائية بحجم المبيعات'!$B$182:$G$212,2,FALSE) -> 1000000 | J9: =VLOOKUP($A$8,'تقرير إحصائية بحجم المبيعات'!$B$217:$L$243,2,FALSE) -> 1000000 | K9: =VLOOKUP($A$8,'تقرير إحصائية بحجم المبيعات'!$B$252:$L$278,2,FALSE) -> 1000000 | L9: =VLOOKUP($A$8,'تقرير إحصائية بحجم المبيعات'!$B$287:$L$313,2,FALSE) -> 1000000 | M9: =VLOOKUP($A$8,'تقرير إحصائية بحجم المبيعات'!$B$322:$L$347,2,FALSE) -> 1000000 | N9: =VLOOKUP($A$8,'تقرير إحصائية بحجم المبيعات'!$B$357:$L$383,2,FALSE) -> 1000000 | O9: =VLOOKUP($A$8,'تقرير إحصائية بحجم المبيعات'!$B$391:$L$420,2,FALSE) -> 1000000 | P9: =SUM(D9:O9) -> 32023500
C10: دليفرى | D10: =VLOOKUP($A$8,'تقرير إحصائية بحجم المبيعات'!$B$7:$L$31,3,FALSE) -> 691551.39 | E10: =VLOOKUP($A$8,'تقرير إحصائية بحجم المبيعات'!$B$42:$G$73,3,FALSE) -> 548271.11 | F10: =VLOOKUP($A$8,'تقرير إحصائية بحجم المبيعات'!$B$78:$E$103,3,FALSE) -> 833928.87 | G10: =VLOOKUP($A$8,'تقرير إحصائية بحجم المبيعات'!$B$112:$G$137,3,FALSE) -> 774333.25 | H10: =VLOOKUP($A$8,'تقرير إحصائية بحجم المبيعات'!$B$147:$G$177,3,FALSE) -> 735167.98 | I10: =VLOOKUP($A$8,'تقرير إحصائية بحجم المبيعات'!$B$182:$G$212,3,FALSE) -> 0 | J10: =VLOOKUP($A$8,'تقرير إحصائية بحجم المبيعات'!$B$217:$L$243,3,FALSE) -> 0 | K10: =VLOOKUP($A$8,'تقرير إحصائية بحجم المبيعات'!$B$252:$L$278,3,FALSE) -> 0 | L10: =VLOOKUP($A$8,'تقرير إحصائية بحجم المبيعات'!$B$287:$L$313,3,FALSE) -> 0 | M10: =VLOOKUP($A$8,'تقرير إحصائية بحجم المبيعات'!$B$322:$L$347,3,FALSE) -> 0 | N10: =VLOOKUP($A$8,'تقرير إحصائية بحجم المبيعات'!$B$357:$L$383,3,FALSE) -> 0 | O10: =VLOOKUP($A$8,'تقرير إحصائية بحجم المبيعات'!$B$391:$L$420,3,FALSE) -> 0 | P10: =SUM(D10:O10) -> 3583252.6
C11: اجل | D11: =VLOOKUP($A$8,'تقرير إحصائية بحجم المبيعات'!$B$7:$L$31,4,FALSE) -> 1830740 | E11: =VLOOKUP($A$8,'تقرير إحصائية بحجم المبيعات'!$B$42:$G$73,4,FALSE) -> 1617987.7 | F11: =VLOOKUP($A$8,'تقرير إحصائية بحجم المبيعات'!$B$78:$E$103,4,FALSE) -> 2270709.9 | G11: =VLOOKUP($A$8,'تقرير إحصائية بحجم المبيعات'!$B$112:$G$137,4,FALSE) -> 2525266.6 | H11: =VLOOKUP($A$8,'تقرير إحصائية بحجم المبيعات'!$B$147:$G$177,4,FALSE) -> 2991551.5 | I11: =VLOOKUP($A$8,'تقرير إحصائية بحجم المبيعات'!$B$182:$G$212,4,FALSE) -> 0 | J11: =VLOOKUP($A$8,'تقرير إحصائية بحجم المبيعات'!$B$217:$L$243,4,FALSE) -> 0 | K11: =VLOOKUP($A$8,'تقرير إحصائية بحجم المبيعات'!$B$252:$L$278,4,FALSE) -> 0 | L11: =VLOOKUP($A$8,'تقرير إحصائية بحجم المبيعات'!$B$287:$L$313,4,FALSE) -> 0 | M11: =VLOOKUP($A$8,'تقرير إحصائية بحجم المبيعات'!$B$322:$L$347,4,FALSE) -> 0 | N11: =VLOOKUP($A$8,'تقرير إحصائية بحجم المبيعات'!$B$357:$L$383,4,FALSE) -> 0 | O11: =VLOOKUP($A$8,'تقرير إحصائية بحجم المبيعات'!$B$391:$L$420,4,FALSE) -> 0 | P11: =SUM(D11:O11) -> 11236256
C12: تكلفة البضاعة المباعة | D12: =VLOOKUP($A$8,'تقرير إحصائية بحجم المبيعات'!$B$7:$L$31,11,FALSE) -> 5833081.1 | E12: =VLOOKUP($A$8,'تقرير إحصائية بحجم المبيعات'!$B$42:$L$73,11,FALSE) -> 4993948.6 | F12: =VLOOKUP($A$8,'تقرير إحصائية بحجم المبيعات'!$B$78:$L$103,11,FALSE) -> 6465151.2 | G12: =VLOOKUP($A$8,'تقرير إحصائية بحجم المبيعات'!$B$112:$L$137,11,FALSE) -> 6707669.3 | H12: =VLOOKUP($A$8,'تقرير إحصائية بحجم المبيعات'!$B$147:$L$177,11,FALSE) -> 7518966.6 | I12: =VLOOKUP($A$8,'تقرير إحصائية بحجم المبيعات'!$B$182:$L$212,11,FALSE) -> 0 | J12: =VLOOKUP($A$8,'تقرير إحصائية بحجم المبيعات'!$B$217:$L$243,11,FALSE) -> 0 | K12: =VLOOKUP($A$8,'تقرير إحصائية بحجم المبيعات'!$B$252:$L$278,11,FALSE) -> 0 | L12: =VLOOKUP($A$8,'تقرير إحصائية بحجم المبيعات'!$B$287:$L$313,11,FALSE) -> 0 | M12: =VLOOKUP($A$8,'تقرير إحصائية بحجم المبيعات'!$B$322:$L$347,11,FALSE) -> 0 | N12: =VLOOKUP($A$8,'تقرير إحصائية بحجم المبيعات'!$B$357:$L$383,11,FALSE) -> 0 | O12: =VLOOKUP($A$8,'تقرير إحصائية بحجم المبيعات'!$B$391:$L$420,11,FALSE) -> 0 | P12: =SUM(D12:O12) -> 31518817
C13: مجمل الربح | D13: =D8-D12 -> 1600095.5 | E13: =E8-E12 -> 1308542.5 | F13: =F8-F12 -> 1637422.2 | G13: =G8-G12 -> 1686811.3 | H13: =H8-H12 -> 2091319.5 | I13: =I8-I12 -> 1000000 | J13: =J8-J12 -> 1000000 | K13: =K8-K12 -> 1000000 | ... O13: =O8-O12 -> 1000000 | P13: =SUM(D13:O13) -> 15324191
C14: خصم نقدى | P14: =SUM(D14:O14) -> 0
C15: ارباح صرف اصناف بيع اصول | P15: =SUM(D15:O15) -> 0
C16: فائض جرد | E16: 2690.8 | F16: 0.16 | P16: =SUM(D16:O16) -> 2690.96
C17: ايرادات اخرى | E17: 2340 | P17: =SUM(D17:O17) -> 2340
C18: إجمالي الايرادات اخرى | D18: =SUM(D14:D17) -> 0 | E18: =SUM(E14:E17) -> 5030.8 | F18: =SUM(F14:F17) -> 0.16 | G18: =SUM(G14:G17) -> 0 | H18: =SUM(H14:H17) -> 0 | I18: =SUM(I14:I17) -> 0 | J18: =SUM(J14:J17) -> 0 | K18: =SUM(K14:K17) -> 0 | ... O18: =SUM(O14:O17) -> 0 | P18: =SUM(D18:O18) -> 5030.96
C19: مجمل الربح | D19: =D13+D18 -> 1600095.5 | E19: =E13+E18 -> 1313573.3 | F19: =F13+F18 -> 1637422.3 | G19: =G13+G18 -> 1686811.3 | H19: =H13+H18 -> 2091319.5 | I19: =I13+I18 -> 1000000 | J19: =J13+J18 -> 1000000 | K19: =K13+K18 -> 1000000 | ... O19: =O13+O18 -> 1000000 | P19: =SUM(D19:O19) -> 15329222
C21: EXPENSE DETAILS | D21: =D23/D8 -> 0.063338422
C22: مرتبات الادارة | D22: =IFERROR(VLOOKUP(C22,'تقرير المصروفات حسب الشهر'!$C$10:$AD$119,3,FALSE),0) -> 0 | E22: =IFERROR(VLOOKUP(C22,'تقرير المصروفات حسب الشهر'!$C$136:$AD$245,3,FALSE),0) -> 0 | F22: =VLOOKUP(C22,'تقرير المصروفات حسب الشهر'!C262:AI378,3,0) -> 0 | G22: =IFERROR(VLOOKUP(C22,'تقرير المصروفات حسب الشهر'!$C$391:$AD$510,3,FALSE),0) -> 0 | H22: =IFERROR(VLOOKUP(C22,'تقرير المصروفات حسب الشهر'!$C$519:$AD$627,3,FALSE),0) -> 0 | I22: =IFERROR(VLOOKUP(C22,'تقرير المصروفات حسب الشهر'!$C$644:$AD$753,3,FALSE),0) -> 0 | J22: =IFERROR(VLOOKUP(C22,'تقرير المصروفات حسب الشهر'!$C$770:$AD$879,3,FALSE),0) -> 0 | K22: =IFERROR(VLOOKUP(C22,'تقرير المصروفات حسب الشهر'!$C$897:$AD$1006,3,FALSE),0) -> 0 | L22: =IFERROR(VLOOKUP(C22,'تقرير المصروفات حسب الشهر'!$C$1023:$AD$1133,3,FALSE),0) -> 0 | M22: =IFERROR(VLOOKUP(C22,'تقرير المصروفات حسب الشهر'!$C$1150:$AD$1261,3,FALSE),0) -> 0 | N22: =IFERROR(VLOOKUP(C22,'تقرير المصروفات حسب الشهر'!$C$1277:$AD$1388,3,FALSE),0) -> 0 | O22: =IFERROR(VLOOKUP(C22,'تقرير المصروفات حسب الشهر'!$C$1404:$AI$1519,3,FALSE),0) -> 0 | P22: =SUM(D22:O22) -> 0
C23: مرتبات الفروع | D23: =IFERROR(VLOOKUP(C23,'تقرير المصروفات حسب الشهر'!$C$10:$AD$119,3,FALSE),0) -> 470805.68 | E23: =IFERROR(VLOOKUP(C23,'تقرير المصروفات حسب الشهر'!$C$136:$AD$245,3,FALSE),0) -> 438097.43 | F23: =VLOOKUP(C23,'تقرير المصروفات حسب الشهر'!C263:AI379,3,0) -> 437682.06 | G23: =IFERROR(VLOOKUP(C23,'تقرير المصروفات حسب الشهر'!$C$391:$AD$510,3,FALSE),0) -> 473266.56 | H23: =IFERROR(VLOOKUP(C23,'تقرير المصروفات حسب الشهر'!$C$519:$AD$627,3,FALSE),0) -> 325607.85 | I23: =IFERROR(VLOOKUP(C23,'تقرير المصروفات حسب الشهر'!$C$644:$AD$753,3,FALSE),0) -> 0 | J23: =IFERROR(VLOOKUP(C23,'تقرير المصروفات حسب الشهر'!$C$770:$AD$879,3,FALSE),0) -> 0 | K23: =IFERROR(VLOOKUP(C23,'تقرير المصروفات حسب الشهر'!$C$897:$AD$1006,3,FALSE),0) -> 0 | L23: =IFERROR(VLOOKUP(C23,'تقرير المصروفات حسب الشهر'!$C$1023:$AD$1133,3,FALSE),0) -> 0 | M23: =IFERROR(VLOOKUP(C23,'تقرير المصروفات حسب الشهر'!$C$1150:$AD$1261,3,FALSE),0) -> 0 | N23: =IFERROR(VLOOKUP(C23,'تقرير المصروفات حسب الشهر'!$C$1277:$AD$1388,3,FALSE),0) -> 0 | O23: =IFERROR(VLOOKUP(C23,'تقرير المصروفات حسب الشهر'!$C$1404:$AI$1519,3,FALSE),0) -> 0 | P23: =SUM(D23:O23) -> 2145459.6
C24: الكهرباء | D24: =IFERROR(VLOOKUP(C24,'تقرير المصروفات حسب الشهر'!$C$10:$AD$119,3,FALSE),0) -> 9191 | E24: =IFERROR(VLOOKUP(C24,'تقرير المصروفات حسب الشهر'!$C$136:$AD$245,3,FALSE),0) -> 3414 | F24: =VLOOKUP(C24,'تقرير المصروفات حسب الشهر'!C264:AI380,3,0) -> 0 | G24: =IFERROR(VLOOKUP(C24,'تقرير المصروفات حسب الشهر'!$C$391:$AD$510,3,FALSE),0) -> 7277 | H24: =IFERROR(VLOOKUP(C24,'تقرير المصروفات حسب الشهر'!$C$519:$AD$627,3,FALSE),0) -> 5455 | I24: =IFERROR(VLOOKUP(C24,'تقرير المصروفات حسب الشهر'!$C$644:$AD$753,3,FALSE),0) -> 0 | J24: =IFERROR(VLOOKUP(C24,'تقرير المصروفات حسب الشهر'!$C$770:$AD$879,3,FALSE),0) -> 0 | K24: =IFERROR(VLOOKUP(C24,'تقرير المصروفات حسب الشهر'!$C$897:$AD$1006,3,FALSE),0) -> 0 | L24: =IFERROR(VLOOKUP(C24,'تقرير المصروفات حسب الشهر'!$C$1023:$AD$1133,3,FALSE),0) -> 0 | M24: =IFERROR(VLOOKUP(C24,'تقرير المصروفات حسب الشهر'!$C$1150:$AD$1261,3,FALSE),0) -> 0 | N24: =IFERROR(VLOOKUP(C24,'تقرير المصروفات حسب الشهر'!$C$1277:$AD$1388,3,FALSE),0) -> 0 | O24: =IFERROR(VLOOKUP(C24,'تقرير المصروفات حسب الشهر'!$C$1404:$AI$1519,3,FALSE),0) -> 0 | P24: =SUM(D24:O24) -> 25337
C25: المياه | D25: =IFERROR(VLOOKUP(C25,'تقرير المصروفات حسب الشهر'!$C$10:$AD$119,3,FALSE),0) -> 650 | E25: =IFERROR(VLOOKUP(C25,'تقرير المصروفات حسب الشهر'!$C$136:$AD$245,3,FALSE),0) -> 650 | F25: =VLOOKUP(C25,'تقرير المصروفات حسب الشهر'!C265:AI381,3,0) -> 600 | G25: =IFERROR(VLOOKUP(C25,'تقرير المصروفات حسب الشهر'!$C$391:$AD$510,3,FALSE),0) -> 0 | H25: =IFERROR(VLOOKUP(C25,'تقرير المصروفات حسب الشهر'!$C$519:$AD$627,3,FALSE),0) -> 960 | I25: =IFERROR(VLOOKUP(C25,'تقرير المصروفات حسب الشهر'!$C$644:$AD$753,3,FALSE),0) -> 0 | J25: =IFERROR(VLOOKUP(C25,'تقرير المصروفات حسب الشهر'!$C$770:$AD$879,3,FALSE),0) -> 0 | K25: =IFERROR(VLOOKUP(C25,'تقرير المصروفات حسب الشهر'!$C$897:$AD$1006,3,FALSE),0) -> 0 | L25: =IFERROR(VLOOKUP(C25,'تقرير المصروفات حسب الشهر'!$C$1023:$AD$1133,3,FALSE),0) -> 0 | M25: =IFERROR(VLOOKUP(C25,'تقرير المصروفات حسب الشهر'!$C$1150:$AD$1261,3,FALSE),0) -> 0 | N25: =IFERROR(VLOOKUP(C25,'تقرير المصروفات حسب الشهر'!$C$1277:$AD$1388,3,FALSE),0) -> 0 | O25: =IFERROR(VLOOKUP(C25,'تقرير المصروفات حسب الشهر'!$C$1404:$AI$1519,3,FALSE),0) -> 0 | P25: =SUM(D25:O25) -> 2860
C26: التليفون الارضي | D26: =IFERROR(VLOOKUP(C26,'تقرير المصروفات حسب الشهر'!$C$10:$AD$119,3,FALSE),0) -> 0 | E26: =IFERROR(VLOOKUP(C26,'تقرير المصروفات حسب الشهر'!$C$136:$AD$245,3,FALSE),0) -> 1200 | F26: =VLOOKUP(C26,'تقرير المصروفات حسب الشهر'!C266:AI382,3,0) -> 0 | G26: =IFERROR(VLOOKUP(C26,'تقرير المصروفات حسب الشهر'!$C$391:$AD$510,3,FALSE),0) -> 0 | H26: =IFERROR(VLOOKUP(C26,'تقرير المصروفات حسب الشهر'!$C$519:$AD$627,3,FALSE),0) -> 0 | I26: =IFERROR(VLOOKUP(C26,'تقرير المصروفات حسب الشهر'!$C$644:$AD$753,3,FALSE),0) -> 0 | J26: =IFERROR(VLOOKUP(C26,'تقرير المصروفات حسب الشهر'!$C$770:$AD$879,3,FALSE),0) -> 0 | K26: =IFERROR(VLOOKUP(C26,'تقرير المصروفات حسب الشهر'!$C$897:$AD$1006,3,FALSE),0) -> 0 | L26: =IFERROR(VLOOKUP(C26,'تقرير المصروفات حسب الشهر'!$C$1023:$AD$1133,3,FALSE),0) -> 0 | M26: =IFERROR(VLOOKUP(C26,'تقرير المصروفات حسب الشهر'!$C$1150:$AD$1261,3,FALSE),0) -> 0 | N26: =IFERROR(VLOOKUP(C26,'تقرير المصروفات حسب الشهر'!$C$1277:$AD$1388,3,FALSE),0) -> 0 | O26: =IFERROR(VLOOKUP(C26,'تقرير المصروفات حسب الشهر'!$C$1404:$AI$1519,3,FALSE),0) -> 0 | P26: =SUM(D26:O26) -> 1200
C27: الايجار - الصيدلية | D27: =IFERROR(VLOOKUP(C27,'تقرير المصروفات حسب الشهر'!$C$10:$AD$119,3,FALSE),0) -> 170000 | E27: =IFERROR(VLOOKUP(C27,'تقرير المصروفات حسب الشهر'!$C$136:$AD$245,3,FALSE),0) -> 170000 | F27: =VLOOKUP(C27,'تقرير المصروفات حسب الشهر'!C267:AI383,3,0) -> 170000 | G27: =IFERROR(VLOOKUP(C27,'تقرير المصروفات حسب الشهر'!$C$391:$AD$510,3,FALSE),0) -> 170000 | H27: =IFERROR(VLOOKUP(C27,'تقرير المصروفات حسب الشهر'!$C$519:$AD$627,3,FALSE),0) -> 170000 | I27: =IFERROR(VLOOKUP(C27,'تقرير المصروفات حسب الشهر'!$C$644:$AD$753,3,FALSE),0) -> 0 | J27: =IFERROR(VLOOKUP(C27,'تقرير المصروفات حسب الشهر'!$C$770:$AD$879,3,FALSE),0) -> 0 | K27: =IFERROR(VLOOKUP(C27,'تقرير المصروفات حسب الشهر'!$C$897:$AD$1006,3,FALSE),0) -> 0 | L27: =IFERROR(VLOOKUP(C27,'تقرير المصروفات حسب الشهر'!$C$1023:$AD$1133,3,FALSE),0) -> 0 | M27: =IFERROR(VLOOKUP(C27,'تقرير المصروفات حسب الشهر'!$C$1150:$AD$1261,3,FALSE),0) -> 0 | N27: =IFERROR(VLOOKUP(C27,'تقرير المصروفات حسب الشهر'!$C$1277:$AD$1388,3,FALSE),0) -> 0 | O27: =IFERROR(VLOOKUP(C27,'تقرير المصروفات حسب الشهر'!$C$1404:$AI$1519,3,FALSE),0) -> 0 | P27: =SUM(D27:O27) -> 850000
C28: الايجار - الادارة | D28: =IFERROR(VLOOKUP(C28,'تقرير المصروفات حسب الشهر'!$C$10:$AD$119,3,FALSE),0) -> 0 | E28: =IFERROR(VLOOKUP(C28,'تقرير المصروفات حسب الشهر'!$C$136:$AD$245,3,FALSE),0) -> 0 | F28: =VLOOKUP(C28,'تقرير المصروفات حسب الشهر'!C268:AI384,3,0) -> 0 | G28: =IFERROR(VLOOKUP(C28,'تقرير المصروفات حسب الشهر'!$C$391:$AD$510,3,FALSE),0) -> 0 | H28: =IFERROR(VLOOKUP(C28,'تقرير المصروفات حسب الشهر'!$C$519:$AD$627,3,FALSE),0) -> 0 | I28: =IFERROR(VLOOKUP(C28,'تقرير المصروفات حسب الشهر'!$C$644:$AD$753,3,FALSE),0) -> 0 | J28: =IFERROR(VLOOKUP(C28,'تقرير المصروفات حسب الشهر'!$C$770:$AD$879,3,FALSE),0) -> 0 | K28: =IFERROR(VLOOKUP(C28,'تقرير المصروفات حسب الشهر'!$C$897:$AD$1006,3,FALSE),0) -> 0 | L28: =IFERROR(VLOOKUP(C28,'تقرير المصروفات حسب الشهر'!$C$1023:$AD$1133,3,FALSE),0) -> 0 | M28: =IFERROR(VLOOKUP(C28,'تقرير المصروفات حسب الشهر'!$C$1150:$AD$1261,3,FALSE),0) -> 0 | N28: =IFERROR(VLOOKUP(C28,'تقرير المصروفات حسب الشهر'!$C$1277:$AD$1388,3,FALSE),0) -> 0 | O28: =IFERROR(VLOOKUP(C28,'تقرير المصروفات حسب الشهر'!$C$1404:$AI$1519,3,FALSE),0) -> 0 | P28: =SUM(D28:O28) -> 0
C29: ايجارات متنوعه | D29: =IFERROR(VLOOKUP(C29,'تقرير المصروفات حسب الشهر'!$C$10:$AD$119,3,FALSE),0) -> 0 | E29: =IFERROR(VLOOKUP(C29,'تقرير المصروفات حسب الشهر'!$C$136:$AD$245,3,FALSE),0) -> 26250 | F29: =VLOOKUP(C29,'تقرير المصروفات حسب الشهر'!C269:AI385,3,0) -> 3500 | G29: =IFERROR(VLOOKUP(C29,'تقرير المصروفات حسب الشهر'!$C$391:$AD$510,3,FALSE),0) -> 3500 | H29: =IFERROR(VLOOKUP(C29,'تقرير المصروفات حسب الشهر'!$C$519:$AD$627,3,FALSE),0) -> 3500 | I29: =IFERROR(VLOOKUP(C29,'تقرير المصروفات حسب الشهر'!$C$644:$AD$753,3,FALSE),0) -> 0 | J29: =IFERROR(VLOOKUP(C29,'تقرير المصروفات حسب الشهر'!$C$770:$AD$879,3,FALSE),0) -> 0 | K29: =IFERROR(VLOOKUP(C29,'تقرير المصروفات حسب الشهر'!$C$897:$AD$1006,3,FALSE),0) -> 0 | L29: =IFERROR(VLOOKUP(C29,'تقرير المصروفات حسب الشهر'!$C$1023:$AD$1133,3,FALSE),0) -> 0 | M29: =IFERROR(VLOOKUP(C29,'تقرير المصروفات حسب الشهر'!$C$1150:$AD$1261,3,FALSE),0) -> 0 | N29: =IFERROR(VLOOKUP(C29,'تقرير المصروفات حسب الشهر'!$C$1277:$AD$1388,3,FALSE),0) -> 0 | O29: =IFERROR(VLOOKUP(C29,'تقرير المصروفات حسب الشهر'!$C$1404:$AI$1519,3,FALSE),0) -> 0 | P29: =SUM(D29:O29) -> 36750
C30: ادوات مكتبية | D30: =IFERROR(VLOOKUP(C30,'تقرير المصروفات حسب الشهر'!$C$10:$AD$119,3,FALSE),0) -> 65 | E30: =IFERROR(VLOOKUP(C30,'تقرير المصروفات حسب الشهر'!$C$136:$AD$245,3,FALSE),0) -> 0 | F30: =VLOOKUP(C30,'تقرير المصروفات حسب الشهر'!C270:AI386,3,0) -> 1130 | G30: =IFERROR(VLOOKUP(C30,'تقرير المصروفات حسب الشهر'!$C$391:$AD$510,3,FALSE),0) -> 30 | H30: =IFERROR(VLOOKUP(C30,'تقرير المصروفات حسب الشهر'!$C$519:$AD$627,3,FALSE),0) -> 1225 | I30: =IFERROR(VLOOKUP(C30,'تقرير المصروفات حسب الشهر'!$C$644:$AD$753,3,FALSE),0) -> 0 | J30: =IFERROR(VLOOKUP(C30,'تقرير المصروفات حسب الشهر'!$C$770:$AD$879,3,FALSE),0) -> 0 | K30: =IFERROR(VLOOKUP(C30,'تقرير المصروفات حسب الشهر'!$C$897:$AD$1006,3,FALSE),0) -> 0 | L30: =IFERROR(VLOOKUP(C30,'تقرير المصروفات حسب الشهر'!$C$1023:$AD$1133,3,FALSE),0) -> 0 | M30: =IFERROR(VLOOKUP(C30,'تقرير المصروفات حسب الشهر'!$C$1150:$AD$1261,3,FALSE),0) -> 0 | N30: =IFERROR(VLOOKUP(C30,'تقرير المصروفات حسب الشهر'!$C$1277:$AD$1388,3,FALSE),0) -> 0 | O30: =IFERROR(VLOOKUP(C30,'تقرير المصروفات حسب الشهر'!$C$1404:$AI$1519,3,FALSE),0) -> 0 | P30: =SUM(D30:O30) -> 2450
C31: فواتير الموبايل | D31: =IFERROR(VLOOKUP(C31,'تقرير المصروفات حسب الشهر'!$C$10:$AD$119,3,FALSE),0) -> 721.98 | E31: =IFERROR(VLOOKUP(C31,'تقرير المصروفات حسب الشهر'!$C$136:$AD$245,3,FALSE),0) -> 721 | F31: =VLOOKUP(C31,'تقرير المصروفات حسب الشهر'!C271:AI387,3,0) -> 724.56 | G31: =IFERROR(VLOOKUP(C31,'تقرير المصروفات حسب الشهر'!$C$391:$AD$510,3,FALSE),0) -> 721.98 | H31: =IFERROR(VLOOKUP(C31,'تقرير المصروفات حسب الشهر'!$C$519:$AD$627,3,FALSE),0) -> 721.98 | I31: =IFERROR(VLOOKUP(C31,'تقرير المصروفات حسب الشهر'!$C$644:$AD$753,3,FALSE),0) -> 0 | J31: =IFERROR(VLOOKUP(C31,'تقرير المصروفات حسب الشهر'!$C$770:$AD$879,3,FALSE),0) -> 0 | K31: =IFERROR(VLOOKUP(C31,'تقرير المصروفات حسب الشهر'!$C$897:$AD$1006,3,FALSE),0) -> 0 | L31: =IFERROR(VLOOKUP(C31,'تقرير المصروفات حسب الشهر'!$C$1023:$AD$1133,3,FALSE),0) -> 0 | M31: =IFERROR(VLOOKUP(C31,'تقرير المصروفات حسب الشهر'!$C$1150:$AD$1261,3,FALSE),0) -> 0 | N31: =IFERROR(VLOOKUP(C31,'تقرير المصروفات حسب الشهر'!$C$1277:$AD$1388,3,FALSE),0) -> 0 | O31: =IFERROR(VLOOKUP(C31,'تقرير المصروفات حسب الشهر'!$C$1404:$AI$1519,3,FALSE),0) -> 0 | P31: =SUM(D31:O31) -> 3611.5
C32: مكافات مبيعات الادوية | D32: =IFERROR(VLOOKUP(C32,'تقرير المصروفات حسب الشهر'!$C$10:$AD$119,3,FALSE),0) -> 0 | E32: =IFERROR(VLOOKUP(C32,'تقرير المصروفات حسب الشهر'!$C$136:$AD$245,3,FALSE),0) -> 0 | F32: =VLOOKUP(C32,'تقرير المصروفات حسب الشهر'!C272:AI388,3,0) -> 0 | G32: =IFERROR(VLOOKUP(C32,'تقرير المصروفات حسب الشهر'!$C$391:$AD$510,3,FALSE),0) -> 0 | H32: =IFERROR(VLOOKUP(C32,'تقرير المصروفات حسب الشهر'!$C$519:$AD$627,3,FALSE),0) -> 0 | I32: =IFERROR(VLOOKUP(C32,'تقرير المصروفات حسب الشهر'!$C$644:$AD$753,3,FALSE),0) -> 0 | J32: =IFERROR(VLOOKUP(C32,'تقرير المصروفات حسب الشهر'!$C$770:$AD$879,3,FALSE),0) -> 0 | K32: =IFERROR(VLOOKUP(C32,'تقرير المصروفات حسب الشهر'!$C$897:$AD$1006,3,FALSE),0) -> 0 | L32: =IFERROR(VLOOKUP(C32,'تقرير المصروفات حسب الشهر'!$C$1023:$AD$1133,3,FALSE),0) -> 0 | M32: =IFERROR(VLOOKUP(C32,'تقرير المصروفات حسب الشهر'!$C$1150:$AD$1261,3,FALSE),0) -> 0 | N32: =IFERROR(VLOOKUP(C32,'تقرير المصروفات حسب الشهر'!$C$1277:$AD$1388,3,FALSE),0) -> 0 | O32: =IFERROR(VLOOKUP(C32,'تقرير المصروفات حسب الشهر'!$C$1404:$AI$1519,3,FALSE),0) -> 0 | P32: =SUM(D32:O32) -> 0
C33: مكافات مبيعات التجميل | D33: =IFERROR(VLOOKUP(C33,'تقرير المصروفات حسب الشهر'!$C$10:$AD$119,3,FALSE),0) -> 1000 | E33: =IFERROR(VLOOKUP(C33,'تقرير المصروفات حسب الشهر'!$C$136:$AD$245,3,FALSE),0) -> 3760 | F33: =VLOOKUP(C33,'تقرير المصروفات حسب الشهر'!C273:AI389,3,0) -> 0 | G33: =IFERROR(VLOOKUP(C33,'تقرير المصروفات حسب الشهر'!$C$391:$AD$510,3,FALSE),0) -> 0 | H33: =IFERROR(VLOOKUP(C33,'تقرير المصروفات حسب الشهر'!$C$519:$AD$627,3,FALSE),0) -> 1780 | I33: =IFERROR(VLOOKUP(C33,'تقرير المصروفات حسب الشهر'!$C$644:$AD$753,3,FALSE),0) -> 0 | J33: =IFERROR(VLOOKUP(C33,'تقرير المصروفات حسب الشهر'!$C$770:$AD$879,3,FALSE),0) -> 0 | K33: =IFERROR(VLOOKUP(C33,'تقرير المصروفات حسب الشهر'!$C$897:$AD$1006,3,FALSE),0) -> 0 | L33: =IFERROR(VLOOKUP(C33,'تقرير المصروفات حسب الشهر'!$C$1023:$AD$1133,3,FALSE),0) -> 0 | M33: =IFERROR(VLOOKUP(C33,'تقرير المصروفات حسب الشهر'!$C$1150:$AD$1261,3,FALSE),0) -> 0 | N33: =IFERROR(VLOOKUP(C33,'تقرير المصروفات حسب الشهر'!$C$1277:$AD$1388,3,FALSE),0) -> 0 | O33: =IFERROR(VLOOKUP(C33,'تقرير المصروفات حسب الشهر'!$C$1404:$AI$1519,3,FALSE),0) -> 0 | P33: =SUM(D33:O33) -> 6540
... C109: هوالك وتوالف | D109: =IFERROR(VLOOKUP(C109,'تقرير المصروفات حسب الشهر'!$C$10:$AD$119,3,FALSE),0) -> 0 | E109: =IFERROR(VLOOKUP(C109,'تقرير المصروفات حسب الشهر'!$C$136:$AD$245,3,FALSE),0) -> 0 | F109: =VLOOKUP(C109,'تقرير المصروفات حسب الشهر'!C349:AI465,3,0) -> 11382.3 | G109: =IFERROR(VLOOKUP(C109,'تقرير المصروفات حسب الشهر'!$C$391:$AD$510,3,FALSE),0) -> 0 | H109: =IFERROR(VLOOKUP(C109,'تقرير المصروفات حسب الشهر'!$C$519:$AD$627,3,FALSE),0) -> 0 | I109: =IFERROR(VLOOKUP(C109,'تقرير المصروفات حسب الشهر'!$C$644:$AD$753,3,FALSE),0) -> 0 | J109: =IFERROR(VLOOKUP(C109,'تقرير المصروفات حسب الشهر'!$C$770:$AD$879,3,FALSE),0) -> 0 | K109: =IFERROR(VLOOKUP(C109,'تقرير المصروفات حسب الشهر'!$C$897:$AD$1006,3,FALSE),0) -> 0 | L109: =IFERROR(VLOOKUP(C109,'تقرير المصروفات حسب الشهر'!$C$1023:$AD$1133,3,FALSE),0) -> 0 | M109: =IFERROR(VLOOKUP(C109,'تقرير المصروفات حسب الشهر'!$C$1150:$AD$1261,3,FALSE),0) -> 0 | N109: =IFERROR(VLOOKUP(C109,'تقرير المصروفات حسب الشهر'!$C$1277:$AD$1388,3,FALSE),0) -> 0 | O109: =IFERROR(VLOOKUP(C109,'تقرير المصروفات حسب الشهر'!$C$1404:$AI$1519,3,FALSE),0) -> 0 | P109: =SUM(D109:O109) -> 11382.3
C110: عجز جرد | D110: 0.23 | E110: =IFERROR(VLOOKUP(C110,'تقرير المصروفات حسب الشهر'!$C$136:$AD$245,3,FALSE),0) -> 0 | F110: =VLOOKUP(C110,'تقرير المصروفات حسب الشهر'!C350:AI466,3,0) -> 0 | G110: =IFERROR(VLOOKUP(C110,'تقرير المصروفات حسب الشهر'!$C$391:$AD$510,3,FALSE),0) -> 564.93 | H110: =IFERROR(VLOOKUP(C110,'تقرير المصروفات حسب الشهر'!$C$519:$AD$627,3,FALSE),0) -> 0 | I110: =IFERROR(VLOOKUP(C110,'تقرير المصروفات حسب الشهر'!$C$644:$AD$753,3,FALSE),0) -> 0 | J110: =IFERROR(VLOOKUP(C110,'تقرير المصروفات حسب الشهر'!$C$770:$AD$879,3,FALSE),0) -> 0 | K110: =IFERROR(VLOOKUP(C110,'تقرير المصروفات حسب الشهر'!$C$897:$AD$1006,3,FALSE),0) -> 0 | L110: =IFERROR(VLOOKUP(C110,'تقرير المصروفات حسب الشهر'!$C$1023:$AD$1133,3,FALSE),0) -> 0 | M110: =IFERROR(VLOOKUP(C110,'تقرير المصروفات حسب الشهر'!$C$1150:$AD$1261,3,FALSE),0) -> 0 | N110: =IFERROR(VLOOKUP(C110,'تقرير المصروفات حسب الشهر'!$C$1277:$AD$1388,3,FALSE),0) -> 0 | O110: =IFERROR(VLOOKUP(C110,'تقرير المصروفات حسب الشهر'!$C$1404:$AI$1519,3,FALSE),0) -> 0 | P110: =SUM(D110:O110) -> 565.16
C111: تامين على السيارات | D111: =IFERROR(VLOOKUP(C111,'تقرير المصروفات حسب الشهر'!$C$10:$AD$119,3,FALSE),0) -> 0 | E111: =IFERROR(VLOOKUP(C111,'تقرير المصروفات حسب الشهر'!$C$136:$AD$245,3,FALSE),0) -> 0 | F111: =VLOOKUP(C111,'تقرير المصروفات حسب الشهر'!C351:AI467,3,0) -> 0 | G111: =IFERROR(VLOOKUP(C111,'تقرير المصروفات حسب الشهر'!$C$391:$AD$510,3,FALSE),0) -> 0 | H111: =IFERROR(VLOOKUP(C111,'تقرير المصروفات حسب الشهر'!$C$519:$AD$627,3,FALSE),0) -> 0 | I111: =IFERROR(VLOOKUP(C111,'تقرير المصروفات حسب الشهر'!$C$644:$AD$753,3,FALSE),0) -> 0 | J111: =IFERROR(VLOOKUP(C111,'تقرير المصروفات حسب الشهر'!$C$770:$AD$879,3,FALSE),0) -> 0 | K111: =IFERROR(VLOOKUP(C111,'تقرير المصروفات حسب الشهر'!$C$897:$AD$1006,3,FALSE),0) -> 0 | L111: =IFERROR(VLOOKUP(C111,'تقرير المصروفات حسب الشهر'!$C$1023:$AD$1133,3,FALSE),0) -> 0 | M111: =IFERROR(VLOOKUP(C111,'تقرير المصروفات حسب الشهر'!$C$1150:$AD$1261,3,FALSE),0) -> 0 | N111: =IFERROR(VLOOKUP(C111,'تقرير المصروفات حسب الشهر'!$C$1277:$AD$1388,3,FALSE),0) -> 0 | O111: =IFERROR(VLOOKUP(C111,'تقرير المصروفات حسب الشهر'!$C$1404:$AI$1519,3,FALSE),0) -> 0 | P111: =SUM(D111:O111) -> 0
C112: مصروفات عملاء تعاقدات | D112: =IFERROR(VLOOKUP(C112,'تقرير المصروفات حسب الشهر'!$C$10:$AD$119,3,FALSE),0) -> 0 | E112: =IFERROR(VLOOKUP(C112,'تقرير المصروفات حسب الشهر'!$C$136:$AD$245,3,FALSE),0) -> 0 | F112: =VLOOKUP(C112,'تقرير المصروفات حسب الشهر'!C352:AI468,3,0) -> 0 | G112: =IFERROR(VLOOKUP(C112,'تقرير المصروفات حسب الشهر'!$C$391:$AD$510,3,FALSE),0) -> 0 | H112: =IFERROR(VLOOKUP(C112,'تقرير المصروفات حسب الشهر'!$C$519:$AD$627,3,FALSE),0) -> 0 | I112: =IFERROR(VLOOKUP(C112,'تقرير المصروفات حسب الشهر'!$C$644:$AD$753,3,FALSE),0) -> 0 | J112: =IFERROR(VLOOKUP(C112,'تقرير المصروفات حسب الشهر'!$C$770:$AD$879,3,FALSE),0) -> 0 | K112: =IFERROR(VLOOKUP(C112,'تقرير المصروفات حسب الشهر'!$C$897:$AD$1006,3,FALSE),0) -> 0 | L112: =IFERROR(VLOOKUP(C112,'تقرير المصروفات حسب الشهر'!$C$1023:$AD$1133,3,FALSE),0) -> 0 | M112: =IFERROR(VLOOKUP(C112,'تقرير المصروفات حسب الشهر'!$C$1150:$AD$1261,3,FALSE),0) -> 0 | N112: =IFERROR(VLOOKUP(C112,'تقرير المصروفات حسب الشهر'!$C$1277:$AD$1388,3,FALSE),0) -> 0 | O112: =IFERROR(VLOOKUP(C112,'تقرير المصروفات حسب الشهر'!$C$1404:$AI$1519,3,FALSE),0) -> 0 | P112: =SUM(D112:O112) -> 0
C113: ارباح دائنون متنوعون | D113: =IFERROR(VLOOKUP(C113,'تقرير المصروفات حسب الشهر'!$C$10:$AD$119,3,FALSE),0) -> 0 | E113: =IFERROR(VLOOKUP(C113,'تقرير المصروفات حسب الشهر'!$C$136:$AD$245,3,FALSE),0) -> 0 | F113: =VLOOKUP(C113,'تقرير المصروفات حسب الشهر'!C353:AI469,3,0) -> 0 | G113: =IFERROR(VLOOKUP(C113,'تقرير المصروفات حسب الشهر'!$C$391:$AD$510,3,FALSE),0) -> 0 | H113: =IFERROR(VLOOKUP(C113,'تقرير المصروفات حسب الشهر'!$C$519:$AD$627,3,FALSE),0) -> 0 | I113: =IFERROR(VLOOKUP(C113,'تقرير المصروفات حسب الشهر'!$C$644:$AD$753,3,FALSE),0) -> 0 | J113: =IFERROR(VLOOKUP(C113,'تقرير المصروفات حسب الشهر'!$C$770:$AD$879,3,FALSE),0) -> 0 | K113: =IFERROR(VLOOKUP(C113,'تقرير المصروفات حسب الشهر'!$C$897:$AD$1006,3,FALSE),0) -> 0 | L113: =IFERROR(VLOOKUP(C113,'تقرير المصروفات حسب الشهر'!$C$1023:$AD$1133,3,FALSE),0) -> 0 | M113: =IFERROR(VLOOKUP(C113,'تقرير المصروفات حسب الشهر'!$C$1150:$AD$1261,3,FALSE),0) -> 0 | N113: =IFERROR(VLOOKUP(C113,'تقرير المصروفات حسب الشهر'!$C$1277:$AD$1388,3,FALSE),0) -> 0 | O113: =IFERROR(VLOOKUP(C113,'تقرير المصروفات حسب الشهر'!$C$1404:$AI$1519,3,FALSE),0) -> 0 | P113: =SUM(D113:O113) -> 0
C114: مصروفات متنوعه - ايام دعاية | D114: =IFERROR(VLOOKUP(C114,'تقرير المصروفات حسب الشهر'!$C$10:$AD$119,3,FALSE),0) -> 0 | E114: =IFERROR(VLOOKUP(C114,'تقرير المصروفات حسب الشهر'!$C$136:$AD$245,3,FALSE),0) -> 0 | F114: =VLOOKUP(C114,'تقرير المصروفات حسب الشهر'!C354:AI470,3,0) -> 0 | G114: =IFERROR(VLOOKUP(C114,'تقرير المصروفات حسب الشهر'!$C$391:$AD$510,3,FALSE),0) -> 0 | H114: =IFERROR(VLOOKUP(C114,'تقرير المصروفات حسب الشهر'!$C$519:$AD$627,3,FALSE),0) -> 0 | I114: =IFERROR(VLOOKUP(C114,'تقرير المصروفات حسب الشهر'!$C$644:$AD$753,3,FALSE),0) -> 0 | J114: =IFERROR(VLOOKUP(C114,'تقرير المصروفات حسب الشهر'!$C$770:$AD$879,3,FALSE),0) -> 0 | K114: =IFERROR(VLOOKUP(C114,'تقرير المصروفات حسب الشهر'!$C$897:$AD$1006,3,FALSE),0) -> 0 | L114: =IFERROR(VLOOKUP(C114,'تقرير المصروفات حسب الشهر'!$C$1023:$AD$1133,3,FALSE),0) -> 0 | M114: =IFERROR(VLOOKUP(C114,'تقرير المصروفات حسب الشهر'!$C$1150:$AD$1261,3,FALSE),0) -> 0 | N114: =IFERROR(VLOOKUP(C114,'تقرير المصروفات حسب الشهر'!$C$1277:$AD$1388,3,FALSE),0) -> 0 | O114: =IFERROR(VLOOKUP(C114,'تقرير المصروفات حسب الشهر'!$C$1404:$AI$1519,3,FALSE),0) -> 0 | P114: =SUM(D114:O114) -> 0
C115: تغليف وشحن بضاعة | D115: =IFERROR(VLOOKUP(C115,'تقرير المصروفات حسب الشهر'!$C$10:$AD$119,3,FALSE),0) -> 0 | E115: =IFERROR(VLOOKUP(C115,'تقرير المصروفات حسب الشهر'!$C$136:$AD$245,3,FALSE),0) -> 0 | F115: =VLOOKUP(C115,'تقرير المصروفات حسب الشهر'!C355:AI471,3,0) -> 0 | G115: =IFERROR(VLOOKUP(C115,'تقرير المصروفات حسب الشهر'!$C$391:$AD$510,3,FALSE),0) -> 0 | H115: =IFERROR(VLOOKUP(C115,'تقرير المصروفات حسب الشهر'!$C$519:$AD$627,3,FALSE),0) -> 0 | I115: =IFERROR(VLOOKUP(C115,'تقرير المصروفات حسب الشهر'!$C$644:$AD$753,3,FALSE),0) -> 0 | J115: =IFERROR(VLOOKUP(C115,'تقرير المصروفات حسب الشهر'!$C$770:$AD$879,3,FALSE),0) -> 0 | K115: =IFERROR(VLOOKUP(C115,'تقرير المصروفات حسب الشهر'!$C$897:$AD$1006,3,FALSE),0) -> 0 | L115: =IFERROR(VLOOKUP(C115,'تقرير المصروفات حسب الشهر'!$C$1023:$AD$1133,3,FALSE),0) -> 0 | M115: =IFERROR(VLOOKUP(C115,'تقرير المصروفات حسب الشهر'!$C$1150:$AD$1261,3,FALSE),0) -> 0 | N115: =IFERROR(VLOOKUP(C115,'تقرير المصروفات حسب الشهر'!$C$1277:$AD$1388,3,FALSE),0) -> 0 | O115: =IFERROR(VLOOKUP(C115,'تقرير المصروفات حسب الشهر'!$C$1404:$AI$1519,3,FALSE),0) -> 0 | P115: =SUM(D115:O115) -> 0
C116: ديون معدومة | D116: =IFERROR(VLOOKUP(C116,'تقرير المصروفات حسب الشهر'!$C$10:$AD$119,3,FALSE),0) -> 0 | E116: =IFERROR(VLOOKUP(C116,'تقرير المصروفات حسب الشهر'!$C$136:$AD$245,3,FALSE),0) -> 0 | F116: =VLOOKUP(C116,'تقرير المصروفات حسب الشهر'!C356:AI472,3,0) -> 0 | G116: =IFERROR(VLOOKUP(C116,'تقرير المصروفات حسب الشهر'!$C$391:$AD$510,3,FALSE),0) -> 0 | H116: =IFERROR(VLOOKUP(C116,'تقرير المصروفات حسب الشهر'!$C$519:$AD$627,3,FALSE),0) -> 0 | I116: =IFERROR(VLOOKUP(C116,'تقرير المصروفات حسب الشهر'!$C$644:$AD$753,3,FALSE),0) -> 0 | J116: =IFERROR(VLOOKUP(C116,'تقرير المصروفات حسب الشهر'!$C$770:$AD$879,3,FALSE),0) -> 0 | K116: =IFERROR(VLOOKUP(C116,'تقرير المصروفات حسب الشهر'!$C$897:$AD$1006,3,FALSE),0) -> 0 | L116: =IFERROR(VLOOKUP(C116,'تقرير المصروفات حسب الشهر'!$C$1023:$AD$1133,3,FALSE),0) -> 0 | M116: =IFERROR(VLOOKUP(C116,'تقرير المصروفات حسب الشهر'!$C$1150:$AD$1261,3,FALSE),0) -> 0 | N116: =IFERROR(VLOOKUP(C116,'تقرير المصروفات حسب الشهر'!$C$1277:$AD$1388,3,FALSE),0) -> 0 | O116: =IFERROR(VLOOKUP(C116,'تقرير المصروفات حسب الشهر'!$C$1404:$AI$1519,3,FALSE),0) -> 0 | P116: =SUM(D116:O116) -> 0
C117: دمغات | D117: =IFERROR(VLOOKUP(C117,'تقرير المصروفات حسب الشهر'!$C$10:$AD$119,3,FALSE),0) -> 0 | E117: =IFERROR(VLOOKUP(C117,'تقرير المصروفات حسب الشهر'!$C$136:$AD$245,3,FALSE),0) -> 0 | F117: =VLOOKUP(C117,'تقرير المصروفات حسب الشهر'!C357:AI473,3,0) -> 0 | G117: =IFERROR(VLOOKUP(C117,'تقرير المصروفات حسب الشهر'!$C$391:$AD$510,3,FALSE),0) -> 0 | H117: =IFERROR(VLOOKUP(C117,'تقرير المصروفات حسب الشهر'!$C$519:$AD$627,3,FALSE),0) -> 0 | I117: =IFERROR(VLOOKUP(C117,'تقرير المصروفات حسب الشهر'!$C$644:$AD$753,3,FALSE),0) -> 0 | J117: =IFERROR(VLOOKUP(C117,'تقرير المصروفات حسب الشهر'!$C$770:$AD$879,3,FALSE),0) -> 0 | K117: =IFERROR(VLOOKUP(C117,'تقرير المصروفات حسب الشهر'!$C$897:$AD$1006,3,FALSE),0) -> 0 | L117: =IFERROR(VLOOKUP(C117,'تقرير المصروفات حسب الشهر'!$C$1023:$AD$1133,3,FALSE),0) -> 0 | M117: =IFERROR(VLOOKUP(C117,'تقرير المصروفات حسب الشهر'!$C$1150:$AD$1261,3,FALSE),0) -> 0 | N117: =IFERROR(VLOOKUP(C117,'تقرير المصروفات حسب الشهر'!$C$1277:$AD$1388,3,FALSE),0) -> 0 | O117: =IFERROR(VLOOKUP(C117,'تقرير المصروفات حسب الشهر'!$C$1404:$AI$1519,3,FALSE),0) -> 0 | P117: =SUM(D117:O117) -> 0
C118: خسائر إستبعاد أصول | D118: =IFERROR(VLOOKUP(C118,'تقرير المصروفات حسب الشهر'!$C$10:$AD$119,3,FALSE),0) -> 0 | E118: =IFERROR(VLOOKUP(C118,'تقرير المصروفات حسب الشهر'!$C$136:$AD$245,3,FALSE),0) -> 0 | F118: =VLOOKUP(C118,'تقرير المصروفات حسب الشهر'!C358:AI474,3,0) -> 0 | G118: =IFERROR(VLOOKUP(C118,'تقرير المصروفات حسب الشهر'!$C$391:$AD$510,3,FALSE),0) -> 0 | H118: =IFERROR(VLOOKUP(C118,'تقرير المصروفات حسب الشهر'!$C$519:$AD$627,3,FALSE),0) -> 0 | I118: =IFERROR(VLOOKUP(C118,'تقرير المصروفات حسب الشهر'!$C$644:$AD$753,3,FALSE),0) -> 0 | J118: =IFERROR(VLOOKUP(C118,'تقرير المصروفات حسب الشهر'!$C$770:$AD$879,3,FALSE),0) -> 0 | K118: =IFERROR(VLOOKUP(C118,'تقرير المصروفات حسب الشهر'!$C$897:$AD$1006,3,FALSE),0) -> 0 | L118: =IFERROR(VLOOKUP(C118,'تقرير المصروفات حسب الشهر'!$C$1023:$AD$1133,3,FALSE),0) -> 0 | M118: =IFERROR(VLOOKUP(C118,'تقرير المصروفات حسب الشهر'!$C$1150:$AD$1261,3,FALSE),0) -> 0 | N118: =IFERROR(VLOOKUP(C118,'تقرير المصروفات حسب الشهر'!$C$1277:$AD$1388,3,FALSE),0) -> 0 | O118: =IFERROR(VLOOKUP(C118,'تقرير المصروفات حسب الشهر'!$C$1404:$AI$1519,3,FALSE),0) -> 0 | P118: =SUM(D118:O118) -> 0
C119: عروض مبيعات التجميل | D119: =IFERROR(VLOOKUP(C119,'تقرير المصروفات حسب الشهر'!$C$10:$AD$119,3,FALSE),0) -> 9179 | E119: =IFERROR(VLOOKUP(C119,'تقرير المصروفات حسب الشهر'!$C$136:$AD$245,3,FALSE),0) -> 0 | F119: =VLOOKUP(C119,'تقرير المصروفات حسب الشهر'!C359:AI475,3,0) -> 9123.96 | G119: =IFERROR(VLOOKUP(C119,'تقرير المصروفات حسب الشهر'!$C$391:$AD$510,3,FALSE),0) -> 35945.14 | H119: =IFERROR(VLOOKUP(C119,'تقرير المصروفات حسب الشهر'!$C$519:$AD$627,3,FALSE),0) -> 0 | I119: =IFERROR(VLOOKUP(C119,'تقرير المصروفات حسب الشهر'!$C$644:$AD$753,3,FALSE),0) -> 0 | J119: =IFERROR(VLOOKUP(C119,'تقرير المصروفات حسب الشهر'!$C$770:$AD$879,3,FALSE),0) -> 0 | K119: =IFERROR(VLOOKUP(C119,'تقرير المصروفات حسب الشهر'!$C$897:$AD$1006,3,FALSE),0) -> 0 | L119: =IFERROR(VLOOKUP(C119,'تقرير المصروفات حسب الشهر'!$C$1023:$AD$1133,3,FALSE),0) -> 0 | M119: =IFERROR(VLOOKUP(C119,'تقرير المصروفات حسب الشهر'!$C$1150:$AD$1261,3,FALSE),0) -> 0 | N119: =IFERROR(VLOOKUP(C119,'تقرير المصروفات حسب الشهر'!$C$1277:$AD$1388,3,FALSE),0) -> 0 | O119: =IFERROR(VLOOKUP(C119,'تقرير المصروفات حسب الشهر'!$C$1404:$AI$1519,3,FALSE),0) -> 0 | P119: =SUM(D119:O119) -> 54248.1
C120: فوائد القروض - ابوظبى الاولFAB | D120: =IFERROR(VLOOKUP(C120,'تقرير المصروفات حسب الشهر'!$C$10:$AD$119,3,FALSE),0) -> 0 | E120: =IFERROR(VLOOKUP(C120,'تقرير المصروفات حسب الشهر'!$C$136:$AD$245,3,FALSE),0) -> 0 | F120: =VLOOKUP(C120,'تقرير المصروفات حسب الشهر'!C360:AI476,3,0) -> 0 | G120: =IFERROR(VLOOKUP(C120,'تقرير المصروفات حسب الشهر'!$C$391:$AD$510,3,FALSE),0) -> 0 | H120: =IFERROR(VLOOKUP(C120,'تقرير المصروفات حسب الشهر'!$C$519:$AD$627,3,FALSE),0) -> 0 | I120: =IFERROR(VLOOKUP(C120,'تقرير المصروفات حسب الشهر'!$C$644:$AD$753,3,FALSE),0) -> 0 | J120: =IFERROR(VLOOKUP(C120,'تقرير المصروفات حسب الشهر'!$C$770:$AD$879,3,FALSE),0) -> 0 | K120: =IFERROR(VLOOKUP(C120,'تقرير المصروفات حسب الشهر'!$C$897:$AD$1006,3,FALSE),0) -> 0 | L120: =IFERROR(VLOOKUP(C120,'تقرير المصروفات حسب الشهر'!$C$1023:$AD$1133,3,FALSE),0) -> 0 | M120: =IFERROR(VLOOKUP(C120,'تقرير المصروفات حسب الشهر'!$C$1150:$AD$1261,3,FALSE),0) -> 0 | N120: =IFERROR(VLOOKUP(C120,'تقرير المصروفات حسب الشهر'!$C$1277:$AD$1388,3,FALSE),0) -> 0 | O120: =IFERROR(VLOOKUP(C120,'تقرير المصروفات حسب الشهر'!$C$1404:$AI$1519,3,FALSE),0) -> 0 | P120: =SUM(D120:O120) -> 0
C121: فوائد القروض بنك ADIB | D121: =IFERROR(VLOOKUP(C121,'تقرير المصروفات حسب الشهر'!$C$10:$AD$119,3,FALSE),0) -> 0 | E121: =IFERROR(VLOOKUP(C121,'تقرير المصروفات حسب الشهر'!$C$136:$AD$245,3,FALSE),0) -> 0 | F121: =VLOOKUP(C121,'تقرير المصروفات حسب الشهر'!C361:AI477,3,0) -> 0 | G121: =IFERROR(VLOOKUP(C121,'تقرير المصروفات حسب الشهر'!$C$391:$AD$510,3,FALSE),0) -> 0 | H121: =IFERROR(VLOOKUP(C121,'تقرير المصروفات حسب الشهر'!$C$519:$AD$627,3,FALSE),0) -> 0 | I121: =IFERROR(VLOOKUP(C121,'تقرير المصروفات حسب الشهر'!$C$644:$AD$753,3,FALSE),0) -> 0 | J121: =IFERROR(VLOOKUP(C121,'تقرير المصروفات حسب الشهر'!$C$770:$AD$879,3,FALSE),0) -> 0 | K121: =IFERROR(VLOOKUP(C121,'تقرير المصروفات حسب الشهر'!$C$897:$AD$1006,3,FALSE),0) -> 0 | L121: =IFERROR(VLOOKUP(C121,'تقرير المصروفات حسب الشهر'!$C$1023:$AD$1133,3,FALSE),0) -> 0 | M121: =IFERROR(VLOOKUP(C121,'تقرير المصروفات حسب الشهر'!$C$1150:$AD$1261,3,FALSE),0) -> 0 | N121: =IFERROR(VLOOKUP(C121,'تقرير المصروفات حسب الشهر'!$C$1277:$AD$1388,3,FALSE),0) -> 0 | O121: =IFERROR(VLOOKUP(C121,'تقرير المصروفات حسب الشهر'!$C$1404:$AI$1519,3,FALSE),0) -> 0 | P121: =SUM(D121:O121) -> 0
C122: فوائد القروض بنك كريدي أجريكول | D122: =IFERROR(VLOOKUP(C122,'تقرير المصروفات حسب الشهر'!$C$10:$AD$119,3,FALSE),0) -> 0 | E122: =IFERROR(VLOOKUP(C122,'تقرير المصروفات حسب الشهر'!$C$136:$AD$245,3,FALSE),0) -> 0 | F122: =VLOOKUP(C122,'تقرير المصروفات حسب الشهر'!C362:AI478,3,0) -> 0 | G122: =IFERROR(VLOOKUP(C122,'تقرير المصروفات حسب الشهر'!$C$391:$AD$510,3,FALSE),0) -> 0 | H122: =IFERROR(VLOOKUP(C122,'تقرير المصروفات حسب الشهر'!$C$519:$AD$627,3,FALSE),0) -> 0 | I122: =IFERROR(VLOOKUP(C122,'تقرير المصروفات حسب الشهر'!$C$644:$AD$753,3,FALSE),0) -> 0 | J122: =IFERROR(VLOOKUP(C122,'تقرير المصروفات حسب الشهر'!$C$770:$AD$879,3,FALSE),0) -> 0 | K122: =IFERROR(VLOOKUP(C122,'تقرير المصروفات حسب الشهر'!$C$897:$AD$1006,3,FALSE),0) -> 0 | L122: =IFERROR(VLOOKUP(C122,'تقرير المصروفات حسب الشهر'!$C$1023:$AD$1133,3,FALSE),0) -> 0 | M122: =IFERROR(VLOOKUP(C122,'تقرير المصروفات حسب الشهر'!$C$1150:$AD$1261,3,FALSE),0) -> 0 | N122: =IFERROR(VLOOKUP(C122,'تقرير المصروفات حسب الشهر'!$C$1277:$AD$1388,3,FALSE),0) -> 0 | O122: =IFERROR(VLOOKUP(C122,'تقرير المصروفات حسب الشهر'!$C$1404:$AI$1519,3,FALSE),0) -> 0 | P122: =SUM(D122:O122) -> 0
... C130: فوائد القروض - التجارى وفا بنك AWB | D130: =IFERROR(VLOOKUP(C130,'تقرير المصروفات حسب الشهر'!$C$10:$AD$119,3,FALSE),0) -> 0 | E130: =IFERROR(VLOOKUP(C130,'تقرير المصروفات حسب الشهر'!$C$136:$AD$245,3,FALSE),0) -> 0 | F130: =VLOOKUP(C130,'تقرير المصروفات حسب الشهر'!C370:AI486,3,0) -> 0 | G130: =IFERROR(VLOOKUP(C130,'تقرير المصروفات حسب الشهر'!$C$391:$AD$510,3,FALSE),0) -> 0 | H130: =IFERROR(VLOOKUP(C130,'تقرير المصروفات حسب الشهر'!$C$519:$AD$627,3,FALSE),0) -> 0 | I130: =IFERROR(VLOOKUP(C130,'تقرير المصروفات حسب الشهر'!$C$644:$AD$753,3,FALSE),0) -> 0 | J130: =IFERROR(VLOOKUP(C130,'تقرير المصروفات حسب الشهر'!$C$770:$AD$879,3,FALSE),0) -> 0 | K130: =IFERROR(VLOOKUP(C130,'تقرير المصروفات حسب الشهر'!$C$897:$AD$1006,3,FALSE),0) -> 0 | L130: =IFERROR(VLOOKUP(C130,'تقرير المصروفات حسب الشهر'!$C$1023:$AD$1133,3,FALSE),0) -> 0 | M130: =IFERROR(VLOOKUP(C130,'تقرير المصروفات حسب الشهر'!$C$1150:$AD$1261,3,FALSE),0) -> 0 | N130: =IFERROR(VLOOKUP(C130,'تقرير المصروفات حسب الشهر'!$C$1277:$AD$1388,3,FALSE),0) -> 0 | O130: =IFERROR(VLOOKUP(C130,'تقرير المصروفات حسب الشهر'!$C$1404:$AI$1519,3,FALSE),0) -> 0 | P130: =SUM(D130:O130) -> 0
C131: فوائد القروض - بنك القاهرة BDC | D131: =IFERROR(VLOOKUP(C131,'تقرير المصروفات حسب الشهر'!$C$10:$AD$119,3,FALSE),0) -> 0 | E131: =IFERROR(VLOOKUP(C131,'تقرير المصروفات حسب الشهر'!$C$136:$AD$245,3,FALSE),0) -> 0 | F131: =VLOOKUP(C131,'تقرير المصروفات حسب الشهر'!C371:AI487,3,0) -> 0 | G131: =IFERROR(VLOOKUP(C131,'تقرير المصروفات حسب الشهر'!$C$391:$AD$510,3,FALSE),0) -> 0 | H131: =IFERROR(VLOOKUP(C131,'تقرير المصروفات حسب الشهر'!$C$519:$AD$627,3,FALSE),0) -> 0 | I131: =IFERROR(VLOOKUP(C131,'تقرير المصروفات حسب الشهر'!$C$644:$AD$753,3,FALSE),0) -> 0 | J131: =IFERROR(VLOOKUP(C131,'تقرير المصروفات حسب الشهر'!$C$770:$AD$879,3,FALSE),0) -> 0 | K131: =IFERROR(VLOOKUP(C131,'تقرير المصروفات حسب الشهر'!$C$897:$AD$1006,3,FALSE),0) -> 0 | L131: =IFERROR(VLOOKUP(C131,'تقرير المصروفات حسب الشهر'!$C$1023:$AI$1135,3,FALSE),0) -> 0 | M131: =IFERROR(VLOOKUP(C131,'تقرير المصروفات حسب الشهر'!$C$1150:$AD$1261,3,FALSE),0) -> 0 | N131: =IFERROR(VLOOKUP(C131,'تقرير المصروفات حسب الشهر'!$C$1277:$AD$1388,3,FALSE),0) -> 0 | O131: =IFERROR(VLOOKUP(C131,'تقرير المصروفات حسب الشهر'!$C$1404:$AI$1519,3,FALSE),0) -> 0 | P131: =SUM(D131:O131) -> 0
C132: خصم أبليكيشن | D132: =IFERROR(VLOOKUP(C132,'تقرير المصروفات حسب الشهر'!$C$10:$AD$124,3,FALSE),0) -> 535895.66 | E132: =IFERROR(VLOOKUP(C132,'تقرير المصروفات حسب الشهر'!$C$136:$AD$254,3,FALSE),0) -> 468700.24 | F132: =VLOOKUP(C132,'تقرير المصروفات حسب الشهر'!C372:AI488,3,0) -> 394321.9 | G132: =IFERROR(VLOOKUP(C132,'تقرير المصروفات حسب الشهر'!$C$391:$AD$510,3,FALSE),0) -> 486060.5 | H132: =IFERROR(VLOOKUP(C132,'تقرير المصروفات حسب الشهر'!$C$519:$AD$629,3,FALSE),0) -> 0 | I132: =IFERROR(VLOOKUP(C132,'تقرير المصروفات حسب الشهر'!$C$644:$AD$757,3,FALSE),0) -> 0 | J132: =IFERROR(VLOOKUP(C132,'تقرير المصروفات حسب الشهر'!$C$770:$AD$884,3,FALSE),0) -> 0 | K132: =IFERROR(VLOOKUP(C132,'تقرير المصروفات حسب الشهر'!$C$897:$AD$1009,3,FALSE),0) -> 0 | L132: =IFERROR(VLOOKUP(C132,'تقرير المصروفات حسب الشهر'!$C$1023:$AI$1135,3,FALSE),0) -> 0 | M132: =IFERROR(VLOOKUP(C132,'تقرير المصروفات حسب الشهر'!$C$1150:$AD$1261,3,FALSE),0) -> 0 | N132: =IFERROR(VLOOKUP(C132,'تقرير المصروفات حسب الشهر'!$C$1277:$AD$1389,3,FALSE),0) -> 0 | O132: =IFERROR(VLOOKUP(C132,'تقرير المصروفات حسب الشهر'!$C$1404:$AI$1519,3,FALSE),0) -> 0 | P132: =SUM(D132:O132) -> 1884978.3
C133: عروض مبيعات ابليكشن | D133: =IFERROR(VLOOKUP(C133,'تقرير المصروفات حسب الشهر'!$C$10:$AD$124,3,FALSE),0) -> 92639.83 | E133: =IFERROR(VLOOKUP(C133,'تقرير المصروفات حسب الشهر'!$C$136:$AD$254,3,FALSE),0) -> 51128.48 | F133: =VLOOKUP(C133,'تقرير المصروفات حسب الشهر'!C373:AI489,3,0) -> 83916.64 | G133: =IFERROR(VLOOKUP(C133,'تقرير المصروفات حسب الشهر'!$C$391:$AD$510,3,FALSE),0) -> 70668.1 | J133: =IFERROR(VLOOKUP(C133,'تقرير المصروفات حسب الشهر'!$C$770:$AD$884,3,FALSE),0) -> 0 | K133: =IFERROR(VLOOKUP(C133,'تقرير المصروفات حسب الشهر'!$C$897:$AD$1009,3,FALSE),0) -> 0 | L133: =IFERROR(VLOOKUP(C133,'تقرير المصروفات حسب الشهر'!$C$1023:$AI$1138,3,FALSE),0) -> 0 | M133: =IFERROR(VLOOKUP(C133,'تقرير المصروفات حسب الشهر'!$C$1150:$AD$1265,3,FALSE),0) -> 0 | N133: =IFERROR(VLOOKUP(C133,'تقرير المصروفات حسب الشهر'!$C$1277:$AD$1390,3,FALSE),0) -> 0 | O133: =IFERROR(VLOOKUP(C133,'تقرير المصروفات حسب الشهر'!$C$1404:$AI$1519,3,FALSE),0) -> 0
C134: إجمالي المصروفات | D134: =SUM(D22:D133) -> 1410764.5 | E134: =SUM(E22:E133) -> 1276622.2 | F134: =SUM(F22:F133) -> 1223542.9 | G134: =SUM(G22:G133) -> 1345757.6 | H134: =SUM(H22:H132) -> 612457.96 | I134: =SUM(I22:I132) -> 0 | J134: =SUM(J22:J133) -> 0 | K134: =SUM(K22:K133) -> 0 | L134: =SUM(L22:L133) -> 0 | M134: =SUM(M22:M133) -> 0 | N134: =SUM(N22:N133) -> 0 | O134: =SUM(O22:O133) -> 0 | P134: =SUM(D134:O134) -> 5869145.1
C136: مجمل الربح | D136: =D19 -> 1600095.5 | E136: =E19 -> 1313573.3 | F136: =F19 -> 1637422.3 | G136: =G19 -> 1686811.3 | H136: =H19 -> 2091319.5 | I136: =I19 -> 1000000 | J136: =J19 -> 1000000 | K136: =K19 -> 1000000 | ... O136: =O19 -> 1000000 | P136: =SUM(D136:O136) -> 15329222
C139: صافي الربح / الخسارة | D139: =D136-D134 -> 189331.03 | E139: =E136-E134 -> 36951.16 | F139: =F136-F134 -> 413879.47 | G139: =G136-G134 -> 341053.75 | H139: =H136-H134 -> 1478861.5 | I139: =I136-I134 -> 1000000 | J139: =J136-J134 -> 1000000 | K139: =K136-K134 -> 1000000 | ... O139: =O136-O134 -> 1000000 | P139: =SUM(D139:O139) -> 9460076.9

Sheet October
C2: INCOME STATEMTN
F3: Income Statement For OCTOBER
D6: Jan | E6: February | F6: March | G6: April | H6: May | I6: June | J6: July | K6: August | L6: September | M6: October | N6: November | O6: December | P6: TOTAL
C7: INCOME DETAILS
A8: اكتوبر | C8: المبيعات | D8: =D9+D10+D11 -> 6542367.1 | E8: =E9+E10+E11 -> 5567842.9 | F8: =F9+F10+F11 -> 6909065.9 | G8: =G9+G10+G11 -> 6203775.2 | H8: =H9+H10+H11 -> 6774086.1 | I8: =I9+I10+I11 -> 1000000 | J8: =J9+J10+J11 -> 1000000 | K8: =K9+K10+K11 -> 1000000 | ... O8: =O9+O10+O11 -> 1000000 | P8: =SUM(D8:O8) -> 38997137
C9: نقدى | D9: =VLOOKUP($A$8,'تقرير إحصائية بحجم المبيعات'!$B$7:$L$31,2,FALSE) -> 4179664.7 | E9: =VLOOKUP($A$8,'تقرير إحصائية بحجم المبيعات'!$B$42:$G$73,2,FALSE) -> 3665658.3 | F9: =VLOOKUP($A$8,'تقرير إحصائية بحجم المبيعات'!$B$78:$E$103,2,FALSE) -> 4504644.6 | G9: =VLOOKUP($A$8,'تقرير إحصائية بحجم المبيعات'!$B$112:$G$137,2,FALSE) -> 4047616.9 | H9: =VLOOKUP($A$8,'تقرير إحصائية بحجم المبيعات'!$B$147:$G$177,2,FALSE) -> 4597896.4 | I9: =VLOOKUP($A$8,'تقرير إحصائية بحجم المبيعات'!$B$182:$G$212,2,FALSE) -> 1000000 | J9: =VLOOKUP($A$8,'تقرير إحصائية بحجم المبيعات'!$B$217:$L$243,2,FALSE) -> 1000000 | K9: =VLOOKUP($A$8,'تقرير إحصائية بحجم المبيعات'!$B$252:$L$278,2,FALSE) -> 1000000 | L9: =VLOOKUP($A$8,'تقرير إحصائية بحجم المبيعات'!$B$287:$L$313,2,FALSE) -> 1000000 | M9: =VLOOKUP($A$8,'تقرير إحصائية بحجم المبيعات'!$B$322:$L$347,2,FALSE) -> 1000000 | N9: =VLOOKUP($A$8,'تقرير إحصائية بحجم المبيعات'!$B$357:$L$383,2,FALSE) -> 1000000 | O9: =VLOOKUP($A$8,'تقرير إحصائية بحجم المبيعات'!$B$391:$L$420,2,FALSE) -> 1000000 | P9: =SUM(D9:O9) -> 27995481
C10: دليفرى | D10: =VLOOKUP($A$8,'تقرير إحصائية بحجم المبيعات'!$B$7:$L$31,3,FALSE) -> 1925049.4 | E10: =VLOOKUP($A$8,'تقرير إحصائية بحجم المبيعات'!$B$42:$G$73,3,FALSE) -> 1506880.4 | F10: =VLOOKUP($A$8,'تقرير إحصائية بحجم المبيعات'!$B$78:$E$103,3,FALSE) -> 1935443.6 | G10: =VLOOKUP($A$8,'تقرير إحصائية بحجم المبيعات'!$B$112:$G$137,3,FALSE) -> 1790110.2 | H10: =VLOOKUP($A$8,'تقرير إحصائية بحجم المبيعات'!$B$147:$G$177,3,FALSE) -> 1743784.3 | I10: =VLOOKUP($A$8,'تقرير إحصائية بحجم المبيعات'!$B$182:$G$212,3,FALSE) -> 0 | J10: =VLOOKUP($A$8,'تقرير إحصائية بحجم المبيعات'!$B$217:$L$243,3,FALSE) -> 0 | K10: =VLOOKUP($A$8,'تقرير إحصائية بحجم المبيعات'!$B$252:$L$278,3,FALSE) -> 0 | L10: =VLOOKUP($A$8,'تقرير إحصائية بحجم المبيعات'!$B$287:$L$313,3,FALSE) -> 0 | M10: =VLOOKUP($A$8,'تقرير إحصائية بحجم المبيعات'!$B$322:$L$347,3,FALSE) -> 0 | N10: =VLOOKUP($A$8,'تقرير إحصائية بحجم المبيعات'!$B$357:$L$383,3,FALSE) -> 0 | O10: =VLOOKUP($A$8,'تقرير إحصائية بحجم المبيعات'!$B$391:$L$420,3,FALSE) -> 0 | P10: =SUM(D10:O10) -> 8901267.8
C11: اجل | D11: =VLOOKUP($A$8,'تقرير إحصائية بحجم المبيعات'!$B$7:$L$31,4,FALSE) -> 437652.99 | E11: =VLOOKUP($A$8,'تقرير إحصائية بحجم المبيعات'!$B$42:$G$73,4,FALSE) -> 395304.26 | F11: =VLOOKUP($A$8,'تقرير إحصائية بحجم المبيعات'!$B$78:$E$103,4,FALSE) -> 468977.74 | G11: =VLOOKUP($A$8,'تقرير إحصائية بحجم المبيعات'!$B$112:$G$137,4,FALSE) -> 366048.14 | H11: =VLOOKUP($A$8,'تقرير إحصائية بحجم المبيعات'!$B$147:$G$177,4,FALSE) -> 432405.42 | I11: =VLOOKUP($A$8,'تقرير إحصائية بحجم المبيعات'!$B$182:$G$212,4,FALSE) -> 0 | J11: =VLOOKUP($A$8,'تقرير إحصائية بحجم المبيعات'!$B$217:$L$243,4,FALSE) -> 0 | K11: =VLOOKUP($A$8,'تقرير إحصائية بحجم المبيعات'!$B$252:$L$278,4,FALSE) -> 0 | L11: =VLOOKUP($A$8,'تقرير إحصائية بحجم المبيعات'!$B$287:$L$313,4,FALSE) -> 0 | M11: =VLOOKUP($A$8,'تقرير إحصائية بحجم المبيعات'!$B$322:$L$347,4,FALSE) -> 0 | N11: =VLOOKUP($A$8,'تقرير إحصائية بحجم المبيعات'!$B$357:$L$383,4,FALSE) -> 0 | O11: =VLOOKUP($A$8,'تقرير إحصائية بحجم المبيعات'!$B$391:$L$420,4,FALSE) -> 0 | P11: =SUM(D11:O11) -> 2100388.5
C12: تكلفة البضاعة المباعة | D12: =VLOOKUP($A$8,'تقرير إحصائية بحجم المبيعات'!$B$7:$L$31,11,FALSE) -> 5137181.7 | E12: =VLOOKUP($A$8,'تقرير إحصائية بحجم المبيعات'!$B$42:$L$73,11,FALSE) -> 4391437 | F12: =VLOOKUP($A$8,'تقرير إحصائية بحجم المبيعات'!$B$78:$L$103,11,FALSE) -> 5479953 | G12: =VLOOKUP($A$8,'تقرير إحصائية بحجم المبيعات'!$B$112:$L$137,11,FALSE) -> 4932173 | H12: =VLOOKUP($A$8,'تقرير إحصائية بحجم المبيعات'!$B$147:$L$177,11,FALSE) -> 5281383.6 | I12: =VLOOKUP($A$8,'تقرير إحصائية بحجم المبيعات'!$B$182:$L$212,11,FALSE) -> 0 | J12: =VLOOKUP($A$8,'تقرير إحصائية بحجم المبيعات'!$B$217:$L$243,11,FALSE) -> 0 | K12: =VLOOKUP($A$8,'تقرير إحصائية بحجم المبيعات'!$B$252:$L$278,11,FALSE) -> 0 | L12: =VLOOKUP($A$8,'تقرير إحصائية بحجم المبيعات'!$B$287:$L$313,11,FALSE) -> 0 | M12: =VLOOKUP($A$8,'تقرير إحصائية بحجم المبيعات'!$B$322:$L$347,11,FALSE) -> 0 | N12: =VLOOKUP($A$8,'تقرير إحصائية بحجم المبيعات'!$B$357:$L$383,11,FALSE) -> 0 | O12: =VLOOKUP($A$8,'تقرير إحصائية بحجم المبيعات'!$B$391:$L$420,11,FALSE) -> 0 | P12: =SUM(D12:O12) -> 25222128
C13: مجمل الربح | D13: =D8-D12 -> 1405185.4 | E13: =E8-E12 -> 1176405.9 | F13: =F8-F12 -> 1429113 | G13: =G8-G12 -> 1271602.2 | H13: =H8-H12 -> 1492702.6 | I13: =I8-I12 -> 1000000 | J13: =J8-J12 -> 1000000 | K13: =K8-K12 -> 1000000 | ... O13: =O8-O12 -> 1000000 | P13: =SUM(D13:O13) -> 13775009
C14: خصم نقدى | P14: =SUM(D14:O14) -> 0
C15: ارباح صرف اصناف بيع اصول | P15: =SUM(D15:O15) -> 0
C16: فائض جرد | D16: 98.33 | E16: 6406.31 | F16: 518.69 | G16: 10212.76 | P16: =SUM(D16:O16) -> 17236.09
C17: ايرادات اخرى | P17: =SUM(D17:O17) -> 0
C18: إجمالي الايرادات اخرى | D18: =SUM(D14:D17) -> 98.33 | E18: =SUM(E14:E17) -> 6406.31 | F18: =SUM(F14:F17) -> 518.69 | G18: =SUM(G14:G17) -> 10212.76 | H18: =SUM(H14:H17) -> 0 | I18: =SUM(I14:I17) -> 0 | J18: =SUM(J14:J17) -> 0 | K18: =SUM(K14:K17) -> 0 | ... O18: =SUM(O14:O17) -> 0 | P18: =SUM(D18:O18) -> 17236.09
C19: مجمل الربح | D19: =D13+D18 -> 1405283.8 | E19: =E13+E18 -> 1182812.2 | F19: =F13+F18 -> 1429631.6 | G19: =G13+G18 -> 1281814.9 | H19: =H13+H18 -> 1492702.6 | I19: =I13+I18 -> 1000000 | J19: =J13+J18 -> 1000000 | K19: =K13+K18 -> 1000000 | ... O19: =O13+O18 -> 1000000 | P19: =SUM(D19:O19) -> 13792245
D20: =D19/D12 -> 0.2735515 | E20: =E19/E12 -> 0.26934515 | F20: =F19/F12 -> 0.26088393 | G20: =G19/G12 -> 0.25988847 | H20: =H19/H12 -> 0.28263476 | I20: =I19/I12 -> #DIV/0! | J20: =J19/J12 -> #DIV/0! | K20: =K19/K12 -> #DIV/0! | ... N20: =N19/N12 -> #DIV/0!
C21: EXPENSE DETAILS
C22: مرتبات الادارة | D22: =IFERROR(VLOOKUP(C22,'تقرير المصروفات حسب الشهر'!$C$10:$AD$119,4,FALSE),0) -> 0 | E22: =IFERROR(VLOOKUP(C22,'تقرير المصروفات حسب الشهر'!$C$136:$AD$245,4,FALSE),0) -> 0 | F22: =VLOOKUP(C22,'تقرير المصروفات حسب الشهر'!C262:AI378,4,0) -> 0 | G22: =IFERROR(VLOOKUP(C22,'تقرير المصروفات حسب الشهر'!$C$391:$AD$499,4,FALSE),0) -> 0 | H22: =IFERROR(VLOOKUP(C22,'تقرير المصروفات حسب الشهر'!$C$519:$AD$627,4,FALSE),0) -> 0 | I22: =IFERROR(VLOOKUP(C22,'تقرير المصروفات حسب الشهر'!$C$644:$AD$753,4,FALSE),0) -> 0 | J22: =IFERROR(VLOOKUP(C22,'تقرير المصروفات حسب الشهر'!$C$770:$AD$879,4,FALSE),0) -> 0 | K22: =IFERROR(VLOOKUP(C22,'تقرير المصروفات حسب الشهر'!$C$897:$AD$1006,4,FALSE),0) -> 0 | L22: =IFERROR(VLOOKUP(C22,'تقرير المصروفات حسب الشهر'!$C$1023:$AD$1133,4,FALSE),0) -> 0 | M22: =IFERROR(VLOOKUP(C22,'تقرير المصروفات حسب الشهر'!$C$1150:$AD$1261,4,FALSE),0) -> 0 | N22: =IFERROR(VLOOKUP(C22,'تقرير المصروفات حسب الشهر'!$C$1277:$AD$1388,4,FALSE),0) -> 0 | O22: =IFERROR(VLOOKUP(C22,'تقرير المصروفات حسب الشهر'!$C$1404:$AI$1519,4,FALSE),0) -> 0 | P22: =SUM(D22:O22) -> 0
C23: مرتبات الفروع | D23: =IFERROR(VLOOKUP(C23,'تقرير المصروفات حسب الشهر'!$C$10:$AD$119,4,FALSE),0) -> 452230.06 | E23: =IFERROR(VLOOKUP(C23,'تقرير المصروفات حسب الشهر'!$C$136:$AD$245,4,FALSE),0) -> 425317.24 | F23: =VLOOKUP(C23,'تقرير المصروفات حسب الشهر'!C263:AI379,4,0) -> 424039.38 | G23: =IFERROR(VLOOKUP(C23,'تقرير المصروفات حسب الشهر'!$C$391:$AD$499,4,FALSE),0) -> 448660.76 | H23: =IFERROR(VLOOKUP(C23,'تقرير المصروفات حسب الشهر'!$C$519:$AD$627,4,FALSE),0) -> 347225.62 | I23: =IFERROR(VLOOKUP(C23,'تقرير المصروفات حسب الشهر'!$C$644:$AD$753,4,FALSE),0) -> 0 | J23: =IFERROR(VLOOKUP(C23,'تقرير المصروفات حسب الشهر'!$C$770:$AD$879,4,FALSE),0) -> 0 | K23: =IFERROR(VLOOKUP(C23,'تقرير المصروفات حسب الشهر'!$C$897:$AD$1006,4,FALSE),0) -> 0 | L23: =IFERROR(VLOOKUP(C23,'تقرير المصروفات حسب الشهر'!$C$1023:$AD$1133,4,FALSE),0) -> 0 | M23: =IFERROR(VLOOKUP(C23,'تقرير المصروفات حسب الشهر'!$C$1150:$AD$1261,4,FALSE),0) -> 0 | N23: =IFERROR(VLOOKUP(C23,'تقرير المصروفات حسب الشهر'!$C$1277:$AD$1388,4,FALSE),0) -> 0 | O23: =IFERROR(VLOOKUP(C23,'تقرير المصروفات حسب الشهر'!$C$1404:$AI$1519,4,FALSE),0) -> 0 | P23: =SUM(D23:O23) -> 2097473.1
C24: الكهرباء | D24: =IFERROR(VLOOKUP(C24,'تقرير المصروفات حسب الشهر'!$C$10:$AD$119,4,FALSE),0) -> 3555 | E24: =IFERROR(VLOOKUP(C24,'تقرير المصروفات حسب الشهر'!$C$136:$AD$245,4,FALSE),0) -> 0 | F24: =VLOOKUP(C24,'تقرير المصروفات حسب الشهر'!C264:AI380,4,0) -> 4050 | G24: =IFERROR(VLOOKUP(C24,'تقرير المصروفات حسب الشهر'!$C$391:$AD$499,4,FALSE),0) -> 1000 | H24: =IFERROR(VLOOKUP(C24,'تقرير المصروفات حسب الشهر'!$C$519:$AD$627,4,FALSE),0) -> 6756 | I24: =IFERROR(VLOOKUP(C24,'تقرير المصروفات حسب الشهر'!$C$644:$AD$753,4,FALSE),0) -> 0 | J24: =IFERROR(VLOOKUP(C24,'تقرير المصروفات حسب الشهر'!$C$770:$AD$879,4,FALSE),0) -> 0 | K24: =IFERROR(VLOOKUP(C24,'تقرير المصروفات حسب الشهر'!$C$897:$AD$1006,4,FALSE),0) -> 0 | L24: =IFERROR(VLOOKUP(C24,'تقرير المصروفات حسب الشهر'!$C$1023:$AD$1133,4,FALSE),0) -> 0 | M24: =IFERROR(VLOOKUP(C24,'تقرير المصروفات حسب الشهر'!$C$1150:$AD$1261,4,FALSE),0) -> 0 | N24: =IFERROR(VLOOKUP(C24,'تقرير المصروفات حسب الشهر'!$C$1277:$AD$1388,4,FALSE),0) -> 0 | O24: =IFERROR(VLOOKUP(C24,'تقرير المصروفات حسب الشهر'!$C$1404:$AI$1519,4,FALSE),0) -> 0 | P24: =SUM(D24:O24) -> 15361
C25: المياه | D25: =IFERROR(VLOOKUP(C25,'تقرير المصروفات حسب الشهر'!$C$10:$AD$119,4,FALSE),0) -> 0 | E25: =IFERROR(VLOOKUP(C25,'تقرير المصروفات حسب الشهر'!$C$136:$AD$245,4,FALSE),0) -> 0 | F25: =VLOOKUP(C25,'تقرير المصروفات حسب الشهر'!C265:AI381,4,0) -> 0 | G25: =IFERROR(VLOOKUP(C25,'تقرير المصروفات حسب الشهر'!$C$391:$AD$499,4,FALSE),0) -> 0 | H25: =IFERROR(VLOOKUP(C25,'تقرير المصروفات حسب الشهر'!$C$519:$AD$627,4,FALSE),0) -> 0 | I25: =IFERROR(VLOOKUP(C25,'تقرير المصروفات حسب الشهر'!$C$644:$AD$753,4,FALSE),0) -> 0 | J25: =IFERROR(VLOOKUP(C25,'تقرير المصروفات حسب الشهر'!$C$770:$AD$879,4,FALSE),0) -> 0 | K25: =IFERROR(VLOOKUP(C25,'تقرير المصروفات حسب الشهر'!$C$897:$AD$1006,4,FALSE),0) -> 0 | L25: =IFERROR(VLOOKUP(C25,'تقرير المصروفات حسب الشهر'!$C$1023:$AD$1133,4,FALSE),0) -> 0 | M25: =IFERROR(VLOOKUP(C25,'تقرير المصروفات حسب الشهر'!$C$1150:$AD$1261,4,FALSE),0) -> 0 | N25: =IFERROR(VLOOKUP(C25,'تقرير المصروفات حسب الشهر'!$C$1277:$AD$1388,4,FALSE),0) -> 0 | O25: =IFERROR(VLOOKUP(C25,'تقرير المصروفات حسب الشهر'!$C$1404:$AI$1519,4,FALSE),0) -> 0 | P25: =SUM(D25:O25) -> 0
C26: التليفون الارضي | D26: =IFERROR(VLOOKUP(C26,'تقرير المصروفات حسب الشهر'!$C$10:$AD$119,4,FALSE),0) -> 0 | E26: =IFERROR(VLOOKUP(C26,'تقرير المصروفات حسب الشهر'!$C$136:$AD$245,4,FALSE),0) -> 1700 | F26: =VLOOKUP(C26,'تقرير المصروفات حسب الشهر'!C266:AI382,4,0) -> 0 | G26: =IFERROR(VLOOKUP(C26,'تقرير المصروفات حسب الشهر'!$C$391:$AD$499,4,FALSE),0) -> 0 | H26: =IFERROR(VLOOKUP(C26,'تقرير المصروفات حسب الشهر'!$C$519:$AD$627,4,FALSE),0) -> 0 | I26: =IFERROR(VLOOKUP(C26,'تقرير المصروفات حسب الشهر'!$C$644:$AD$753,4,FALSE),0) -> 0 | J26: =IFERROR(VLOOKUP(C26,'تقرير المصروفات حسب الشهر'!$C$770:$AD$879,4,FALSE),0) -> 0 | K26: =IFERROR(VLOOKUP(C26,'تقرير المصروفات حسب الشهر'!$C$897:$AD$1006,4,FALSE),0) -> 0 | L26: =IFERROR(VLOOKUP(C26,'تقرير المصروفات حسب الشهر'!$C$1023:$AD$1133,4,FALSE),0) -> 0 | M26: =IFERROR(VLOOKUP(C26,'تقرير المصروفات حسب الشهر'!$C$1150:$AD$1261,4,FALSE),0) -> 0 | N26: =IFERROR(VLOOKUP(C26,'تقرير المصروفات حسب الشهر'!$C$1277:$AD$1388,4,FALSE),0) -> 0 | O26: =IFERROR(VLOOKUP(C26,'تقرير المصروفات حسب الشهر'!$C$1404:$AI$1519,4,FALSE),0) -> 0 | P26: =SUM(D26:O26) -> 1700
C27: الايجار - الصيدلية | D27: =IFERROR(VLOOKUP(C27,'تقرير المصروفات حسب الشهر'!$C$10:$AD$119,4,FALSE),0) -> 170000 | E27: =IFERROR(VLOOKUP(C27,'تقرير المصروفات حسب الشهر'!$C$136:$AD$245,4,FALSE),0) -> 170000 | F27: =VLOOKUP(C27,'تقرير المصروفات حسب الشهر'!C267:AI383,4,0) -> 170000 | G27: =IFERROR(VLOOKUP(C27,'تقرير المصروفات حسب الشهر'!$C$391:$AD$499,4,FALSE),0) -> 170000 | H27: =IFERROR(VLOOKUP(C27,'تقرير المصروفات حسب الشهر'!$C$519:$AD$627,4,FALSE),0) -> 170000 | I27: =IFERROR(VLOOKUP(C27,'تقرير المصروفات حسب الشهر'!$C$644:$AD$753,4,FALSE),0) -> 0 | J27: =IFERROR(VLOOKUP(C27,'تقرير المصروفات حسب الشهر'!$C$770:$AD$879,4,FALSE),0) -> 0 | K27: =IFERROR(VLOOKUP(C27,'تقرير المصروفات حسب الشهر'!$C$897:$AD$1006,4,FALSE),0) -> 0 | L27: =IFERROR(VLOOKUP(C27,'تقرير المصروفات حسب الشهر'!$C$1023:$AD$1133,4,FALSE),0) -> 0 | M27: =IFERROR(VLOOKUP(C27,'تقرير المصروفات حسب الشهر'!$C$1150:$AD$1261,4,FALSE),0) -> 0 | N27: =IFERROR(VLOOKUP(C27,'تقرير المصروفات حسب الشهر'!$C$1277:$AD$1388,4,FALSE),0) -> 0 | O27: =IFERROR(VLOOKUP(C27,'تقرير المصروفات حسب الشهر'!$C$1404:$AI$1519,4,FALSE),0) -> 0 | P27: =SUM(D27:O27) -> 850000
C28: الايجار - الادارة | D28: =IFERROR(VLOOKUP(C28,'تقرير المصروفات حسب الشهر'!$C$10:$AD$119,4,FALSE),0) -> 0 | E28: =IFERROR(VLOOKUP(C28,'تقرير المصروفات حسب الشهر'!$C$136:$AD$245,4,FALSE),0) -> 0 | F28: =VLOOKUP(C28,'تقرير المصروفات حسب الشهر'!C268:AI384,4,0) -> 0 | G28: =IFERROR(VLOOKUP(C28,'تقرير المصروفات حسب الشهر'!$C$391:$AD$499,4,FALSE),0) -> 0 | H28: =IFERROR(VLOOKUP(C28,'تقرير المصروفات حسب الشهر'!$C$519:$AD$627,4,FALSE),0) -> 0 | I28: =IFERROR(VLOOKUP(C28,'تقرير المصروفات حسب الشهر'!$C$644:$AD$753,4,FALSE),0) -> 0 | J28: =IFERROR(VLOOKUP(C28,'تقرير المصروفات حسب الشهر'!$C$770:$AD$879,4,FALSE),0) -> 0 | K28: =IFERROR(VLOOKUP(C28,'تقرير المصروفات حسب الشهر'!$C$897:$AD$1006,4,FALSE),0) -> 0 | L28: =IFERROR(VLOOKUP(C28,'تقرير المصروفات حسب الشهر'!$C$1023:$AD$1133,4,FALSE),0) -> 0 | M28: =IFERROR(VLOOKUP(C28,'تقرير المصروفات حسب الشهر'!$C$1150:$AD$1261,4,FALSE),0) -> 0 | N28: =IFERROR(VLOOKUP(C28,'تقرير المصروفات حسب الشهر'!$C$1277:$AD$1388,4,FALSE),0) -> 0 | O28: =IFERROR(VLOOKUP(C28,'تقرير المصروفات حسب الشهر'!$C$1404:$AI$1519,4,FALSE),0) -> 0 | P28: =SUM(D28:O28) -> 0
C29: ايجارات متنوعه | D29: =IFERROR(VLOOKUP(C29,'تقرير المصروفات حسب الشهر'!$C$10:$AD$119,4,FALSE),0) -> 23200 | E29: =IFERROR(VLOOKUP(C29,'تقرير المصروفات حسب الشهر'!$C$136:$AD$245,4,FALSE),0) -> 23200 | F29: =VLOOKUP(C29,'تقرير المصروفات حسب الشهر'!C269:AI385,4,0) -> 23200 | G29: =IFERROR(VLOOKUP(C29,'تقرير المصروفات حسب الشهر'!$C$391:$AD$499,4,FALSE),0) -> 23200 | H29: =IFERROR(VLOOKUP(C29,'تقرير المصروفات حسب الشهر'!$C$519:$AD$627,4,FALSE),0) -> 23200 | I29: =IFERROR(VLOOKUP(C29,'تقرير المصروفات حسب الشهر'!$C$644:$AD$753,4,FALSE),0) -> 0 | J29: =IFERROR(VLOOKUP(C29,'تقرير المصروفات حسب الشهر'!$C$770:$AD$879,4,FALSE),0) -> 0 | K29: =IFERROR(VLOOKUP(C29,'تقرير المصروفات حسب الشهر'!$C$897:$AD$1006,4,FALSE),0) -> 0 | L29: =IFERROR(VLOOKUP(C29,'تقرير المصروفات حسب الشهر'!$C$1023:$AD$1133,4,FALSE),0) -> 0 | M29: =IFERROR(VLOOKUP(C29,'تقرير المصروفات حسب الشهر'!$C$1150:$AD$1261,4,FALSE),0) -> 0 | N29: =IFERROR(VLOOKUP(C29,'تقرير المصروفات حسب الشهر'!$C$1277:$AD$1388,4,FALSE),0) -> 0 | O29: =IFERROR(VLOOKUP(C29,'تقرير المصروفات حسب الشهر'!$C$1404:$AI$1519,4,FALSE),0) -> 0 | P29: =SUM(D29:O29) -> 116000
C30: ادوات مكتبية | D30: =IFERROR(VLOOKUP(C30,'تقرير المصروفات حسب الشهر'!$C$10:$AD$119,4,FALSE),0) -> 0 | E30: =IFERROR(VLOOKUP(C30,'تقرير المصروفات حسب الشهر'!$C$136:$AD$245,4,FALSE),0) -> 0 | F30: =VLOOKUP(C30,'تقرير المصروفات حسب الشهر'!C270:AI386,4,0) -> 1320 | G30: =IFERROR(VLOOKUP(C30,'تقرير المصروفات حسب الشهر'!$C$391:$AD$499,4,FALSE),0) -> 0 | H30: =IFERROR(VLOOKUP(C30,'تقرير المصروفات حسب الشهر'!$C$519:$AD$627,4,FALSE),0) -> 1365 | I30: =IFERROR(VLOOKUP(C30,'تقرير المصروفات حسب الشهر'!$C$644:$AD$753,4,FALSE),0) -> 0 | J30: =IFERROR(VLOOKUP(C30,'تقرير المصروفات حسب الشهر'!$C$770:$AD$879,4,FALSE),0) -> 0 | K30: =IFERROR(VLOOKUP(C30,'تقرير المصروفات حسب الشهر'!$C$897:$AD$1006,4,FALSE),0) -> 0 | L30: =IFERROR(VLOOKUP(C30,'تقرير المصروفات حسب الشهر'!$C$1023:$AD$1133,4,FALSE),0) -> 0 | M30: =IFERROR(VLOOKUP(C30,'تقرير المصروفات حسب الشهر'!$C$1150:$AD$1261,4,FALSE),0) -> 0 | N30: =IFERROR(VLOOKUP(C30,'تقرير المصروفات حسب الشهر'!$C$1277:$AD$1388,4,FALSE),0) -> 0 | O30: =IFERROR(VLOOKUP(C30,'تقرير المصروفات حسب الشهر'!$C$1404:$AI$1519,4,FALSE),0) -> 0 | P30: =SUM(D30:O30) -> 2685
C31: فواتير الموبايل | D31: =IFERROR(VLOOKUP(C31,'تقرير المصروفات حسب الشهر'!$C$10:$AD$119,4,FALSE),0) -> 100 | E31: =IFERROR(VLOOKUP(C31,'تقرير المصروفات حسب الشهر'!$C$136:$AD$245,4,FALSE),0) -> 670 | F31: =VLOOKUP(C31,'تقرير المصروفات حسب الشهر'!C271:AI387,4,0) -> 365 | G31: =IFERROR(VLOOKUP(C31,'تقرير المصروفات حسب الشهر'!$C$391:$AD$499,4,FALSE),0) -> 390 | H31: =IFERROR(VLOOKUP(C31,'تقرير المصروفات حسب الشهر'!$C$519:$AD$627,4,FALSE),0) -> 450 | I31: =IFERROR(VLOOKUP(C31,'تقرير المصروفات حسب الشهر'!$C$644:$AD$753,4,FALSE),0) -> 0 | J31: =IFERROR(VLOOKUP(C31,'تقرير المصروفات حسب الشهر'!$C$770:$AD$879,4,FALSE),0) -> 0 | K31: =IFERROR(VLOOKUP(C31,'تقرير المصروفات حسب الشهر'!$C$897:$AD$1006,4,FALSE),0) -> 0 | L31: =IFERROR(VLOOKUP(C31,'تقرير المصروفات حسب الشهر'!$C$1023:$AD$1133,4,FALSE),0) -> 0 | M31: =IFERROR(VLOOKUP(C31,'تقرير المصروفات حسب الشهر'!$C$1150:$AD$1261,4,FALSE),0) -> 0 | N31: =IFERROR(VLOOKUP(C31,'تقرير المصروفات حسب الشهر'!$C$1277:$AD$1388,4,FALSE),0) -> 0 | O31: =IFERROR(VLOOKUP(C31,'تقرير المصروفات حسب الشهر'!$C$1404:$AI$1519,4,FALSE),0) -> 0 | P31: =SUM(D31:O31) -> 1975
C32: مكافات مبيعات الادوية | D32: =IFERROR(VLOOKUP(C32,'تقرير المصروفات حسب الشهر'!$C$10:$AD$119,4,FALSE),0) -> 0 | E32: =IFERROR(VLOOKUP(C32,'تقرير المصروفات حسب الشهر'!$C$136:$AD$245,4,FALSE),0) -> 0 | F32: =VLOOKUP(C32,'تقرير المصروفات حسب الشهر'!C272:AI388,4,0) -> 0 | G32: =IFERROR(VLOOKUP(C32,'تقرير المصروفات حسب الشهر'!$C$391:$AD$499,4,FALSE),0) -> 0 | H32: =IFERROR(VLOOKUP(C32,'تقرير المصروفات حسب الشهر'!$C$519:$AD$627,4,FALSE),0) -> 0 | I32: =IFERROR(VLOOKUP(C32,'تقرير المصروفات حسب الشهر'!$C$644:$AD$753,4,FALSE),0) -> 0 | J32: =IFERROR(VLOOKUP(C32,'تقرير المصروفات حسب الشهر'!$C$770:$AD$879,4,FALSE),0) -> 0 | K32: =IFERROR(VLOOKUP(C32,'تقرير المصروفات حسب الشهر'!$C$897:$AD$1006,4,FALSE),0) -> 0 | L32: =IFERROR(VLOOKUP(C32,'تقرير المصروفات حسب الشهر'!$C$1023:$AD$1133,4,FALSE),0) -> 0 | M32: =IFERROR(VLOOKUP(C32,'تقرير المصروفات حسب الشهر'!$C$1150:$AD$1261,4,FALSE),0) -> 0 | N32: =IFERROR(VLOOKUP(C32,'تقرير المصروفات حسب الشهر'!$C$1277:$AD$1388,4,FALSE),0) -> 0 | O32: =IFERROR(VLOOKUP(C32,'تقرير المصروفات حسب الشهر'!$C$1404:$AI$1519,4,FALSE),0) -> 0 | P32: =SUM(D32:O32) -> 0
C33: مكافات مبيعات التجميل | D33: =IFERROR(VLOOKUP(C33,'تقرير المصروفات حسب الشهر'!$C$10:$AD$119,4,FALSE),0) -> 400 | E33: =IFERROR(VLOOKUP(C33,'تقرير المصروفات حسب الشهر'!$C$136:$AD$245,4,FALSE),0) -> 1465 | F33: =VLOOKUP(C33,'تقرير المصروفات حسب الشهر'!C273:AI389,4,0) -> 0 | G33: =IFERROR(VLOOKUP(C33,'تقرير المصروفات حسب الشهر'!$C$391:$AD$499,4,FALSE),0) -> 0 | H33: =IFERROR(VLOOKUP(C33,'تقرير المصروفات حسب الشهر'!$C$519:$AD$627,4,FALSE),0) -> 0 | I33: =IFERROR(VLOOKUP(C33,'تقرير المصروفات حسب الشهر'!$C$644:$AD$753,4,FALSE),0) -> 0 | J33: =IFERROR(VLOOKUP(C33,'تقرير المصروفات حسب الشهر'!$C$770:$AD$879,4,FALSE),0) -> 0 | K33: =IFERROR(VLOOKUP(C33,'تقرير المصروفات حسب الشهر'!$C$897:$AD$1006,4,FALSE),0) -> 0 | L33: =IFERROR(VLOOKUP(C33,'تقرير المصروفات حسب الشهر'!$C$1023:$AD$1133,4,FALSE),0) -> 0 | M33: =IFERROR(VLOOKUP(C33,'تقرير المصروفات حسب الشهر'!$C$1150:$AD$1261,4,FALSE),0) -> 0 | N33: =IFERROR(VLOOKUP(C33,'تقرير المصروفات حسب الشهر'!$C$1277:$AD$1388,4,FALSE),0) -> 0 | O33: =IFERROR(VLOOKUP(C33,'تقرير المصروفات حسب الشهر'!$C$1404:$AI$1519,4,FALSE),0) -> 0 | P33: =SUM(D33:O33) -> 1865
... C129: تأمينات اجتماعية - حصة الشركة | D129: =IFERROR(VLOOKUP(C129,'تقرير المصروفات حسب الشهر'!$C$10:$AD$119,4,FALSE),0) -> 4050 | E129: =IFERROR(VLOOKUP(C129,'تقرير المصروفات حسب الشهر'!$C$136:$AD$245,4,FALSE),0) -> 4050 | F129: =VLOOKUP(C129,'تقرير المصروفات حسب الشهر'!C369:AI485,4,0) -> 4050 | G129: =IFERROR(VLOOKUP(C129,'تقرير المصروفات حسب الشهر'!$C$391:$AD$499,4,FALSE),0) -> 4050 | H129: =IFERROR(VLOOKUP(C129,'تقرير المصروفات حسب الشهر'!$C$519:$AD$627,4,FALSE),0) -> 0 | I129: =IFERROR(VLOOKUP(C129,'تقرير المصروفات حسب الشهر'!$C$644:$AD$753,4,FALSE),0) -> 0 | J129: =IFERROR(VLOOKUP(C129,'تقرير المصروفات حسب الشهر'!$C$770:$AD$879,4,FALSE),0) -> 0 | K129: =IFERROR(VLOOKUP(C129,'تقرير المصروفات حسب الشهر'!$C$897:$AD$1006,4,FALSE),0) -> 0 | L129: =IFERROR(VLOOKUP(C129,'تقرير المصروفات حسب الشهر'!$C$1023:$AD$1133,4,FALSE),0) -> 0 | M129: =IFERROR(VLOOKUP(C129,'تقرير المصروفات حسب الشهر'!$C$1150:$AD$1261,4,FALSE),0) -> 0 | N129: =IFERROR(VLOOKUP(C129,'تقرير المصروفات حسب الشهر'!$C$1277:$AD$1388,4,FALSE),0) -> 0 | O129: =IFERROR(VLOOKUP(C129,'تقرير المصروفات حسب الشهر'!$C$1404:$AI$1519,4,FALSE),0) -> 0 | P129: =SUM(D129:O129) -> 16200
C130: فوائد القروض - التجارى وفا بنك AWB | D130: =IFERROR(VLOOKUP(C130,'تقرير المصروفات حسب الشهر'!$C$10:$AD$119,4,FALSE),0) -> 0 | E130: =IFERROR(VLOOKUP(C130,'تقرير المصروفات حسب الشهر'!$C$136:$AD$245,4,FALSE),0) -> 0 | F130: =VLOOKUP(C130,'تقرير المصروفات حسب الشهر'!C370:AI486,4,0) -> 0 | G130: =IFERROR(VLOOKUP(C130,'تقرير المصروفات حسب الشهر'!$C$391:$AD$499,4,FALSE),0) -> 0 | H130: =IFERROR(VLOOKUP(C130,'تقرير المصروفات حسب الشهر'!$C$519:$AD$627,4,FALSE),0) -> 0 | I130: =IFERROR(VLOOKUP(C130,'تقرير المصروفات حسب الشهر'!$C$644:$AD$753,4,FALSE),0) -> 0 | J130: =IFERROR(VLOOKUP(C130,'تقرير المصروفات حسب الشهر'!$C$770:$AD$879,4,FALSE),0) -> 0 | K130: =IFERROR(VLOOKUP(C130,'تقرير المصروفات حسب الشهر'!$C$897:$AD$1006,4,FALSE),0) -> 0 | L130: =IFERROR(VLOOKUP(C130,'تقرير المصروفات حسب الشهر'!$C$1023:$AI$1135,4,FALSE),0) -> 0 | M130: =IFERROR(VLOOKUP(C130,'تقرير المصروفات حسب الشهر'!$C$1150:$AD$1261,4,FALSE),0) -> 0 | N130: =IFERROR(VLOOKUP(C130,'تقرير المصروفات حسب الشهر'!$C$1277:$AD$1388,4,FALSE),0) -> 0 | O130: =IFERROR(VLOOKUP(C130,'تقرير المصروفات حسب الشهر'!$C$1404:$AI$1519,4,FALSE),0) -> 0 | P130: =SUM(D130:O130) -> 0
C131: فوائد القروض - بنك القاهرة BDC | D131: =IFERROR(VLOOKUP(C131,'تقرير المصروفات حسب الشهر'!$C$10:$AD$119,4,FALSE),0) -> 0 | E131: =IFERROR(VLOOKUP(C131,'تقرير المصروفات حسب الشهر'!$C$136:$AD$245,4,FALSE),0) -> 0 | F131: =VLOOKUP(C131,'تقرير المصروفات حسب الشهر'!C371:AI487,4,0) -> 0 | G131: =IFERROR(VLOOKUP(C131,'تقرير المصروفات حسب الشهر'!$C$391:$AD$499,4,FALSE),0) -> 0 | H131: =IFERROR(VLOOKUP(C131,'تقرير المصروفات حسب الشهر'!$C$519:$AD$627,4,FALSE),0) -> 0 | I131: =IFERROR(VLOOKUP(C131,'تقرير المصروفات حسب الشهر'!$C$644:$AD$753,4,FALSE),0) -> 0 | J131: =IFERROR(VLOOKUP(C131,'تقرير المصروفات حسب الشهر'!$C$770:$AD$879,4,FALSE),0) -> 0 | K131: =IFERROR(VLOOKUP(C131,'تقرير المصروفات حسب الشهر'!$C$897:$AD$1006,4,FALSE),0) -> 0 | L131: =IFERROR(VLOOKUP(C131,'تقرير المصروفات حسب الشهر'!$C$1023:$AI$1135,4,FALSE),0) -> 0 | M131: =IFERROR(VLOOKUP(C131,'تقرير المصروفات حسب الشهر'!$C$1150:$AD$1261,4,FALSE),0) -> 0 | N131: =IFERROR(VLOOKUP(C131,'تقرير المصروفات حسب الشهر'!$C$1277:$AD$1388,4,FALSE),0) -> 0 | O131: =IFERROR(VLOOKUP(C131,'تقرير المصروفات حسب الشهر'!$C$1404:$AI$1519,4,FALSE),0) -> 0 | P131: =SUM(D131:O131) -> 0
C132: خصم أبليكيشن | D132: =IFERROR(VLOOKUP(C132,'تقرير المصروفات حسب الشهر'!$C$10:$AD$124,4,FALSE),0) -> 338754.84 | E132: =IFERROR(VLOOKUP(C132,'تقرير المصروفات حسب الشهر'!$C$136:$AD$254,4,FALSE),0) -> 314332.47 | F132: =VLOOKUP(C132,'تقرير المصروفات حسب الشهر'!C372:AI488,4,0) -> 298117.41 | G132: =IFERROR(VLOOKUP(C132,'تقرير المصروفات حسب الشهر'!$C$391:$AD$510,4,FALSE),0) -> 342595.48 | H132: =IFERROR(VLOOKUP(C132,'تقرير المصروفات حسب الشهر'!$C$519:$AD$629,4,FALSE),0) -> 0 | I132: =IFERROR(VLOOKUP(C132,'تقرير المصروفات حسب الشهر'!$C$644:$AD$757,4,FALSE),0) -> 0 | J132: =IFERROR(VLOOKUP(C132,'تقرير المصروفات حسب الشهر'!$C$770:$AD$884,4,FALSE),0) -> 0 | K132: =IFERROR(VLOOKUP(C132,'تقرير المصروفات حسب الشهر'!$C$897:$AD$1009,4,FALSE),0) -> 0 | L132: =IFERROR(VLOOKUP(C132,'تقرير المصروفات حسب الشهر'!$C$1023:$AI$1135,4,FALSE),0) -> 0 | M132: =IFERROR(VLOOKUP(C132,'تقرير المصروفات حسب الشهر'!$C$1150:$AD$1261,4,FALSE),0) -> 0 | N132: =IFERROR(VLOOKUP(C132,'تقرير المصروفات حسب الشهر'!$C$1277:$AD$1389,4,FALSE),0) -> 0 | O132: =IFERROR(VLOOKUP(C132,'تقرير المصروفات حسب الشهر'!$C$1404:$AI$1519,4,FALSE),0) -> 0 | P132: =SUM(D132:O132) -> 1293800.2
C133: عروض مبيعات ابليكشن | D133: =IFERROR(VLOOKUP(C133,'تقرير المصروفات حسب الشهر'!$C$10:$AD$124,4,FALSE),0) -> 82640.29 | E133: =IFERROR(VLOOKUP(C133,'تقرير المصروفات حسب الشهر'!$C$136:$AD$254,4,FALSE),0) -> 61474.83 | F133: =VLOOKUP(C133,'تقرير المصروفات حسب الشهر'!C373:AI489,4,0) -> 97840.19 | G133: =IFERROR(VLOOKUP(C133,'تقرير المصروفات حسب الشهر'!$C$391:$AD$510,4,FALSE),0) -> 77232.79 | J133: =IFERROR(VLOOKUP(C133,'تقرير المصروفات حسب الشهر'!$C$770:$AD$884,4,FALSE),0) -> 0 | K133: =IFERROR(VLOOKUP(C133,'تقرير المصروفات حسب الشهر'!$C$897:$AD$1009,4,FALSE),0) -> 0 | L133: =IFERROR(VLOOKUP(C133,'تقرير المصروفات حسب الشهر'!$C$1023:$AI$1138,4,FALSE),0) -> 0 | M133: =IFERROR(VLOOKUP(C133,'تقرير المصروفات حسب الشهر'!$C$1150:$AD$1265,4,FALSE),0) -> 0 | N133: =IFERROR(VLOOKUP(C133,'تقرير المصروفات حسب الشهر'!$C$1277:$AI$1395,4,FALSE),0) -> 0 | O133: =IFERROR(VLOOKUP(C133,'تقرير المصروفات حسب الشهر'!$C$1404:$AI$1519,4,FALSE),0) -> 0
C134: إجمالي المصروفات | D134: =SUM(D22:D133) -> 1193812 | E134: =SUM(E22:E133) -> 1105411.5 | F134: =SUM(F22:F133) -> 1131065 | G134: =SUM(G22:G133) -> 1195858.3 | H134: =SUM(H22:H133) -> 642797.12 | I134: =SUM(I22:I133) -> 0 | J134: =SUM(J22:J133) -> 0 | K134: =SUM(K22:K133) -> 0 | ... O134: =SUM(O22:O133) -> 0 | P134: =SUM(D134:O134) -> 5268943.8
C136: مجمل الربح | D136: =D19 -> 1405283.8 | E136: =E19 -> 1182812.2 | F136: =F19 -> 1429631.6 | G136: =G19 -> 1281814.9 | H136: =H19 -> 1492702.6 | I136: =I19 -> 1000000 | J136: =J19 -> 1000000 | K136: =K19 -> 1000000 | ... O136: =O19 -> 1000000 | P136: =SUM(D136:O136) -> 13792245
C139: صافي الربح / الخسارة | D139: =D136-D134 -> 211471.8 | E139: =E136-E134 -> 77400.76 | F139: =F136-F134 -> 298566.61 | G139: =G136-G134 -> 85956.65 | H139: =H136-H134 -> 849905.44 | I139: =I136-I134 -> 1000000 | J139: =J136-J134 -> 1000000 | K139: =K136-K134 -> 1000000 | ... O139: =O136-O134 -> 1000000 | P139: =SUM(D139:O139) -> 8523301.3
D143: =211471.8-D139 -> 0 | G143: =85956.65-G139 -> -3.783498e-10

Sheet Batal
C2: INCOME STATEMTN
F3: Income Statement For Batal
D6: Jan | E6: February | F6: March | G6: April | H6: May | I6: June | J6: July | K6: August | L6: September | M6: October | N6: November | O6: December | P6: TOTAL
C7: INCOME DETAILS
A8: البطل | C8: المبيعات | D8: =D9+D10+D11 -> 4219483.2 | E8: =E9+E10+E11 -> 3218448.5 | F8: =F9+F10+F11 -> 3869133 | G8: =G9+G10+G11 -> 4194375 | H8: =H9+H10+H11 -> 4393530.5 | I8: =I9+I10+I11 -> 1000000 | J8: =J9+J10+J11 -> 1000000 | K8: =K9+K10+K11 -> 1000000 | ... O8: =O9+O10+O11 -> 1000000 | P8: =SUM(D8:O8) -> 26894970
C9: نقدى | D9: =VLOOKUP($A$8,'تقرير إحصائية بحجم المبيعات'!$B$7:$L$31,2,FALSE) -> 2157000.6 | E9: =VLOOKUP($A$8,'تقرير إحصائية بحجم المبيعات'!$B$42:$G$73,2,FALSE) -> 1652999.2 | F9: =VLOOKUP($A$8,'تقرير إحصائية بحجم المبيعات'!$B$78:$E$103,2,FALSE) -> 1698348 | G9: =VLOOKUP($A$8,'تقرير إحصائية بحجم المبيعات'!$B$112:$G$137,2,FALSE) -> 2078989.3 | H9: =VLOOKUP($A$8,'تقرير إحصائية بحجم المبيعات'!$B$147:$G$177,2,FALSE) -> 2281682.5 | I9: =VLOOKUP($A$8,'تقرير إحصائية بحجم المبيعات'!$B$182:$G$212,2,FALSE) -> 1000000 | J9: =VLOOKUP($A$8,'تقرير إحصائية بحجم المبيعات'!$B$217:$L$243,2,FALSE) -> 1000000 | K9: =VLOOKUP($A$8,'تقرير إحصائية بحجم المبيعات'!$B$252:$L$278,2,FALSE) -> 1000000 | L9: =VLOOKUP($A$8,'تقرير إحصائية بحجم المبيعات'!$B$287:$L$313,2,FALSE) -> 1000000 | M9: =VLOOKUP($A$8,'تقرير إحصائية بحجم المبيعات'!$B$322:$L$347,2,FALSE) -> 1000000 | N9: =VLOOKUP($A$8,'تقرير إحصائية بحجم المبيعات'!$B$357:$L$383,2,FALSE) -> 1000000 | O9: =VLOOKUP($A$8,'تقرير إحصائية بحجم المبيعات'!$B$391:$L$420,2,FALSE) -> 1000000 | P9: =SUM(D9:O9) -> 16869020
C10: دليفرى | D10: =VLOOKUP($A$8,'تقرير إحصائية بحجم المبيعات'!$B$7:$L$31,3,FALSE) -> 620723.23 | E10: =VLOOKUP($A$8,'تقرير إحصائية بحجم المبيعات'!$B$42:$G$73,3,FALSE) -> 441172.37 | F10: =VLOOKUP($A$8,'تقرير إحصائية بحجم المبيعات'!$B$78:$E$103,3,FALSE) -> 574992.46 | G10: =VLOOKUP($A$8,'تقرير إحصائية بحجم المبيعات'!$B$112:$G$137,3,FALSE) -> 652463.44 | H10: =VLOOKUP($A$8,'تقرير إحصائية بحجم المبيعات'!$B$147:$G$177,3,FALSE) -> 564017.35 | I10: =VLOOKUP($A$8,'تقرير إحصائية بحجم المبيعات'!$B$182:$G$212,3,FALSE) -> 0 | J10: =VLOOKUP($A$8,'تقرير إحصائية بحجم المبيعات'!$B$217:$L$243,3,FALSE) -> 0 | K10: =VLOOKUP($A$8,'تقرير إحصائية بحجم المبيعات'!$B$252:$L$278,3,FALSE) -> 0 | L10: =VLOOKUP($A$8,'تقرير إحصائية بحجم المبيعات'!$B$287:$L$313,3,FALSE) -> 0 | M10: =VLOOKUP($A$8,'تقرير إحصائية بحجم المبيعات'!$B$322:$L$347,3,FALSE) -> 0 | N10: =VLOOKUP($A$8,'تقرير إحصائية بحجم المبيعات'!$B$357:$L$383,3,FALSE) -> 0 | O10: =VLOOKUP($A$8,'تقرير إحصائية بحجم المبيعات'!$B$391:$L$420,3,FALSE) -> 0 | P10: =SUM(D10:O10) -> 2853368.9
C11: اجل | D11: =VLOOKUP($A$8,'تقرير إحصائية بحجم المبيعات'!$B$7:$L$31,4,FALSE) -> 1441759.4 | E11: =VLOOKUP($A$8,'تقرير إحصائية بحجم المبيعات'!$B$42:$G$73,4,FALSE) -> 1124276.9 | F11: =VLOOKUP($A$8,'تقرير إحصائية بحجم المبيعات'!$B$78:$E$103,4,FALSE) -> 1595792.5 | G11: =VLOOKUP($A$8,'تقرير إحصائية بحجم المبيعات'!$B$112:$G$137,4,FALSE) -> 1462922.2 | H11: =VLOOKUP($A$8,'تقرير إحصائية بحجم المبيعات'!$B$147:$G$177,4,FALSE) -> 1547830.7 | I11: =VLOOKUP($A$8,'تقرير إحصائية بحجم المبيعات'!$B$182:$G$212,4,FALSE) -> 0 | J11: =VLOOKUP($A$8,'تقرير إحصائية بحجم المبيعات'!$B$217:$L$243,4,FALSE) -> 0 | K11: =VLOOKUP($A$8,'تقرير إحصائية بحجم المبيعات'!$B$252:$L$278,4,FALSE) -> 0 | L11: =VLOOKUP($A$8,'تقرير إحصائية بحجم المبيعات'!$B$287:$L$313,4,FALSE) -> 0 | M11: =VLOOKUP($A$8,'تقرير إحصائية بحجم المبيعات'!$B$322:$L$347,4,FALSE) -> 0 | N11: =VLOOKUP($A$8,'تقرير إحصائية بحجم المبيعات'!$B$357:$L$383,4,FALSE) -> 0 | O11: =VLOOKUP($A$8,'تقرير إحصائية بحجم المبيعات'!$B$391:$L$420,4,FALSE) -> 0 | P11: =SUM(D11:O11) -> 7172581.7
C12: تكلفة البضاعة المباعة | D12: =VLOOKUP($A$8,'تقرير إحصائية بحجم المبيعات'!$B$7:$L$31,11,FALSE) -> 3382313.2 | E12: =VLOOKUP($A$8,'تقرير إحصائية بحجم المبيعات'!$B$42:$L$73,11,FALSE) -> 2553456.9 | F12: =VLOOKUP($A$8,'تقرير إحصائية بحجم المبيعات'!$B$78:$L$103,11,FALSE) -> 3092649.6 | G12: =VLOOKUP($A$8,'تقرير إحصائية بحجم المبيعات'!$B$112:$L$137,11,FALSE) -> 3291739.3 | H12: =VLOOKUP($A$8,'تقرير إحصائية بحجم المبيعات'!$B$147:$L$177,11,FALSE) -> 3468541.9 | I12: =VLOOKUP($A$8,'تقرير إحصائية بحجم المبيعات'!$B$182:$L$212,11,FALSE) -> 0 | J12: =VLOOKUP($A$8,'تقرير إحصائية بحجم المبيعات'!$B$217:$L$243,11,FALSE) -> 0 | K12: =VLOOKUP($A$8,'تقرير إحصائية بحجم المبيعات'!$B$252:$L$278,11,FALSE) -> 0 | L12: =VLOOKUP($A$8,'تقرير إحصائية بحجم المبيعات'!$B$287:$L$313,11,FALSE) -> 0 | M12: =VLOOKUP($A$8,'تقرير إحصائية بحجم المبيعات'!$B$322:$L$347,11,FALSE) -> 0 | N12: =VLOOKUP($A$8,'تقرير إحصائية بحجم المبيعات'!$B$357:$L$383,11,FALSE) -> 0 | O12: =VLOOKUP($A$8,'تقرير إحصائية بحجم المبيعات'!$B$391:$L$420,11,FALSE) -> 0 | P12: =SUM(D12:O12) -> 15788701
C13: مجمل الربح | D13: =D8-D12 -> 837170.03 | E13: =E8-E12 -> 664991.56 | F13: =F8-F12 -> 776483.36 | G13: =G8-G12 -> 902635.7 | H13: =H8-H12 -> 924988.6 | I13: =I8-I12 -> 1000000 | J13: =J8-J12 -> 1000000 | K13: =K8-K12 -> 1000000 | ... O13: =O8-O12 -> 1000000 | P13: =SUM(D13:O13) -> 11106269
C14: خصم نقدى | P14: =SUM(D14:O14) -> 0
C15: ارباح صرف اصناف بيع اصول | P15: =SUM(D15:O15) -> 0
C16: فائض جرد | D16: 0 | E16: 7150.6 | G16: 3932.06 | P16: =SUM(D16:O16) -> 11082.66
C17: ايرادات اخرى | P17: =SUM(D17:O17) -> 0
C18: إجمالي الايرادات اخرى | D18: =SUM(D14:D17) -> 0 | E18: =SUM(E14:E17) -> 7150.6 | F18: =SUM(F14:F17) -> 0 | G18: =SUM(G14:G17) -> 3932.06 | H18: =SUM(H14:H17) -> 0 | I18: =SUM(I14:I17) -> 0 | J18: =SUM(J14:J17) -> 0 | K18: =SUM(K14:K17) -> 0 | ... O18: =SUM(O14:O17) -> 0 | P18: =SUM(D18:O18) -> 11082.66
C19: مجمل الربح | D19: =D13+D18 -> 837170.03 | E19: =E13+E18 -> 672142.16 | F19: =F13+F18 -> 776483.36 | G19: =G13+G18 -> 906567.76 | H19: =H13+H18 -> 924988.6 | I19: =I13+I18 -> 1000000 | J19: =J13+J18 -> 1000000 | K19: =K13+K18 -> 1000000 | ... O19: =O13+O18 -> 1000000 | P19: =SUM(D19:O19) -> 11117352
C21: EXPENSE DETAILS
C22: مرتبات الادارة | D22: =IFERROR(VLOOKUP(C22,'تقرير المصروفات حسب الشهر'!$C$10:$AD$119,5,FALSE),0) -> 0 | E22: =IFERROR(VLOOKUP(C22,'تقرير المصروفات حسب الشهر'!$C$136:$AD$245,5,FALSE),0) -> 0 | F22: =VLOOKUP(C22,'تقرير المصروفات حسب الشهر'!C262:AI378,5,0) -> 0 | G22: =IFERROR(VLOOKUP(C22,'تقرير المصروفات حسب الشهر'!$C$391:$AD$499,5,FALSE),0) -> 0 | H22: =IFERROR(VLOOKUP(C22,'تقرير المصروفات حسب الشهر'!$C$519:$AD$627,5,FALSE),0) -> 0 | I22: =IFERROR(VLOOKUP(C22,'تقرير المصروفات حسب الشهر'!$C$644:$AD$753,5,FALSE),0) -> 0 | J22: =IFERROR(VLOOKUP(C22,'تقرير المصروفات حسب الشهر'!$C$770:$AD$879,5,FALSE),0) -> 0 | K22: =IFERROR(VLOOKUP(C22,'تقرير المصروفات حسب الشهر'!$C$897:$AD$1006,5,FALSE),0) -> 0 | L22: =IFERROR(VLOOKUP(C22,'تقرير المصروفات حسب الشهر'!$C$1023:$AD$1133,5,FALSE),0) -> 0 | M22: =IFERROR(VLOOKUP(C22,'تقرير المصروفات حسب الشهر'!$C$1150:$AD$1261,5,FALSE),0) -> 0 | N22: =IFERROR(VLOOKUP(C22,'تقرير المصروفات حسب الشهر'!$C$1277:$AD$1388,5,FALSE),0) -> 0 | O22: =IFERROR(VLOOKUP(C22,'تقرير المصروفات حسب الشهر'!$C$1404:$AD$1519,5,FALSE),0) -> 0 | P22: =SUM(D22:O22) -> 0
C23: مرتبات الفروع | D23: =IFERROR(VLOOKUP(C23,'تقرير المصروفات حسب الشهر'!$C$10:$AD$119,5,FALSE),0) -> 275232.51 | E23: =IFERROR(VLOOKUP(C23,'تقرير المصروفات حسب الشهر'!$C$136:$AD$245,5,FALSE),0) -> 249954.32 | F23: =VLOOKUP(C23,'تقرير المصروفات حسب الشهر'!C263:AI379,5,0) -> 260080.1 | G23: =IFERROR(VLOOKUP(C23,'تقرير المصروفات حسب الشهر'!$C$391:$AD$499,5,FALSE),0) -> 274699.26 | H23: =IFERROR(VLOOKUP(C23,'تقرير المصروفات حسب الشهر'!$C$519:$AD$627,5,FALSE),0) -> 29014.29 | I23: =IFERROR(VLOOKUP(C23,'تقرير المصروفات حسب الشهر'!$C$644:$AD$753,5,FALSE),0) -> 0 | J23: =IFERROR(VLOOKUP(C23,'تقرير المصروفات حسب الشهر'!$C$770:$AD$879,5,FALSE),0) -> 0 | K23: =IFERROR(VLOOKUP(C23,'تقرير المصروفات حسب الشهر'!$C$897:$AD$1006,5,FALSE),0) -> 0 | L23: =IFERROR(VLOOKUP(C23,'تقرير المصروفات حسب الشهر'!$C$1023:$AD$1133,5,FALSE),0) -> 0 | M23: =IFERROR(VLOOKUP(C23,'تقرير المصروفات حسب الشهر'!$C$1150:$AD$1261,5,FALSE),0) -> 0 | N23: =IFERROR(VLOOKUP(C23,'تقرير المصروفات حسب الشهر'!$C$1277:$AD$1388,5,FALSE),0) -> 0 | O23: =IFERROR(VLOOKUP(C23,'تقرير المصروفات حسب الشهر'!$C$1404:$AD$1519,5,FALSE),0) -> 0 | P23: =SUM(D23:O23) -> 1088980.5
C24: الكهرباء | D24: =IFERROR(VLOOKUP(C24,'تقرير المصروفات حسب الشهر'!$C$10:$AD$119,5,FALSE),0) -> 7115 | E24: =IFERROR(VLOOKUP(C24,'تقرير المصروفات حسب الشهر'!$C$136:$AD$245,5,FALSE),0) -> 6355 | F24: =VLOOKUP(C24,'تقرير المصروفات حسب الشهر'!C264:AI380,5,0) -> 6271 | G24: =IFERROR(VLOOKUP(C24,'تقرير المصروفات حسب الشهر'!$C$391:$AD$499,5,FALSE),0) -> 5103 | H24: =IFERROR(VLOOKUP(C24,'تقرير المصروفات حسب الشهر'!$C$519:$AD$627,5,FALSE),0) -> 6975 | I24: =IFERROR(VLOOKUP(C24,'تقرير المصروفات حسب الشهر'!$C$644:$AD$753,5,FALSE),0) -> 0 | J24: =IFERROR(VLOOKUP(C24,'تقرير المصروفات حسب الشهر'!$C$770:$AD$879,5,FALSE),0) -> 0 | K24: =IFERROR(VLOOKUP(C24,'تقرير المصروفات حسب الشهر'!$C$897:$AD$1006,5,FALSE),0) -> 0 | L24: =IFERROR(VLOOKUP(C24,'تقرير المصروفات حسب الشهر'!$C$1023:$AD$1133,5,FALSE),0) -> 0 | M24: =IFERROR(VLOOKUP(C24,'تقرير المصروفات حسب الشهر'!$C$1150:$AD$1261,5,FALSE),0) -> 0 | N24: =IFERROR(VLOOKUP(C24,'تقرير المصروفات حسب الشهر'!$C$1277:$AD$1388,5,FALSE),0) -> 0 | O24: =IFERROR(VLOOKUP(C24,'تقرير المصروفات حسب الشهر'!$C$1404:$AD$1519,5,FALSE),0) -> 0 | P24: =SUM(D24:O24) -> 31819
C25: المياه | D25: =IFERROR(VLOOKUP(C25,'تقرير المصروفات حسب الشهر'!$C$10:$AD$119,5,FALSE),0) -> 230 | E25: =IFERROR(VLOOKUP(C25,'تقرير المصروفات حسب الشهر'!$C$136:$AD$245,5,FALSE),0) -> 85 | F25: =VLOOKUP(C25,'تقرير المصروفات حسب الشهر'!C265:AI381,5,0) -> 108 | G25: =IFERROR(VLOOKUP(C25,'تقرير المصروفات حسب الشهر'!$C$391:$AD$499,5,FALSE),0) -> 108 | H25: =IFERROR(VLOOKUP(C25,'تقرير المصروفات حسب الشهر'!$C$519:$AD$627,5,FALSE),0) -> 130 | I25: =IFERROR(VLOOKUP(C25,'تقرير المصروفات حسب الشهر'!$C$644:$AD$753,5,FALSE),0) -> 0 | J25: =IFERROR(VLOOKUP(C25,'تقرير المصروفات حسب الشهر'!$C$770:$AD$879,5,FALSE),0) -> 0 | K25: =IFERROR(VLOOKUP(C25,'تقرير المصروفات حسب الشهر'!$C$897:$AD$1006,5,FALSE),0) -> 0 | L25: =IFERROR(VLOOKUP(C25,'تقرير المصروفات حسب الشهر'!$C$1023:$AD$1133,5,FALSE),0) -> 0 | M25: =IFERROR(VLOOKUP(C25,'تقرير المصروفات حسب الشهر'!$C$1150:$AD$1261,5,FALSE),0) -> 0 | N25: =IFERROR(VLOOKUP(C25,'تقرير المصروفات حسب الشهر'!$C$1277:$AD$1388,5,FALSE),0) -> 0 | O25: =IFERROR(VLOOKUP(C25,'تقرير المصروفات حسب الشهر'!$C$1404:$AD$1519,5,FALSE),0) -> 0 | P25: =SUM(D25:O25) -> 661
C26: التليفون الارضي | D26: =IFERROR(VLOOKUP(C26,'تقرير المصروفات حسب الشهر'!$C$10:$AD$119,5,FALSE),0) -> 0 | E26: =IFERROR(VLOOKUP(C26,'تقرير المصروفات حسب الشهر'!$C$136:$AD$245,5,FALSE),0) -> 1200 | F26: =VLOOKUP(C26,'تقرير المصروفات حسب الشهر'!C266:AI382,5,0) -> 0 | G26: =IFERROR(VLOOKUP(C26,'تقرير المصروفات حسب الشهر'!$C$391:$AD$499,5,FALSE),0) -> 0 | H26: =IFERROR(VLOOKUP(C26,'تقرير المصروفات حسب الشهر'!$C$519:$AD$627,5,FALSE),0) -> 0 | I26: =IFERROR(VLOOKUP(C26,'تقرير المصروفات حسب الشهر'!$C$644:$AD$753,5,FALSE),0) -> 0 | J26: =IFERROR(VLOOKUP(C26,'تقرير المصروفات حسب الشهر'!$C$770:$AD$879,5,FALSE),0) -> 0 | K26: =IFERROR(VLOOKUP(C26,'تقرير المصروفات حسب الشهر'!$C$897:$AD$1006,5,FALSE),0) -> 0 | L26: =IFERROR(VLOOKUP(C26,'تقرير المصروفات حسب الشهر'!$C$1023:$AD$1133,5,FALSE),0) -> 0 | M26: =IFERROR(VLOOKUP(C26,'تقرير المصروفات حسب الشهر'!$C$1150:$AD$1261,5,FALSE),0) -> 0 | N26: =IFERROR(VLOOKUP(C26,'تقرير المصروفات حسب الشهر'!$C$1277:$AD$1388,5,FALSE),0) -> 0 | O26: =IFERROR(VLOOKUP(C26,'تقرير المصروفات حسب الشهر'!$C$1404:$AD$1519,5,FALSE),0) -> 0 | P26: =SUM(D26:O26) -> 1200
C27: الايجار - الصيدلية | D27: =IFERROR(VLOOKUP(C27,'تقرير المصروفات حسب الشهر'!$C$10:$AD$119,5,FALSE),0) -> 170000 | E27: =IFERROR(VLOOKUP(C27,'تقرير المصروفات حسب الشهر'!$C$136:$AD$245,5,FALSE),0) -> 170000 | F27: =VLOOKUP(C27,'تقرير المصروفات حسب الشهر'!C267:AI383,5,0) -> 170000 | G27: =IFERROR(VLOOKUP(C27,'تقرير المصروفات حسب الشهر'!$C$391:$AD$499,5,FALSE),0) -> 170000 | H27: =IFERROR(VLOOKUP(C27,'تقرير المصروفات حسب الشهر'!$C$519:$AD$627,5,FALSE),0) -> 170000 | I27: =IFERROR(VLOOKUP(C27,'تقرير المصروفات حسب الشهر'!$C$644:$AD$753,5,FALSE),0) -> 0 | J27: =IFERROR(VLOOKUP(C27,'تقرير المصروفات حسب الشهر'!$C$770:$AD$879,5,FALSE),0) -> 0 | K27: =IFERROR(VLOOKUP(C27,'تقرير المصروفات حسب الشهر'!$C$897:$AD$1006,5,FALSE),0) -> 0 | L27: =IFERROR(VLOOKUP(C27,'تقرير المصروفات حسب الشهر'!$C$1023:$AD$1133,5,FALSE),0) -> 0 | M27: =IFERROR(VLOOKUP(C27,'تقرير المصروفات حسب الشهر'!$C$1150:$AD$1261,5,FALSE),0) -> 0 | N27: =IFERROR(VLOOKUP(C27,'تقرير المصروفات حسب الشهر'!$C$1277:$AD$1388,5,FALSE),0) -> 0 | O27: =IFERROR(VLOOKUP(C27,'تقرير المصروفات حسب الشهر'!$C$1404:$AD$1519,5,FALSE),0) -> 0 | P27: =SUM(D27:O27) -> 850000
C28: الايجار - الادارة | D28: =IFERROR(VLOOKUP(C28,'تقرير المصروفات حسب الشهر'!$C$10:$AD$119,5,FALSE),0) -> 0 | E28: =IFERROR(VLOOKUP(C28,'تقرير المصروفات حسب الشهر'!$C$136:$AD$245,5,FALSE),0) -> 0 | F28: =VLOOKUP(C28,'تقرير المصروفات حسب الشهر'!C268:AI384,5,0) -> 0 | G28: =IFERROR(VLOOKUP(C28,'تقرير المصروفات حسب الشهر'!$C$391:$AD$499,5,FALSE),0) -> 0 | H28: =IFERROR(VLOOKUP(C28,'تقرير المصروفات حسب الشهر'!$C$519:$AD$627,5,FALSE),0) -> 0 | I28: =IFERROR(VLOOKUP(C28,'تقرير المصروفات حسب الشهر'!$C$644:$AD$753,5,FALSE),0) -> 0 | J28: =IFERROR(VLOOKUP(C28,'تقرير المصروفات حسب الشهر'!$C$770:$AD$879,5,FALSE),0) -> 0 | K28: =IFERROR(VLOOKUP(C28,'تقرير المصروفات حسب الشهر'!$C$897:$AD$1006,5,FALSE),0) -> 0 | L28: =IFERROR(VLOOKUP(C28,'تقرير المصروفات حسب الشهر'!$C$1023:$AD$1133,5,FALSE),0) -> 0 | M28: =IFERROR(VLOOKUP(C28,'تقرير المصروفات حسب الشهر'!$C$1150:$AD$1261,5,FALSE),0) -> 0 | N28: =IFERROR(VLOOKUP(C28,'تقرير المصروفات حسب الشهر'!$C$1277:$AD$1388,5,FALSE),0) -> 0 | O28: =IFERROR(VLOOKUP(C28,'تقرير المصروفات حسب الشهر'!$C$1404:$AD$1519,5,FALSE),0) -> 0 | P28: =SUM(D28:O28) -> 0
C29: ايجارات متنوعه | D29: =IFERROR(VLOOKUP(C29,'تقرير المصروفات حسب الشهر'!$C$10:$AD$119,5,FALSE),0) -> 0 | E29: =IFERROR(VLOOKUP(C29,'تقرير المصروفات حسب الشهر'!$C$136:$AD$245,5,FALSE),0) -> 0 | F29: =VLOOKUP(C29,'تقرير المصروفات حسب الشهر'!C269:AI385,5,0) -> 0 | G29: =IFERROR(VLOOKUP(C29,'تقرير المصروفات حسب الشهر'!$C$391:$AD$499,5,FALSE),0) -> 0 | H29: =IFERROR(VLOOKUP(C29,'تقرير المصروفات حسب الشهر'!$C$519:$AD$627,5,FALSE),0) -> 0 | I29: =IFERROR(VLOOKUP(C29,'تقرير المصروفات حسب الشهر'!$C$644:$AD$753,5,FALSE),0) -> 0 | J29: =IFERROR(VLOOKUP(C29,'تقرير المصروفات حسب الشهر'!$C$770:$AD$879,5,FALSE),0) -> 0 | K29: =IFERROR(VLOOKUP(C29,'تقرير المصروفات حسب الشهر'!$C$897:$AD$1006,5,FALSE),0) -> 0 | L29: =IFERROR(VLOOKUP(C29,'تقرير المصروفات حسب الشهر'!$C$1023:$AD$1133,5,FALSE),0) -> 0 | M29: =IFERROR(VLOOKUP(C29,'تقرير المصروفات حسب الشهر'!$C$1150:$AD$1261,5,FALSE),0) -> 0 | N29: =IFERROR(VLOOKUP(C29,'تقرير المصروفات حسب الشهر'!$C$1277:$AD$1388,5,FALSE),0) -> 0 | O29: =IFERROR(VLOOKUP(C29,'تقرير المصروفات حسب الشهر'!$C$1404:$AD$1519,5,FALSE),0) -> 0 | P29: =SUM(D29:O29) -> 0
C30: ادوات مكتبية | D30: =IFERROR(VLOOKUP(C30,'تقرير المصروفات حسب الشهر'!$C$10:$AD$119,5,FALSE),0) -> 0 | E30: =IFERROR(VLOOKUP(C30,'تقرير المصروفات حسب الشهر'!$C$136:$AD$245,5,FALSE),0) -> 0 | F30: =VLOOKUP(C30,'تقرير المصروفات حسب الشهر'!C270:AI386,5,0) -> 870 | G30: =IFERROR(VLOOKUP(C30,'تقرير المصروفات حسب الشهر'!$C$391:$AD$499,5,FALSE),0) -> 50 | H30: =IFERROR(VLOOKUP(C30,'تقرير المصروفات حسب الشهر'!$C$519:$AD$627,5,FALSE),0) -> 1100 | I30: =IFERROR(VLOOKUP(C30,'تقرير المصروفات حسب الشهر'!$C$644:$AD$753,5,FALSE),0) -> 0 | J30: =IFERROR(VLOOKUP(C30,'تقرير المصروفات حسب الشهر'!$C$770:$AD$879,5,FALSE),0) -> 0 | K30: =IFERROR(VLOOKUP(C30,'تقرير المصروفات حسب الشهر'!$C$897:$AD$1006,5,FALSE),0) -> 0 | L30: =IFERROR(VLOOKUP(C30,'تقرير المصروفات حسب الشهر'!$C$1023:$AD$1133,5,FALSE),0) -> 0 | M30: =IFERROR(VLOOKUP(C30,'تقرير المصروفات حسب الشهر'!$C$1150:$AD$1261,5,FALSE),0) -> 0 | N30: =IFERROR(VLOOKUP(C30,'تقرير المصروفات حسب الشهر'!$C$1277:$AD$1388,5,FALSE),0) -> 0 | O30: =IFERROR(VLOOKUP(C30,'تقرير المصروفات حسب الشهر'!$C$1404:$AD$1519,5,FALSE),0) -> 0 | P30: =SUM(D30:O30) -> 2020
C31: فواتير الموبايل | D31: =IFERROR(VLOOKUP(C31,'تقرير المصروفات حسب الشهر'!$C$10:$AD$119,5,FALSE),0) -> 444.46 | E31: =IFERROR(VLOOKUP(C31,'تقرير المصروفات حسب الشهر'!$C$136:$AD$245,5,FALSE),0) -> 444.46 | F31: =VLOOKUP(C31,'تقرير المصروفات حسب الشهر'!C271:AI387,5,0) -> 444.46 | G31: =IFERROR(VLOOKUP(C31,'تقرير المصروفات حسب الشهر'!$C$391:$AD$499,5,FALSE),0) -> 444.46 | H31: =IFERROR(VLOOKUP(C31,'تقرير المصروفات حسب الشهر'!$C$519:$AD$627,5,FALSE),0) -> 656.46 | I31: =IFERROR(VLOOKUP(C31,'تقرير المصروفات حسب الشهر'!$C$644:$AD$753,5,FALSE),0) -> 0 | J31: =IFERROR(VLOOKUP(C31,'تقرير المصروفات حسب الشهر'!$C$770:$AD$879,5,FALSE),0) -> 0 | K31: =IFERROR(VLOOKUP(C31,'تقرير المصروفات حسب الشهر'!$C$897:$AD$1006,5,FALSE),0) -> 0 | L31: =IFERROR(VLOOKUP(C31,'تقرير المصروفات حسب الشهر'!$C$1023:$AD$1133,5,FALSE),0) -> 0 | M31: =IFERROR(VLOOKUP(C31,'تقرير المصروفات حسب الشهر'!$C$1150:$AD$1261,5,FALSE),0) -> 0 | N31: =IFERROR(VLOOKUP(C31,'تقرير المصروفات حسب الشهر'!$C$1277:$AD$1388,5,FALSE),0) -> 0 | O31: =IFERROR(VLOOKUP(C31,'تقرير المصروفات حسب الشهر'!$C$1404:$AD$1519,5,FALSE),0) -> 0 | P31: =SUM(D31:O31) -> 2434.3
C32: مكافات مبيعات الادوية | D32: =IFERROR(VLOOKUP(C32,'تقرير المصروفات حسب الشهر'!$C$10:$AD$119,5,FALSE),0) -> 0 | E32: =IFERROR(VLOOKUP(C32,'تقرير المصروفات حسب الشهر'!$C$136:$AD$245,5,FALSE),0) -> 0 | F32: =VLOOKUP(C32,'تقرير المصروفات حسب الشهر'!C272:AI388,5,0) -> 0 | G32: =IFERROR(VLOOKUP(C32,'تقرير المصروفات حسب الشهر'!$C$391:$AD$499,5,FALSE),0) -> 0 | H32: =IFERROR(VLOOKUP(C32,'تقرير المصروفات حسب الشهر'!$C$519:$AD$627,5,FALSE),0) -> 0 | I32: =IFERROR(VLOOKUP(C32,'تقرير المصروفات حسب الشهر'!$C$644:$AD$753,5,FALSE),0) -> 0 | J32: =IFERROR(VLOOKUP(C32,'تقرير المصروفات حسب الشهر'!$C$770:$AD$879,5,FALSE),0) -> 0 | K32: =IFERROR(VLOOKUP(C32,'تقرير المصروفات حسب الشهر'!$C$897:$AD$1006,5,FALSE),0) -> 0 | L32: =IFERROR(VLOOKUP(C32,'تقرير المصروفات حسب الشهر'!$C$1023:$AD$1133,5,FALSE),0) -> 0 | M32: =IFERROR(VLOOKUP(C32,'تقرير المصروفات حسب الشهر'!$C$1150:$AD$1261,5,FALSE),0) -> 0 | N32: =IFERROR(VLOOKUP(C32,'تقرير المصروفات حسب الشهر'!$C$1277:$AD$1388,5,FALSE),0) -> 0 | O32: =IFERROR(VLOOKUP(C32,'تقرير المصروفات حسب الشهر'!$C$1404:$AD$1519,5,FALSE),0) -> 0 | P32: =SUM(D32:O32) -> 0
C33: مكافات مبيعات التجميل | D33: =IFERROR(VLOOKUP(C33,'تقرير المصروفات حسب الشهر'!$C$10:$AD$119,5,FALSE),0) -> 0 | E33: =IFERROR(VLOOKUP(C33,'تقرير المصروفات حسب الشهر'!$C$136:$AD$245,5,FALSE),0) -> 0 | F33: =VLOOKUP(C33,'تقرير المصروفات حسب الشهر'!C273:AI389,5,0) -> 0 | G33: =IFERROR(VLOOKUP(C33,'تقرير المصروفات حسب الشهر'!$C$391:$AD$499,5,FALSE),0) -> 0 | H33: =IFERROR(VLOOKUP(C33,'تقرير المصروفات حسب الشهر'!$C$519:$AD$627,5,FALSE),0) -> 1055 | I33: =IFERROR(VLOOKUP(C33,'تقرير المصروفات حسب الشهر'!$C$644:$AD$753,5,FALSE),0) -> 0 | J33: =IFERROR(VLOOKUP(C33,'تقرير المصروفات حسب الشهر'!$C$770:$AD$879,5,FALSE),0) -> 0 | K33: =IFERROR(VLOOKUP(C33,'تقرير المصروفات حسب الشهر'!$C$897:$AD$1006,5,FALSE),0) -> 0 | L33: =IFERROR(VLOOKUP(C33,'تقرير المصروفات حسب الشهر'!$C$1023:$AD$1133,5,FALSE),0) -> 0 | M33: =IFERROR(VLOOKUP(C33,'تقرير المصروفات حسب الشهر'!$C$1150:$AD$1261,5,FALSE),0) -> 0 | N33: =IFERROR(VLOOKUP(C33,'تقرير المصروفات حسب الشهر'!$C$1277:$AD$1388,5,FALSE),0) -> 0 | O33: =IFERROR(VLOOKUP(C33,'تقرير المصروفات حسب الشهر'!$C$1404:$AD$1519,5,FALSE),0) -> 0 | P33: =SUM(D33:O33) -> 1055
... C131: فوائد القروض - بنك القاهرة BDC | D131: =IFERROR(VLOOKUP(C131,'تقرير المصروفات حسب الشهر'!$C$10:$AD$119,5,FALSE),0) -> 0 | E131: =IFERROR(VLOOKUP(C131,'تقرير المصروفات حسب الشهر'!$C$136:$AD$245,5,FALSE),0) -> 0 | F131: =VLOOKUP(C131,'تقرير المصروفات حسب الشهر'!C371:AI487,5,0) -> 0 | G131: =IFERROR(VLOOKUP(C131,'تقرير المصروفات حسب الشهر'!$C$391:$AD$499,5,FALSE),0) -> 0 | H131: =IFERROR(VLOOKUP(C131,'تقرير المصروفات حسب الشهر'!$C$519:$AD$627,5,FALSE),0) -> 0 | I131: =IFERROR(VLOOKUP(C131,'تقرير المصروفات حسب الشهر'!$C$644:$AD$753,5,FALSE),0) -> 0 | J131: =IFERROR(VLOOKUP(C131,'تقرير المصروفات حسب الشهر'!$C$770:$AD$879,5,FALSE),0) -> 0 | K131: =IFERROR(VLOOKUP(C131,'تقرير المصروفات حسب الشهر'!$C$897:$AD$1006,5,FALSE),0) -> 0 | L131: =IFERROR(VLOOKUP(C131,'تقرير المصروفات حسب الشهر'!$C$1023:$AD$1133,5,FALSE),0) -> 0 | M131: =IFERROR(VLOOKUP(C131,'تقرير المصروفات حسب الشهر'!$C$1150:$AD$1261,5,FALSE),0) -> 0 | N131: =IFERROR(VLOOKUP(C131,'تقرير المصروفات حسب الشهر'!$C$1277:$AD$1388,5,FALSE),0) -> 0 | O131: =IFERROR(VLOOKUP(C131,'تقرير المصروفات حسب الشهر'!$C$1404:$AD$1519,5,FALSE),0) -> 0 | P131: =SUM(D131:O131) -> 0
C132: خصم أبليكيشن | D132: =IFERROR(VLOOKUP(C132,'تقرير المصروفات حسب الشهر'!$C$10:$AD$119,5,FALSE),0) -> 0 | E132: =IFERROR(VLOOKUP(C132,'تقرير المصروفات حسب الشهر'!$C$136:$AD$254,5,FALSE),0) -> 0 | F132: =VLOOKUP(C132,'تقرير المصروفات حسب الشهر'!C372:AI488,5,0) -> 0 | G132: =IFERROR(VLOOKUP(C132,'تقرير المصروفات حسب الشهر'!$C$391:$AD$510,5,FALSE),0) -> 0 | H132: =IFERROR(VLOOKUP(C132,'تقرير المصروفات حسب الشهر'!$C$519:$AD$627,5,FALSE),0) -> 0 | I132: =IFERROR(VLOOKUP(C132,'تقرير المصروفات حسب الشهر'!$C$644:$AD$753,5,FALSE),0) -> 0 | J132: =IFERROR(VLOOKUP(C132,'تقرير المصروفات حسب الشهر'!$C$770:$AD$879,5,FALSE),0) -> 0 | K132: =IFERROR(VLOOKUP(C132,'تقرير المصروفات حسب الشهر'!$C$897:$AD$1006,5,FALSE),0) -> 0 | L132: =IFERROR(VLOOKUP(C132,'تقرير المصروفات حسب الشهر'!$C$1023:$AD$1133,5,FALSE),0) -> 0 | M132: =IFERROR(VLOOKUP(C132,'تقرير المصروفات حسب الشهر'!$C$1150:$AD$1261,5,FALSE),0) -> 0 | N132: =IFERROR(VLOOKUP(C132,'تقرير المصروفات حسب الشهر'!$C$1277:$AD$1389,5,FALSE),0) -> 0 | O132: =IFERROR(VLOOKUP(C132,'تقرير المصروفات حسب الشهر'!$C$1404:$AD$1519,5,FALSE),0) -> 0 | P132: =SUM(D132:O132) -> 0
C133: إجمالي المصروفات | D133: =SUM(D22:D132) -> 583846.86 | E133: =SUM(E22:E132) -> 550262.55 | F133: =SUM(F22:F132) -> 554770.46 | G133: =SUM(G22:G132) -> 599813.37 | H133: =SUM(H22:H132) -> 264953.75 | I133: =SUM(I22:I132) -> 0 | J133: =SUM(J22:J132) -> 0 | K133: =SUM(K22:K132) -> 0 | ... O133: =SUM(O22:O132) -> 0 | P133: =SUM(D133:O133) -> 2553647
C135: مجمل الربح | D135: =D19 -> 837170.03 | E135: =E19 -> 672142.16 | F135: =F19 -> 776483.36 | G135: =G19 -> 906567.76 | H135: =H19 -> 924988.6 | I135: =I19 -> 1000000 | J135: =J19 -> 1000000 | K135: =K19 -> 1000000 | ... O135: =O19 -> 1000000 | P135: =SUM(D135:O135) -> 11117352
C138: صافي الربح / الخسارة | D138: =D135-D133 -> 253323.17 | E138: =E135-E133 -> 121879.61 | F138: =F135-F133 -> 221712.9 | G138: =G135-G133 -> 306754.39 | H138: =H135-H133 -> 660034.85 | I138: =I135-I133 -> 1000000 | J138: =J135-J133 -> 1000000 | K138: =K135-K133 -> 1000000 | ... O138: =O135-O133 -> 1000000 | P138: =SUM(D138:O138) -> 8563704.9

Sheet Nasr City
C2: INCOME STATEMTN
F3: Income Statement For Nasr City
D6: Jan | E6: February | F6: March | G6: April | H6: May | I6: June | J6: July | K6: August | L6: September | M6: October | N6: November | O6: December | P6: TOTAL
C7: INCOME DETAILS
A8: م.نصر | C8: المبيعات | D8: =D9+D10+D11 -> 9245620.6 | E8: =E9+E10+E11 -> 8242666.4 | F8: =F9+F10+F11 -> 10096832 | G8: =G9+G10+G11 -> 10883655 | H8: =H9+H10+H11 -> 10949322 | I8: =I9+I10+I11 -> 1000000 | J8: =J9+J10+J11 -> 1000000 | K8: =K9+K10+K11 -> 1000000 | ... O8: =O9+O10+O11 -> 1000000 | P8: =SUM(D8:O8) -> 56418096
C9: نقدى | D9: =VLOOKUP($A$8,'تقرير إحصائية بحجم المبيعات'!$B$7:$L$31,2,FALSE) -> 6344504.4 | E9: =VLOOKUP($A$8,'تقرير إحصائية بحجم المبيعات'!$B$42:$G$73,2,FALSE) -> 5866764.8 | F9: =VLOOKUP($A$8,'تقرير إحصائية بحجم المبيعات'!$B$78:$E$103,2,FALSE) -> 7499614.8 | G9: =VLOOKUP($A$8,'تقرير إحصائية بحجم المبيعات'!$B$112:$G$137,2,FALSE) -> 8095806 | H9: =VLOOKUP($A$8,'تقرير إحصائية بحجم المبيعات'!$B$147:$G$177,2,FALSE) -> 8004534.2 | I9: =VLOOKUP($A$8,'تقرير إحصائية بحجم المبيعات'!$B$182:$G$212,2,FALSE) -> 1000000 | J9: =VLOOKUP($A$8,'تقرير إحصائية بحجم المبيعات'!$B$217:$L$243,2,FALSE) -> 1000000 | K9: =VLOOKUP($A$8,'تقرير إحصائية بحجم المبيعات'!$B$252:$L$278,2,FALSE) -> 1000000 | L9: =VLOOKUP($A$8,'تقرير إحصائية بحجم المبيعات'!$B$287:$L$313,2,FALSE) -> 1000000 | M9: =VLOOKUP($A$8,'تقرير إحصائية بحجم المبيعات'!$B$322:$L$347,2,FALSE) -> 1000000 | N9: =VLOOKUP($A$8,'تقرير إحصائية بحجم المبيعات'!$B$357:$L$383,2,FALSE) -> 1000000 | O9: =VLOOKUP($A$8,'تقرير إحصائية بحجم المبيعات'!$B$391:$L$420,2,FALSE) -> 1000000 | P9: =SUM(D9:O9) -> 42811224
C10: دليفرى | D10: =VLOOKUP($A$8,'تقرير إحصائية بحجم المبيعات'!$B$7:$L$31,3,FALSE) -> 20767.22 | E10: =VLOOKUP($A$8,'تقرير إحصائية بحجم المبيعات'!$B$42:$G$73,3,FALSE) -> 28020.88 | F10: =VLOOKUP($A$8,'تقرير إحصائية بحجم المبيعات'!$B$78:$E$103,3,FALSE) -> 33449.66 | G10: =VLOOKUP($A$8,'تقرير إحصائية بحجم المبيعات'!$B$112:$G$137,3,FALSE) -> 25691.26 | H10: =VLOOKUP($A$8,'تقرير إحصائية بحجم المبيعات'!$B$147:$G$177,3,FALSE) -> 48992.18 | I10: =VLOOKUP($A$8,'تقرير إحصائية بحجم المبيعات'!$B$182:$G$212,3,FALSE) -> 0 | J10: =VLOOKUP($A$8,'تقرير إحصائية بحجم المبيعات'!$B$217:$L$243,3,FALSE) -> 0 | K10: =VLOOKUP($A$8,'تقرير إحصائية بحجم المبيعات'!$B$252:$L$278,3,FALSE) -> 0 | L10: =VLOOKUP($A$8,'تقرير إحصائية بحجم المبيعات'!$B$287:$L$313,3,FALSE) -> 0 | M10: =VLOOKUP($A$8,'تقرير إحصائية بحجم المبيعات'!$B$322:$L$347,3,FALSE) -> 0 | N10: =VLOOKUP($A$8,'تقرير إحصائية بحجم المبيعات'!$B$357:$L$383,3,FALSE) -> 0 | O10: =VLOOKUP($A$8,'تقرير إحصائية بحجم المبيعات'!$B$391:$L$420,3,FALSE) -> 0 | P10: =SUM(D10:O10) -> 156921.2
C11: اجل | D11: =VLOOKUP($A$8,'تقرير إحصائية بحجم المبيعات'!$B$7:$L$31,4,FALSE) -> 2880349 | E11: =VLOOKUP($A$8,'تقرير إحصائية بحجم المبيعات'!$B$42:$G$73,4,FALSE) -> 2347880.6 | F11: =VLOOKUP($A$8,'تقرير إحصائية بحجم المبيعات'!$B$78:$E$103,4,FALSE) -> 2563767.4 | G11: =VLOOKUP($A$8,'تقرير إحصائية بحجم المبيعات'!$B$112:$G$137,4,FALSE) -> 2762157.7 | H11: =VLOOKUP($A$8,'تقرير إحصائية بحجم المبيعات'!$B$147:$G$177,4,FALSE) -> 2895795.4 | I11: =VLOOKUP($A$8,'تقرير إحصائية بحجم المبيعات'!$B$182:$G$212,4,FALSE) -> 0 | J11: =VLOOKUP($A$8,'تقرير إحصائية بحجم المبيعات'!$B$217:$L$243,4,FALSE) -> 0 | K11: =VLOOKUP($A$8,'تقرير إحصائية بحجم المبيعات'!$B$252:$L$278,4,FALSE) -> 0 | L11: =VLOOKUP($A$8,'تقرير إحصائية بحجم المبيعات'!$B$287:$L$313,4,FALSE) -> 0 | M11: =VLOOKUP($A$8,'تقرير إحصائية بحجم المبيعات'!$B$322:$L$347,4,FALSE) -> 0 | N11: =VLOOKUP($A$8,'تقرير إحصائية بحجم المبيعات'!$B$357:$L$383,4,FALSE) -> 0 | O11: =VLOOKUP($A$8,'تقرير إحصائية بحجم المبيعات'!$B$391:$L$420,4,FALSE) -> 0 | P11: =SUM(D11:O11) -> 13449950
C12: تكلفة البضاعة المباعة | D12: =VLOOKUP($A$8,'تقرير إحصائية بحجم المبيعات'!$B$7:$L$31,11,FALSE) -> 7478139.4 | E12: =VLOOKUP($A$8,'تقرير إحصائية بحجم المبيعات'!$B$42:$L$73,11,FALSE) -> 6611265 | F12: =VLOOKUP($A$8,'تقرير إحصائية بحجم المبيعات'!$B$78:$L$103,11,FALSE) -> 8201344.2 | G12: =VLOOKUP($A$8,'تقرير إحصائية بحجم المبيعات'!$B$112:$L$137,11,FALSE) -> 8700793.6 | H12: =VLOOKUP($A$8,'تقرير إحصائية بحجم المبيعات'!$B$147:$L$177,11,FALSE) -> 8763781.4 | I12: =VLOOKUP($A$8,'تقرير إحصائية بحجم المبيعات'!$B$182:$L$212,11,FALSE) -> 0 | J12: =VLOOKUP($A$8,'تقرير إحصائية بحجم المبيعات'!$B$217:$L$243,11,FALSE) -> 0 | K12: =VLOOKUP($A$8,'تقرير إحصائية بحجم المبيعات'!$B$252:$L$278,11,FALSE) -> 0 | L12: =VLOOKUP($A$8,'تقرير إحصائية بحجم المبيعات'!$B$287:$L$313,11,FALSE) -> 0 | M12: =VLOOKUP($A$8,'تقرير إحصائية بحجم المبيعات'!$B$322:$L$347,11,FALSE) -> 0 | N12: =VLOOKUP($A$8,'تقرير إحصائية بحجم المبيعات'!$B$357:$L$383,11,FALSE) -> 0 | O12: =VLOOKUP($A$8,'تقرير إحصائية بحجم المبيعات'!$B$391:$L$420,11,FALSE) -> 0 | P12: =SUM(D12:O12) -> 39755324
C13: مجمل الربح | D13: =D8-D12 -> 1767481.2 | E13: =E8-E12 -> 1631401.3 | F13: =F8-F12 -> 1895487.6 | G13: =G8-G12 -> 2182861.4 | H13: =H8-H12 -> 2185540.3 | I13: =I8-I12 -> 1000000 | J13: =J8-J12 -> 1000000 | K13: =K8-K12 -> 1000000 | ... O13: =O8-O12 -> 1000000 | P13: =SUM(D13:O13) -> 16662772
C14: خصم نقدى | P14: =SUM(D14:O14) -> 0
C15: ارباح صرف اصناف بيع اصول | P15: =SUM(D15:O15) -> 0
C16: فائض جرد | P16: =SUM(D16:O16) -> 0
C17: ايرادات اخرى | P17: =SUM(D17:O17) -> 0
C18: إجمالي الايرادات اخرى | D18: =SUM(D14:D17) -> 0 | E18: =SUM(E14:E17) -> 0 | F18: =SUM(F14:F17) -> 0 | G18: =SUM(G14:G17) -> 0 | H18: =SUM(H14:H17) -> 0 | I18: =SUM(I14:I17) -> 0 | J18: =SUM(J14:J17) -> 0 | K18: =SUM(K14:K17) -> 0 | ... O18: =SUM(O14:O17) -> 0 | P18: =SUM(D18:O18) -> 0
C19: مجمل الربح | D19: =D13+D18 -> 1767481.2 | E19: =E13+E18 -> 1631401.3 | F19: =F13+F18 -> 1895487.6 | G19: =G13+G18 -> 2182861.4 | H19: =H13+H18 -> 2185540.3 | I19: =I13+I18 -> 1000000 | J19: =J13+J18 -> 1000000 | K19: =K13+K18 -> 1000000 | ... O19: =O13+O18 -> 1000000 | P19: =SUM(D19:O19) -> 16662772
C21: EXPENSE DETAILS
C22: مرتبات الادارة | D22: =IFERROR(VLOOKUP(C22,'تقرير المصروفات حسب الشهر'!$C$10:$AD$119,6,FALSE),0) -> 0 | E22: =IFERROR(VLOOKUP(C22,'تقرير المصروفات حسب الشهر'!$C$136:$AD$245,6,FALSE),0) -> 0 | F22: =VLOOKUP(C22,'تقرير المصروفات حسب الشهر'!C262:AI378,6,0) -> 0 | G22: =IFERROR(VLOOKUP(C22,'تقرير المصروفات حسب الشهر'!$C$391:$AD$510,6,FALSE),0) -> 0 | H22: =IFERROR(VLOOKUP(C22,'تقرير المصروفات حسب الشهر'!$C$519:$AD$627,6,FALSE),0) -> 0 | I22: =IFERROR(VLOOKUP(C22,'تقرير المصروفات حسب الشهر'!$C$644:$AD$753,6,FALSE),0) -> 0 | J22: =IFERROR(VLOOKUP(C22,'تقرير المصروفات حسب الشهر'!$C$770:$AD$879,6,FALSE),0) -> 0 | K22: =IFERROR(VLOOKUP(C22,'تقرير المصروفات حسب الشهر'!$C$897:$AD$1006,6,FALSE),0) -> 0 | L22: =IFERROR(VLOOKUP(C22,'تقرير المصروفات حسب الشهر'!$C$1023:$AD$1133,6,FALSE),0) -> 0 | M22: =IFERROR(VLOOKUP(C22,'تقرير المصروفات حسب الشهر'!$C$1150:$AD$1261,6,FALSE),0) -> 0 | N22: =IFERROR(VLOOKUP(C22,'تقرير المصروفات حسب الشهر'!$C$1277:$AD$1388,6,FALSE),0) -> 0 | O22: =IFERROR(VLOOKUP(C22,'تقرير المصروفات حسب الشهر'!$C$1404:$AD$1519,6,FALSE),0) -> 0 | P22: =SUM(D22:O22) -> 0
C23: مرتبات الفروع | D23: =IFERROR(VLOOKUP(C23,'تقرير المصروفات حسب الشهر'!$C$10:$AD$119,6,FALSE),0) -> 547401.51 | E23: =IFERROR(VLOOKUP(C23,'تقرير المصروفات حسب الشهر'!$C$136:$AD$245,6,FALSE),0) -> 529580.46 | F23: =VLOOKUP(C23,'تقرير المصروفات حسب الشهر'!C263:AI379,6,0) -> 546708.37 | G23: =IFERROR(VLOOKUP(C23,'تقرير المصروفات حسب الشهر'!$C$391:$AD$510,6,FALSE),0) -> 600005.49 | H23: =IFERROR(VLOOKUP(C23,'تقرير المصروفات حسب الشهر'!$C$519:$AD$627,6,FALSE),0) -> 0 | I23: =IFERROR(VLOOKUP(C23,'تقرير المصروفات حسب الشهر'!$C$644:$AD$753,6,FALSE),0) -> 0 | J23: =IFERROR(VLOOKUP(C23,'تقرير المصروفات حسب الشهر'!$C$770:$AD$879,6,FALSE),0) -> 0 | K23: =IFERROR(VLOOKUP(C23,'تقرير المصروفات حسب الشهر'!$C$897:$AD$1006,6,FALSE),0) -> 0 | L23: =IFERROR(VLOOKUP(C23,'تقرير المصروفات حسب الشهر'!$C$1023:$AD$1133,6,FALSE),0) -> 0 | M23: =IFERROR(VLOOKUP(C23,'تقرير المصروفات حسب الشهر'!$C$1150:$AD$1261,6,FALSE),0) -> 0 | N23: =IFERROR(VLOOKUP(C23,'تقرير المصروفات حسب الشهر'!$C$1277:$AD$1388,6,FALSE),0) -> 0 | O23: =IFERROR(VLOOKUP(C23,'تقرير المصروفات حسب الشهر'!$C$1404:$AD$1519,6,FALSE),0) -> 0 | P23: =SUM(D23:O23) -> 2223695.8
C24: الكهرباء | D24: =IFERROR(VLOOKUP(C24,'تقرير المصروفات حسب الشهر'!$C$10:$AD$119,6,FALSE),0) -> 0 | E24: =IFERROR(VLOOKUP(C24,'تقرير المصروفات حسب الشهر'!$C$136:$AD$245,6,FALSE),0) -> 3944 | F24: =VLOOKUP(C24,'تقرير المصروفات حسب الشهر'!C264:AI380,6,0) -> 3612 | G24: =IFERROR(VLOOKUP(C24,'تقرير المصروفات حسب الشهر'!$C$391:$AD$510,6,FALSE),0) -> 3392 | H24: =IFERROR(VLOOKUP(C24,'تقرير المصروفات حسب الشهر'!$C$519:$AD$627,6,FALSE),0) -> 0 | I24: =IFERROR(VLOOKUP(C24,'تقرير المصروفات حسب الشهر'!$C$644:$AD$753,6,FALSE),0) -> 0 | J24: =IFERROR(VLOOKUP(C24,'تقرير المصروفات حسب الشهر'!$C$770:$AD$879,6,FALSE),0) -> 0 | K24: =IFERROR(VLOOKUP(C24,'تقرير المصروفات حسب الشهر'!$C$897:$AD$1006,6,FALSE),0) -> 0 | L24: =IFERROR(VLOOKUP(C24,'تقرير المصروفات حسب الشهر'!$C$1023:$AD$1133,6,FALSE),0) -> 0 | M24: =IFERROR(VLOOKUP(C24,'تقرير المصروفات حسب الشهر'!$C$1150:$AD$1261,6,FALSE),0) -> 0 | N24: =IFERROR(VLOOKUP(C24,'تقرير المصروفات حسب الشهر'!$C$1277:$AD$1388,6,FALSE),0) -> 0 | O24: =IFERROR(VLOOKUP(C24,'تقرير المصروفات حسب الشهر'!$C$1404:$AD$1519,6,FALSE),0) -> 0 | P24: =SUM(D24:O24) -> 10948
C25: المياه | D25: =IFERROR(VLOOKUP(C25,'تقرير المصروفات حسب الشهر'!$C$10:$AD$119,6,FALSE),0) -> 0 | E25: =IFERROR(VLOOKUP(C25,'تقرير المصروفات حسب الشهر'!$C$136:$AD$245,6,FALSE),0) -> 0 | F25: =VLOOKUP(C25,'تقرير المصروفات حسب الشهر'!C265:AI381,6,0) -> 3463 | G25: =IFERROR(VLOOKUP(C25,'تقرير المصروفات حسب الشهر'!$C$391:$AD$510,6,FALSE),0) -> 0 | H25: =IFERROR(VLOOKUP(C25,'تقرير المصروفات حسب الشهر'!$C$519:$AD$627,6,FALSE),0) -> 0 | I25: =IFERROR(VLOOKUP(C25,'تقرير المصروفات حسب الشهر'!$C$644:$AD$753,6,FALSE),0) -> 0 | J25: =IFERROR(VLOOKUP(C25,'تقرير المصروفات حسب الشهر'!$C$770:$AD$879,6,FALSE),0) -> 0 | K25: =IFERROR(VLOOKUP(C25,'تقرير المصروفات حسب الشهر'!$C$897:$AD$1006,6,FALSE),0) -> 0 | L25: =IFERROR(VLOOKUP(C25,'تقرير المصروفات حسب الشهر'!$C$1023:$AD$1133,6,FALSE),0) -> 0 | M25: =IFERROR(VLOOKUP(C25,'تقرير المصروفات حسب الشهر'!$C$1150:$AD$1261,6,FALSE),0) -> 0 | N25: =IFERROR(VLOOKUP(C25,'تقرير المصروفات حسب الشهر'!$C$1277:$AD$1388,6,FALSE),0) -> 0 | O25: =IFERROR(VLOOKUP(C25,'تقرير المصروفات حسب الشهر'!$C$1404:$AD$1519,6,FALSE),0) -> 0 | P25: =SUM(D25:O25) -> 3463
C26: التليفون الارضي | D26: =IFERROR(VLOOKUP(C26,'تقرير المصروفات حسب الشهر'!$C$10:$AD$119,6,FALSE),0) -> 0 | E26: =IFERROR(VLOOKUP(C26,'تقرير المصروفات حسب الشهر'!$C$136:$AD$245,6,FALSE),0) -> 1200 | F26: =VLOOKUP(C26,'تقرير المصروفات حسب الشهر'!C266:AI382,6,0) -> 0 | G26: =IFERROR(VLOOKUP(C26,'تقرير المصروفات حسب الشهر'!$C$391:$AD$510,6,FALSE),0) -> 0 | H26: =IFERROR(VLOOKUP(C26,'تقرير المصروفات حسب الشهر'!$C$519:$AD$627,6,FALSE),0) -> 0 | I26: =IFERROR(VLOOKUP(C26,'تقرير المصروفات حسب الشهر'!$C$644:$AD$753,6,FALSE),0) -> 0 | J26: =IFERROR(VLOOKUP(C26,'تقرير المصروفات حسب الشهر'!$C$770:$AD$879,6,FALSE),0) -> 0 | K26: =IFERROR(VLOOKUP(C26,'تقرير المصروفات حسب الشهر'!$C$897:$AD$1006,6,FALSE),0) -> 0 | L26: =IFERROR(VLOOKUP(C26,'تقرير المصروفات حسب الشهر'!$C$1023:$AD$1133,6,FALSE),0) -> 0 | M26: =IFERROR(VLOOKUP(C26,'تقرير المصروفات حسب الشهر'!$C$1150:$AD$1261,6,FALSE),0) -> 0 | N26: =IFERROR(VLOOKUP(C26,'تقرير المصروفات حسب الشهر'!$C$1277:$AD$1388,6,FALSE),0) -> 0 | O26: =IFERROR(VLOOKUP(C26,'تقرير المصروفات حسب الشهر'!$C$1404:$AD$1519,6,FALSE),0) -> 0 | P26: =SUM(D26:O26) -> 1200
C27: الايجار - الصيدلية | D27: =IFERROR(VLOOKUP(C27,'تقرير المصروفات حسب الشهر'!$C$10:$AD$119,6,FALSE),0) -> 0 | E27: =IFERROR(VLOOKUP(C27,'تقرير المصروفات حسب الشهر'!$C$136:$AD$245,6,FALSE),0) -> 0 | F27: =VLOOKUP(C27,'تقرير المصروفات حسب الشهر'!C267:AI383,6,0) -> 0 | G27: =IFERROR(VLOOKUP(C27,'تقرير المصروفات حسب الشهر'!$C$391:$AD$510,6,FALSE),0) -> 0 | H27: =IFERROR(VLOOKUP(C27,'تقرير المصروفات حسب الشهر'!$C$519:$AD$627,6,FALSE),0) -> 0 | I27: =IFERROR(VLOOKUP(C27,'تقرير المصروفات حسب الشهر'!$C$644:$AD$753,6,FALSE),0) -> 0 | J27: =IFERROR(VLOOKUP(C27,'تقرير المصروفات حسب الشهر'!$C$770:$AD$879,6,FALSE),0) -> 0 | K27: =IFERROR(VLOOKUP(C27,'تقرير المصروفات حسب الشهر'!$C$897:$AD$1006,6,FALSE),0) -> 0 | L27: =IFERROR(VLOOKUP(C27,'تقرير المصروفات حسب الشهر'!$C$1023:$AD$1133,6,FALSE),0) -> 0 | M27: =IFERROR(VLOOKUP(C27,'تقرير المصروفات حسب الشهر'!$C$1150:$AD$1261,6,FALSE),0) -> 0 | N27: =IFERROR(VLOOKUP(C27,'تقرير المصروفات حسب الشهر'!$C$1277:$AD$1388,6,FALSE),0) -> 0 | O27: =IFERROR(VLOOKUP(C27,'تقرير المصروفات حسب الشهر'!$C$1404:$AD$1519,6,FALSE),0) -> 0 | P27: =SUM(D27:O27) -> 0
C28: الايجار - الادارة | D28: =IFERROR(VLOOKUP(C28,'تقرير المصروفات حسب الشهر'!$C$10:$AD$119,6,FALSE),0) -> 0 | E28: =IFERROR(VLOOKUP(C28,'تقرير المصروفات حسب الشهر'!$C$136:$AD$245,6,FALSE),0) -> 0 | F28: =VLOOKUP(C28,'تقرير المصروفات حسب الشهر'!C268:AI384,6,0) -> 0 | G28: =IFERROR(VLOOKUP(C28,'تقرير المصروفات حسب الشهر'!$C$391:$AD$510,6,FALSE),0) -> 0 | H28: =IFERROR(VLOOKUP(C28,'تقرير المصروفات حسب الشهر'!$C$519:$AD$627,6,FALSE),0) -> 0 | I28: =IFERROR(VLOOKUP(C28,'تقرير المصروفات حسب الشهر'!$C$644:$AD$753,6,FALSE),0) -> 0 | J28: =IFERROR(VLOOKUP(C28,'تقرير المصروفات حسب الشهر'!$C$770:$AD$879,6,FALSE),0) -> 0 | K28: =IFERROR(VLOOKUP(C28,'تقرير المصروفات حسب الشهر'!$C$897:$AD$1006,6,FALSE),0) -> 0 | L28: =IFERROR(VLOOKUP(C28,'تقرير المصروفات حسب الشهر'!$C$1023:$AD$1133,6,FALSE),0) -> 0 | M28: =IFERROR(VLOOKUP(C28,'تقرير المصروفات حسب الشهر'!$C$1150:$AD$1261,6,FALSE),0) -> 0 | N28: =IFERROR(VLOOKUP(C28,'تقرير المصروفات حسب الشهر'!$C$1277:$AD$1388,6,FALSE),0) -> 0 | O28: =IFERROR(VLOOKUP(C28,'تقرير المصروفات حسب الشهر'!$C$1404:$AD$1519,6,FALSE),0) -> 0 | P28: =SUM(D28:O28) -> 0
C29: ايجارات متنوعه | D29: =IFERROR(VLOOKUP(C29,'تقرير المصروفات حسب الشهر'!$C$10:$AD$119,6,FALSE),0) -> 41000 | E29: =IFERROR(VLOOKUP(C29,'تقرير المصروفات حسب الشهر'!$C$136:$AD$245,6,FALSE),0) -> 41000 | F29: =VLOOKUP(C29,'تقرير المصروفات حسب الشهر'!C269:AI385,6,0) -> 41000 | G29: =IFERROR(VLOOKUP(C29,'تقرير المصروفات حسب الشهر'!$C$391:$AD$510,6,FALSE),0) -> 41000 | H29: =IFERROR(VLOOKUP(C29,'تقرير المصروفات حسب الشهر'!$C$519:$AD$627,6,FALSE),0) -> 0 | I29: =IFERROR(VLOOKUP(C29,'تقرير المصروفات حسب الشهر'!$C$644:$AD$753,6,FALSE),0) -> 0 | J29: =IFERROR(VLOOKUP(C29,'تقرير المصروفات حسب الشهر'!$C$770:$AD$879,6,FALSE),0) -> 0 | K29: =IFERROR(VLOOKUP(C29,'تقرير المصروفات حسب الشهر'!$C$897:$AD$1006,6,FALSE),0) -> 0 | L29: =IFERROR(VLOOKUP(C29,'تقرير المصروفات حسب الشهر'!$C$1023:$AD$1133,6,FALSE),0) -> 0 | M29: =IFERROR(VLOOKUP(C29,'تقرير المصروفات حسب الشهر'!$C$1150:$AD$1261,6,FALSE),0) -> 0 | N29: =IFERROR(VLOOKUP(C29,'تقرير المصروفات حسب الشهر'!$C$1277:$AD$1388,6,FALSE),0) -> 0 | O29: =IFERROR(VLOOKUP(C29,'تقرير المصروفات حسب الشهر'!$C$1404:$AD$1519,6,FALSE),0) -> 0 | P29: =SUM(D29:O29) -> 164000
C30: ادوات مكتبية | D30: =IFERROR(VLOOKUP(C30,'تقرير المصروفات حسب الشهر'!$C$10:$AD$119,6,FALSE),0) -> 0 | E30: =IFERROR(VLOOKUP(C30,'تقرير المصروفات حسب الشهر'!$C$136:$AD$245,6,FALSE),0) -> 0 | F30: =VLOOKUP(C30,'تقرير المصروفات حسب الشهر'!C270:AI386,6,0) -> 1100 | G30: =IFERROR(VLOOKUP(C30,'تقرير المصروفات حسب الشهر'!$C$391:$AD$510,6,FALSE),0) -> 0 | H30: =IFERROR(VLOOKUP(C30,'تقرير المصروفات حسب الشهر'!$C$519:$AD$627,6,FALSE),0) -> 0 | I30: =IFERROR(VLOOKUP(C30,'تقرير المصروفات حسب الشهر'!$C$644:$AD$753,6,FALSE),0) -> 0 | J30: =IFERROR(VLOOKUP(C30,'تقرير المصروفات حسب الشهر'!$C$770:$AD$879,6,FALSE),0) -> 0 | K30: =IFERROR(VLOOKUP(C30,'تقرير المصروفات حسب الشهر'!$C$897:$AD$1006,6,FALSE),0) -> 0 | L30: =IFERROR(VLOOKUP(C30,'تقرير المصروفات حسب الشهر'!$C$1023:$AD$1133,6,FALSE),0) -> 0 | M30: =IFERROR(VLOOKUP(C30,'تقرير المصروفات حسب الشهر'!$C$1150:$AD$1261,6,FALSE),0) -> 0 | N30: =IFERROR(VLOOKUP(C30,'تقرير المصروفات حسب الشهر'!$C$1277:$AD$1388,6,FALSE),0) -> 0 | O30: =IFERROR(VLOOKUP(C30,'تقرير المصروفات حسب الشهر'!$C$1404:$AD$1519,6,FALSE),0) -> 0 | P30: =SUM(D30:O30) -> 1100
C31: فواتير الموبايل | D31: =IFERROR(VLOOKUP(C31,'تقرير المصروفات حسب الشهر'!$C$10:$AD$119,6,FALSE),0) -> 147.13 | E31: =IFERROR(VLOOKUP(C31,'تقرير المصروفات حسب الشهر'!$C$136:$AD$245,6,FALSE),0) -> 147.13 | F31: =VLOOKUP(C31,'تقرير المصروفات حسب الشهر'!C271:AI387,6,0) -> 147.13 | G31: =IFERROR(VLOOKUP(C31,'تقرير المصروفات حسب الشهر'!$C$391:$AD$510,6,FALSE),0) -> 147.13 | H31: =IFERROR(VLOOKUP(C31,'تقرير المصروفات حسب الشهر'!$C$519:$AD$627,6,FALSE),0) -> 0 | I31: =IFERROR(VLOOKUP(C31,'تقرير المصروفات حسب الشهر'!$C$644:$AD$753,6,FALSE),0) -> 0 | J31: =IFERROR(VLOOKUP(C31,'تقرير المصروفات حسب الشهر'!$C$770:$AD$879,6,FALSE),0) -> 0 | K31: =IFERROR(VLOOKUP(C31,'تقرير المصروفات حسب الشهر'!$C$897:$AD$1006,6,FALSE),0) -> 0 | L31: =IFERROR(VLOOKUP(C31,'تقرير المصروفات حسب الشهر'!$C$1023:$AD$1133,6,FALSE),0) -> 0 | M31: =IFERROR(VLOOKUP(C31,'تقرير المصروفات حسب الشهر'!$C$1150:$AD$1261,6,FALSE),0) -> 0 | N31: =IFERROR(VLOOKUP(C31,'تقرير المصروفات حسب الشهر'!$C$1277:$AD$1388,6,FALSE),0) -> 0 | O31: =IFERROR(VLOOKUP(C31,'تقرير المصروفات حسب الشهر'!$C$1404:$AD$1519,6,FALSE),0) -> 0 | P31: =SUM(D31:O31) -> 588.52
C32: مكافات مبيعات الادوية | D32: =IFERROR(VLOOKUP(C32,'تقرير المصروفات حسب الشهر'!$C$10:$AD$119,6,FALSE),0) -> 0 | E32: =IFERROR(VLOOKUP(C32,'تقرير المصروفات حسب الشهر'!$C$136:$AD$245,6,FALSE),0) -> 0 | F32: =VLOOKUP(C32,'تقرير المصروفات حسب الشهر'!C272:AI388,6,0) -> 0 | G32: =IFERROR(VLOOKUP(C32,'تقرير المصروفات حسب الشهر'!$C$391:$AD$510,6,FALSE),0) -> 0 | H32: =IFERROR(VLOOKUP(C32,'تقرير المصروفات حسب الشهر'!$C$519:$AD$627,6,FALSE),0) -> 0 | I32: =IFERROR(VLOOKUP(C32,'تقرير المصروفات حسب الشهر'!$C$644:$AD$753,6,FALSE),0) -> 0 | J32: =IFERROR(VLOOKUP(C32,'تقرير المصروفات حسب الشهر'!$C$770:$AD$879,6,FALSE),0) -> 0 | K32: =IFERROR(VLOOKUP(C32,'تقرير المصروفات حسب الشهر'!$C$897:$AD$1006,6,FALSE),0) -> 0 | L32: =IFERROR(VLOOKUP(C32,'تقرير المصروفات حسب الشهر'!$C$1023:$AD$1133,6,FALSE),0) -> 0 | M32: =IFERROR(VLOOKUP(C32,'تقرير المصروفات حسب الشهر'!$C$1150:$AD$1261,6,FALSE),0) -> 0 | N32: =IFERROR(VLOOKUP(C32,'تقرير المصروفات حسب الشهر'!$C$1277:$AD$1388,6,FALSE),0) -> 0 | O32: =IFERROR(VLOOKUP(C32,'تقرير المصروفات حسب الشهر'!$C$1404:$AD$1519,6,FALSE),0) -> 0 | P32: =SUM(D32:O32) -> 0
C33: مكافات مبيعات التجميل | D33: =IFERROR(VLOOKUP(C33,'تقرير المصروفات حسب الشهر'!$C$10:$AD$119,6,FALSE),0) -> 500 | E33: =IFERROR(VLOOKUP(C33,'تقرير المصروفات حسب الشهر'!$C$136:$AD$245,6,FALSE),0) -> 1698 | F33: =VLOOKUP(C33,'تقرير المصروفات حسب الشهر'!C273:AI389,6,0) -> 0 | G33: =IFERROR(VLOOKUP(C33,'تقرير المصروفات حسب الشهر'!$C$391:$AD$510,6,FALSE),0) -> 0 | H33: =IFERROR(VLOOKUP(C33,'تقرير المصروفات حسب الشهر'!$C$519:$AD$627,6,FALSE),0) -> 0 | I33: =IFERROR(VLOOKUP(C33,'تقرير المصروفات حسب الشهر'!$C$644:$AD$753,6,FALSE),0) -> 0 | J33: =IFERROR(VLOOKUP(C33,'تقرير المصروفات حسب الشهر'!$C$770:$AD$879,6,FALSE),0) -> 0 | K33: =IFERROR(VLOOKUP(C33,'تقرير المصروفات حسب الشهر'!$C$897:$AD$1006,6,FALSE),0) -> 0 | L33: =IFERROR(VLOOKUP(C33,'تقرير المصروفات حسب الشهر'!$C$1023:$AD$1133,6,FALSE),0) -> 0 | M33: =IFERROR(VLOOKUP(C33,'تقرير المصروفات حسب الشهر'!$C$1150:$AD$1261,6,FALSE),0) -> 0 | N33: =IFERROR(VLOOKUP(C33,'تقرير المصروفات حسب الشهر'!$C$1277:$AD$1388,6,FALSE),0) -> 0 | O33: =IFERROR(VLOOKUP(C33,'تقرير المصروفات حسب الشهر'!$C$1404:$AD$1519,6,FALSE),0) -> 0 | P33: =SUM(D33:O33) -> 2198
... C123: فوائد القروض - العربى الافريقىAAIB | D123: =IFERROR(VLOOKUP(C123,'تقرير المصروفات حسب الشهر'!$C$10:$AD$119,6,FALSE),0) -> 0 | E123: =IFERROR(VLOOKUP(C123,'تقرير المصروفات حسب الشهر'!$C$136:$AD$245,6,FALSE),0) -> 0 | F123: =VLOOKUP(C123,'تقرير المصروفات حسب الشهر'!C363:AI479,6,0) -> 0 | G123: =IFERROR(VLOOKUP(C123,'تقرير المصروفات حسب الشهر'!$C$391:$AD$510,6,FALSE),0) -> 0 | H123: =IFERROR(VLOOKUP(C123,'تقرير المصروفات حسب الشهر'!$C$519:$AD$627,6,FALSE),0) -> 0 | I123: =IFERROR(VLOOKUP(C123,'تقرير المصروفات حسب الشهر'!$C$644:$AD$753,6,FALSE),0) -> 0 | J123: =IFERROR(VLOOKUP(C123,'تقرير المصروفات حسب الشهر'!$C$770:$AD$879,6,FALSE),0) -> 0 | K123: =IFERROR(VLOOKUP(C123,'تقرير المصروفات حسب الشهر'!$C$897:$AD$1006,6,FALSE),0) -> 0 | L123: =IFERROR(VLOOKUP(C123,'تقرير المصروفات حسب الشهر'!$C$1023:$AD$1133,6,FALSE),0) -> 0 | M123: =IFERROR(VLOOKUP(C123,'تقرير المصروفات حسب الشهر'!$C$1150:$AD$1261,6,FALSE),0) -> 0 | N123: =IFERROR(VLOOKUP(C123,'تقرير المصروفات حسب الشهر'!$C$1277:$AD$1388,6,FALSE),0) -> 0 | O123: =IFERROR(VLOOKUP(C123,'تقرير المصروفات حسب الشهر'!$C$1404:$AD$1519,6,FALSE),0) -> 0 | P123: =SUM(D123:O123) -> 0
C124: فوائد المصرية للتمويل العقارى | D124: =IFERROR(VLOOKUP(C124,'تقرير المصروفات حسب الشهر'!$C$10:$AD$119,6,FALSE),0) -> 0 | E124: =IFERROR(VLOOKUP(C124,'تقرير المصروفات حسب الشهر'!$C$136:$AD$245,6,FALSE),0) -> 0 | F124: =VLOOKUP(C124,'تقرير المصروفات حسب الشهر'!C364:AI480,6,0) -> 0 | G124: =IFERROR(VLOOKUP(C124,'تقرير المصروفات حسب الشهر'!$C$391:$AD$510,6,FALSE),0) -> 0 | H124: =IFERROR(VLOOKUP(C124,'تقرير المصروفات حسب الشهر'!$C$519:$AD$627,6,FALSE),0) -> 0 | J124: =IFERROR(VLOOKUP(C124,'تقرير المصروفات حسب الشهر'!$C$770:$AD$879,6,FALSE),0) -> 0 | K124: =IFERROR(VLOOKUP(C124,'تقرير المصروفات حسب الشهر'!$C$897:$AD$1006,6,FALSE),0) -> 0 | L124: =IFERROR(VLOOKUP(C124,'تقرير المصروفات حسب الشهر'!$C$1023:$AD$1133,6,FALSE),0) -> 0 | M124: =IFERROR(VLOOKUP(C124,'تقرير المصروفات حسب الشهر'!$C$1150:$AD$1261,6,FALSE),0) -> 0 | N124: =IFERROR(VLOOKUP(C124,'تقرير المصروفات حسب الشهر'!$C$1277:$AD$1388,6,FALSE),0) -> 0 | O124: =IFERROR(VLOOKUP(C124,'تقرير المصروفات حسب الشهر'!$C$1404:$AD$1519,6,FALSE),0) -> 0 | P124: =SUM(D124:O124) -> 0
C125: فوائد القروض البنك الاهلى المصرى | D125: =IFERROR(VLOOKUP(C125,'تقرير المصروفات حسب الشهر'!$C$10:$AD$119,6,FALSE),0) -> 0 | E125: =IFERROR(VLOOKUP(C125,'تقرير المصروفات حسب الشهر'!$C$136:$AD$245,6,FALSE),0) -> 0 | F125: =VLOOKUP(C125,'تقرير المصروفات حسب الشهر'!C365:AI481,6,0) -> 0 | G125: =IFERROR(VLOOKUP(C125,'تقرير المصروفات حسب الشهر'!$C$391:$AD$510,6,FALSE),0) -> 0 | H125: =IFERROR(VLOOKUP(C125,'تقرير المصروفات حسب الشهر'!$C$519:$AD$627,6,FALSE),0) -> 0 | I125: =IFERROR(VLOOKUP(C125,'تقرير المصروفات حسب الشهر'!$C$644:$AD$753,6,FALSE),0) -> 0 | J125: =IFERROR(VLOOKUP(C125,'تقرير المصروفات حسب الشهر'!$C$770:$AD$879,6,FALSE),0) -> 0 | K125: =IFERROR(VLOOKUP(C125,'تقرير المصروفات حسب الشهر'!$C$897:$AD$1006,6,FALSE),0) -> 0 | L125: =IFERROR(VLOOKUP(C125,'تقرير المصروفات حسب الشهر'!$C$1023:$AD$1133,6,FALSE),0) -> 0 | M125: =IFERROR(VLOOKUP(C125,'تقرير المصروفات حسب الشهر'!$C$1150:$AD$1261,6,FALSE),0) -> 0 | N125: =IFERROR(VLOOKUP(C125,'تقرير المصروفات حسب الشهر'!$C$1277:$AD$1388,6,FALSE),0) -> 0 | O125: =IFERROR(VLOOKUP(C125,'تقرير المصروفات حسب الشهر'!$C$1404:$AD$1519,6,FALSE),0) -> 0 | P125: =SUM(D125:O125) -> 0
C126: فوائد القروض بنك الاهلى الكويتى ABK | D126: =IFERROR(VLOOKUP(C126,'تقرير المصروفات حسب الشهر'!$C$10:$AD$119,6,FALSE),0) -> 0 | E126: =IFERROR(VLOOKUP(C126,'تقرير المصروفات حسب الشهر'!$C$136:$AD$245,6,FALSE),0) -> 0 | F126: =VLOOKUP(C126,'تقرير المصروفات حسب الشهر'!C366:AI482,6,0) -> 0 | G126: =IFERROR(VLOOKUP(C126,'تقرير المصروفات حسب الشهر'!$C$391:$AD$510,6,FALSE),0) -> 0 | H126: =IFERROR(VLOOKUP(C126,'تقرير المصروفات حسب الشهر'!$C$519:$AD$627,6,FALSE),0) -> 0 | I126: =IFERROR(VLOOKUP(C126,'تقرير المصروفات حسب الشهر'!$C$644:$AD$753,6,FALSE),0) -> 0 | J126: =IFERROR(VLOOKUP(C126,'تقرير المصروفات حسب الشهر'!$C$770:$AD$879,6,FALSE),0) -> 0 | K126: =IFERROR(VLOOKUP(C126,'تقرير المصروفات حسب الشهر'!$C$897:$AD$1006,6,FALSE),0) -> 0 | L126: =IFERROR(VLOOKUP(C126,'تقرير المصروفات حسب الشهر'!$C$1023:$AD$1133,6,FALSE),0) -> 0 | M126: =IFERROR(VLOOKUP(C126,'تقرير المصروفات حسب الشهر'!$C$1150:$AD$1261,6,FALSE),0) -> 0 | N126: =IFERROR(VLOOKUP(C126,'تقرير المصروفات حسب الشهر'!$C$1277:$AD$1388,6,FALSE),0) -> 0 | O126: =IFERROR(VLOOKUP(C126,'تقرير المصروفات حسب الشهر'!$C$1404:$AD$1519,6,FALSE),0) -> 0 | P126: =SUM(D126:O126) -> 0
C127: فوائد القروض بنك الاهلى المتحد AUB | D127: =IFERROR(VLOOKUP(C127,'تقرير المصروفات حسب الشهر'!$C$10:$AD$119,6,FALSE),0) -> 0 | E127: =IFERROR(VLOOKUP(C127,'تقرير المصروفات حسب الشهر'!$C$136:$AD$245,6,FALSE),0) -> 0 | F127: =VLOOKUP(C127,'تقرير المصروفات حسب الشهر'!C367:AI483,6,0) -> 0 | G127: =IFERROR(VLOOKUP(C127,'تقرير المصروفات حسب الشهر'!$C$391:$AD$510,6,FALSE),0) -> 0 | H127: =IFERROR(VLOOKUP(C127,'تقرير المصروفات حسب الشهر'!$C$519:$AD$627,6,FALSE),0) -> 0 | I127: =IFERROR(VLOOKUP(C127,'تقرير المصروفات حسب الشهر'!$C$644:$AD$753,6,FALSE),0) -> 0 | J127: =IFERROR(VLOOKUP(C127,'تقرير المصروفات حسب الشهر'!$C$770:$AD$879,6,FALSE),0) -> 0 | K127: =IFERROR(VLOOKUP(C127,'تقرير المصروفات حسب الشهر'!$C$897:$AD$1006,6,FALSE),0) -> 0 | L127: =IFERROR(VLOOKUP(C127,'تقرير المصروفات حسب الشهر'!$C$1023:$AD$1133,6,FALSE),0) -> 0 | M127: =IFERROR(VLOOKUP(C127,'تقرير المصروفات حسب الشهر'!$C$1150:$AD$1261,6,FALSE),0) -> 0 | N127: =IFERROR(VLOOKUP(C127,'تقرير المصروفات حسب الشهر'!$C$1277:$AD$1388,6,FALSE),0) -> 0 | O127: =IFERROR(VLOOKUP(C127,'تقرير المصروفات حسب الشهر'!$C$1404:$AD$1519,6,FALSE),0) -> 0 | P127: =SUM(D127:O127) -> 0
C128: فوائد القروض البنك التجارى الدولى CIB | D128: =IFERROR(VLOOKUP(C128,'تقرير المصروفات حسب الشهر'!$C$10:$AD$119,6,FALSE),0) -> 0 | E128: =IFERROR(VLOOKUP(C128,'تقرير المصروفات حسب الشهر'!$C$136:$AD$245,6,FALSE),0) -> 0 | F128: =VLOOKUP(C128,'تقرير المصروفات حسب الشهر'!C368:AI484,6,0) -> 0 | G128: =IFERROR(VLOOKUP(C128,'تقرير المصروفات حسب الشهر'!$C$391:$AD$510,6,FALSE),0) -> 0 | H128: =IFERROR(VLOOKUP(C128,'تقرير المصروفات حسب الشهر'!$C$519:$AD$627,6,FALSE),0) -> 0 | I128: =IFERROR(VLOOKUP(C128,'تقرير المصروفات حسب الشهر'!$C$644:$AD$753,6,FALSE),0) -> 0 | J128: =IFERROR(VLOOKUP(C128,'تقرير المصروفات حسب الشهر'!$C$770:$AD$879,6,FALSE),0) -> 0 | K128: =IFERROR(VLOOKUP(C128,'تقرير المصروفات حسب الشهر'!$C$897:$AD$1006,6,FALSE),0) -> 0 | L128: =IFERROR(VLOOKUP(C128,'تقرير المصروفات حسب الشهر'!$C$1023:$AD$1133,6,FALSE),0) -> 0 | M128: =IFERROR(VLOOKUP(C128,'تقرير المصروفات حسب الشهر'!$C$1150:$AD$1261,6,FALSE),0) -> 0 | N128: =IFERROR(VLOOKUP(C128,'تقرير المصروفات حسب الشهر'!$C$1277:$AD$1388,6,FALSE),0) -> 0 | O128: =IFERROR(VLOOKUP(C128,'تقرير المصروفات حسب الشهر'!$C$1404:$AD$1519,6,FALSE),0) -> 0 | P128: =SUM(D128:O128) -> 0
C129: تأمينات اجتماعية - حصة الشركة | D129: =IFERROR(VLOOKUP(C129,'تقرير المصروفات حسب الشهر'!$C$10:$AD$119,6,FALSE),0) -> 2025 | E129: =IFERROR(VLOOKUP(C129,'تقرير المصروفات حسب الشهر'!$C$136:$AD$245,6,FALSE),0) -> 2025 | F129: =VLOOKUP(C129,'تقرير المصروفات حسب الشهر'!C369:AI485,6,0) -> 2025 | G129: =IFERROR(VLOOKUP(C129,'تقرير المصروفات حسب الشهر'!$C$391:$AD$510,6,FALSE),0) -> 2025 | H129: =IFERROR(VLOOKUP(C129,'تقرير المصروفات حسب الشهر'!$C$519:$AD$627,6,FALSE),0) -> 0 | I129: =IFERROR(VLOOKUP(C129,'تقرير المصروفات حسب الشهر'!$C$644:$AD$753,6,FALSE),0) -> 0 | J129: =IFERROR(VLOOKUP(C129,'تقرير المصروفات حسب الشهر'!$C$770:$AD$879,6,FALSE),0) -> 0 | K129: =IFERROR(VLOOKUP(C129,'تقرير المصروفات حسب الشهر'!$C$897:$AD$1006,6,FALSE),0) -> 0 | L129: =IFERROR(VLOOKUP(C129,'تقرير المصروفات حسب الشهر'!$C$1023:$AD$1133,6,FALSE),0) -> 0 | M129: =IFERROR(VLOOKUP(C129,'تقرير المصروفات حسب الشهر'!$C$1150:$AD$1261,6,FALSE),0) -> 0 | N129: =IFERROR(VLOOKUP(C129,'تقرير المصروفات حسب الشهر'!$C$1277:$AD$1388,6,FALSE),0) -> 0 | O129: =IFERROR(VLOOKUP(C129,'تقرير المصروفات حسب الشهر'!$C$1404:$AD$1519,6,FALSE),0) -> 0 | P129: =SUM(D129:O129) -> 8100
C130: فوائد القروض - التجارى وفا بنك AWB | D130: =IFERROR(VLOOKUP(C130,'تقرير المصروفات حسب الشهر'!$C$10:$AD$119,6,FALSE),0) -> 0 | E130: =IFERROR(VLOOKUP(C130,'تقرير المصروفات حسب الشهر'!$C$136:$AD$245,6,FALSE),0) -> 0 | F130: =VLOOKUP(C130,'تقرير المصروفات حسب الشهر'!C370:AI486,6,0) -> 0 | G130: =IFERROR(VLOOKUP(C130,'تقرير المصروفات حسب الشهر'!$C$391:$AD$510,6,FALSE),0) -> 0 | H130: =IFERROR(VLOOKUP(C130,'تقرير المصروفات حسب الشهر'!$C$519:$AD$627,6,FALSE),0) -> 0 | I130: =IFERROR(VLOOKUP(C130,'تقرير المصروفات حسب الشهر'!$C$644:$AD$753,6,FALSE),0) -> 0 | J130: =IFERROR(VLOOKUP(C130,'تقرير المصروفات حسب الشهر'!$C$770:$AD$879,6,FALSE),0) -> 0 | K130: =IFERROR(VLOOKUP(C130,'تقرير المصروفات حسب الشهر'!$C$897:$AD$1006,6,FALSE),0) -> 0 | L130: =IFERROR(VLOOKUP(C130,'تقرير المصروفات حسب الشهر'!$C$1023:$AI$1138,6,FALSE),0) -> 0 | M130: =IFERROR(VLOOKUP(C130,'تقرير المصروفات حسب الشهر'!$C$1150:$AD$1261,6,FALSE),0) -> 0 | N130: =IFERROR(VLOOKUP(C130,'تقرير المصروفات حسب الشهر'!$C$1277:$AD$1388,6,FALSE),0) -> 0 | O130: =IFERROR(VLOOKUP(C130,'تقرير المصروفات حسب الشهر'!$C$1404:$AD$1519,6,FALSE),0) -> 0 | P130: =SUM(D130:O130) -> 0
C131: فوائد القروض - بنك القاهرة BDC | D131: =IFERROR(VLOOKUP(C131,'تقرير المصروفات حسب الشهر'!$C$10:$AD$119,6,FALSE),0) -> 0 | E131: =IFERROR(VLOOKUP(C131,'تقرير المصروفات حسب الشهر'!$C$136:$AD$245,6,FALSE),0) -> 0 | F131: =VLOOKUP(C131,'تقرير المصروفات حسب الشهر'!C371:AI487,6,0) -> 0 | G131: =IFERROR(VLOOKUP(C131,'تقرير المصروفات حسب الشهر'!$C$391:$AD$510,6,FALSE),0) -> 0 | H131: =IFERROR(VLOOKUP(C131,'تقرير المصروفات حسب الشهر'!$C$519:$AD$627,6,FALSE),0) -> 0 | I131: =IFERROR(VLOOKUP(C131,'تقرير المصروفات حسب الشهر'!$C$644:$AD$753,6,FALSE),0) -> 0 | J131: =IFERROR(VLOOKUP(C131,'تقرير المصروفات حسب الشهر'!$C$770:$AD$879,6,FALSE),0) -> 0 | K131: =IFERROR(VLOOKUP(C131,'تقرير المصروفات حسب الشهر'!$C$897:$AD$1006,6,FALSE),0) -> 0 | L131: =IFERROR(VLOOKUP(C131,'تقرير المصروفات حسب الشهر'!$C$1023:$AI$1138,6,FALSE),0) -> 0 | M131: =IFERROR(VLOOKUP(C131,'تقرير المصروفات حسب الشهر'!$C$1150:$AD$1261,6,FALSE),0) -> 0 | N131: =IFERROR(VLOOKUP(C131,'تقرير المصروفات حسب الشهر'!$C$1277:$AD$1388,6,FALSE),0) -> 0 | O131: =IFERROR(VLOOKUP(C131,'تقرير المصروفات حسب الشهر'!$C$1404:$AD$1519,6,FALSE),0) -> 0 | P131: =SUM(D131:O131) -> 0
C132: خصم أبليكيشن | D132: =IFERROR(VLOOKUP(C132,'تقرير المصروفات حسب الشهر'!$C$10:$AD$125,6,FALSE),0) -> 690393.56 | E132: =IFERROR(VLOOKUP(C132,'تقرير المصروفات حسب الشهر'!$C$136:$AD$254,6,FALSE),0) -> 693413.14 | F132: =VLOOKUP(C132,'تقرير المصروفات حسب الشهر'!C372:AI488,6,0) -> 588825.34 | G132: =IFERROR(VLOOKUP(C132,'تقرير المصروفات حسب الشهر'!$C$391:$AD$510,6,FALSE),0) -> 820578.2 | H132: =IFERROR(VLOOKUP(C132,'تقرير المصروفات حسب الشهر'!$C$519:$AD$629,6,FALSE),0) -> 0 | I132: =IFERROR(VLOOKUP(C132,'تقرير المصروفات حسب الشهر'!$C$644:$AD$757,6,FALSE),0) -> 0 | J132: =IFERROR(VLOOKUP(C132,'تقرير المصروفات حسب الشهر'!$C$770:$AD$884,6,FALSE),0) -> 0 | K132: =IFERROR(VLOOKUP(C132,'تقرير المصروفات حسب الشهر'!$C$897:$AD$1014,6,FALSE),0) -> 0 | L132: =IFERROR(VLOOKUP(C132,'تقرير المصروفات حسب الشهر'!$C$1023:$AI$1138,6,FALSE),0) -> 0 | M132: =IFERROR(VLOOKUP(C132,'تقرير المصروفات حسب الشهر'!$C$1150:$AD$1261,6,FALSE),0) -> 0 | N132: =IFERROR(VLOOKUP(C132,'تقرير المصروفات حسب الشهر'!$C$1277:$AD$1389,6,FALSE),0) -> 0 | O132: =IFERROR(VLOOKUP(C132,'تقرير المصروفات حسب الشهر'!$C$1404:$AD$1519,6,FALSE),0) -> 0 | P132: =SUM(D132:O132) -> 2793210.2
C133: مفقودات ومسروقات | D133: =IFERROR(VLOOKUP(C133,'تقرير المصروفات حسب الشهر'!$C$10:$AD$125,6,FALSE),0) -> 0 | E133: =IFERROR(VLOOKUP(C133,'تقرير المصروفات حسب الشهر'!$C$136:$AD$254,6,FALSE),0) -> 0 | F133: =VLOOKUP(C133,'تقرير المصروفات حسب الشهر'!C373:AI489,6,0) -> 0 | G133: =IFERROR(VLOOKUP(C133,'تقرير المصروفات حسب الشهر'!$C$391:$AD$510,6,FALSE),0) -> 0 | I133: =IFERROR(VLOOKUP(C133,'تقرير المصروفات حسب الشهر'!$C$644:$AD$757,6,FALSE),0) -> 0 | J133: =IFERROR(VLOOKUP(C133,'تقرير المصروفات حسب الشهر'!$C$770:$AD$884,6,FALSE),0) -> 0 | K133: =IFERROR(VLOOKUP(C133,'تقرير المصروفات حسب الشهر'!$C$897:$AD$1014,6,FALSE),0) -> 0 | L133: =IFERROR(VLOOKUP(C133,'تقرير المصروفات حسب الشهر'!$C$1023:$AI$1138,6,FALSE),0) -> 0 | M133: =IFERROR(VLOOKUP(C133,'تقرير المصروفات حسب الشهر'!$C$1150:$AD$1261,6,FALSE),0) -> 0 | N133: =IFERROR(VLOOKUP(C133,'تقرير المصروفات حسب الشهر'!$C$1277:$AI$1391,6,FALSE),0) -> 0 | O133: =IFERROR(VLOOKUP(C133,'تقرير المصروفات حسب الشهر'!$C$1404:$AD$1519,6,FALSE),0) -> 0 | P133: =SUM(D133:O133) -> 0
C134: عروض مبيعات ابليكشن | D134: =IFERROR(VLOOKUP(C134,'تقرير المصروفات حسب الشهر'!$C$10:$AD$125,6,FALSE),0) -> 114715.61 | E134: =IFERROR(VLOOKUP(C134,'تقرير المصروفات حسب الشهر'!$C$136:$AD$254,6,FALSE),0) -> 67747.68 | F134: =VLOOKUP(C134,'تقرير المصروفات حسب الشهر'!C374:AI490,6,0) -> 120095.26 | G134: =IFERROR(VLOOKUP(C134,'تقرير المصروفات حسب الشهر'!$C$391:$AD$510,6,FALSE),0) -> 117005.58 | J134: =IFERROR(VLOOKUP(C134,'تقرير المصروفات حسب الشهر'!$C$770:$AD$884,6,FALSE),0) -> 0 | K134: =IFERROR(VLOOKUP(C134,'تقرير المصروفات حسب الشهر'!$C$897:$AD$1014,6,FALSE),0) -> 0 | L134: =IFERROR(VLOOKUP(C134,'تقرير المصروفات حسب الشهر'!$C$1023:$AI$1138,6,FALSE),0) -> 0 | M134: =IFERROR(VLOOKUP(C134,'تقرير المصروفات حسب الشهر'!$C$1150:$AD$1265,6,FALSE),0) -> 0 | N134: =IFERROR(VLOOKUP(C134,'تقرير المصروفات حسب الشهر'!$C$1277:$AI$1391,6,FALSE),0) -> 0 | O134: =IFERROR(VLOOKUP(C134,'تقرير المصروفات حسب الشهر'!$C$1404:$AD$1519,6,FALSE),0) -> 0 | P134: =SUM(D134:O134) -> 419564.13
C135: إجمالي المصروفات | D135: =SUM(D22:D134) -> 1519561.2 | E135: =SUM(E22:E134) -> 1420510.9 | F135: =SUM(F22:F134) -> 1378502.1 | G135: =SUM(G22:G134) -> 1709433.4 | H135: =SUM(H22:H132) -> 0 | I135: =SUM(I22:I133) -> 0 | J135: =SUM(J22:J134) -> 0 | K135: =SUM(K22:K134) -> 0 | L135: =SUM(L22:L134) -> 0 | M135: =SUM(M22:M134) -> 0 | N135: =SUM(N22:N134) -> 0 | O135: =SUM(O22:O134) -> 0 | P135: =SUM(D135:O135) -> 6028007.6
C137: مجمل الربح | D137: =D19 -> 1767481.2 | E137: =E19 -> 1631401.3 | F137: =F19 -> 1895487.6 | G137: =G19 -> 2182861.4 | H137: =H19 -> 2185540.3 | I137: =I19 -> 1000000 | J137: =J19 -> 1000000 | K137: =K19 -> 1000000 | ... O137: =O19 -> 1000000 | P137: =SUM(D137:O137) -> 16662772
C140: صافي الربح / الخسارة | D140: =D137-D135 -> 247919.98 | E140: =E137-E135 -> 210890.43 | F140: =F137-F135 -> 516985.5 | G140: =G137-G135 -> 473427.97 | H140: =H137-H135 -> 2185540.3 | I140: =I137-I135 -> 1000000 | J140: =J137-J135 -> 1000000 | K140: =K137-K135 -> 1000000 | ... O140: =O137-O135 -> 1000000 | P140: =SUM(D140:O140) -> 10634764

Sheet Sweedy
C2: INCOME STATEMTN
F3: Income Statement For Sweedy
D6: Jan | E6: February | F6: March | G6: April | H6: May | I6: June | J6: July | K6: August | L6: September | M6: October | N6: November | O6: December | P6: TOTAL
C7: INCOME DETAILS
A8: السويدى | C8: المبيعات | D8: =D9+D10+D11 -> 1248476.2 | E8: =E9+E10+E11 -> 1729590.7 | F8: =F9+F10+F11 -> 1710654.6 | G8: =G9+G10+G11 -> 1685296 | H8: =H9+H10+H11 -> 1572349.7 | I8: =I9+I10+I11 -> 1000000 | J8: =J9+J10+J11 -> 1000000 | K8: =K9+K10+K11 -> 1000000 | ... O8: =O9+O10+O11 -> 1000000 | P8: =SUM(D8:O8) -> 14946367
C9: نقدى | D9: =VLOOKUP($A$8,'تقرير إحصائية بحجم المبيعات'!$B$7:$L$31,2,FALSE) -> 73229.47 | E9: =VLOOKUP($A$8,'تقرير إحصائية بحجم المبيعات'!$B$42:$G$73,2,FALSE) -> 25927.58 | F9: =VLOOKUP($A$8,'تقرير إحصائية بحجم المبيعات'!$B$78:$E$103,2,FALSE) -> 46011.19 | G9: =VLOOKUP($A$8,'تقرير إحصائية بحجم المبيعات'!$B$112:$G$137,2,FALSE) -> 142942.66 | H9: =VLOOKUP($A$8,'تقرير إحصائية بحجم المبيعات'!$B$147:$G$177,2,FALSE) -> 167917.75 | I9: =VLOOKUP($A$8,'تقرير إحصائية بحجم المبيعات'!$B$182:$G$212,2,FALSE) -> 1000000 | J9: =VLOOKUP($A$8,'تقرير إحصائية بحجم المبيعات'!$B$217:$L$243,2,FALSE) -> 1000000 | K9: =VLOOKUP($A$8,'تقرير إحصائية بحجم المبيعات'!$B$252:$L$278,2,FALSE) -> 1000000 | L9: =VLOOKUP($A$8,'تقرير إحصائية بحجم المبيعات'!$B$287:$L$313,2,FALSE) -> 1000000 | M9: =VLOOKUP($A$8,'تقرير إحصائية بحجم المبيعات'!$B$322:$L$347,2,FALSE) -> 1000000 | N9: =VLOOKUP($A$8,'تقرير إحصائية بحجم المبيعات'!$B$357:$L$383,2,FALSE) -> 1000000 | O9: =VLOOKUP($A$8,'تقرير إحصائية بحجم المبيعات'!$B$391:$L$420,2,FALSE) -> 1000000 | P9: =SUM(D9:O9) -> 7456028.7
C10: دليفرى | D10: =VLOOKUP($A$8,'تقرير إحصائية بحجم المبيعات'!$B$7:$L$31,3,FALSE) -> 0 | E10: =VLOOKUP($A$8,'تقرير إحصائية بحجم المبيعات'!$B$42:$G$73,3,FALSE) -> 0 | F10: =VLOOKUP($A$8,'تقرير إحصائية بحجم المبيعات'!$B$78:$E$103,3,FALSE) -> 0 | G10: =VLOOKUP($A$8,'تقرير إحصائية بحجم المبيعات'!$B$112:$G$137,3,FALSE) -> 0 | H10: =VLOOKUP($A$8,'تقرير إحصائية بحجم المبيعات'!$B$147:$G$177,3,FALSE) -> 0 | I10: =VLOOKUP($A$8,'تقرير إحصائية بحجم المبيعات'!$B$182:$G$212,3,FALSE) -> 0 | J10: =VLOOKUP($A$8,'تقرير إحصائية بحجم المبيعات'!$B$217:$L$243,3,FALSE) -> 0 | K10: =VLOOKUP($A$8,'تقرير إحصائية بحجم المبيعات'!$B$252:$L$278,3,FALSE) -> 0 | L10: =VLOOKUP($A$8,'تقرير إحصائية بحجم المبيعات'!$B$287:$L$313,3,FALSE) -> 0 | M10: =VLOOKUP($A$8,'تقرير إحصائية بحجم المبيعات'!$B$322:$L$347,3,FALSE) -> 0 | N10: =VLOOKUP($A$8,'تقرير إحصائية بحجم المبيعات'!$B$357:$L$383,3,FALSE) -> 0 | O10: =VLOOKUP($A$8,'تقرير إحصائية بحجم المبيعات'!$B$391:$L$420,3,FALSE) -> 0 | P10: =SUM(D10:O10) -> 0
C11: اجل | D11: =VLOOKUP($A$8,'تقرير إحصائية بحجم المبيعات'!$B$7:$L$31,4,FALSE) -> 1175246.7 | E11: =VLOOKUP($A$8,'تقرير إحصائية بحجم المبيعات'!$B$42:$G$73,4,FALSE) -> 1703663.1 | F11: =VLOOKUP($A$8,'تقرير إحصائية بحجم المبيعات'!$B$78:$E$103,4,FALSE) -> 1664643.4 | G11: =VLOOKUP($A$8,'تقرير إحصائية بحجم المبيعات'!$B$112:$G$137,4,FALSE) -> 1542353.4 | H11: =VLOOKUP($A$8,'تقرير إحصائية بحجم المبيعات'!$B$147:$G$177,4,FALSE) -> 1404432 | I11: =VLOOKUP($A$8,'تقرير إحصائية بحجم المبيعات'!$B$182:$G$212,4,FALSE) -> 0 | J11: =VLOOKUP($A$8,'تقرير إحصائية بحجم المبيعات'!$B$217:$L$243,4,FALSE) -> 0 | K11: =VLOOKUP($A$8,'تقرير إحصائية بحجم المبيعات'!$B$252:$L$278,4,FALSE) -> 0 | L11: =VLOOKUP($A$8,'تقرير إحصائية بحجم المبيعات'!$B$287:$L$313,4,FALSE) -> 0 | M11: =VLOOKUP($A$8,'تقرير إحصائية بحجم المبيعات'!$B$322:$L$347,4,FALSE) -> 0 | N11: =VLOOKUP($A$8,'تقرير إحصائية بحجم المبيعات'!$B$357:$L$383,4,FALSE) -> 0 | O11: =VLOOKUP($A$8,'تقرير إحصائية بحجم المبيعات'!$B$391:$L$420,4,FALSE) -> 0 | P11: =SUM(D11:O11) -> 7490338.7
C12: تكلفة البضاعة المباعة | D12: =VLOOKUP($A$8,'تقرير إحصائية بحجم المبيعات'!$B$7:$L$31,11,FALSE) -> 1094037.7 | E12: =VLOOKUP($A$8,'تقرير إحصائية بحجم المبيعات'!$B$42:$L$73,11,FALSE) -> 1537583.1 | F12: =VLOOKUP($A$8,'تقرير إحصائية بحجم المبيعات'!$B$78:$L$103,11,FALSE) -> 1498886.7 | G12: =VLOOKUP($A$8,'تقرير إحصائية بحجم المبيعات'!$B$112:$L$137,11,FALSE) -> 1439895.8 | H12: =VLOOKUP($A$8,'تقرير إحصائية بحجم المبيعات'!$B$147:$L$177,11,FALSE) -> 1380696.6 | I12: =VLOOKUP($A$8,'تقرير إحصائية بحجم المبيعات'!$B$182:$L$212,11,FALSE) -> 0 | J12: =VLOOKUP($A$8,'تقرير إحصائية بحجم المبيعات'!$B$217:$L$243,11,FALSE) -> 0 | K12: =VLOOKUP($A$8,'تقرير إحصائية بحجم المبيعات'!$B$252:$L$278,11,FALSE) -> 0 | L12: =VLOOKUP($A$8,'تقرير إحصائية بحجم المبيعات'!$B$287:$L$313,11,FALSE) -> 0 | M12: =VLOOKUP($A$8,'تقرير إحصائية بحجم المبيعات'!$B$322:$L$347,11,FALSE) -> 0 | N12: =VLOOKUP($A$8,'تقرير إحصائية بحجم المبيعات'!$B$357:$L$383,11,FALSE) -> 0 | O12: =VLOOKUP($A$8,'تقرير إحصائية بحجم المبيعات'!$B$391:$L$420,11,FALSE) -> 0 | P12: =SUM(D12:O12) -> 6951100
C13: مجمل الربح | D13: =D8-D12 -> 154438.48 | E13: =E8-E12 -> 192007.66 | F13: =F8-F12 -> 211767.87 | G13: =G8-G12 -> 245400.23 | H13: =H8-H12 -> 191653.08 | I13: =I8-I12 -> 1000000 | J13: =J8-J12 -> 1000000 | K13: =K8-K12 -> 1000000 | ... O13: =O8-O12 -> 1000000 | P13: =SUM(D13:O13) -> 7995267.3
C14: خصم نقدى | P14: =SUM(D14:O14) -> 0
C15: ارباح صرف اصناف بيع اصول | P15: =SUM(D15:O15) -> 0
C16: فائض جرد | D16: 100202.37 | E16: 263271.04 | G16: 264047.81 | P16: =SUM(D16:O16) -> 627521.22
C17: ايرادات اخرى | P17: =SUM(D17:O17) -> 0
C18: إجمالي الايرادات اخرى | D18: =SUM(D14:D17) -> 100202.37 | E18: =SUM(E14:E17) -> 263271.04 | F18: =SUM(F14:F17) -> 0 | G18: =SUM(G14:G17) -> 264047.81 | H18: =SUM(H14:H17) -> 0 | I18: =SUM(I14:I17) -> 0 | J18: =SUM(J14:J17) -> 0 | K18: =SUM(K14:K17) -> 0 | ... O18: =SUM(O14:O17) -> 0 | P18: =SUM(D18:O18) -> 627521.22
C19: مجمل الربح | D19: =D13+D18 -> 254640.85 | E19: =E13+E18 -> 455278.7 | F19: =F13+F18 -> 211767.87 | G19: =G13+G18 -> 509448.04 | H19: =H13+H18 -> 191653.08 | I19: =I13+I18 -> 1000000 | J19: =J13+J18 -> 1000000 | K19: =K13+K18 -> 1000000 | ... O19: =O13+O18 -> 1000000 | P19: =SUM(D19:O19) -> 8622788.5
C21: EXPENSE DETAILS
C22: مرتبات الادارة | D22: =IFERROR(VLOOKUP(C22,'تقرير المصروفات حسب الشهر'!$C$10:$AD$119,7,FALSE),0) -> 0 | E22: =IFERROR(VLOOKUP(C22,'تقرير المصروفات حسب الشهر'!$C$136:$AD$245,7,FALSE),0) -> 0 | F22: =VLOOKUP(C22,'تقرير المصروفات حسب الشهر'!C262:AI378,7,0) -> 0 | G22: =IFERROR(VLOOKUP(C22,'تقرير المصروفات حسب الشهر'!$C$391:$AD$499,7,FALSE),0) -> 0 | H22: =IFERROR(VLOOKUP(C22,'تقرير المصروفات حسب الشهر'!$C$519:$AD$627,7,FALSE),0) -> 0 | I22: =IFERROR(VLOOKUP(C22,'تقرير المصروفات حسب الشهر'!$C$644:$AD$753,7,FALSE),0) -> 0 | J22: =IFERROR(VLOOKUP(C22,'تقرير المصروفات حسب الشهر'!$C$770:$AD$879,7,FALSE),0) -> 0 | K22: =IFERROR(VLOOKUP(C22,'تقرير المصروفات حسب الشهر'!$C$897:$AD$1006,7,FALSE),0) -> 0 | L22: =IFERROR(VLOOKUP(C22,'تقرير المصروفات حسب الشهر'!$C$1023:$AD$1133,7,FALSE),0) -> 0 | M22: =IFERROR(VLOOKUP(C22,'تقرير المصروفات حسب الشهر'!$C$1150:$AD$1261,7,FALSE),0) -> 0 | N22: =IFERROR(VLOOKUP(C22,'تقرير المصروفات حسب الشهر'!$C$1277:$AD$1388,7,FALSE),0) -> 0 | O22: =IFERROR(VLOOKUP(C22,'تقرير المصروفات حسب الشهر'!$C$1404:$AD$1519,7,FALSE),0) -> 0 | P22: =SUM(D22:O22) -> 0
C23: مرتبات الفروع | D23: =IFERROR(VLOOKUP(C23,'تقرير المصروفات حسب الشهر'!$C$10:$AD$119,7,FALSE),0) -> 50665.82 | E23: =IFERROR(VLOOKUP(C23,'تقرير المصروفات حسب الشهر'!$C$136:$AD$245,7,FALSE),0) -> 47700.88 | F23: =VLOOKUP(C23,'تقرير المصروفات حسب الشهر'!C263:AI379,7,0) -> 47179.08 | G23: =IFERROR(VLOOKUP(C23,'تقرير المصروفات حسب الشهر'!$C$391:$AD$499,7,FALSE),0) -> 52836.51 | H23: =IFERROR(VLOOKUP(C23,'تقرير المصروفات حسب الشهر'!$C$519:$AD$627,7,FALSE),0) -> 45561.24 | I23: =IFERROR(VLOOKUP(C23,'تقرير المصروفات حسب الشهر'!$C$644:$AD$753,7,FALSE),0) -> 0 | J23: =IFERROR(VLOOKUP(C23,'تقرير المصروفات حسب الشهر'!$C$770:$AD$879,7,FALSE),0) -> 0 | K23: =IFERROR(VLOOKUP(C23,'تقرير المصروفات حسب الشهر'!$C$897:$AD$1006,7,FALSE),0) -> 0 | L23: =IFERROR(VLOOKUP(C23,'تقرير المصروفات حسب الشهر'!$C$1023:$AD$1133,7,FALSE),0) -> 0 | M23: =IFERROR(VLOOKUP(C23,'تقرير المصروفات حسب الشهر'!$C$1150:$AD$1261,7,FALSE),0) -> 0 | N23: =IFERROR(VLOOKUP(C23,'تقرير المصروفات حسب الشهر'!$C$1277:$AD$1388,7,FALSE),0) -> 0 | O23: =IFERROR(VLOOKUP(C23,'تقرير المصروفات حسب الشهر'!$C$1404:$AD$1519,7,FALSE),0) -> 0 | P23: =SUM(D23:O23) -> 243943.53
C24: الكهرباء | D24: =IFERROR(VLOOKUP(C24,'تقرير المصروفات حسب الشهر'!$C$10:$AD$119,7,FALSE),0) -> 0 | E24: =IFERROR(VLOOKUP(C24,'تقرير المصروفات حسب الشهر'!$C$136:$AD$245,7,FALSE),0) -> 0 | F24: =VLOOKUP(C24,'تقرير المصروفات حسب الشهر'!C264:AI380,7,0) -> 0 | G24: =IFERROR(VLOOKUP(C24,'تقرير المصروفات حسب الشهر'!$C$391:$AD$499,7,FALSE),0) -> 0 | H24: =IFERROR(VLOOKUP(C24,'تقرير المصروفات حسب الشهر'!$C$519:$AD$627,7,FALSE),0) -> 0 | I24: =IFERROR(VLOOKUP(C24,'تقرير المصروفات حسب الشهر'!$C$644:$AD$753,7,FALSE),0) -> 0 | J24: =IFERROR(VLOOKUP(C24,'تقرير المصروفات حسب الشهر'!$C$770:$AD$879,7,FALSE),0) -> 0 | K24: =IFERROR(VLOOKUP(C24,'تقرير المصروفات حسب الشهر'!$C$897:$AD$1006,7,FALSE),0) -> 0 | L24: =IFERROR(VLOOKUP(C24,'تقرير المصروفات حسب الشهر'!$C$1023:$AD$1133,7,FALSE),0) -> 0 | M24: =IFERROR(VLOOKUP(C24,'تقرير المصروفات حسب الشهر'!$C$1150:$AD$1261,7,FALSE),0) -> 0 | N24: =IFERROR(VLOOKUP(C24,'تقرير المصروفات حسب الشهر'!$C$1277:$AD$1388,7,FALSE),0) -> 0 | O24: =IFERROR(VLOOKUP(C24,'تقرير المصروفات حسب الشهر'!$C$1404:$AD$1519,7,FALSE),0) -> 0 | P24: =SUM(D24:O24) -> 0
C25: المياه | D25: =IFERROR(VLOOKUP(C25,'تقرير المصروفات حسب الشهر'!$C$10:$AD$119,7,FALSE),0) -> 0 | E25: =IFERROR(VLOOKUP(C25,'تقرير المصروفات حسب الشهر'!$C$136:$AD$245,7,FALSE),0) -> 0 | F25: =VLOOKUP(C25,'تقرير المصروفات حسب الشهر'!C265:AI381,7,0) -> 0 | G25: =IFERROR(VLOOKUP(C25,'تقرير المصروفات حسب الشهر'!$C$391:$AD$499,7,FALSE),0) -> 0 | H25: =IFERROR(VLOOKUP(C25,'تقرير المصروفات حسب الشهر'!$C$519:$AD$627,7,FALSE),0) -> 0 | I25: =IFERROR(VLOOKUP(C25,'تقرير المصروفات حسب الشهر'!$C$644:$AD$753,7,FALSE),0) -> 0 | J25: =IFERROR(VLOOKUP(C25,'تقرير المصروفات حسب الشهر'!$C$770:$AD$879,7,FALSE),0) -> 0 | K25: =IFERROR(VLOOKUP(C25,'تقرير المصروفات حسب الشهر'!$C$897:$AD$1006,7,FALSE),0) -> 0 | L25: =IFERROR(VLOOKUP(C25,'تقرير المصروفات حسب الشهر'!$C$1023:$AD$1133,7,FALSE),0) -> 0 | M25: =IFERROR(VLOOKUP(C25,'تقرير المصروفات حسب الشهر'!$C$1150:$AD$1261,7,FALSE),0) -> 0 | N25: =IFERROR(VLOOKUP(C25,'تقرير المصروفات حسب الشهر'!$C$1277:$AD$1388,7,FALSE),0) -> 0 | O25: =IFERROR(VLOOKUP(C25,'تقرير المصروفات حسب الشهر'!$C$1404:$AD$1519,7,FALSE),0) -> 0 | P25: =SUM(D25:O25) -> 0
C26: التليفون الارضي | D26: =IFERROR(VLOOKUP(C26,'تقرير المصروفات حسب الشهر'!$C$10:$AD$119,7,FALSE),0) -> 0 | E26: =IFERROR(VLOOKUP(C26,'تقرير المصروفات حسب الشهر'!$C$136:$AD$245,7,FALSE),0) -> 0 | F26: =VLOOKUP(C26,'تقرير المصروفات حسب الشهر'!C266:AI382,7,0) -> 0 | G26: =IFERROR(VLOOKUP(C26,'تقرير المصروفات حسب الشهر'!$C$391:$AD$499,7,FALSE),0) -> 0 | H26: =IFERROR(VLOOKUP(C26,'تقرير المصروفات حسب الشهر'!$C$519:$AD$627,7,FALSE),0) -> 0 | I26: =IFERROR(VLOOKUP(C26,'تقرير المصروفات حسب الشهر'!$C$644:$AD$753,7,FALSE),0) -> 0 | J26: =IFERROR(VLOOKUP(C26,'تقرير المصروفات حسب الشهر'!$C$770:$AD$879,7,FALSE),0) -> 0 | K26: =IFERROR(VLOOKUP(C26,'تقرير المصروفات حسب الشهر'!$C$897:$AD$1006,7,FALSE),0) -> 0 | L26: =IFERROR(VLOOKUP(C26,'تقرير المصروفات حسب الشهر'!$C$1023:$AD$1133,7,FALSE),0) -> 0 | M26: =IFERROR(VLOOKUP(C26,'تقرير المصروفات حسب الشهر'!$C$1150:$AD$1261,7,FALSE),0) -> 0 | N26: =IFERROR(VLOOKUP(C26,'تقرير المصروفات حسب الشهر'!$C$1277:$AD$1388,7,FALSE),0) -> 0 | O26: =IFERROR(VLOOKUP(C26,'تقرير المصروفات حسب الشهر'!$C$1404:$AD$1519,7,FALSE),0) -> 0 | P26: =SUM(D26:O26) -> 0
C27: الايجار - الصيدلية | D27: =IFERROR(VLOOKUP(C27,'تقرير المصروفات حسب الشهر'!$C$10:$AD$119,7,FALSE),0) -> 0 | E27: =IFERROR(VLOOKUP(C27,'تقرير المصروفات حسب الشهر'!$C$136:$AD$245,7,FALSE),0) -> 0 | F27: =VLOOKUP(C27,'تقرير المصروفات حسب الشهر'!C267:AI383,7,0) -> 0 | G27: =IFERROR(VLOOKUP(C27,'تقرير المصروفات حسب الشهر'!$C$391:$AD$499,7,FALSE),0) -> 0 | H27: =IFERROR(VLOOKUP(C27,'تقرير المصروفات حسب الشهر'!$C$519:$AD$627,7,FALSE),0) -> 0 | I27: =IFERROR(VLOOKUP(C27,'تقرير المصروفات حسب الشهر'!$C$644:$AD$753,7,FALSE),0) -> 0 | J27: =IFERROR(VLOOKUP(C27,'تقرير المصروفات حسب الشهر'!$C$770:$AD$879,7,FALSE),0) -> 0 | K27: =IFERROR(VLOOKUP(C27,'تقرير المصروفات حسب الشهر'!$C$897:$AD$1006,7,FALSE),0) -> 0 | L27: =IFERROR(VLOOKUP(C27,'تقرير المصروفات حسب الشهر'!$C$1023:$AD$1133,7,FALSE),0) -> 0 | M27: =IFERROR(VLOOKUP(C27,'تقرير المصروفات حسب الشهر'!$C$1150:$AD$1261,7,FALSE),0) -> 0 | N27: =IFERROR(VLOOKUP(C27,'تقرير المصروفات حسب الشهر'!$C$1277:$AD$1388,7,FALSE),0) -> 0 | O27: =IFERROR(VLOOKUP(C27,'تقرير المصروفات حسب الشهر'!$C$1404:$AD$1519,7,FALSE),0) -> 0 | P27: =SUM(D27:O27) -> 0
C28: الايجار - الادارة | D28: =IFERROR(VLOOKUP(C28,'تقرير المصروفات حسب الشهر'!$C$10:$AD$119,7,FALSE),0) -> 0 | E28: =IFERROR(VLOOKUP(C28,'تقرير المصروفات حسب الشهر'!$C$136:$AD$245,7,FALSE),0) -> 0 | F28: =VLOOKUP(C28,'تقرير المصروفات حسب الشهر'!C268:AI384,7,0) -> 0 | G28: =IFERROR(VLOOKUP(C28,'تقرير المصروفات حسب الشهر'!$C$391:$AD$499,7,FALSE),0) -> 0 | H28: =IFERROR(VLOOKUP(C28,'تقرير المصروفات حسب الشهر'!$C$519:$AD$627,7,FALSE),0) -> 0 | I28: =IFERROR(VLOOKUP(C28,'تقرير المصروفات حسب الشهر'!$C$644:$AD$753,7,FALSE),0) -> 0 | J28: =IFERROR(VLOOKUP(C28,'تقرير المصروفات حسب الشهر'!$C$770:$AD$879,7,FALSE),0) -> 0 | K28: =IFERROR(VLOOKUP(C28,'تقرير المصروفات حسب الشهر'!$C$897:$AD$1006,7,FALSE),0) -> 0 | L28: =IFERROR(VLOOKUP(C28,'تقرير المصروفات حسب الشهر'!$C$1023:$AD$1133,7,FALSE),0) -> 0 | M28: =IFERROR(VLOOKUP(C28,'تقرير المصروفات حسب الشهر'!$C$1150:$AD$1261,7,FALSE),0) -> 0 | N28: =IFERROR(VLOOKUP(C28,'تقرير المصروفات حسب الشهر'!$C$1277:$AD$1388,7,FALSE),0) -> 0 | O28: =IFERROR(VLOOKUP(C28,'تقرير المصروفات حسب الشهر'!$C$1404:$AD$1519,7,FALSE),0) -> 0 | P28: =SUM(D28:O28) -> 0
C29: ايجارات متنوعه | D29: =IFERROR(VLOOKUP(C29,'تقرير المصروفات حسب الشهر'!$C$10:$AD$119,7,FALSE),0) -> 0 | E29: =IFERROR(VLOOKUP(C29,'تقرير المصروفات حسب الشهر'!$C$136:$AD$245,7,FALSE),0) -> 0 | F29: =VLOOKUP(C29,'تقرير المصروفات حسب الشهر'!C269:AI385,7,0) -> 0 | G29: =IFERROR(VLOOKUP(C29,'تقرير المصروفات حسب الشهر'!$C$391:$AD$499,7,FALSE),0) -> 0 | H29: =IFERROR(VLOOKUP(C29,'تقرير المصروفات حسب الشهر'!$C$519:$AD$627,7,FALSE),0) -> 0 | I29: =IFERROR(VLOOKUP(C29,'تقرير المصروفات حسب الشهر'!$C$644:$AD$753,7,FALSE),0) -> 0 | J29: =IFERROR(VLOOKUP(C29,'تقرير المصروفات حسب الشهر'!$C$770:$AD$879,7,FALSE),0) -> 0 | K29: =IFERROR(VLOOKUP(C29,'تقرير المصروفات حسب الشهر'!$C$897:$AD$1006,7,FALSE),0) -> 0 | L29: =IFERROR(VLOOKUP(C29,'تقرير المصروفات حسب الشهر'!$C$1023:$AD$1133,7,FALSE),0) -> 0 | M29: =IFERROR(VLOOKUP(C29,'تقرير المصروفات حسب الشهر'!$C$1150:$AD$1261,7,FALSE),0) -> 0 | N29: =IFERROR(VLOOKUP(C29,'تقرير المصروفات حسب الشهر'!$C$1277:$AD$1388,7,FALSE),0) -> 0 | O29: =IFERROR(VLOOKUP(C29,'تقرير المصروفات حسب الشهر'!$C$1404:$AD$1519,7,FALSE),0) -> 0 | P29: =SUM(D29:O29) -> 0
C30: ادوات مكتبية | D30: =IFERROR(VLOOKUP(C30,'تقرير المصروفات حسب الشهر'!$C$10:$AD$119,7,FALSE),0) -> 0 | E30: =IFERROR(VLOOKUP(C30,'تقرير المصروفات حسب الشهر'!$C$136:$AD$245,7,FALSE),0) -> 0 | F30: =VLOOKUP(C30,'تقرير المصروفات حسب الشهر'!C270:AI386,7,0) -> 0 | G30: =IFERROR(VLOOKUP(C30,'تقرير المصروفات حسب الشهر'!$C$391:$AD$499,7,FALSE),0) -> 0 | H30: =IFERROR(VLOOKUP(C30,'تقرير المصروفات حسب الشهر'!$C$519:$AD$627,7,FALSE),0) -> 0 | I30: =IFERROR(VLOOKUP(C30,'تقرير المصروفات حسب الشهر'!$C$644:$AD$753,7,FALSE),0) -> 0 | J30: =IFERROR(VLOOKUP(C30,'تقرير المصروفات حسب الشهر'!$C$770:$AD$879,7,FALSE),0) -> 0 | K30: =IFERROR(VLOOKUP(C30,'تقرير المصروفات حسب الشهر'!$C$897:$AD$1006,7,FALSE),0) -> 0 | L30: =IFERROR(VLOOKUP(C30,'تقرير المصروفات حسب الشهر'!$C$1023:$AD$1133,7,FALSE),0) -> 0 | M30: =IFERROR(VLOOKUP(C30,'تقرير المصروفات حسب الشهر'!$C$1150:$AD$1261,7,FALSE),0) -> 0 | N30: =IFERROR(VLOOKUP(C30,'تقرير المصروفات حسب الشهر'!$C$1277:$AD$1388,7,FALSE),0) -> 0 | O30: =IFERROR(VLOOKUP(C30,'تقرير المصروفات حسب الشهر'!$C$1404:$AD$1519,7,FALSE),0) -> 0 | P30: =SUM(D30:O30) -> 0
C31: فواتير الموبايل | D31: =IFERROR(VLOOKUP(C31,'تقرير المصروفات حسب الشهر'!$C$10:$AD$119,7,FALSE),0) -> 84.95 | E31: =IFERROR(VLOOKUP(C31,'تقرير المصروفات حسب الشهر'!$C$136:$AD$245,7,FALSE),0) -> 84.95 | F31: =VLOOKUP(C31,'تقرير المصروفات حسب الشهر'!C271:AI387,7,0) -> 84.95 | G31: =IFERROR(VLOOKUP(C31,'تقرير المصروفات حسب الشهر'!$C$391:$AD$499,7,FALSE),0) -> 84.95 | H31: =IFERROR(VLOOKUP(C31,'تقرير المصروفات حسب الشهر'!$C$519:$AD$627,7,FALSE),0) -> 84.95 | I31: =IFERROR(VLOOKUP(C31,'تقرير المصروفات حسب الشهر'!$C$644:$AD$753,7,FALSE),0) -> 0 | J31: =IFERROR(VLOOKUP(C31,'تقرير المصروفات حسب الشهر'!$C$770:$AD$879,7,FALSE),0) -> 0 | K31: =IFERROR(VLOOKUP(C31,'تقرير المصروفات حسب الشهر'!$C$897:$AD$1006,7,FALSE),0) -> 0 | L31: =IFERROR(VLOOKUP(C31,'تقرير المصروفات حسب الشهر'!$C$1023:$AD$1133,7,FALSE),0) -> 0 | M31: =IFERROR(VLOOKUP(C31,'تقرير المصروفات حسب الشهر'!$C$1150:$AD$1261,7,FALSE),0) -> 0 | N31: =IFERROR(VLOOKUP(C31,'تقرير المصروفات حسب الشهر'!$C$1277:$AD$1388,7,FALSE),0) -> 0 | O31: =IFERROR(VLOOKUP(C31,'تقرير المصروفات حسب الشهر'!$C$1404:$AD$1519,7,FALSE),0) -> 0 | P31: =SUM(D31:O31) -> 424.75
C32: مكافات مبيعات الادوية | D32: =IFERROR(VLOOKUP(C32,'تقرير المصروفات حسب الشهر'!$C$10:$AD$119,7,FALSE),0) -> 500 | E32: =IFERROR(VLOOKUP(C32,'تقرير المصروفات حسب الشهر'!$C$136:$AD$245,7,FALSE),0) -> 0 | F32: =VLOOKUP(C32,'تقرير المصروفات حسب الشهر'!C272:AI388,7,0) -> 0 | G32: =IFERROR(VLOOKUP(C32,'تقرير المصروفات حسب الشهر'!$C$391:$AD$499,7,FALSE),0) -> 0 | H32: =IFERROR(VLOOKUP(C32,'تقرير المصروفات حسب الشهر'!$C$519:$AD$627,7,FALSE),0) -> 0 | I32: =IFERROR(VLOOKUP(C32,'تقرير المصروفات حسب الشهر'!$C$644:$AD$753,7,FALSE),0) -> 0 | J32: =IFERROR(VLOOKUP(C32,'تقرير المصروفات حسب الشهر'!$C$770:$AD$879,7,FALSE),0) -> 0 | K32: =IFERROR(VLOOKUP(C32,'تقرير المصروفات حسب الشهر'!$C$897:$AD$1006,7,FALSE),0) -> 0 | L32: =IFERROR(VLOOKUP(C32,'تقرير المصروفات حسب الشهر'!$C$1023:$AD$1133,7,FALSE),0) -> 0 | M32: =IFERROR(VLOOKUP(C32,'تقرير المصروفات حسب الشهر'!$C$1150:$AD$1261,7,FALSE),0) -> 0 | N32: =IFERROR(VLOOKUP(C32,'تقرير المصروفات حسب الشهر'!$C$1277:$AD$1388,7,FALSE),0) -> 0 | O32: =IFERROR(VLOOKUP(C32,'تقرير المصروفات حسب الشهر'!$C$1404:$AD$1519,7,FALSE),0) -> 0 | P32: =SUM(D32:O32) -> 500
C33: مكافات مبيعات التجميل | D33: =IFERROR(VLOOKUP(C33,'تقرير المصروفات حسب الشهر'!$C$10:$AD$119,7,FALSE),0) -> 800 | E33: =IFERROR(VLOOKUP(C33,'تقرير المصروفات حسب الشهر'!$C$136:$AD$245,7,FALSE),0) -> 0 | F33: =VLOOKUP(C33,'تقرير المصروفات حسب الشهر'!C273:AI389,7,0) -> 0 | G33: =IFERROR(VLOOKUP(C33,'تقرير المصروفات حسب الشهر'!$C$391:$AD$499,7,FALSE),0) -> 0 | H33: =IFERROR(VLOOKUP(C33,'تقرير المصروفات حسب الشهر'!$C$519:$AD$627,7,FALSE),0) -> 0 | I33: =IFERROR(VLOOKUP(C33,'تقرير المصروفات حسب الشهر'!$C$644:$AD$753,7,FALSE),0) -> 0 | J33: =IFERROR(VLOOKUP(C33,'تقرير المصروفات حسب الشهر'!$C$770:$AD$879,7,FALSE),0) -> 0 | K33: =IFERROR(VLOOKUP(C33,'تقرير المصروفات حسب الشهر'!$C$897:$AD$1006,7,FALSE),0) -> 0 | L33: =IFERROR(VLOOKUP(C33,'تقرير المصروفات حسب الشهر'!$C$1023:$AD$1133,7,FALSE),0) -> 0 | M33: =IFERROR(VLOOKUP(C33,'تقرير المصروفات حسب الشهر'!$C$1150:$AD$1261,7,FALSE),0) -> 0 | N33: =IFERROR(VLOOKUP(C33,'تقرير المصروفات حسب الشهر'!$C$1277:$AD$1388,7,FALSE),0) -> 0 | O33: =IFERROR(VLOOKUP(C33,'تقرير المصروفات حسب الشهر'!$C$1404:$AD$1519,7,FALSE),0) -> 0 | P33: =SUM(D33:O33) -> 800
